Workbook

Sheet Capa
B3: Nome: | F3: "As empresas excelentes não acreditam na excelência, apenas na melhoria contínua e na mudança constante" Tom Peters
B5: E-mail:
B7: Empresa:
B9: Cel/ Whats:

Sheet Levantamento inicial
B1: Desvendando o potencial de melhoria da sua empresa
C6: ="Percentual de conclusão: "&ROUND(E6*100,0)&"%" -> Percentual de conclusão: 0% | E6: =COUNTA(E8,E12,E14,E16,E18,E20,E10)/7 -> 0
C8: 1.1 | D8: Quantidade de funcionários (CLT + PJ):
C10: 1.2 | D10: Quantas unidades a sua empresa têm (matriz + filiais)?
C12: 1.3 | D12: Volume total de clientes (quantidade total de clientes que já foram atendidos na história da empresa)
C14: 1.4 | D14: Volume atual de clientes ativos (quantidade atual de clientes que estão em atendimento no momento)
C16: 1.5 | D16: Quantidade atual de produtos ou serviços a sua empresa tem no portifólio? | F16: =IF(E16>=5,10,IF(E16>=3,5,0)) -> 0
C18: 1.6 | D18: Preço médio praticado:
C20: 1.7 | D20: Há uma projeção de vendas, receitas e despesas para o ano corrente, confiável? | F20: =IF(E20="SIM",10,0) -> 0
C23: =IF(E6<>100%,"Termine o preenchimento para descobrir sua nota!","Sua nota média em levantamento inicial é: "&F23) -> Termine o preenchimento para descobrir sua nota! | F23: =ROUND(AVERAGE(F20,F16),1) -> 0

Sheet Mercado
B1: Desvendando o potencial de melhoria da sua empresa
C6: ="Percentual de conclusão: "&ROUND(E6*100,0)&"%" -> Percentual de conclusão: 80% | E6: =COUNTA(C9,E11,C14,C17,E19,E21,C24,E26,C29,C32)/10 -> 0.8
C8: 2.1 | D8: Qual o perfil do cliente ideal da sua empresa? | M8: =IF(ISERROR(AVERAGE(#REF!)),"",AVERAGE(#REF!)) | W8: Desconheço | X8: 10
C9: Empresas que faturam R$ 50 mil reais por mês e que tenha 3 funcionários
C11: 2.2 | D11: Qual é o índice de satisfação do seu cliente (%)? | E11: 0.75 | F11: =IF(E11>=90%,10,IF(E11<90%,0,0)) -> 0
C13: 2.3 | D13: Quais as principais dores do seu cliente? | W13: Sim | X13: 0
C16: 2.4 | D16: Quais os principais desejos do seu PCI? | W16: Não | X16: 10
C19: 2.5 | D19: Os produtos da sua empresa atendem as dores e desejos de seu cliente de forma clara? | E19: Sim | F19: =IF(E19="",0,IF(E19="Ainda é precisamos fazer ajustes",0,IF(E19="Parcialmente",5,10))) -> 10
C21: 2.6 | D21: A comunicação (site e outros materiais) é clara e objetiva quanto às soluções para dores e desejos de seu cliente? | E21: Parcialmente | F21: =IF(E21="",0,IF(E21="Ainda é precisamos fazer ajustes",0,IF(E21="Parcialmente",5,10))) -> 5
C23: 2.7 | D23: Quais são os seus principais concorrentes?
C24: EAG, MARCOS MARQUES, ANDRE MENEZES MARCUS FREITAS
C26: 2.8 | D26: Qual a qualidade da comunicação deles em relação as dores e desejos que vocês resolvem? | E26: São assertivos | F26: =IF(E26="São Confusos",10,0) -> 0
C28: 2.9 | D28: Quais as suas principais forças e oportunidades quando comparado à seus competidores? (destaque as 3 mais relevantes)
C29: Geram conteúdo de valor, mantém constância, estão em múltiplos canais
C31: 2.10 | D31: Quais suas principais fraquezas e ameaças quando comparado a seus competidores? (destaque as 3 mais relevantes) | W31: z
C32: Não ter a autoridade que eles tem, sobrecarga, falta de equipe
C34: =IF(E6<>100%,"Termine o preenchimento para descobrir sua nota!","Sua nota média em mercado é: "&F34) -> Termine o preenchimento para descobrir sua nota! | F34: =ROUND(AVERAGE(F26,F21,F19,F11),1) -> 3.8

Sheet Processos
B1: Desvendando o potencial de melhoria da sua empresa
C6: ="Percentual de conclusão: "&ROUND(E6*100,0)&"%" -> Percentual de conclusão: 88% | E6: =COUNTA(C9,E11,E17,E19,E23,E13,E15,E21)/8 -> 0.875
C8: 3.1 | D8: Descreva os processos que foram definidos em sua empresa | M8: =IF(ISERROR(AVERAGE(#REF!)),"",AVERAGE(#REF!)) | W8: Desconheço | X8: 10
C11: 3.2 | D11: Ainda existem gargalos (filas) no seu processo? (alguma atividade fica parada aguardando decisões ou finalizações de outras atividades? | E11: Sim | F11: =IF(E11="",0,IF(E11="Não",10,IF(E11="Parcialmente",5,0))) -> 0
C13: 3.3 | D13: Durante o processo, as pessoas têm de recorrer a esforços heróicos ou intervenções a fim de ter o trabalho realizado? | E13: Não | F13: =IF(E13="",0,IF(E13="Não",10,IF(E13="Parcialmente",5,0))) -> 10 | W13: Sim | X13: 0
C15: 3.4 | D15: Existem pessoas com papéis semelhantes realizando trabalhos diferentes ou realizando o mesmo trabalho de forma diferente? | E15: Parcialmente | F15: =IF(E15="",0,IF(E15="Não",10,IF(E15="Parcialmente",5,0))) -> 5 | W15: Não | X15: 10
C17: 3.5 | D17: Há ociosidade no processo? | E17: Parcialmente | F17: =IF(E17="",0,IF(E17="Não",10,IF(E17="Parcialmente",5,0))) -> 5
C19: 3.6 | D19: Existem regras de negócios definidas que cobrem os possíveis cenários decisórios ou de variação do processo? | E19: Parcialmente | F19: =IF(E19="",0,IF(E19="Ainda é precisamos fazer ajustes",0,IF(E19="Parcialmente",5,10))) -> 5
C21: 3.7 | D21: O processo tem atingido as metas determinadas? | E21: Não | F21: =IF(E21="",0,IF(E21="Sim",10,IF(E21="Parcialmente",5,0))) -> 0
C23: 3.8 | D23: Durante o processo, o trabalho ou a informação passa das mãos de um colaborador para o outro várias vezes (vai e vem)? | E23: Sim | F23: =IF(E23="",0,IF(E23="Sim",0,IF(E23="Parcialmente",5,10))) -> 0
C25: =IF(E6<>100%,"Termine o preenchimento para descobrir sua nota!","Sua nota média em processos é: "&F25) -> Termine o preenchimento para descobrir sua nota! | F25: =ROUND(AVERAGE(F23,F19,F17,F11,F13,F15,F21),1) -> 3.6

Sheet Marketing
B1: Desvendando o potencial de melhoria da sua empresa
C6: ="Percentual de conclusão: "&ROUND(E6*100,0)&"%" -> Percentual de conclusão: 100% | E6: =COUNTA(E8,E10,E12,E14,E16,E18,E20,E22,E24,E26,E28,E31,E32,E33,E34,E35,E36,E37,E38,E40,E42,E44,E46,E48,E50,E52,E54)/27 -> 1
C8: 4.1 | D8: Qual a tecnologia que seu site foi desenvolvido? | E8: Wordpress | F8: =IF(E8="",0,IF(E8="NÃO SEI",0,IF(E8="WIX",5,10))) -> 10 | M8: =IF(ISERROR(AVERAGE(#REF!)),"",(AVERAGE(#REF!)))
C10: 4.2 | D10: O Google Analytics está instalado em todas as páginas? | E10: NÃO SEI | F10: =IF(E10="SIM",10,0) -> 0
C12: 4.3 | D12: O Google Search Console está ativado? | E12: NÃO SEI | F12: =IF(E12="SIM",10,0) -> 0
C14: 4.4 | D14: Quais ferramentas utiliza para encontrar problemas de SEO (Moz, Semrush, outras…)? | E14: SemRush | F14: =IF(E14="",0,IF(E14<>"NÃO SEI",10,0)) -> 10
C16: 4.5 | D16: Qual o ranking no Alexa? Link: https://www.alexa.com/siteinfo | E16: 0 | F16: =IF(E16="",0,IF(E16<300000,10,0)) -> 10
C18: 4.6 | D18: Qual a frequência de publicação de post no seu blog por mês? (use 0 caso não tenha ou não publique) | E18: 5 | F18: =IF(E18>=4,10,IF(E18>=2,5,0)) -> 10
C20: 4.7 | D20: Quantos comentários seus posts recebem em média por mês? (use 0 caso não tenha ou não saiba) | E20: 0 | F20: =IF(E20>=4,10,IF(E20>=2,5,0)) -> 0
C22: 4.8 | D22: Quantas vezes por mês você publica vídeos no youtube? (use 0 caso não tenha ou não saiba) | E22: 0 | F22: =IF(E22>=2,10,IF(E22>=1,5,0)) -> 0
C24: 4.9 | D24: Quantas vezes por mês você publica no Facebook? (use 0 caso não tenha ou não saiba) | E24: 30 | F24: =IF(E24>=4,10,IF(E24>=2,5,0)) -> 10
C26: 4.10 | D26: Quantas vezes por mês você publica no Instagram? (use 0 caso não tenha ou não saiba) | E26: 30 | F26: =IF(E26>=4,10,IF(E26>=2,5,0)) -> 10
C28: 4.11 | D28: Quantas vezes por mês você publica no LinkedIn? (use 0 caso não tenha ou não saiba) | E28: 0 | F28: =IF(E28>=4,10,IF(E28>=2,5,0)) -> 0
C30: 4.12 | D30: Defina as etapas de seu funil com as respectivas taxas de conversão e volume (fique a vontade para alterar a sugestão abaixo:) | E30: Volume médio mensal | F30: Taxa de conversão
D31: Volume total de impressões de suas keywords (orgânico e pago) | E31: 300 | G31: =IF(E31>=10000,10,IF(E31>=5000,5,0)) -> 0
D32: Volume total de trafego (usuário único) em todas as páginas (site+blog) | E32: 300 | F32: =IF(ISERROR(E32/E31),0,E32/E31) -> 1
D33: Total de Cadastros realizados | E33: 3 | F33: =IF(ISERROR(E33/E32),0,E33/E32) -> 0.01 | G33: =IF(E33>=500,10,IF(E33>=100,5,0)) -> 0
D34: MQLs (leads não qualificados que serão aquecidos pelo marketing) | E34: 10 | F34: =IF(ISERROR(E34/E33),0,E34/E33) -> 3.3333333
D35: SQLs (leads qualificados que serão distribuídos para os vendedores) | E35: 0 | F35: =IF(ISERROR(E35/E33),0,E35/E33) -> 0
D36: Reunião Agendada | E36: 15 | F36: =IF(ISERROR(E36/E35),0,E36/E35) -> 0
D37: Análise de proposta / contrato | E37: 5 | F37: =IF(ISERROR(E37/E36),0,E37/E36) -> 0.33333333
D38: Vendas | E38: 3 | F38: =IF(ISERROR(E38/E37),0,E38/E37) -> 0.6 | G38: =IF(E38>=5,10,IF(E38>=2,5,0)) -> 5
C40: 4.13 | D40: Quantas vendas por indicação são realizadas em média por mês? | E40: 0 | F40: =IF(E40>=5,10,IF(E40>=2,5,0)) -> 0
C42: 4.14 | D42: Quais fermentas utiliza para nutrir os leads (Mailchimp, RD, LeadLovers, outras…)? | E42: Brevo | F42: =IF(E42="",0,IF(E42="NÃO SEI",0,10)) -> 10
C44: 4.15 | D44: Qual o investimento médio em Google Ads por mês? (use 0 caso não faça) | E44: 0 | F44: =IF(E44>=1500,10,IF(E44>=700,5,0)) -> 0
C46: 4.16 | D46: Qual o investimento médio em FB Ads por mês? (use 0 caso não faça) | E46: 100 | F46: =IF(E46>=750,10,IF(E46>=300,5,0)) -> 0
C48: 4.17 | D48: Qual o investimento médio em Instagram por mês? (use 0 caso não faça) | E48: 500 | F48: =IF(E48>=300,10,IF(E48>=150,5,0)) -> 10
C50: 4.18 | D50: Qual o investimento médio em LinkedIn por mês? (use 0 caso não faça) | E50: 0 | F50: =IF(E50>=1000,10,IF(E50>=500,5,0)) -> 0
C52: 4.19 | D52: Há alguma estratégia de outbound? (prospecção de leads em LinkedIn, outros canais, compra ou construção de listas) | E52: Sim | F52: =IF(E52="SIM",10,0) -> 10
C54: 4.20 | D54: Quais ferramentas utiliza na estratégia de outbound (Ramper, Reev, outras…) | E54: Redrive | F54: =IF(E54="",0,IF(E54="NÃO SEI",0,10)) -> 10
C56: =IF(E6<>100%,"Termine o preenchimento para descobrir sua nota!","Sua nota média em marketing é: "&F56) -> Sua nota média em marketing é: 4,77272727272727 | F56: =AVERAGE(F54,F52,F50,F48,F46,F44,F42,F40,G38,G33,G31,F28,F26,F24,F22,F20,F18,F16,F14,F12,F10,F8) -> 4.7727273

Sheet Vendas
B1: Desvendando o potencial de melhoria da sua empresa
C6: ="Percentual de conclusão: "&ROUND(E6*100,0)&"%" -> Percentual de conclusão: 100% | E6: =COUNTA(E8,E10,E12,E14,E16,E18,E20,E22,E26,E28,E30,E32,E34,E36,E38,E24,E40)/17 -> 1
C8: 5.1 | D8: Quais ferramentas utiliza para gerenciar o relacionamento e funil de vendas (Pipedrive, Meetime, Agendor, Moskit, RD, LeadLovers, outras…)? | E8: KOMMO | F8: =IF(E8="",0,IF(E8="NÃO SEI",0,IF(E8="Não Uso",0,10))) -> 10 | M8: =IF(ISERROR(AVERAGE(#REF!)),"",AVERAGE(#REF!)) | W8: Desconheço | X8: 10
C10: 5.2 | D10: Há alguém responsável exclusivamente por vendas na sua estrutura? | E10: Não | F10: =IF(E10="SIM",10,0) -> 0
C12: 5.3 | D12: Quantos vendedores você têm no time? (use 0 caso não tenha) | E12: 0 | F12: =IF(E12>=4,10,IF(E12>=2,5,0)) -> 0 | W12: Sim | X12: 0
C14: 5.4 | D14: Quantos pré-vendedores / qualificadores você tem no time? (use 0 caso não tenha) | E14: 0 | F14: =IF(E14>=2,10,IF(E14>=1,5,0)) -> 0 | W14: Não | X14: 10
C16: 5.5 | D16: Há uma política clara e objetiva de comissionamento? | E16: Sim | F16: =IF(E16="SIM",10,0) -> 10
C18: 5.6 | D18: As metas são conhecidas e amplamente divulgadas? | E18: Sim | F18: =IF(E18="SIM",10,0) -> 10
C20: 5.7 | D20: Há regras de bonificação para vendedores que superam as metas? | E20: Sim | F20: =IF(E20="SIM",10,0) -> 10
C22: 5.8 | D22: Você utiliza o SPIN Selling como método? | E22: Sim | F22: =IF(E22="SIM",10,0) -> 10
C24: 5.9 | D24: Você utiliza BANT framework? | E24: Não | F24: =IF(E24="SIM",10,0) -> 0
C26: 5.10 | D26: Os vendedores recebem treinamento frequente sobre os produtos / serviços que precisam vender? | E26: Não | F26: =IF(E26="SIM",10,0) -> 0
C28: 5.11 | D28: Os vendedores recebem treinamento frequente sobre técnicas e método de vendas? | E28: Sim | F28: =IF(E28="SIM",10,0) -> 10
C30: 5.12 | D30: O pitch de vendas é homogêneo? (a variação do discurso entre os vendedores é mínima) | E30: Não | F30: =IF(E30="SIM",10,0) -> 0 | W30: z
C32: 5.13 | D32: Qual ferramenta você utiliza para gerenciar / gravar os atendimentos dos vendedores (Meetime, Skype, outras…) | E32: Google Meet | F32: =IF(E32="",0,IF(E32="NÃO SEI",0,IF(E32="Não Uso",0,10))) -> 10
C34: 5.14 | D34: Qual ferramenta você utiliza para enviar e monitorar propostas (Proposeful, Docsales, outras…) | E34: Não Uso | F34: =IF(E34="",0,IF(E34="NÃO SEI",0,IF(E34="Não Uso",0,10))) -> 0
C36: 5.15 | D36: As regras de preço, desconto e negociação estão pré definidas? | E36: Não | F36: =IF(E36="SIM",10,0) -> 0
C38: 5.16 | D38: Os preços foram definidos com base em um método objetivo? (com base em custeio; com base em margem de contribuição; etc.) | E38: Não | F38: =IF(E38="SIM",10,0) -> 0
C40: 5.17 | D40: As margens de contribuição e lucro são conhecidas com exatidão? | E40: Não | F40: =IF(E40="SIM",10,0) -> 0
C42: =IF(E6<>100%,"Termine o preenchimento para descobrir sua nota!","Sua nota média em vendas é: "&F42) -> Sua nota média em vendas é: 4,1 | F42: =ROUND(AVERAGE(F40,F24,F38,F36,F34,F32,F30,F28,F26,F22,F20,F18,F16,F14,F12,F10,F8),1) -> 4.1

Sheet Operação
B1: Desvendando o potencial de melhoria da sua empresa
C6: ="Percentual de conclusão: "&ROUND(E6*100,0)&"%" -> Percentual de conclusão: 100% | E6: =COUNTA(E8,E10,E12,E14,E16,E18,E20,E22,C25,E27,E29)/11 -> 1
C8: 6.1 | D8: O Conhecimento de execução do seu produto ou serviço é centralizado em poucos profissionais ou disseminado entre todos? | E8: Centralizado | F8: =IF(E8="",0,IF(E8="centralizado",0,10)) -> 0
C10: 6.2 | D10: Qual o prazo médio de duração do serviço? | E10: 4 | F10: =IF(E10="SIM",10,0) -> 0
C12: 6.3 | D12: A empresa possui procedimentos documentados para os processos operacionais? | E12: Não | F12: =IF(E12="SIM",10,0) -> 0
C14: 6.4 | D14: Existe rastreabilidade da sua operação? | E14: Sim | F14: =IF(E14="SIM",10,0) -> 10
C16: 6.5 | D16: O controle de estoque é realizado de forma manual? | E16: Não | F16: =IF(E16="",0,IF(E16="SIM",0,10)) -> 10
C18: 6.6 | D18: Qual é o software utilizado em sua operação? | E18: Monday | F18: =IF(E18="Não uso",0,10) -> 10
C20: 6.7 | D20: Ainda existem falhas na sua operação que são encontradas somente pelo cliente? | E20: Sim | F20: =IF(E20="SIM",0,10) -> 0
C22: 6.8 | D22: Vocês controlam as falhas da operação? | E22: Sim | F22: =IF(E22="SIM",10,0) -> 10
T23: 1% a 10% | U23: 10
C24: 6.9 | D24: Resumir modelo de operação atual (descreva como funciona o dia a dia da sua operação)
C25: nao
C27: 6.10 | D27: Quais ferramenta vocês utilizam durante a operação para gerenciar o andamento do processo (Pipefy, Excel, Trello, Asana, outras…) | E27: Monday | F27: =IF(E27="",0,IF(E27="evolutto",10,IF(E27="NÃO SEI",0,IF(E27="Não Uso",0,5)))) -> 5
C29: 6.11 | D29: A infraestrutura de operação está adequada para as necessidades da empresa? | E29: Não | F29: =IF(E29="SIM",10,0) -> 0
C31: =IF(E6<>100%,"Termine o preenchimento para descobrir sua nota!","Sua nota média em atendimento é: "&F31) -> Sua nota média em atendimento é: 5 | F31: =ROUND(AVERAGE(F29,F27,F22,F20,F18,F16,F14,F12,F8),1) -> 5

Sheet Gestão de Pessoas
B1: Desvendando o potencial de melhoria da sua empresa
C6: ="Percentual de conclusão: "&ROUND(E6*100,0)&"%" -> Percentual de conclusão: 100% | E6: =COUNTA(E26,E16,E14,E12,E10,E8,E18,E20,E22,E24)/10 -> 1
C8: 7.1 | D8: A empresa já aplicou algum método para identificar o perfil comportamental de seus colaboradores (DISC, ISTJ, etc...)? | E8: Sim | F8: =IF(E8="SIM",10,0) -> 10
C10: 7.2 | D10: A empresa realiza avaliação de desempenho dos colaboradores? | E10: Sim | F10: =IF(E10="SIM",10,0) -> 10
C12: 7.3 | D12: A empresa possui alguma estratégia de desenvolvimento dos colaboradores? | E12: Não | F12: =IF(E12="SIM",10,0) -> 0
C14: 7.4 | D14: A empresa sabe qual é o índice de rotatividade e absenteísmo? | E14: Não | F14: =IF(E14="SIM",10,0) -> 0
C16: 7.5 | D16: A empresa possui alguma estratégia de learning organization? | E16: Não | F16: =IF(E16="",0,IF(E16="SIM",10,0)) -> 0
C18: 7.6 | D18: A empresa possui processo formal de feedback ou feedfoward? | E18: Sim | F18: =IF(E18="",0,IF(E18="SIM",10,0)) -> 10
C20: 7.7 | D20: A empresa realiza pesquisas de satisfação interna ou de clima organzacional? | E20: Não | F20: =IF(E20="",0,IF(E20="SIM",10,0)) -> 0
C22: 7.8 | D22: Os resultados encontrados nas pesquisas são tratados de forma eficiente? | E22: Não | F22: =IF(E22="",0,IF(E22="SIM",10,0)) -> 0
C24: 7.9 | D24: A empresa mantém programas de bem-estar ou wellness para os colaboradores? | E24: Não | F24: =IF(E24="",0,IF(E24="SIM",10,0)) -> 0
C26: 7.10 | D26: A empresa incentiva a boa convivência entre os colaboradores? | E26: Sim | F26: =IF(E26="SIM",10,0) -> 10
C29: =IF(E6<>100%,"Termine o preenchimento para descobrir sua nota!","Sua nota média em gestão é: "&F29) -> Sua nota média em gestão é: 4 | F29: =ROUND(AVERAGE(F8,F10,F12,F14,F16,F26,F18,F20,F22,F24),1) -> 4

Sheet Gestão
B1: Desvendando o potencial de melhoria da sua empresa
C6: ="Percentual de conclusão: "&ROUND(E6*100,0)&"%" -> Percentual de conclusão: 100% | E6: =COUNTA(E26,E16,E14,E12,E10,E8,E18,E20,E22,E24)/10 -> 1
C8: 8.1 | D8: Quantas pessoas trabalham no administrativo (Departamento Pessoal, Contas a Pagar, Receber, etc..)? | E8: 1 | F8: =IF(E8>0,10,0) -> 10
C10: 8.2 | D10: O faturamento (venda e emissão de boletos ou processamento de cartões) é automatizado? | E10: Não | F10: =IF(E10="SIM",10,0) -> 0
C12: 8.3 | D12: A empresa se enquadra em que regime: (MEI, Simples, Lucro real, Lucro presumido) | E12: MEI | F12: =IF(E12="",0,IF(E12="MEI",5,IF(E12="NÃO SEI",0,10))) -> 5
C14: 8.4 | D14: A emissão de Nota Fiscal é automatizada? | E14: Não | F14: =IF(E14="SIM",10,0) -> 0
C16: 8.5 | D16: A sua empresa segue o planejamento estratégico definido? | E16: Não | F16: =IF(E16="",0,IF(E16="SIM",10,0)) -> 0
C18: 8.6 | D18: A sua empresa é lucrativa? | E18: Sim | F18: =IF(E18="",0,IF(E18="SIM",10,0)) -> 10
C20: 8.7 | D20: A sua empresa possui objetivos estratégicos, táticos e operacionais definidos e coerentes com o planejamento estratégico? | E20: Não | F20: =IF(E20="",0,IF(E20="SIM",10,0)) -> 0
C22: 8.8 | D22: As metas são alcançadas consistentemente? | E22: Não | F22: =IF(E22="",0,IF(E22="SIM",10,0)) -> 0
C24: 8.9 | D24: As pessoas trabalham felizes na sua empresa? | E24: Não | F24: =IF(E24="",0,IF(E24="SIM",10,0)) -> 0
C26: 8.10 | D26: Sua empresa funcionaria bem se você se afastasse por 30 dias seguidos? | E26: Não | F26: =IF(E26="SIM",10,0) -> 0
C29: =IF(E6<>100%,"Termine o preenchimento para descobrir sua nota!","Sua nota média em gestão é: "&F29) -> Sua nota média em gestão é: 2,5 | F29: =ROUND(AVERAGE(F8,F10,F12,F14,F16,F26,F18,F20,F22,F24),1) -> 2.5

Sheet Resultado
B1: Desvendando o potencial de melhoria da sua empresa
B12: Nota Geral | H12: Pontos Fortes / Pontos Fracos
AE13: Levantamento Inicial | AF13: ='Levantamento inicial'!F23 -> 0 | AJ13: Indicador | AK13: =AF22/10 -> 0.29180195 | AM13: Partes do Velocímetro | AN13: Coseno(x) | AO13: Seno(y)
AE14: Mercado | AF14: =Mercado!F34 -> 3.8 | AM14: 10 | AN14: 0 | AO14: 0
AE15: Marketing | AF15: =Marketing!F56 -> 4.7727273 | AM15: 10 | AN15: =-COS(PI()*AK13/AM25*100) -> -0.6084242 | AO15: =SIN(PI()*AK13/AM25*100) -> 0.79361199
AE16: Vendas | AF16: =Vendas!F42 -> 4.1 | AM16: 10
AE17: Operação | AF17: ='Operação'!F30 | AM17: 10
AE18: Gestão de Pessoas | AF18: ='Gestão de Pessoas'!F29 -> 4 | AM18: 10
AE19: Gestão | AF19: ='Gestão'!F29 -> 2.5 | AM19: 10
AE20: Tranformação Digital | AF20: =AF36 -> 0.57142857
AE21: Processos | AF21: =Processos!F25 -> 3.6 | AM21: 10
AF22: =AVERAGE(AF13:AF21) -> 2.9180195 | AM22: 10
AM23: 10
AM24: 10
E25: Transformação Digital | AM25: 100
AF29: ='Levantamento inicial'!F20 -> 0
AF30: =Marketing!F8 -> 10
AF31: =Vendas!F8 -> 10
AF32: ='Operação'!F18 -> 10
AF33: ='Operação'!F16 -> 10
AF34: ='Gestão'!F10 -> 0
AF35: ='Gestão'!F14 -> 0
AF36: =(AF29+AF30+AF31+AF32+AF33+AF34+AF35)/70 -> 0.57142857
