Workbook

Sheet Início
C1: ANÁLISE SWOT ORGANIZACIONAL
C3: Com esta planilha você conseguirá fazer uma Análise SWOT Organizacional de acordo com os seus objetivos a curto prazo. Coloque detalhadamente os fatores internos (forças e fraquezas) e fatores externos (oportunidades e ameaças) quanto a gestão de seu negócio/ projeto para extrair as melhores e maiores reflexões possíveis.
B4: IMPORTANTE: LEIA OS PASSOS E ENTENDA A PLANILHA
C6: Passo 1 | E6: CADASTROS
C7: Cadastre os seus objetivos para seu negócio ou projeto a curto prazo. Descreva os objetivos de acordo com o planejamento estabelecido a curto prazo.
C11: Passo 2 | E11: FATORES INTERNOS
C12: Segundo a metodologia da análise SWOT a matriz é composta por elementos que compõem o ambiente interno e externo da empresa
C14: 1.1. Forças: defina a lista com as suas forças, o que faz com que os clientes optem por seu negócio; qual disponibilidade de recursos imprescindíveis para a manutenção dos serviços ou produtos; o que diferencia seu negócio dos demais.
C15: 1.2. Fraquezas: defina a lista com as suas fraquezas (altos custos com transporte; maiores gastos com a manutenção de equipamentos, colaboradores com valor/hora mais caro etc.).
C20: Passo 3 | E20: FATORES EXTERNOS
C21: Após ter definido os fatores internos, defina os seus fatores externos: oportunidades e ameaças.
C23: 2.1. Oportunidades: defina a lista com as oportunidades (fatores econômicos, oportunidades que estão surgindo e mudanças do mercado que podem favorecer seus clientes).
C24: 2.2. Ameaças: defina a lista com as ameaças identificadas no mercado (cenário no qual se concentram todos os fatores desfavoráveis para a empresa). Assim, além da ausência de controle sobre as questões, elas se apresentam como grandes ameaças para o negócio.
C29: Passo 4 | E29: MATRIZ SWOT
C30: Nesta parte da planilha será possível visualizar a visão geral da sua pontuação para as forças, fraquezas, oportunidades e ameaças. A partir desta visão, você terá o retorno da planilha sobre o seu momento profissional atual (desenvolvimento, manutenção, crescimento e sobrevivência). Além dos indicadores, veja também a lista com todas as forças, fraquezas, ameaças e oportunidades hierarquizadas, de acordo com sua pontuação.
C37: Passo 5 | E37: CRUZAMENTOS
C39: Uma vez definido seus fatores internos e externos, chegou a hora de cruzar os dados combinando suas forças e fraquezas com ameças e oportunidades. Você pode traçar planos de ação para as combinações.
C42: Passo 6 | E42: PLANOS DE AÇÃO
C43: Crie planos de ação de acordo com os principais itens da Análise SWOT e dos Cruzamentos feitas para obter grandes melhorias no curte e longo prazos.
C47: Passo 7 | E47: RESULTADOS SWOT
C48: Veja os resultados da SWOT como Índice de Favorabilidade, Análise Individual dos Fatores Internos e Externose gráficos da Matriz SWOT.
C52: Passo 8 | E52: RESULTADOS PLANOS DE AÇÃO
C53: Veja os resultados dos seus planos de ação graficamente.
C55: 8.1. Gráficos: gráficos de desenvolvimento de planos de ação, status e conformidade dos planos em execução.
C56: 8.2. Análise por Área: veja a análise geral em relação aos planos de ação com cada status e o desempenho geral delas.
C59: Passo 9 | E59: RELATÓRIO DE IMPRESSÃO
C60: Imprima somente o que importa. Esta parte gera um relatório formatado para impressão em 7 páginas A4 com seu plano de ação para todas as combinações entre forças, fraquezas, oportunidades e ameaças. Além disso, tenha os gráficos, a lista hierarquizada, o ínidice de favorabilidade e as dicas.

Sheet Forças
C1: 2. FATORES INTERNOS
C4: Item | D4: Importância | E4: Intensidade | F4: Tendência | G4: Pontuação | S4: 1 | T4: 1 | U4: 1 | V4: 1 | W4: 2 | X4: 2 | Y4: 2 | Z4: 2 | AA4: 2 | AB4: 2 | AC4: 2 | AD4: 2 | AE4: 2 | AF4: 2 | AG4: 2 | AH4: 2 | AI4: 3 | AJ4: 3 | AK4: 3 | AL4: 3 | AM4: 3 | AN4: 3 | AO4: 3 | AP4: 3 | AQ4: 3 | AR4: 3 | AS4: 3 | AT4: 3
C5: Ex.: A marca é reconhecida no mercado | D5: Ex.: Importante | E5: Ex.: Média | F5: Ex.: Mantém | G5: Ex.: 27
G6: =IF(ISERROR(VLOOKUP(D6,$I$8:$J$12,2,FALSE)*VLOOKUP(E6,$I$16:$J$20,2,FALSE)*VLOOKUP(F6,$I$24:$J$28,2,FALSE)),"",VLOOKUP(D6,$I$8:$J$12,2,FALSE)*VLOOKUP(E6,$I$16:$J$20,2,FALSE)*VLOOKUP(F6,$I$24:$J$28,2,FALSE)) | I6: Importância | L6: 0.0002 | M6: =IF(G6="","",G6+L6) | N6: =IF(C6=0,"",C6) | O6: =G6
G7: =IF(ISERROR(VLOOKUP(D7,$I$8:$J$12,2,FALSE)*VLOOKUP(E7,$I$16:$J$20,2,FALSE)*VLOOKUP(F7,$I$24:$J$28,2,FALSE)),"",VLOOKUP(D7,$I$8:$J$12,2,FALSE)*VLOOKUP(E7,$I$16:$J$20,2,FALSE)*VLOOKUP(F7,$I$24:$J$28,2,FALSE)) | L7: 0.00019 | M7: =IF(G7="","",G7+L7) | N7: =IF(C7=0,"",C7) | O7: =G7
G8: =IF(ISERROR(VLOOKUP(D8,$I$8:$J$12,2,FALSE)*VLOOKUP(E8,$I$16:$J$20,2,FALSE)*VLOOKUP(F8,$I$24:$J$28,2,FALSE)),"",VLOOKUP(D8,$I$8:$J$12,2,FALSE)*VLOOKUP(E8,$I$16:$J$20,2,FALSE)*VLOOKUP(F8,$I$24:$J$28,2,FALSE)) | I8: Sem importância | J8: 1 | L8: 0.00018 | M8: =IF(G8="","",G8+L8) | N8: =IF(C8=0,"",C8) | O8: =G8
G9: =IF(ISERROR(VLOOKUP(D9,$I$8:$J$12,2,FALSE)*VLOOKUP(E9,$I$16:$J$20,2,FALSE)*VLOOKUP(F9,$I$24:$J$28,2,FALSE)),"",VLOOKUP(D9,$I$8:$J$12,2,FALSE)*VLOOKUP(E9,$I$16:$J$20,2,FALSE)*VLOOKUP(F9,$I$24:$J$28,2,FALSE)) | I9: Pouco importante | J9: 2 | L9: 0.00017 | M9: =IF(G9="","",G9+L9) | N9: =IF(C9=0,"",C9) | O9: =G9
G10: =IF(ISERROR(VLOOKUP(D10,$I$8:$J$12,2,FALSE)*VLOOKUP(E10,$I$16:$J$20,2,FALSE)*VLOOKUP(F10,$I$24:$J$28,2,FALSE)),"",VLOOKUP(D10,$I$8:$J$12,2,FALSE)*VLOOKUP(E10,$I$16:$J$20,2,FALSE)*VLOOKUP(F10,$I$24:$J$28,2,FALSE)) | I10: Importante | J10: 3 | L10: 0.00016 | M10: =IF(G10="","",G10+L10) | N10: =IF(C10=0,"",C10) | O10: =G10
G11: =IF(ISERROR(VLOOKUP(D11,$I$8:$J$12,2,FALSE)*VLOOKUP(E11,$I$16:$J$20,2,FALSE)*VLOOKUP(F11,$I$24:$J$28,2,FALSE)),"",VLOOKUP(D11,$I$8:$J$12,2,FALSE)*VLOOKUP(E11,$I$16:$J$20,2,FALSE)*VLOOKUP(F11,$I$24:$J$28,2,FALSE)) | I11: Muito importante | J11: 4 | L11: 0.00015 | M11: =IF(G11="","",G11+L11) | N11: =IF(C11=0,"",C11) | O11: =G11
G12: =IF(ISERROR(VLOOKUP(D12,$I$8:$J$12,2,FALSE)*VLOOKUP(E12,$I$16:$J$20,2,FALSE)*VLOOKUP(F12,$I$24:$J$28,2,FALSE)),"",VLOOKUP(D12,$I$8:$J$12,2,FALSE)*VLOOKUP(E12,$I$16:$J$20,2,FALSE)*VLOOKUP(F12,$I$24:$J$28,2,FALSE)) | I12: Totalmente importante | J12: 5 | L12: 0.00014 | M12: =IF(G12="","",G12+L12) | N12: =IF(C12=0,"",C12) | O12: =G12
G13: =IF(ISERROR(VLOOKUP(D13,$I$8:$J$12,2,FALSE)*VLOOKUP(E13,$I$16:$J$20,2,FALSE)*VLOOKUP(F13,$I$24:$J$28,2,FALSE)),"",VLOOKUP(D13,$I$8:$J$12,2,FALSE)*VLOOKUP(E13,$I$16:$J$20,2,FALSE)*VLOOKUP(F13,$I$24:$J$28,2,FALSE)) | L13: 0.00013 | M13: =IF(G13="","",G13+L13) | N13: =IF(C13=0,"",C13) | O13: =G13
G14: =IF(ISERROR(VLOOKUP(D14,$I$8:$J$12,2,FALSE)*VLOOKUP(E14,$I$16:$J$20,2,FALSE)*VLOOKUP(F14,$I$24:$J$28,2,FALSE)),"",VLOOKUP(D14,$I$8:$J$12,2,FALSE)*VLOOKUP(E14,$I$16:$J$20,2,FALSE)*VLOOKUP(F14,$I$24:$J$28,2,FALSE)) | I14: Intensidade | L14: 0.00012 | M14: =IF(G14="","",G14+L14) | N14: =IF(C14=0,"",C14) | O14: =G14
G15: =IF(ISERROR(VLOOKUP(D15,$I$8:$J$12,2,FALSE)*VLOOKUP(E15,$I$16:$J$20,2,FALSE)*VLOOKUP(F15,$I$24:$J$28,2,FALSE)),"",VLOOKUP(D15,$I$8:$J$12,2,FALSE)*VLOOKUP(E15,$I$16:$J$20,2,FALSE)*VLOOKUP(F15,$I$24:$J$28,2,FALSE)) | L15: 0.00011 | M15: =IF(G15="","",G15+L15) | N15: =IF(C15=0,"",C15) | O15: =G15
G16: =IF(ISERROR(VLOOKUP(D16,$I$8:$J$12,2,FALSE)*VLOOKUP(E16,$I$16:$J$20,2,FALSE)*VLOOKUP(F16,$I$24:$J$28,2,FALSE)),"",VLOOKUP(D16,$I$8:$J$12,2,FALSE)*VLOOKUP(E16,$I$16:$J$20,2,FALSE)*VLOOKUP(F16,$I$24:$J$28,2,FALSE)) | I16: Muito forte | J16: 5 | L16: 0.0001 | M16: =IF(G16="","",G16+L16) | N16: =IF(C16=0,"",C16) | O16: =G16
G17: =IF(ISERROR(VLOOKUP(D17,$I$8:$J$12,2,FALSE)*VLOOKUP(E17,$I$16:$J$20,2,FALSE)*VLOOKUP(F17,$I$24:$J$28,2,FALSE)),"",VLOOKUP(D17,$I$8:$J$12,2,FALSE)*VLOOKUP(E17,$I$16:$J$20,2,FALSE)*VLOOKUP(F17,$I$24:$J$28,2,FALSE)) | I17: Forte | J17: 4 | L17: 9e-05 | M17: =IF(G17="","",G17+L17) | N17: =IF(C17=0,"",C17) | O17: =G17
G18: =IF(ISERROR(VLOOKUP(D18,$I$8:$J$12,2,FALSE)*VLOOKUP(E18,$I$16:$J$20,2,FALSE)*VLOOKUP(F18,$I$24:$J$28,2,FALSE)),"",VLOOKUP(D18,$I$8:$J$12,2,FALSE)*VLOOKUP(E18,$I$16:$J$20,2,FALSE)*VLOOKUP(F18,$I$24:$J$28,2,FALSE)) | I18: Média | J18: 3 | L18: 8e-05 | M18: =IF(G18="","",G18+L18) | N18: =IF(C18=0,"",C18) | O18: =G18
G19: =IF(ISERROR(VLOOKUP(D19,$I$8:$J$12,2,FALSE)*VLOOKUP(E19,$I$16:$J$20,2,FALSE)*VLOOKUP(F19,$I$24:$J$28,2,FALSE)),"",VLOOKUP(D19,$I$8:$J$12,2,FALSE)*VLOOKUP(E19,$I$16:$J$20,2,FALSE)*VLOOKUP(F19,$I$24:$J$28,2,FALSE)) | I19: Fraca | J19: 2 | L19: 7e-05 | M19: =IF(G19="","",G19+L19) | N19: =IF(C19=0,"",C19) | O19: =G19
G20: =IF(ISERROR(VLOOKUP(D20,$I$8:$J$12,2,FALSE)*VLOOKUP(E20,$I$16:$J$20,2,FALSE)*VLOOKUP(F20,$I$24:$J$28,2,FALSE)),"",VLOOKUP(D20,$I$8:$J$12,2,FALSE)*VLOOKUP(E20,$I$16:$J$20,2,FALSE)*VLOOKUP(F20,$I$24:$J$28,2,FALSE)) | I20: Muito fraca | J20: 1 | L20: 6e-05 | M20: =IF(G20="","",G20+L20) | N20: =IF(C20=0,"",C20) | O20: =G20
G21: =IF(ISERROR(VLOOKUP(D21,$I$8:$J$12,2,FALSE)*VLOOKUP(E21,$I$16:$J$20,2,FALSE)*VLOOKUP(F21,$I$24:$J$28,2,FALSE)),"",VLOOKUP(D21,$I$8:$J$12,2,FALSE)*VLOOKUP(E21,$I$16:$J$20,2,FALSE)*VLOOKUP(F21,$I$24:$J$28,2,FALSE)) | L21: 5e-05 | M21: =IF(G21="","",G21+L21) | N21: =IF(C21=0,"",C21) | O21: =G21
G22: =IF(ISERROR(VLOOKUP(D22,$I$8:$J$12,2,FALSE)*VLOOKUP(E22,$I$16:$J$20,2,FALSE)*VLOOKUP(F22,$I$24:$J$28,2,FALSE)),"",VLOOKUP(D22,$I$8:$J$12,2,FALSE)*VLOOKUP(E22,$I$16:$J$20,2,FALSE)*VLOOKUP(F22,$I$24:$J$28,2,FALSE)) | I22: Tendência | L22: 4e-05 | M22: =IF(G22="","",G22+L22) | N22: =IF(C22=0,"",C22) | O22: =G22
G23: =IF(ISERROR(VLOOKUP(D23,$I$8:$J$12,2,FALSE)*VLOOKUP(E23,$I$16:$J$20,2,FALSE)*VLOOKUP(F23,$I$24:$J$28,2,FALSE)),"",VLOOKUP(D23,$I$8:$J$12,2,FALSE)*VLOOKUP(E23,$I$16:$J$20,2,FALSE)*VLOOKUP(F23,$I$24:$J$28,2,FALSE)) | L23: 3e-05 | M23: =IF(G23="","",G23+L23) | N23: =IF(C23=0,"",C23) | O23: =G23
G24: =IF(ISERROR(VLOOKUP(D24,$I$8:$J$12,2,FALSE)*VLOOKUP(E24,$I$16:$J$20,2,FALSE)*VLOOKUP(F24,$I$24:$J$28,2,FALSE)),"",VLOOKUP(D24,$I$8:$J$12,2,FALSE)*VLOOKUP(E24,$I$16:$J$20,2,FALSE)*VLOOKUP(F24,$I$24:$J$28,2,FALSE)) | I24: Melhora muito | J24: 5 | L24: 2e-05 | M24: =IF(G24="","",G24+L24) | N24: =IF(C24=0,"",C24) | O24: =G24
G25: =IF(ISERROR(VLOOKUP(D25,$I$8:$J$12,2,FALSE)*VLOOKUP(E25,$I$16:$J$20,2,FALSE)*VLOOKUP(F25,$I$24:$J$28,2,FALSE)),"",VLOOKUP(D25,$I$8:$J$12,2,FALSE)*VLOOKUP(E25,$I$16:$J$20,2,FALSE)*VLOOKUP(F25,$I$24:$J$28,2,FALSE)) | I25: Melhora | J25: 4 | L25: 1e-05 | M25: =IF(G25="","",G25+L25) | N25: =IF(C25=0,"",C25) | O25: =G25
C26: Pontuação geral das suas Forças | F26: → | G26: =SUM(G6:G25) -> 0 | I26: Mantém | J26: 3
I27: Piora | J27: 2
I28: Piora muito | J28: 1

Sheet Fraquezas
C1: 2. FATORES INTERNOS
C4: Item | D4: Importância | E4: Intensidade | F4: Tendência | G4: Pontuação | S4: 1 | T4: 1 | U4: 1 | V4: 1 | W4: 2 | X4: 2 | Y4: 2 | Z4: 2 | AA4: 2 | AB4: 2 | AC4: 2 | AD4: 2 | AE4: 2 | AF4: 2 | AG4: 2 | AH4: 2 | AI4: 3 | AJ4: 3 | AK4: 3 | AL4: 3 | AM4: 3 | AN4: 3 | AO4: 3 | AP4: 3 | AQ4: 3 | AR4: 3 | AS4: 3 | AT4: 3
C5: Ex.: A marca é reconhecida no mercado | D5: Ex.: Importante | E5: Ex.: Média | F5: Ex.: Mantém | G5: Ex.: 27
G6: =IF(ISERROR(VLOOKUP(D6,$I$8:$J$12,2,FALSE)*VLOOKUP(E6,$I$16:$J$20,2,FALSE)*VLOOKUP(F6,$I$24:$J$28,2,FALSE)),"",VLOOKUP(D6,$I$8:$J$12,2,FALSE)*VLOOKUP(E6,$I$16:$J$20,2,FALSE)*VLOOKUP(F6,$I$24:$J$28,2,FALSE)) | I6: Importância | L6: 0.0002 | M6: =IF(G6="","",G6+L6) | N6: =IF(C6=0,"",C6) | O6: =G6
G7: =IF(ISERROR(VLOOKUP(D7,$I$8:$J$12,2,FALSE)*VLOOKUP(E7,$I$16:$J$20,2,FALSE)*VLOOKUP(F7,$I$24:$J$28,2,FALSE)),"",VLOOKUP(D7,$I$8:$J$12,2,FALSE)*VLOOKUP(E7,$I$16:$J$20,2,FALSE)*VLOOKUP(F7,$I$24:$J$28,2,FALSE)) | L7: 0.00019 | M7: =IF(G7="","",G7+L7) | N7: =IF(C7=0,"",C7) | O7: =G7
G8: =IF(ISERROR(VLOOKUP(D8,$I$8:$J$12,2,FALSE)*VLOOKUP(E8,$I$16:$J$20,2,FALSE)*VLOOKUP(F8,$I$24:$J$28,2,FALSE)),"",VLOOKUP(D8,$I$8:$J$12,2,FALSE)*VLOOKUP(E8,$I$16:$J$20,2,FALSE)*VLOOKUP(F8,$I$24:$J$28,2,FALSE)) | I8: Sem importância | J8: 1 | L8: 0.00018 | M8: =IF(G8="","",G8+L8) | N8: =IF(C11=0,"",C11) | O8: =G8
G9: =IF(ISERROR(VLOOKUP(D9,$I$8:$J$12,2,FALSE)*VLOOKUP(E9,$I$16:$J$20,2,FALSE)*VLOOKUP(F9,$I$24:$J$28,2,FALSE)),"",VLOOKUP(D9,$I$8:$J$12,2,FALSE)*VLOOKUP(E9,$I$16:$J$20,2,FALSE)*VLOOKUP(F9,$I$24:$J$28,2,FALSE)) | I9: Pouco importante | J9: 2 | L9: 0.00017 | M9: =IF(G9="","",G9+L9) | N9: =IF(C12=0,"",C12) | O9: =G9
G10: =IF(ISERROR(VLOOKUP(D10,$I$8:$J$12,2,FALSE)*VLOOKUP(E10,$I$16:$J$20,2,FALSE)*VLOOKUP(F10,$I$24:$J$28,2,FALSE)),"",VLOOKUP(D10,$I$8:$J$12,2,FALSE)*VLOOKUP(E10,$I$16:$J$20,2,FALSE)*VLOOKUP(F10,$I$24:$J$28,2,FALSE)) | I10: Importante | J10: 3 | L10: 0.00016 | M10: =IF(G10="","",G10+L10) | N10: =IF(C13=0,"",C13) | O10: =G10
G11: =IF(ISERROR(VLOOKUP(D11,$I$8:$J$12,2,FALSE)*VLOOKUP(E11,$I$16:$J$20,2,FALSE)*VLOOKUP(F11,$I$24:$J$28,2,FALSE)),"",VLOOKUP(D11,$I$8:$J$12,2,FALSE)*VLOOKUP(E11,$I$16:$J$20,2,FALSE)*VLOOKUP(F11,$I$24:$J$28,2,FALSE)) | I11: Muito importante | J11: 4 | L11: 0.00015 | M11: =IF(G11="","",G11+L11) | N11: =IF(C14=0,"",C14) | O11: =G11
G12: =IF(ISERROR(VLOOKUP(D12,$I$8:$J$12,2,FALSE)*VLOOKUP(E12,$I$16:$J$20,2,FALSE)*VLOOKUP(F12,$I$24:$J$28,2,FALSE)),"",VLOOKUP(D12,$I$8:$J$12,2,FALSE)*VLOOKUP(E12,$I$16:$J$20,2,FALSE)*VLOOKUP(F12,$I$24:$J$28,2,FALSE)) | I12: Totalmente importante | J12: 5 | L12: 0.00014 | M12: =IF(G12="","",G12+L12) | N12: =IF(C15=0,"",C15) | O12: =G12
G13: =IF(ISERROR(VLOOKUP(D13,$I$8:$J$12,2,FALSE)*VLOOKUP(E13,$I$16:$J$20,2,FALSE)*VLOOKUP(F13,$I$24:$J$28,2,FALSE)),"",VLOOKUP(D13,$I$8:$J$12,2,FALSE)*VLOOKUP(E13,$I$16:$J$20,2,FALSE)*VLOOKUP(F13,$I$24:$J$28,2,FALSE)) | L13: 0.00013 | M13: =IF(G13="","",G13+L13) | N13: =IF(C16=0,"",C16) | O13: =G13
G14: =IF(ISERROR(VLOOKUP(D14,$I$8:$J$12,2,FALSE)*VLOOKUP(E14,$I$16:$J$20,2,FALSE)*VLOOKUP(F14,$I$24:$J$28,2,FALSE)),"",VLOOKUP(D14,$I$8:$J$12,2,FALSE)*VLOOKUP(E14,$I$16:$J$20,2,FALSE)*VLOOKUP(F14,$I$24:$J$28,2,FALSE)) | I14: Intensidade | L14: 0.00012 | M14: =IF(G14="","",G14+L14) | N14: =IF(C17=0,"",C17) | O14: =G14
G15: =IF(ISERROR(VLOOKUP(D15,$I$8:$J$12,2,FALSE)*VLOOKUP(E15,$I$16:$J$20,2,FALSE)*VLOOKUP(F15,$I$24:$J$28,2,FALSE)),"",VLOOKUP(D15,$I$8:$J$12,2,FALSE)*VLOOKUP(E15,$I$16:$J$20,2,FALSE)*VLOOKUP(F15,$I$24:$J$28,2,FALSE)) | L15: 0.00011 | M15: =IF(G15="","",G15+L15) | N15: =IF(C18=0,"",C18) | O15: =G15
G16: =IF(ISERROR(VLOOKUP(D16,$I$8:$J$12,2,FALSE)*VLOOKUP(E16,$I$16:$J$20,2,FALSE)*VLOOKUP(F16,$I$24:$J$28,2,FALSE)),"",VLOOKUP(D16,$I$8:$J$12,2,FALSE)*VLOOKUP(E16,$I$16:$J$20,2,FALSE)*VLOOKUP(F16,$I$24:$J$28,2,FALSE)) | I16: Muito forte | J16: 1 | L16: 0.0001 | M16: =IF(G16="","",G16+L16) | N16: =IF(C19=0,"",C19) | O16: =G16
G17: =IF(ISERROR(VLOOKUP(D17,$I$8:$J$12,2,FALSE)*VLOOKUP(E17,$I$16:$J$20,2,FALSE)*VLOOKUP(F17,$I$24:$J$28,2,FALSE)),"",VLOOKUP(D17,$I$8:$J$12,2,FALSE)*VLOOKUP(E17,$I$16:$J$20,2,FALSE)*VLOOKUP(F17,$I$24:$J$28,2,FALSE)) | I17: Forte | J17: 2 | L17: 9e-05 | M17: =IF(G17="","",G17+L17) | N17: =IF(C20=0,"",C20) | O17: =G17
G18: =IF(ISERROR(VLOOKUP(D18,$I$8:$J$12,2,FALSE)*VLOOKUP(E18,$I$16:$J$20,2,FALSE)*VLOOKUP(F18,$I$24:$J$28,2,FALSE)),"",VLOOKUP(D18,$I$8:$J$12,2,FALSE)*VLOOKUP(E18,$I$16:$J$20,2,FALSE)*VLOOKUP(F18,$I$24:$J$28,2,FALSE)) | I18: Média | J18: 3 | L18: 8e-05 | M18: =IF(G18="","",G18+L18) | N18: =IF(C21=0,"",C21) | O18: =G18
G19: =IF(ISERROR(VLOOKUP(D19,$I$8:$J$12,2,FALSE)*VLOOKUP(E19,$I$16:$J$20,2,FALSE)*VLOOKUP(F19,$I$24:$J$28,2,FALSE)),"",VLOOKUP(D19,$I$8:$J$12,2,FALSE)*VLOOKUP(E19,$I$16:$J$20,2,FALSE)*VLOOKUP(F19,$I$24:$J$28,2,FALSE)) | I19: Fraca | J19: 4 | L19: 7e-05 | M19: =IF(G19="","",G19+L19) | N19: =IF(C22=0,"",C22) | O19: =G19
G20: =IF(ISERROR(VLOOKUP(D20,$I$8:$J$12,2,FALSE)*VLOOKUP(E20,$I$16:$J$20,2,FALSE)*VLOOKUP(F20,$I$24:$J$28,2,FALSE)),"",VLOOKUP(D20,$I$8:$J$12,2,FALSE)*VLOOKUP(E20,$I$16:$J$20,2,FALSE)*VLOOKUP(F20,$I$24:$J$28,2,FALSE)) | I20: Muito fraca | J20: 5 | L20: 6e-05 | M20: =IF(G20="","",G20+L20) | N20: =IF(C23=0,"",C23) | O20: =G20
G21: =IF(ISERROR(VLOOKUP(D21,$I$8:$J$12,2,FALSE)*VLOOKUP(E21,$I$16:$J$20,2,FALSE)*VLOOKUP(F21,$I$24:$J$28,2,FALSE)),"",VLOOKUP(D21,$I$8:$J$12,2,FALSE)*VLOOKUP(E21,$I$16:$J$20,2,FALSE)*VLOOKUP(F21,$I$24:$J$28,2,FALSE)) | L21: 5e-05 | M21: =IF(G21="","",G21+L21) | N21: =IF(#REF!=0,"",#REF!) -> #REF! | O21: =G21
G22: =IF(ISERROR(VLOOKUP(D22,$I$8:$J$12,2,FALSE)*VLOOKUP(E22,$I$16:$J$20,2,FALSE)*VLOOKUP(F22,$I$24:$J$28,2,FALSE)),"",VLOOKUP(D22,$I$8:$J$12,2,FALSE)*VLOOKUP(E22,$I$16:$J$20,2,FALSE)*VLOOKUP(F22,$I$24:$J$28,2,FALSE)) | I22: Tendência | L22: 4e-05 | M22: =IF(G22="","",G22+L22) | N22: =IF(#REF!=0,"",#REF!) -> #REF! | O22: =G22
G23: =IF(ISERROR(VLOOKUP(D23,$I$8:$J$12,2,FALSE)*VLOOKUP(E23,$I$16:$J$20,2,FALSE)*VLOOKUP(F23,$I$24:$J$28,2,FALSE)),"",VLOOKUP(D23,$I$8:$J$12,2,FALSE)*VLOOKUP(E23,$I$16:$J$20,2,FALSE)*VLOOKUP(F23,$I$24:$J$28,2,FALSE)) | L23: 3e-05 | M23: =IF(G23="","",G23+L23) | N23: =IF(#REF!=0,"",#REF!) -> #REF! | O23: =G23
G24: =IF(ISERROR(VLOOKUP(D24,$I$8:$J$12,2,FALSE)*VLOOKUP(E24,$I$16:$J$20,2,FALSE)*VLOOKUP(F24,$I$24:$J$28,2,FALSE)),"",VLOOKUP(D24,$I$8:$J$12,2,FALSE)*VLOOKUP(E24,$I$16:$J$20,2,FALSE)*VLOOKUP(F24,$I$24:$J$28,2,FALSE)) | I24: Melhora muito | J24: 1 | L24: 2e-05 | M24: =IF(G24="","",G24+L24) | N24: =IF(C24=0,"",C24) | O24: =G24
G25: =IF(ISERROR(VLOOKUP(D25,$I$8:$J$12,2,FALSE)*VLOOKUP(E25,$I$16:$J$20,2,FALSE)*VLOOKUP(F25,$I$24:$J$28,2,FALSE)),"",VLOOKUP(D25,$I$8:$J$12,2,FALSE)*VLOOKUP(E25,$I$16:$J$20,2,FALSE)*VLOOKUP(F25,$I$24:$J$28,2,FALSE)) | I25: Melhora | J25: 2 | L25: 1e-05 | M25: =IF(G25="","",G25+L25) | N25: =IF(C25=0,"",C25) | O25: =G25
C26: Pontuação geral das suas Fraquezas | F26: → | G26: =SUM(G6:G25) -> 0 | I26: Mantém | J26: 3
I27: Piora | J27: 4
I28: Piora muito | J28: 5

Sheet Oportunidades
C1: 3. FATORES EXTERNOS
C4: Item | D4: Importância | E4: Urgência | F4: Tendência | G4: Pontuação | S4: 1 | T4: 1 | U4: 1 | V4: 1 | W4: 2 | X4: 2 | Y4: 2 | Z4: 2 | AA4: 2 | AB4: 2 | AC4: 2 | AD4: 2 | AE4: 2 | AF4: 2 | AG4: 2 | AH4: 2 | AI4: 3 | AJ4: 3 | AK4: 3 | AL4: 3 | AM4: 3 | AN4: 3 | AO4: 3 | AP4: 3 | AQ4: 3 | AR4: 3 | AS4: 3 | AT4: 3
C5: Ex.: Existem mercados inexplorados | D5: Ex.: Importante | E5: Ex.: Urgente | F5: Ex.: Mantém | G5: Ex.: 27
G6: =IF(ISERROR(VLOOKUP(D6,$I$8:$J$12,2,FALSE)*VLOOKUP(E6,$I$16:$J$20,2,FALSE)*VLOOKUP(F6,$I$24:$J$28,2,FALSE)),"",VLOOKUP(D6,$I$8:$J$12,2,FALSE)*VLOOKUP(E6,$I$16:$J$20,2,FALSE)*VLOOKUP(F6,$I$24:$J$28,2,FALSE)) | I6: Importância | L6: 0.0002 | M6: =IF(G6="","",G6+L7) | N6: =IF(C6=0,"",C6) | O6: =G6
G7: =IF(ISERROR(VLOOKUP(D7,$I$8:$J$12,2,FALSE)*VLOOKUP(E7,$I$16:$J$20,2,FALSE)*VLOOKUP(F7,$I$24:$J$28,2,FALSE)),"",VLOOKUP(D7,$I$8:$J$12,2,FALSE)*VLOOKUP(E7,$I$16:$J$20,2,FALSE)*VLOOKUP(F7,$I$24:$J$28,2,FALSE)) | L7: 0.00019 | M7: =IF(G7="","",G7+L8) | N7: =IF(C7=0,"",C7) | O7: =G7
G8: =IF(ISERROR(VLOOKUP(D8,$I$8:$J$12,2,FALSE)*VLOOKUP(E8,$I$16:$J$20,2,FALSE)*VLOOKUP(F8,$I$24:$J$28,2,FALSE)),"",VLOOKUP(D8,$I$8:$J$12,2,FALSE)*VLOOKUP(E8,$I$16:$J$20,2,FALSE)*VLOOKUP(F8,$I$24:$J$28,2,FALSE)) | I8: Sem importância | J8: 1 | L8: 0.00018 | M8: =IF(G8="","",G8+L9) | N8: =IF(C8=0,"",C8) | O8: =G8
G9: =IF(ISERROR(VLOOKUP(D9,$I$8:$J$12,2,FALSE)*VLOOKUP(E9,$I$16:$J$20,2,FALSE)*VLOOKUP(F9,$I$24:$J$28,2,FALSE)),"",VLOOKUP(D9,$I$8:$J$12,2,FALSE)*VLOOKUP(E9,$I$16:$J$20,2,FALSE)*VLOOKUP(F9,$I$24:$J$28,2,FALSE)) | I9: Pouco importante | J9: 2 | L9: 0.00017 | M9: =IF(G9="","",G9+L10) | N9: =IF(C9=0,"",C9) | O9: =G9
G10: =IF(ISERROR(VLOOKUP(D10,$I$8:$J$12,2,FALSE)*VLOOKUP(E10,$I$16:$J$20,2,FALSE)*VLOOKUP(F10,$I$24:$J$28,2,FALSE)),"",VLOOKUP(D10,$I$8:$J$12,2,FALSE)*VLOOKUP(E10,$I$16:$J$20,2,FALSE)*VLOOKUP(F10,$I$24:$J$28,2,FALSE)) | I10: Importante | J10: 3 | L10: 0.00016 | M10: =IF(G10="","",G10+L11) | N10: =IF(C10=0,"",C10) | O10: =G10
G11: =IF(ISERROR(VLOOKUP(D11,$I$8:$J$12,2,FALSE)*VLOOKUP(E11,$I$16:$J$20,2,FALSE)*VLOOKUP(F11,$I$24:$J$28,2,FALSE)),"",VLOOKUP(D11,$I$8:$J$12,2,FALSE)*VLOOKUP(E11,$I$16:$J$20,2,FALSE)*VLOOKUP(F11,$I$24:$J$28,2,FALSE)) | I11: Muito importante | J11: 4 | L11: 0.00015 | M11: =IF(G11="","",G11+L12) | N11: =IF(C11=0,"",C11) | O11: =G11
G12: =IF(ISERROR(VLOOKUP(D12,$I$8:$J$12,2,FALSE)*VLOOKUP(E12,$I$16:$J$20,2,FALSE)*VLOOKUP(F12,$I$24:$J$28,2,FALSE)),"",VLOOKUP(D12,$I$8:$J$12,2,FALSE)*VLOOKUP(E12,$I$16:$J$20,2,FALSE)*VLOOKUP(F12,$I$24:$J$28,2,FALSE)) | I12: Totalmente importante | J12: 5 | L12: 0.00014 | M12: =IF(G12="","",G12+L13) | N12: =IF(C12=0,"",C12) | O12: =G12
G13: =IF(ISERROR(VLOOKUP(D13,$I$8:$J$12,2,FALSE)*VLOOKUP(E13,$I$16:$J$20,2,FALSE)*VLOOKUP(F13,$I$24:$J$28,2,FALSE)),"",VLOOKUP(D13,$I$8:$J$12,2,FALSE)*VLOOKUP(E13,$I$16:$J$20,2,FALSE)*VLOOKUP(F13,$I$24:$J$28,2,FALSE)) | L13: 0.00013 | M13: =IF(G13="","",G13+L14) | N13: =IF(C13=0,"",C13) | O13: =G13
G14: =IF(ISERROR(VLOOKUP(D14,$I$8:$J$12,2,FALSE)*VLOOKUP(E14,$I$16:$J$20,2,FALSE)*VLOOKUP(F14,$I$24:$J$28,2,FALSE)),"",VLOOKUP(D14,$I$8:$J$12,2,FALSE)*VLOOKUP(E14,$I$16:$J$20,2,FALSE)*VLOOKUP(F14,$I$24:$J$28,2,FALSE)) | I14: Urgência | L14: 0.00012 | M14: =IF(G14="","",G14+L15) | N14: =IF(C14=0,"",C14) | O14: =G14
G15: =IF(ISERROR(VLOOKUP(D15,$I$8:$J$12,2,FALSE)*VLOOKUP(E15,$I$16:$J$20,2,FALSE)*VLOOKUP(F15,$I$24:$J$28,2,FALSE)),"",VLOOKUP(D15,$I$8:$J$12,2,FALSE)*VLOOKUP(E15,$I$16:$J$20,2,FALSE)*VLOOKUP(F15,$I$24:$J$28,2,FALSE)) | L15: 0.00011 | M15: =IF(G15="","",G15+L16) | N15: =IF(C15=0,"",C15) | O15: =G15
G16: =IF(ISERROR(VLOOKUP(D16,$I$8:$J$12,2,FALSE)*VLOOKUP(E16,$I$16:$J$20,2,FALSE)*VLOOKUP(F16,$I$24:$J$28,2,FALSE)),"",VLOOKUP(D16,$I$8:$J$12,2,FALSE)*VLOOKUP(E16,$I$16:$J$20,2,FALSE)*VLOOKUP(F16,$I$24:$J$28,2,FALSE)) | I16: Nada urgente | J16: 1 | L16: 0.0001 | M16: =IF(G16="","",G16+L17) | N16: =IF(C16=0,"",C16) | O16: =G16
G17: =IF(ISERROR(VLOOKUP(D17,$I$8:$J$12,2,FALSE)*VLOOKUP(E17,$I$16:$J$20,2,FALSE)*VLOOKUP(F17,$I$24:$J$28,2,FALSE)),"",VLOOKUP(D17,$I$8:$J$12,2,FALSE)*VLOOKUP(E17,$I$16:$J$20,2,FALSE)*VLOOKUP(F17,$I$24:$J$28,2,FALSE)) | I17: Pouco urgente | J17: 2 | L17: 9e-05 | M17: =IF(G17="","",G17+L18) | N17: =IF(C17=0,"",C17) | O17: =G17
G18: =IF(ISERROR(VLOOKUP(D18,$I$8:$J$12,2,FALSE)*VLOOKUP(E18,$I$16:$J$20,2,FALSE)*VLOOKUP(F18,$I$24:$J$28,2,FALSE)),"",VLOOKUP(D18,$I$8:$J$12,2,FALSE)*VLOOKUP(E18,$I$16:$J$20,2,FALSE)*VLOOKUP(F18,$I$24:$J$28,2,FALSE)) | I18: Urgente | J18: 3 | L18: 8e-05 | M18: =IF(G18="","",G18+L19) | N18: =IF(C18=0,"",C18) | O18: =G18
G19: =IF(ISERROR(VLOOKUP(D19,$I$8:$J$12,2,FALSE)*VLOOKUP(E19,$I$16:$J$20,2,FALSE)*VLOOKUP(F19,$I$24:$J$28,2,FALSE)),"",VLOOKUP(D19,$I$8:$J$12,2,FALSE)*VLOOKUP(E19,$I$16:$J$20,2,FALSE)*VLOOKUP(F19,$I$24:$J$28,2,FALSE)) | I19: Muito urgente | J19: 4 | L19: 7e-05 | M19: =IF(G19="","",G19+L20) | N19: =IF(C19=0,"",C19) | O19: =G19
G20: =IF(ISERROR(VLOOKUP(D20,$I$8:$J$12,2,FALSE)*VLOOKUP(E20,$I$16:$J$20,2,FALSE)*VLOOKUP(F20,$I$24:$J$28,2,FALSE)),"",VLOOKUP(D20,$I$8:$J$12,2,FALSE)*VLOOKUP(E20,$I$16:$J$20,2,FALSE)*VLOOKUP(F20,$I$24:$J$28,2,FALSE)) | I20: Pra ontem | J20: 5 | L20: 6e-05 | M20: =IF(G20="","",G20+L21) | N20: =IF(C20=0,"",C20) | O20: =G20
G21: =IF(ISERROR(VLOOKUP(D21,$I$8:$J$12,2,FALSE)*VLOOKUP(E21,$I$16:$J$20,2,FALSE)*VLOOKUP(F21,$I$24:$J$28,2,FALSE)),"",VLOOKUP(D21,$I$8:$J$12,2,FALSE)*VLOOKUP(E21,$I$16:$J$20,2,FALSE)*VLOOKUP(F21,$I$24:$J$28,2,FALSE)) | L21: 5e-05 | M21: =IF(G21="","",G21+L22) | N21: =IF(C21=0,"",C21) | O21: =G21
G22: =IF(ISERROR(VLOOKUP(D22,$I$8:$J$12,2,FALSE)*VLOOKUP(E22,$I$16:$J$20,2,FALSE)*VLOOKUP(F22,$I$24:$J$28,2,FALSE)),"",VLOOKUP(D22,$I$8:$J$12,2,FALSE)*VLOOKUP(E22,$I$16:$J$20,2,FALSE)*VLOOKUP(F22,$I$24:$J$28,2,FALSE)) | I22: Tendência | L22: 4e-05 | M22: =IF(G22="","",G22+L23) | N22: =IF(C22=0,"",C22) | O22: =G22
G23: =IF(ISERROR(VLOOKUP(D23,$I$8:$J$12,2,FALSE)*VLOOKUP(E23,$I$16:$J$20,2,FALSE)*VLOOKUP(F23,$I$24:$J$28,2,FALSE)),"",VLOOKUP(D23,$I$8:$J$12,2,FALSE)*VLOOKUP(E23,$I$16:$J$20,2,FALSE)*VLOOKUP(F23,$I$24:$J$28,2,FALSE)) | L23: 3e-05 | M23: =IF(G23="","",G23+L24) | N23: =IF(C23=0,"",C23) | O23: =G23
G24: =IF(ISERROR(VLOOKUP(D24,$I$8:$J$12,2,FALSE)*VLOOKUP(E24,$I$16:$J$20,2,FALSE)*VLOOKUP(F24,$I$24:$J$28,2,FALSE)),"",VLOOKUP(D24,$I$8:$J$12,2,FALSE)*VLOOKUP(E24,$I$16:$J$20,2,FALSE)*VLOOKUP(F24,$I$24:$J$28,2,FALSE)) | I24: Melhora muito | J24: 5 | L24: 2e-05 | M24: =IF(G24="","",G24+L25) | N24: =IF(C24=0,"",C24) | O24: =G24
G25: =IF(ISERROR(VLOOKUP(D25,$I$8:$J$12,2,FALSE)*VLOOKUP(E25,$I$16:$J$20,2,FALSE)*VLOOKUP(F25,$I$24:$J$28,2,FALSE)),"",VLOOKUP(D25,$I$8:$J$12,2,FALSE)*VLOOKUP(E25,$I$16:$J$20,2,FALSE)*VLOOKUP(F25,$I$24:$J$28,2,FALSE)) | I25: Melhora | J25: 4 | L25: 1e-05 | M25: =IF(G25="","",G25+L26) | N25: =IF(C25=0,"",C25) | O25: =G25
C26: Pontuação geral das suas Oportunidades | F26: → | G26: =SUM(G6:G25) -> 0 | I26: Mantém | J26: 3
I27: Piora | J27: 2
I28: Piora muito | J28: 1

Sheet Ameaças
C1: 3. FATORES EXTERNOS
C4: Item | D4: Importância | E4: Urgência | F4: Tendência | G4: Pontuação | S4: 1 | T4: 1 | U4: 1 | V4: 1 | W4: 2 | X4: 2 | Y4: 2 | Z4: 2 | AA4: 2 | AB4: 2 | AC4: 2 | AD4: 2 | AE4: 2 | AF4: 2 | AG4: 2 | AH4: 2 | AI4: 3 | AJ4: 3 | AK4: 3 | AL4: 3 | AM4: 3 | AN4: 3 | AO4: 3 | AP4: 3 | AQ4: 3 | AR4: 3 | AS4: 3 | AT4: 3
C5: Ex.: Existem mercados inexplorados | D5: Ex.: Importante | E5: Ex.: Urgente | F5: Ex.: Mantém | G5: Ex.: 27
G6: =IF(ISERROR(VLOOKUP(D6,$I$8:$J$12,2,FALSE)*VLOOKUP(E6,$I$16:$J$20,2,FALSE)*VLOOKUP(F6,$I$24:$J$28,2,FALSE)),"",VLOOKUP(D6,$I$8:$J$12,2,FALSE)*VLOOKUP(E6,$I$16:$J$20,2,FALSE)*VLOOKUP(F6,$I$24:$J$28,2,FALSE)) | I6: Importância | L6: 0.0002 | M6: =IF(G6="","",G6+L7) | N6: =IF(C6=0,"",C6) | O6: =G6
G7: =IF(ISERROR(VLOOKUP(D7,$I$8:$J$12,2,FALSE)*VLOOKUP(E7,$I$16:$J$20,2,FALSE)*VLOOKUP(F7,$I$24:$J$28,2,FALSE)),"",VLOOKUP(D7,$I$8:$J$12,2,FALSE)*VLOOKUP(E7,$I$16:$J$20,2,FALSE)*VLOOKUP(F7,$I$24:$J$28,2,FALSE)) | L7: 0.00019 | M7: =IF(G7="","",G7+L8) | N7: =IF(C7=0,"",C7) | O7: =G7
G8: =IF(ISERROR(VLOOKUP(D8,$I$8:$J$12,2,FALSE)*VLOOKUP(E8,$I$16:$J$20,2,FALSE)*VLOOKUP(F8,$I$24:$J$28,2,FALSE)),"",VLOOKUP(D8,$I$8:$J$12,2,FALSE)*VLOOKUP(E8,$I$16:$J$20,2,FALSE)*VLOOKUP(F8,$I$24:$J$28,2,FALSE)) | I8: Sem importância | J8: 1 | L8: 0.00018 | M8: =IF(G8="","",G8+L9) | N8: =IF(C8=0,"",C8) | O8: =G8
G9: =IF(ISERROR(VLOOKUP(D9,$I$8:$J$12,2,FALSE)*VLOOKUP(E9,$I$16:$J$20,2,FALSE)*VLOOKUP(F9,$I$24:$J$28,2,FALSE)),"",VLOOKUP(D9,$I$8:$J$12,2,FALSE)*VLOOKUP(E9,$I$16:$J$20,2,FALSE)*VLOOKUP(F9,$I$24:$J$28,2,FALSE)) | I9: Pouco importante | J9: 2 | L9: 0.00017 | M9: =IF(G9="","",G9+L10) | N9: =IF(C9=0,"",C9) | O9: =G9
G10: =IF(ISERROR(VLOOKUP(D10,$I$8:$J$12,2,FALSE)*VLOOKUP(E10,$I$16:$J$20,2,FALSE)*VLOOKUP(F10,$I$24:$J$28,2,FALSE)),"",VLOOKUP(D10,$I$8:$J$12,2,FALSE)*VLOOKUP(E10,$I$16:$J$20,2,FALSE)*VLOOKUP(F10,$I$24:$J$28,2,FALSE)) | I10: Importante | J10: 3 | L10: 0.00016 | M10: =IF(G10="","",G10+L11) | N10: =IF(C10=0,"",C10) | O10: =G10
G11: =IF(ISERROR(VLOOKUP(D11,$I$8:$J$12,2,FALSE)*VLOOKUP(E11,$I$16:$J$20,2,FALSE)*VLOOKUP(F11,$I$24:$J$28,2,FALSE)),"",VLOOKUP(D11,$I$8:$J$12,2,FALSE)*VLOOKUP(E11,$I$16:$J$20,2,FALSE)*VLOOKUP(F11,$I$24:$J$28,2,FALSE)) | I11: Muito importante | J11: 4 | L11: 0.00015 | M11: =IF(G11="","",G11+L12) | N11: =IF(C11=0,"",C11) | O11: =G11
G12: =IF(ISERROR(VLOOKUP(D12,$I$8:$J$12,2,FALSE)*VLOOKUP(E12,$I$16:$J$20,2,FALSE)*VLOOKUP(F12,$I$24:$J$28,2,FALSE)),"",VLOOKUP(D12,$I$8:$J$12,2,FALSE)*VLOOKUP(E12,$I$16:$J$20,2,FALSE)*VLOOKUP(F12,$I$24:$J$28,2,FALSE)) | I12: Totalmente importante | J12: 5 | L12: 0.00014 | M12: =IF(G12="","",G12+L13) | N12: =IF(C12=0,"",C12) | O12: =G12
G13: =IF(ISERROR(VLOOKUP(D13,$I$8:$J$12,2,FALSE)*VLOOKUP(E13,$I$16:$J$20,2,FALSE)*VLOOKUP(F13,$I$24:$J$28,2,FALSE)),"",VLOOKUP(D13,$I$8:$J$12,2,FALSE)*VLOOKUP(E13,$I$16:$J$20,2,FALSE)*VLOOKUP(F13,$I$24:$J$28,2,FALSE)) | L13: 0.00013 | M13: =IF(G13="","",G13+L14) | N13: =IF(C13=0,"",C13) | O13: =G13
G14: =IF(ISERROR(VLOOKUP(D14,$I$8:$J$12,2,FALSE)*VLOOKUP(E14,$I$16:$J$20,2,FALSE)*VLOOKUP(F14,$I$24:$J$28,2,FALSE)),"",VLOOKUP(D14,$I$8:$J$12,2,FALSE)*VLOOKUP(E14,$I$16:$J$20,2,FALSE)*VLOOKUP(F14,$I$24:$J$28,2,FALSE)) | I14: Urgência | L14: 0.00012 | M14: =IF(G14="","",G14+L15) | N14: =IF(C14=0,"",C14) | O14: =G14
G15: =IF(ISERROR(VLOOKUP(D15,$I$8:$J$12,2,FALSE)*VLOOKUP(E15,$I$16:$J$20,2,FALSE)*VLOOKUP(F15,$I$24:$J$28,2,FALSE)),"",VLOOKUP(D15,$I$8:$J$12,2,FALSE)*VLOOKUP(E15,$I$16:$J$20,2,FALSE)*VLOOKUP(F15,$I$24:$J$28,2,FALSE)) | L15: 0.00011 | M15: =IF(G15="","",G15+L16) | N15: =IF(C15=0,"",C15) | O15: =G15
G16: =IF(ISERROR(VLOOKUP(D16,$I$8:$J$12,2,FALSE)*VLOOKUP(E16,$I$16:$J$20,2,FALSE)*VLOOKUP(F16,$I$24:$J$28,2,FALSE)),"",VLOOKUP(D16,$I$8:$J$12,2,FALSE)*VLOOKUP(E16,$I$16:$J$20,2,FALSE)*VLOOKUP(F16,$I$24:$J$28,2,FALSE)) | I16: Nada urgente | J16: 1 | L16: 0.0001 | M16: =IF(G16="","",G16+L17) | N16: =IF(C16=0,"",C16) | O16: =G16
G17: =IF(ISERROR(VLOOKUP(D17,$I$8:$J$12,2,FALSE)*VLOOKUP(E17,$I$16:$J$20,2,FALSE)*VLOOKUP(F17,$I$24:$J$28,2,FALSE)),"",VLOOKUP(D17,$I$8:$J$12,2,FALSE)*VLOOKUP(E17,$I$16:$J$20,2,FALSE)*VLOOKUP(F17,$I$24:$J$28,2,FALSE)) | I17: Pouco urgente | J17: 2 | L17: 9e-05 | M17: =IF(G17="","",G17+L18) | N17: =IF(C17=0,"",C17) | O17: =G17
G18: =IF(ISERROR(VLOOKUP(D18,$I$8:$J$12,2,FALSE)*VLOOKUP(E18,$I$16:$J$20,2,FALSE)*VLOOKUP(F18,$I$24:$J$28,2,FALSE)),"",VLOOKUP(D18,$I$8:$J$12,2,FALSE)*VLOOKUP(E18,$I$16:$J$20,2,FALSE)*VLOOKUP(F18,$I$24:$J$28,2,FALSE)) | I18: Urgente | J18: 3 | L18: 8e-05 | M18: =IF(G18="","",G18+L19) | N18: =IF(C18=0,"",C18) | O18: =G18
G19: =IF(ISERROR(VLOOKUP(D19,$I$8:$J$12,2,FALSE)*VLOOKUP(E19,$I$16:$J$20,2,FALSE)*VLOOKUP(F19,$I$24:$J$28,2,FALSE)),"",VLOOKUP(D19,$I$8:$J$12,2,FALSE)*VLOOKUP(E19,$I$16:$J$20,2,FALSE)*VLOOKUP(F19,$I$24:$J$28,2,FALSE)) | I19: Muito urgente | J19: 4 | L19: 7e-05 | M19: =IF(G19="","",G19+L20) | N19: =IF(C19=0,"",C19) | O19: =G19
G20: =IF(ISERROR(VLOOKUP(D20,$I$8:$J$12,2,FALSE)*VLOOKUP(E20,$I$16:$J$20,2,FALSE)*VLOOKUP(F20,$I$24:$J$28,2,FALSE)),"",VLOOKUP(D20,$I$8:$J$12,2,FALSE)*VLOOKUP(E20,$I$16:$J$20,2,FALSE)*VLOOKUP(F20,$I$24:$J$28,2,FALSE)) | I20: Pra ontem | J20: 5 | L20: 6e-05 | M20: =IF(G20="","",G20+L21) | N20: =IF(C20=0,"",C20) | O20: =G20
G21: =IF(ISERROR(VLOOKUP(D21,$I$8:$J$12,2,FALSE)*VLOOKUP(E21,$I$16:$J$20,2,FALSE)*VLOOKUP(F21,$I$24:$J$28,2,FALSE)),"",VLOOKUP(D21,$I$8:$J$12,2,FALSE)*VLOOKUP(E21,$I$16:$J$20,2,FALSE)*VLOOKUP(F21,$I$24:$J$28,2,FALSE)) | L21: 5e-05 | M21: =IF(G21="","",G21+L22) | N21: =IF(C21=0,"",C21) | O21: =G21
G22: =IF(ISERROR(VLOOKUP(D22,$I$8:$J$12,2,FALSE)*VLOOKUP(E22,$I$16:$J$20,2,FALSE)*VLOOKUP(F22,$I$24:$J$28,2,FALSE)),"",VLOOKUP(D22,$I$8:$J$12,2,FALSE)*VLOOKUP(E22,$I$16:$J$20,2,FALSE)*VLOOKUP(F22,$I$24:$J$28,2,FALSE)) | I22: Tendência | L22: 4e-05 | M22: =IF(G22="","",G22+L23) | N22: =IF(C22=0,"",C22) | O22: =G22
G23: =IF(ISERROR(VLOOKUP(D23,$I$8:$J$12,2,FALSE)*VLOOKUP(E23,$I$16:$J$20,2,FALSE)*VLOOKUP(F23,$I$24:$J$28,2,FALSE)),"",VLOOKUP(D23,$I$8:$J$12,2,FALSE)*VLOOKUP(E23,$I$16:$J$20,2,FALSE)*VLOOKUP(F23,$I$24:$J$28,2,FALSE)) | L23: 3e-05 | M23: =IF(G23="","",G23+L24) | N23: =IF(C23=0,"",C23) | O23: =G23
G24: =IF(ISERROR(VLOOKUP(D24,$I$8:$J$12,2,FALSE)*VLOOKUP(E24,$I$16:$J$20,2,FALSE)*VLOOKUP(F24,$I$24:$J$28,2,FALSE)),"",VLOOKUP(D24,$I$8:$J$12,2,FALSE)*VLOOKUP(E24,$I$16:$J$20,2,FALSE)*VLOOKUP(F24,$I$24:$J$28,2,FALSE)) | I24: Melhora muito | J24: 1 | L24: 2e-05 | M24: =IF(G24="","",G24+L25) | N24: =IF(C24=0,"",C24) | O24: =G24
G25: =IF(ISERROR(VLOOKUP(D25,$I$8:$J$12,2,FALSE)*VLOOKUP(E25,$I$16:$J$20,2,FALSE)*VLOOKUP(F25,$I$24:$J$28,2,FALSE)),"",VLOOKUP(D25,$I$8:$J$12,2,FALSE)*VLOOKUP(E25,$I$16:$J$20,2,FALSE)*VLOOKUP(F25,$I$24:$J$28,2,FALSE)) | I25: Melhora | J25: 2 | L25: 1e-05 | M25: =IF(G25="","",G25+L26) | N25: =IF(C25=0,"",C25) | O25: =G25
C26: Pontuação geral das suas Ameaças | F26: → | G26: =SUM(G6:G25) -> 0 | I26: Mantém | J26: 3
I27: Piora | J27: 4
I28: Piora muito | J28: 5

Sheet Matriz SWOT
C1: 4. MATRIZ SWOT
C4: 1. Fatores internos
C5: 1.1 Top 5 Forças | D5: =SUM(D6:D10) -> 0 | E5: 1.2 Top 5 Fraquezas | F5: =SUM(F6:F10) -> 0 | H5: 0.0002 | I5: =H5+L5 -> 0.0002 | J5: =C6 | K5: Força | L5: =D6 -> 0
B6: 1 | C6: =IF(ISERROR(VLOOKUP(LARGE('Forças'!$M$6:$M$25,$B6),'Forças'!$M$6:$N$25,2,FALSE)),"",VLOOKUP(LARGE('Forças'!$M$6:$M$25,$B6),'Forças'!$M$6:$N$25,2,FALSE)) | D6: =IF(ISERROR(VLOOKUP(LARGE('Forças'!$M$6:$M$25,$B6),'Forças'!$M$6:$O$25,3,FALSE)),0,VLOOKUP(LARGE('Forças'!$M$6:$M$25,$B6),'Forças'!$M$6:$O$25,3,FALSE)) -> 0 | E6: =IF(ISERROR(VLOOKUP(LARGE(Fraquezas!$M$6:$M$25,$B6),Fraquezas!$M$6:$N$25,2,FALSE)),"",VLOOKUP(LARGE(Fraquezas!$M$6:$M$25,$B6),Fraquezas!$M$6:$N$25,2,FALSE)) | F6: =IF(ISERROR(VLOOKUP(LARGE(Fraquezas!$M$6:$M$25,$B6),Fraquezas!$M$6:$O$25,3,FALSE)),0,VLOOKUP(LARGE(Fraquezas!$M$6:$M$25,$B6),Fraquezas!$M$6:$O$25,3,FALSE)) -> 0 | H6: 0.00019 | I6: =H6+L6 -> 0.00019 | J6: =C7 | K6: Força | L6: =D7 -> 0
B7: 2 | C7: =IF(ISERROR(VLOOKUP(LARGE('Forças'!$M$6:$M$25,$B7),'Forças'!$M$6:$N$25,2,FALSE)),"",VLOOKUP(LARGE('Forças'!$M$6:$M$25,$B7),'Forças'!$M$6:$N$25,2,FALSE)) | D7: =IF(ISERROR(VLOOKUP(LARGE('Forças'!$M$6:$M$25,$B7),'Forças'!$M$6:$O$25,3,FALSE)),0,VLOOKUP(LARGE('Forças'!$M$6:$M$25,$B7),'Forças'!$M$6:$O$25,3,FALSE)) -> 0 | E7: =IF(ISERROR(VLOOKUP(LARGE(Fraquezas!$M$6:$M$25,$B7),Fraquezas!$M$6:$N$25,2,FALSE)),"",VLOOKUP(LARGE(Fraquezas!$M$6:$M$25,$B7),Fraquezas!$M$6:$N$25,2,FALSE)) | F7: =IF(ISERROR(VLOOKUP(LARGE(Fraquezas!$M$6:$M$25,$B7),Fraquezas!$M$6:$O$25,3,FALSE)),0,VLOOKUP(LARGE(Fraquezas!$M$6:$M$25,$B7),Fraquezas!$M$6:$O$25,3,FALSE)) -> 0 | H7: 0.00018 | I7: =H7+L7 -> 0.00018 | J7: =C8 | K7: Força | L7: =D8 -> 0
B8: 3 | C8: =IF(ISERROR(VLOOKUP(LARGE('Forças'!$M$6:$M$25,$B8),'Forças'!$M$6:$N$25,2,FALSE)),"",VLOOKUP(LARGE('Forças'!$M$6:$M$25,$B8),'Forças'!$M$6:$N$25,2,FALSE)) | D8: =IF(ISERROR(VLOOKUP(LARGE('Forças'!$M$6:$M$25,$B8),'Forças'!$M$6:$O$25,3,FALSE)),0,VLOOKUP(LARGE('Forças'!$M$6:$M$25,$B8),'Forças'!$M$6:$O$25,3,FALSE)) -> 0 | E8: =IF(ISERROR(VLOOKUP(LARGE(Fraquezas!$M$6:$M$25,$B8),Fraquezas!$M$6:$N$25,2,FALSE)),"",VLOOKUP(LARGE(Fraquezas!$M$6:$M$25,$B8),Fraquezas!$M$6:$N$25,2,FALSE)) | F8: =IF(ISERROR(VLOOKUP(LARGE(Fraquezas!$M$6:$M$25,$B8),Fraquezas!$M$6:$O$25,3,FALSE)),0,VLOOKUP(LARGE(Fraquezas!$M$6:$M$25,$B8),Fraquezas!$M$6:$O$25,3,FALSE)) -> 0 | H8: 0.00017 | I8: =H8+L8 -> 0.00017 | J8: =C9 | K8: Força | L8: =D9 -> 0
B9: 4 | C9: =IF(ISERROR(VLOOKUP(LARGE('Forças'!$M$6:$M$25,$B9),'Forças'!$M$6:$N$25,2,FALSE)),"",VLOOKUP(LARGE('Forças'!$M$6:$M$25,$B9),'Forças'!$M$6:$N$25,2,FALSE)) | D9: =IF(ISERROR(VLOOKUP(LARGE('Forças'!$M$6:$M$25,$B9),'Forças'!$M$6:$O$25,3,FALSE)),0,VLOOKUP(LARGE('Forças'!$M$6:$M$25,$B9),'Forças'!$M$6:$O$25,3,FALSE)) -> 0 | E9: =IF(ISERROR(VLOOKUP(LARGE(Fraquezas!$M$6:$M$25,$B9),Fraquezas!$M$6:$N$25,2,FALSE)),"",VLOOKUP(LARGE(Fraquezas!$M$6:$M$25,$B9),Fraquezas!$M$6:$N$25,2,FALSE)) | F9: =IF(ISERROR(VLOOKUP(LARGE(Fraquezas!$M$6:$M$25,$B9),Fraquezas!$M$6:$O$25,3,FALSE)),0,VLOOKUP(LARGE(Fraquezas!$M$6:$M$25,$B9),Fraquezas!$M$6:$O$25,3,FALSE)) -> 0 | H9: 0.00016 | I9: =H9+L9 -> 0.00016 | J9: =C10 | K9: Força | L9: =D10 -> 0
B10: 5 | C10: =IF(ISERROR(VLOOKUP(LARGE('Forças'!$M$6:$M$25,$B10),'Forças'!$M$6:$N$25,2,FALSE)),"",VLOOKUP(LARGE('Forças'!$M$6:$M$25,$B10),'Forças'!$M$6:$N$25,2,FALSE)) | D10: =IF(ISERROR(VLOOKUP(LARGE('Forças'!$M$6:$M$25,$B10),'Forças'!$M$6:$O$25,3,FALSE)),0,VLOOKUP(LARGE('Forças'!$M$6:$M$25,$B10),'Forças'!$M$6:$O$25,3,FALSE)) -> 0 | E10: =IF(ISERROR(VLOOKUP(LARGE(Fraquezas!$M$6:$M$25,$B10),Fraquezas!$M$6:$N$25,2,FALSE)),"",VLOOKUP(LARGE(Fraquezas!$M$6:$M$25,$B10),Fraquezas!$M$6:$N$25,2,FALSE)) | F10: =IF(ISERROR(VLOOKUP(LARGE(Fraquezas!$M$6:$M$25,$B10),Fraquezas!$M$6:$O$25,3,FALSE)),0,VLOOKUP(LARGE(Fraquezas!$M$6:$M$25,$B10),Fraquezas!$M$6:$O$25,3,FALSE)) -> 0 | H10: 0.00015 | I10: =H10+L10 -> 0.00015 | J10: =E6 | K10: Fraqueza | L10: =F6 -> 0
H11: 0.00014 | I11: =H11+L11 -> 0.00014 | J11: =E7 | K11: Fraqueza | L11: =F7 -> 0
C12: 2. Fatores externos | H12: 0.00013 | I12: =H12+L12 -> 0.00013 | J12: =E8 | K12: Fraqueza | L12: =F8 -> 0
C13: 2.1 Top 5 Oportunidades | D13: =SUM(D14:D18) -> 0 | E13: 2.2 Top 5 Ameaças | F13: =SUM(F14:F18) -> 0 | H13: 0.00012 | I13: =H13+L13 -> 0.00012 | J13: =E9 | K13: Fraqueza | L13: =F9 -> 0
B14: 1 | C14: =IF(ISERROR(VLOOKUP(LARGE(Oportunidades!$M$6:$M$25,$B14),Oportunidades!$M$6:$N$25,2,FALSE)),"",VLOOKUP(LARGE(Oportunidades!$M$6:$M$25,$B14),Oportunidades!$M$6:$N$25,2,FALSE)) | D14: =IF(ISERROR(VLOOKUP(LARGE(Oportunidades!$M$6:$M$25,$B14),Oportunidades!$M$6:$O$25,3,FALSE)),0,VLOOKUP(LARGE(Oportunidades!$M$6:$M$25,$B14),Oportunidades!$M$6:$O$25,3,FALSE)) -> 0 | E14: =IF(ISERROR(VLOOKUP(LARGE('Ameaças'!$M$6:$M$25,$B14),'Ameaças'!$M$6:$N$25,2,FALSE)),"",VLOOKUP(LARGE('Ameaças'!$M$6:$M$25,$B14),'Ameaças'!$M$6:$N$25,2,FALSE)) | F14: =IF(ISERROR(VLOOKUP(LARGE('Ameaças'!$M$6:$M$25,$B14),'Ameaças'!$M$6:$O$25,3,FALSE)),0,VLOOKUP(LARGE('Ameaças'!$M$6:$M$25,$B14),'Ameaças'!$M$6:$O$25,3,FALSE)) -> 0 | H14: 0.00011 | I14: =H14+L14 -> 0.00011 | J14: =E10 | K14: Fraqueza | L14: =F10 -> 0
B15: 2 | C15: =IF(ISERROR(VLOOKUP(LARGE(Oportunidades!$M$6:$M$25,$B15),Oportunidades!$M$6:$N$25,2,FALSE)),"",VLOOKUP(LARGE(Oportunidades!$M$6:$M$25,$B15),Oportunidades!$M$6:$N$25,2,FALSE)) | D15: =IF(ISERROR(VLOOKUP(LARGE(Oportunidades!$M$6:$M$25,$B15),Oportunidades!$M$6:$O$25,3,FALSE)),0,VLOOKUP(LARGE(Oportunidades!$M$6:$M$25,$B15),Oportunidades!$M$6:$O$25,3,FALSE)) -> 0 | E15: =IF(ISERROR(VLOOKUP(LARGE('Ameaças'!$M$6:$M$25,$B15),'Ameaças'!$M$6:$N$25,2,FALSE)),"",VLOOKUP(LARGE('Ameaças'!$M$6:$M$25,$B15),'Ameaças'!$M$6:$N$25,2,FALSE)) | F15: =IF(ISERROR(VLOOKUP(LARGE('Ameaças'!$M$6:$M$25,$B15),'Ameaças'!$M$6:$O$25,3,FALSE)),0,VLOOKUP(LARGE('Ameaças'!$M$6:$M$25,$B15),'Ameaças'!$M$6:$O$25,3,FALSE)) -> 0 | H15: 0.0001 | I15: =H15+L15 -> 0.0001 | J15: =C14 | K15: Oportunidade | L15: =D14 -> 0
B16: 3 | C16: =IF(ISERROR(VLOOKUP(LARGE(Oportunidades!$M$6:$M$25,$B16),Oportunidades!$M$6:$N$25,2,FALSE)),"",VLOOKUP(LARGE(Oportunidades!$M$6:$M$25,$B16),Oportunidades!$M$6:$N$25,2,FALSE)) | D16: =IF(ISERROR(VLOOKUP(LARGE(Oportunidades!$M$6:$M$25,$B16),Oportunidades!$M$6:$O$25,3,FALSE)),0,VLOOKUP(LARGE(Oportunidades!$M$6:$M$25,$B16),Oportunidades!$M$6:$O$25,3,FALSE)) -> 0 | E16: =IF(ISERROR(VLOOKUP(LARGE('Ameaças'!$M$6:$M$25,$B16),'Ameaças'!$M$6:$N$25,2,FALSE)),"",VLOOKUP(LARGE('Ameaças'!$M$6:$M$25,$B16),'Ameaças'!$M$6:$N$25,2,FALSE)) | F16: =IF(ISERROR(VLOOKUP(LARGE('Ameaças'!$M$6:$M$25,$B16),'Ameaças'!$M$6:$O$25,3,FALSE)),0,VLOOKUP(LARGE('Ameaças'!$M$6:$M$25,$B16),'Ameaças'!$M$6:$O$25,3,FALSE)) -> 0 | H16: 9e-05 | I16: =H16+L16 -> 9e-05 | J16: =C15 | K16: Oportunidade | L16: =D15 -> 0
B17: 4 | C17: =IF(ISERROR(VLOOKUP(LARGE(Oportunidades!$M$6:$M$25,$B17),Oportunidades!$M$6:$N$25,2,FALSE)),"",VLOOKUP(LARGE(Oportunidades!$M$6:$M$25,$B17),Oportunidades!$M$6:$N$25,2,FALSE)) | D17: =IF(ISERROR(VLOOKUP(LARGE(Oportunidades!$M$6:$M$25,$B17),Oportunidades!$M$6:$O$25,3,FALSE)),0,VLOOKUP(LARGE(Oportunidades!$M$6:$M$25,$B17),Oportunidades!$M$6:$O$25,3,FALSE)) -> 0 | E17: =IF(ISERROR(VLOOKUP(LARGE('Ameaças'!$M$6:$M$25,$B17),'Ameaças'!$M$6:$N$25,2,FALSE)),"",VLOOKUP(LARGE('Ameaças'!$M$6:$M$25,$B17),'Ameaças'!$M$6:$N$25,2,FALSE)) | F17: =IF(ISERROR(VLOOKUP(LARGE('Ameaças'!$M$6:$M$25,$B17),'Ameaças'!$M$6:$O$25,3,FALSE)),0,VLOOKUP(LARGE('Ameaças'!$M$6:$M$25,$B17),'Ameaças'!$M$6:$O$25,3,FALSE)) -> 0 | H17: 8e-05 | I17: =H17+L17 -> 8e-05 | J17: =C16 | K17: Oportunidade | L17: =D16 -> 0
B18: 5 | C18: =IF(ISERROR(VLOOKUP(LARGE(Oportunidades!$M$6:$M$25,$B18),Oportunidades!$M$6:$N$25,2,FALSE)),"",VLOOKUP(LARGE(Oportunidades!$M$6:$M$25,$B18),Oportunidades!$M$6:$N$25,2,FALSE)) | D18: =IF(ISERROR(VLOOKUP(LARGE(Oportunidades!$M$6:$M$25,$B18),Oportunidades!$M$6:$O$25,3,FALSE)),0,VLOOKUP(LARGE(Oportunidades!$M$6:$M$25,$B18),Oportunidades!$M$6:$O$25,3,FALSE)) -> 0 | E18: =IF(ISERROR(VLOOKUP(LARGE('Ameaças'!$M$6:$M$25,$B18),'Ameaças'!$M$6:$N$25,2,FALSE)),"",VLOOKUP(LARGE('Ameaças'!$M$6:$M$25,$B18),'Ameaças'!$M$6:$N$25,2,FALSE)) | F18: =IF(ISERROR(VLOOKUP(LARGE('Ameaças'!$M$6:$M$25,$B18),'Ameaças'!$M$6:$O$25,3,FALSE)),0,VLOOKUP(LARGE('Ameaças'!$M$6:$M$25,$B18),'Ameaças'!$M$6:$O$25,3,FALSE)) -> 0 | H18: 7e-05 | I18: =H18+L18 -> 7e-05 | J18: =C17 | K18: Oportunidade | L18: =D17 -> 0
H19: 6e-05 | I19: =H19+L19 -> 6e-05 | J19: =C18 | K19: Oportunidade | L19: =D18 -> 0
H20: 5e-05 | I20: =H20+L20 -> 5e-05 | J20: =E14 | K20: Ameaça | L20: =F14 -> 0
H21: 4e-05 | I21: =H21+L21 -> 4e-05 | J21: =E15 | K21: Ameaça | L21: =F15 -> 0
H22: 3e-05 | I22: =H22+L22 -> 3e-05 | J22: =E16 | K22: Ameaça | L22: =F16 -> 0
H23: 2e-05 | I23: =H23+L23 -> 2e-05 | J23: =E17 | K23: Ameaça | L23: =F17 -> 0
H24: 1e-05 | I24: =H24+L24 -> 1e-05 | J24: =E18 | K24: Ameaça | L24: =F18 -> 0

Sheet Cruzamento
C1: 5. CRUZAMENTOS
C4: Importante: Veja o potencial ofensivo e desenvolva a melhor estratégia para impulsionar suas forças e resuzir as fraquezas relacionando-as com oportunidades e ameaças. Apenas as 5 principais forças, fraquezas, oportunidades e ameaças (as mais bem pontuadas em "Fatores internos" e "Fatores externos") estão sendo exibidas para que você tenha foco e objetividade nas ações.
R6: Setembro | S6: Outubro | T6: Novembro | U6: Dezembro | V6: Janeiro | W6: Fevereiro | X6: Março | Y6: Abril | Z6: Maio
C7: Forças e Fraquezas | D7: No seu negócio | E7: Oportunidades e Ameaças | F7: No seu negócio | G7: Tipo de estratégia | H7: Recomendação | R7: 1 | S7: 1 | T7: 1 | U7: 1 | V7: 2 | W7: 2 | X7: 2 | Y7: 2 | Z7: 2
C8: Ex.: O portfólio de produtos/serviços é variado | D8: Ex.: Força | E8: Ex.: Aproveita avanço tecnológico | F8: Ex.: Ameaça | G8: Ex.: Estratégia ofensiva | H8: Ex.: Procure criar planos de ação para desenvolver as vantagens competitivas.
D9: =IF(ISERROR(VLOOKUP(C9,'Matriz SWOT'!$J$5:$K$14,2,FALSE)),"",VLOOKUP(C9,'Matriz SWOT'!$J$5:$K$14,2,FALSE)) | F9: =IF(ISERROR(VLOOKUP(E9,'Matriz SWOT'!$J$5:$K$24,2,FALSE)),"",VLOOKUP(E9,'Matriz SWOT'!$J$5:$K$24,2,FALSE)) | G9: =IF(F9="","",VLOOKUP(D9&F9,$M$9:$O$12,2,FALSE)) | H9: =IF(G9="","",VLOOKUP(G9,$N$9:$O$12,2,FALSE)) | I9: 1 | J9: =VLOOKUP(LARGE('Matriz SWOT'!$I$5:$I$14,Cruzamento!I9),'Matriz SWOT'!$I$5:$J$14,2,FALSE) | K9: =VLOOKUP(LARGE('Matriz SWOT'!$I$15:$I$24,Cruzamento!I9),'Matriz SWOT'!$I$15:$J$24,2,FALSE) | M9: ForçaOportunidade | N9: Estratégia ofensiva | O9: Procure criar planos de ação para desenvolver as vantagens competitivas.
D10: =IF(ISERROR(VLOOKUP(C10,'Matriz SWOT'!$J$5:$K$14,2,FALSE)),"",VLOOKUP(C10,'Matriz SWOT'!$J$5:$K$14,2,FALSE)) | F10: =IF(ISERROR(VLOOKUP(E10,'Matriz SWOT'!$J$5:$K$24,2,FALSE)),"",VLOOKUP(E10,'Matriz SWOT'!$J$5:$K$24,2,FALSE)) | G10: =IF(F10="","",VLOOKUP(D10&F10,$M$9:$O$12,2,FALSE)) | H10: =IF(G10="","",VLOOKUP(G10,$N$9:$O$12,2,FALSE)) | I10: 2 | J10: =VLOOKUP(LARGE('Matriz SWOT'!$I$5:$I$14,Cruzamento!I10),'Matriz SWOT'!$I$5:$J$14,2,FALSE) | K10: =VLOOKUP(LARGE('Matriz SWOT'!$I$15:$I$24,Cruzamento!I10),'Matriz SWOT'!$I$15:$J$24,2,FALSE) | M10: ForçaAmeaça | N10: Estratégia de confronto | O10: Procure elaborar planos de ação para modificar o ambiente a favor do seu negócio.
D11: =IF(ISERROR(VLOOKUP(C11,'Matriz SWOT'!$J$5:$K$14,2,FALSE)),"",VLOOKUP(C11,'Matriz SWOT'!$J$5:$K$14,2,FALSE)) | F11: =IF(ISERROR(VLOOKUP(E11,'Matriz SWOT'!$J$5:$K$24,2,FALSE)),"",VLOOKUP(E11,'Matriz SWOT'!$J$5:$K$24,2,FALSE)) | G11: =IF(F11="","",VLOOKUP(D11&F11,$M$9:$O$12,2,FALSE)) | H11: =IF(G11="","",VLOOKUP(G11,$N$9:$O$12,2,FALSE)) | I11: 3 | J11: =VLOOKUP(LARGE('Matriz SWOT'!$I$5:$I$14,Cruzamento!I11),'Matriz SWOT'!$I$5:$J$14,2,FALSE) | K11: =VLOOKUP(LARGE('Matriz SWOT'!$I$15:$I$24,Cruzamento!I11),'Matriz SWOT'!$I$15:$J$24,2,FALSE) | M11: FraquezaOportunidade | N11: Estratégia de reforço | O11: Procure criar planos de ação para aproveitar melhor as oportunidades que o ambiente proporciona.
D12: =IF(ISERROR(VLOOKUP(C12,'Matriz SWOT'!$J$5:$K$14,2,FALSE)),"",VLOOKUP(C12,'Matriz SWOT'!$J$5:$K$14,2,FALSE)) | F12: =IF(ISERROR(VLOOKUP(E12,'Matriz SWOT'!$J$5:$K$24,2,FALSE)),"",VLOOKUP(E12,'Matriz SWOT'!$J$5:$K$24,2,FALSE)) | G12: =IF(F12="","",VLOOKUP(D12&F12,$M$9:$O$12,2,FALSE)) | H12: =IF(G12="","",VLOOKUP(G12,$N$9:$O$12,2,FALSE)) | I12: 4 | J12: =VLOOKUP(LARGE('Matriz SWOT'!$I$5:$I$14,Cruzamento!I12),'Matriz SWOT'!$I$5:$J$14,2,FALSE) | K12: =VLOOKUP(LARGE('Matriz SWOT'!$I$15:$I$24,Cruzamento!I12),'Matriz SWOT'!$I$15:$J$24,2,FALSE) | M12: FraquezaAmeaça | N12: Estratégia defensiva | O12: Isto pode ser um sinal de que você precisará fazer profundas mudanças para proteger a empresa.
D13: =IF(ISERROR(VLOOKUP(C13,'Matriz SWOT'!$J$5:$K$14,2,FALSE)),"",VLOOKUP(C13,'Matriz SWOT'!$J$5:$K$14,2,FALSE)) | F13: =IF(ISERROR(VLOOKUP(E13,'Matriz SWOT'!$J$5:$K$24,2,FALSE)),"",VLOOKUP(E13,'Matriz SWOT'!$J$5:$K$24,2,FALSE)) | G13: =IF(F13="","",VLOOKUP(D13&F13,$M$9:$O$12,2,FALSE)) | H13: =IF(G13="","",VLOOKUP(G13,$N$9:$O$12,2,FALSE)) | I13: 5 | J13: =VLOOKUP(LARGE('Matriz SWOT'!$I$5:$I$14,Cruzamento!I13),'Matriz SWOT'!$I$5:$J$14,2,FALSE) | K13: =VLOOKUP(LARGE('Matriz SWOT'!$I$15:$I$24,Cruzamento!I13),'Matriz SWOT'!$I$15:$J$24,2,FALSE)
D14: =IF(ISERROR(VLOOKUP(C14,'Matriz SWOT'!$J$5:$K$14,2,FALSE)),"",VLOOKUP(C14,'Matriz SWOT'!$J$5:$K$14,2,FALSE)) | F14: =IF(ISERROR(VLOOKUP(E14,'Matriz SWOT'!$J$5:$K$24,2,FALSE)),"",VLOOKUP(E14,'Matriz SWOT'!$J$5:$K$24,2,FALSE)) | G14: =IF(F14="","",VLOOKUP(D14&F14,$M$9:$O$12,2,FALSE)) | H14: =IF(G14="","",VLOOKUP(G14,$N$9:$O$12,2,FALSE)) | I14: 6 | J14: =VLOOKUP(LARGE('Matriz SWOT'!$I$5:$I$14,Cruzamento!I14),'Matriz SWOT'!$I$5:$J$14,2,FALSE) | K14: =VLOOKUP(LARGE('Matriz SWOT'!$I$15:$I$24,Cruzamento!I14),'Matriz SWOT'!$I$15:$J$24,2,FALSE)
D15: =IF(ISERROR(VLOOKUP(C15,'Matriz SWOT'!$J$5:$K$14,2,FALSE)),"",VLOOKUP(C15,'Matriz SWOT'!$J$5:$K$14,2,FALSE)) | F15: =IF(ISERROR(VLOOKUP(E15,'Matriz SWOT'!$J$5:$K$24,2,FALSE)),"",VLOOKUP(E15,'Matriz SWOT'!$J$5:$K$24,2,FALSE)) | G15: =IF(F15="","",VLOOKUP(D15&F15,$M$9:$O$12,2,FALSE)) | H15: =IF(G15="","",VLOOKUP(G15,$N$9:$O$12,2,FALSE)) | I15: 7 | J15: =VLOOKUP(LARGE('Matriz SWOT'!$I$5:$I$14,Cruzamento!I15),'Matriz SWOT'!$I$5:$J$14,2,FALSE) | K15: =VLOOKUP(LARGE('Matriz SWOT'!$I$15:$I$24,Cruzamento!I15),'Matriz SWOT'!$I$15:$J$24,2,FALSE)
D16: =IF(ISERROR(VLOOKUP(C16,'Matriz SWOT'!$J$5:$K$14,2,FALSE)),"",VLOOKUP(C16,'Matriz SWOT'!$J$5:$K$14,2,FALSE)) | F16: =IF(ISERROR(VLOOKUP(E16,'Matriz SWOT'!$J$5:$K$24,2,FALSE)),"",VLOOKUP(E16,'Matriz SWOT'!$J$5:$K$24,2,FALSE)) | G16: =IF(F16="","",VLOOKUP(D16&F16,$M$9:$O$12,2,FALSE)) | H16: =IF(G16="","",VLOOKUP(G16,$N$9:$O$12,2,FALSE)) | I16: 8 | J16: =VLOOKUP(LARGE('Matriz SWOT'!$I$5:$I$14,Cruzamento!I16),'Matriz SWOT'!$I$5:$J$14,2,FALSE) | K16: =VLOOKUP(LARGE('Matriz SWOT'!$I$15:$I$24,Cruzamento!I16),'Matriz SWOT'!$I$15:$J$24,2,FALSE)
D17: =IF(ISERROR(VLOOKUP(C17,'Matriz SWOT'!$J$5:$K$14,2,FALSE)),"",VLOOKUP(C17,'Matriz SWOT'!$J$5:$K$14,2,FALSE)) | F17: =IF(ISERROR(VLOOKUP(E17,'Matriz SWOT'!$J$5:$K$24,2,FALSE)),"",VLOOKUP(E17,'Matriz SWOT'!$J$5:$K$24,2,FALSE)) | G17: =IF(F17="","",VLOOKUP(D17&F17,$M$9:$O$12,2,FALSE)) | H17: =IF(G17="","",VLOOKUP(G17,$N$9:$O$12,2,FALSE)) | I17: 9 | J17: =VLOOKUP(LARGE('Matriz SWOT'!$I$5:$I$14,Cruzamento!I17),'Matriz SWOT'!$I$5:$J$14,2,FALSE) | K17: =VLOOKUP(LARGE('Matriz SWOT'!$I$15:$I$24,Cruzamento!I17),'Matriz SWOT'!$I$15:$J$24,2,FALSE)
D18: =IF(ISERROR(VLOOKUP(C18,'Matriz SWOT'!$J$5:$K$14,2,FALSE)),"",VLOOKUP(C18,'Matriz SWOT'!$J$5:$K$14,2,FALSE)) | F18: =IF(ISERROR(VLOOKUP(E18,'Matriz SWOT'!$J$5:$K$24,2,FALSE)),"",VLOOKUP(E18,'Matriz SWOT'!$J$5:$K$24,2,FALSE)) | G18: =IF(F18="","",VLOOKUP(D18&F18,$M$9:$O$12,2,FALSE)) | H18: =IF(G18="","",VLOOKUP(G18,$N$9:$O$12,2,FALSE)) | I18: 10 | J18: =VLOOKUP(LARGE('Matriz SWOT'!$I$5:$I$14,Cruzamento!I18),'Matriz SWOT'!$I$5:$J$14,2,FALSE) | K18: =VLOOKUP(LARGE('Matriz SWOT'!$I$15:$I$24,Cruzamento!I18),'Matriz SWOT'!$I$15:$J$24,2,FALSE)
D19: =IF(ISERROR(VLOOKUP(C19,'Matriz SWOT'!$J$5:$K$14,2,FALSE)),"",VLOOKUP(C19,'Matriz SWOT'!$J$5:$K$14,2,FALSE)) | F19: =IF(ISERROR(VLOOKUP(E19,'Matriz SWOT'!$J$5:$K$24,2,FALSE)),"",VLOOKUP(E19,'Matriz SWOT'!$J$5:$K$24,2,FALSE)) | G19: =IF(F19="","",VLOOKUP(D19&F19,$M$9:$O$12,2,FALSE)) | H19: =IF(G19="","",VLOOKUP(G19,$N$9:$O$12,2,FALSE))
D20: =IF(ISERROR(VLOOKUP(C20,'Matriz SWOT'!$J$5:$K$14,2,FALSE)),"",VLOOKUP(C20,'Matriz SWOT'!$J$5:$K$14,2,FALSE)) | F20: =IF(ISERROR(VLOOKUP(E20,'Matriz SWOT'!$J$5:$K$24,2,FALSE)),"",VLOOKUP(E20,'Matriz SWOT'!$J$5:$K$24,2,FALSE)) | G20: =IF(F20="","",VLOOKUP(D20&F20,$M$9:$O$12,2,FALSE)) | H20: =IF(G20="","",VLOOKUP(G20,$N$9:$O$12,2,FALSE))
D21: =IF(ISERROR(VLOOKUP(C21,'Matriz SWOT'!$J$5:$K$14,2,FALSE)),"",VLOOKUP(C21,'Matriz SWOT'!$J$5:$K$14,2,FALSE)) | F21: =IF(ISERROR(VLOOKUP(E21,'Matriz SWOT'!$J$5:$K$24,2,FALSE)),"",VLOOKUP(E21,'Matriz SWOT'!$J$5:$K$24,2,FALSE)) | G21: =IF(F21="","",VLOOKUP(D21&F21,$M$9:$O$12,2,FALSE)) | H21: =IF(G21="","",VLOOKUP(G21,$N$9:$O$12,2,FALSE))
D22: =IF(ISERROR(VLOOKUP(C22,'Matriz SWOT'!$J$5:$K$14,2,FALSE)),"",VLOOKUP(C22,'Matriz SWOT'!$J$5:$K$14,2,FALSE)) | F22: =IF(ISERROR(VLOOKUP(E22,'Matriz SWOT'!$J$5:$K$24,2,FALSE)),"",VLOOKUP(E22,'Matriz SWOT'!$J$5:$K$24,2,FALSE)) | G22: =IF(F22="","",VLOOKUP(D22&F22,$M$9:$O$12,2,FALSE)) | H22: =IF(G22="","",VLOOKUP(G22,$N$9:$O$12,2,FALSE))
D23: =IF(ISERROR(VLOOKUP(C23,'Matriz SWOT'!$J$5:$K$14,2,FALSE)),"",VLOOKUP(C23,'Matriz SWOT'!$J$5:$K$14,2,FALSE)) | F23: =IF(ISERROR(VLOOKUP(E23,'Matriz SWOT'!$J$5:$K$24,2,FALSE)),"",VLOOKUP(E23,'Matriz SWOT'!$J$5:$K$24,2,FALSE)) | G23: =IF(F23="","",VLOOKUP(D23&F23,$M$9:$O$12,2,FALSE)) | H23: =IF(G23="","",VLOOKUP(G23,$N$9:$O$12,2,FALSE))
D24: =IF(ISERROR(VLOOKUP(C24,'Matriz SWOT'!$J$5:$K$14,2,FALSE)),"",VLOOKUP(C24,'Matriz SWOT'!$J$5:$K$14,2,FALSE)) | F24: =IF(ISERROR(VLOOKUP(E24,'Matriz SWOT'!$J$5:$K$24,2,FALSE)),"",VLOOKUP(E24,'Matriz SWOT'!$J$5:$K$24,2,FALSE)) | G24: =IF(F24="","",VLOOKUP(D24&F24,$M$9:$O$12,2,FALSE)) | H24: =IF(G24="","",VLOOKUP(G24,$N$9:$O$12,2,FALSE))
D25: =IF(ISERROR(VLOOKUP(C25,'Matriz SWOT'!$J$5:$K$14,2,FALSE)),"",VLOOKUP(C25,'Matriz SWOT'!$J$5:$K$14,2,FALSE)) | F25: =IF(ISERROR(VLOOKUP(E25,'Matriz SWOT'!$J$5:$K$24,2,FALSE)),"",VLOOKUP(E25,'Matriz SWOT'!$J$5:$K$24,2,FALSE)) | G25: =IF(F25="","",VLOOKUP(D25&F25,$M$9:$O$12,2,FALSE)) | H25: =IF(G25="","",VLOOKUP(G25,$N$9:$O$12,2,FALSE))
D26: =IF(ISERROR(VLOOKUP(C26,'Matriz SWOT'!$J$5:$K$14,2,FALSE)),"",VLOOKUP(C26,'Matriz SWOT'!$J$5:$K$14,2,FALSE)) | F26: =IF(ISERROR(VLOOKUP(E26,'Matriz SWOT'!$J$5:$K$24,2,FALSE)),"",VLOOKUP(E26,'Matriz SWOT'!$J$5:$K$24,2,FALSE)) | G26: =IF(F26="","",VLOOKUP(D26&F26,$M$9:$O$12,2,FALSE)) | H26: =IF(G26="","",VLOOKUP(G26,$N$9:$O$12,2,FALSE))
D27: =IF(ISERROR(VLOOKUP(C27,'Matriz SWOT'!$J$5:$K$14,2,FALSE)),"",VLOOKUP(C27,'Matriz SWOT'!$J$5:$K$14,2,FALSE)) | F27: =IF(ISERROR(VLOOKUP(E27,'Matriz SWOT'!$J$5:$K$24,2,FALSE)),"",VLOOKUP(E27,'Matriz SWOT'!$J$5:$K$24,2,FALSE)) | G27: =IF(F27="","",VLOOKUP(D27&F27,$M$9:$O$12,2,FALSE)) | H27: =IF(G27="","",VLOOKUP(G27,$N$9:$O$12,2,FALSE))
D28: =IF(ISERROR(VLOOKUP(C28,'Matriz SWOT'!$J$5:$K$14,2,FALSE)),"",VLOOKUP(C28,'Matriz SWOT'!$J$5:$K$14,2,FALSE)) | F28: =IF(ISERROR(VLOOKUP(E28,'Matriz SWOT'!$J$5:$K$24,2,FALSE)),"",VLOOKUP(E28,'Matriz SWOT'!$J$5:$K$24,2,FALSE)) | G28: =IF(F28="","",VLOOKUP(D28&F28,$M$9:$O$12,2,FALSE)) | H28: =IF(G28="","",VLOOKUP(G28,$N$9:$O$12,2,FALSE))
D29: =IF(ISERROR(VLOOKUP(C29,'Matriz SWOT'!$J$5:$K$14,2,FALSE)),"",VLOOKUP(C29,'Matriz SWOT'!$J$5:$K$14,2,FALSE)) | F29: =IF(ISERROR(VLOOKUP(E29,'Matriz SWOT'!$J$5:$K$24,2,FALSE)),"",VLOOKUP(E29,'Matriz SWOT'!$J$5:$K$24,2,FALSE)) | G29: =IF(F29="","",VLOOKUP(D29&F29,$M$9:$O$12,2,FALSE)) | H29: =IF(G29="","",VLOOKUP(G29,$N$9:$O$12,2,FALSE))
D30: =IF(ISERROR(VLOOKUP(C30,'Matriz SWOT'!$J$5:$K$14,2,FALSE)),"",VLOOKUP(C30,'Matriz SWOT'!$J$5:$K$14,2,FALSE)) | F30: =IF(ISERROR(VLOOKUP(E30,'Matriz SWOT'!$J$5:$K$24,2,FALSE)),"",VLOOKUP(E30,'Matriz SWOT'!$J$5:$K$24,2,FALSE)) | G30: =IF(F30="","",VLOOKUP(D30&F30,$M$9:$O$12,2,FALSE)) | H30: =IF(G30="","",VLOOKUP(G30,$N$9:$O$12,2,FALSE))
... D108: =IF(ISERROR(VLOOKUP(C108,'Matriz SWOT'!$J$5:$K$14,2,FALSE)),"",VLOOKUP(C108,'Matriz SWOT'!$J$5:$K$14,2,FALSE)) | F108: =IF(ISERROR(VLOOKUP(E108,'Matriz SWOT'!$J$5:$K$24,2,FALSE)),"",VLOOKUP(E108,'Matriz SWOT'!$J$5:$K$24,2,FALSE)) | G108: =IF(F108="","",VLOOKUP(D108&F108,$M$9:$O$12,2,FALSE)) | H108: =IF(G108="","",VLOOKUP(G108,$N$9:$O$12,2,FALSE))

Sheet Cruzamento - FxO
C1: 6. PLANOS DE AÇÃO
C4: Importante: Desenvolva planos de ação para impulsionar os itens da SWOT. Apenas os 20 principais itens (os mais bem pontuados) estão sendo exibidos para que você tenha foco e objetividade nas ações.
V5: Setembro | W5: Outubro | X5: Novembro | Y5: Dezembro | Z5: Janeiro | AA5: Fevereiro | AB5: Março | AC5: Abril | AD5: Maio | AE5: Junho | AF5: Julho | AG5: Agosto | AH5: Setembro | AI5: Outubro | AJ5: Novembro | AK5: Dezembro | AL5: Janeiro | AM5: Fevereiro | AN5: Março | AO5: Abril | AP5: Maio | AQ5: Junho | AR5: Julho | AS5: Agosto | AT5: Setembro | AU5: Outubro | AV5: Novembro | AW5: Dezembro
C6: Planos de ação | D6: Itens | F6: Responsável | G6: Área | H6: Previsão início | I6: Previsão fim | J6: Andamento | K6: Status | V6: 1 | W6: 1 | X6: 1 | Y6: 1 | Z6: 2 | AA6: 2 | AB6: 2 | AC6: 2 | AD6: 2 | AE6: 2 | AF6: 2 | AG6: 2 | AH6: 2 | AI6: 2 | AJ6: 2 | AK6: 2 | AL6: 3 | AM6: 3 | AN6: 3 | AO6: 3 | AP6: 3 | AQ6: 3 | AR6: 3 | AS6: 3 | AT6: 3 | AU6: 3 | AV6: 3 | AW6: 3
C7: Ex.: Aumentar a divulgação da empresa | D7: Ex.: O serviço é de qualidade | E7: Ex.: Força | F7: Ex.: Luis Carlos Almeida | G7: Ex.: Merketing | H7: Ex.: 01/01/2016 | I7: Ex.: 31/12/2016 | J7: Ex.: Concluído | K7: Ex.: Atrasado
E8: =IF(ISERROR(VLOOKUP(D8,'Matriz SWOT'!$J$5:$K$24,2,FALSE)),"",VLOOKUP(D8,'Matriz SWOT'!$J$5:$K$24,2,FALSE)) | M8: =#REF! -> #REF! | O8: 1 | P8: =VLOOKUP(LARGE('Matriz SWOT'!$I$5:$I$24,$O8),'Matriz SWOT'!$I$5:$J$24,2,FALSE)
E9: =IF(ISERROR(VLOOKUP(D9,'Matriz SWOT'!$J$5:$K$24,2,FALSE)),"",VLOOKUP(D9,'Matriz SWOT'!$J$5:$K$24,2,FALSE)) | M9: =#REF! -> #REF! | O9: 2 | P9: =VLOOKUP(LARGE('Matriz SWOT'!$I$5:$I$24,$O9),'Matriz SWOT'!$I$5:$J$24,2,FALSE)
E10: =IF(ISERROR(VLOOKUP(D10,'Matriz SWOT'!$J$5:$K$24,2,FALSE)),"",VLOOKUP(D10,'Matriz SWOT'!$J$5:$K$24,2,FALSE)) | M10: =#REF! -> #REF! | O10: 3 | P10: =VLOOKUP(LARGE('Matriz SWOT'!$I$5:$I$24,$O10),'Matriz SWOT'!$I$5:$J$24,2,FALSE)
E11: =IF(ISERROR(VLOOKUP(D11,'Matriz SWOT'!$J$5:$K$24,2,FALSE)),"",VLOOKUP(D11,'Matriz SWOT'!$J$5:$K$24,2,FALSE)) | M11: =#REF! -> #REF! | O11: 4 | P11: =VLOOKUP(LARGE('Matriz SWOT'!$I$5:$I$24,$O11),'Matriz SWOT'!$I$5:$J$24,2,FALSE)
E12: =IF(ISERROR(VLOOKUP(D12,'Matriz SWOT'!$J$5:$K$24,2,FALSE)),"",VLOOKUP(D12,'Matriz SWOT'!$J$5:$K$24,2,FALSE)) | M12: =#REF! -> #REF! | O12: 5 | P12: =VLOOKUP(LARGE('Matriz SWOT'!$I$5:$I$24,$O12),'Matriz SWOT'!$I$5:$J$24,2,FALSE)
E13: =IF(ISERROR(VLOOKUP(D13,'Matriz SWOT'!$J$5:$K$24,2,FALSE)),"",VLOOKUP(D13,'Matriz SWOT'!$J$5:$K$24,2,FALSE)) | M13: =#REF! -> #REF! | O13: 6 | P13: =VLOOKUP(LARGE('Matriz SWOT'!$I$5:$I$24,$O13),'Matriz SWOT'!$I$5:$J$24,2,FALSE)
E14: =IF(ISERROR(VLOOKUP(D14,'Matriz SWOT'!$J$5:$K$24,2,FALSE)),"",VLOOKUP(D14,'Matriz SWOT'!$J$5:$K$24,2,FALSE)) | M14: =#REF! -> #REF! | O14: 7 | P14: =VLOOKUP(LARGE('Matriz SWOT'!$I$5:$I$24,$O14),'Matriz SWOT'!$I$5:$J$24,2,FALSE)
E15: =IF(ISERROR(VLOOKUP(D15,'Matriz SWOT'!$J$5:$K$24,2,FALSE)),"",VLOOKUP(D15,'Matriz SWOT'!$J$5:$K$24,2,FALSE)) | M15: =#REF! -> #REF! | O15: 8 | P15: =VLOOKUP(LARGE('Matriz SWOT'!$I$5:$I$24,$O15),'Matriz SWOT'!$I$5:$J$24,2,FALSE)
E16: =IF(ISERROR(VLOOKUP(D16,'Matriz SWOT'!$J$5:$K$24,2,FALSE)),"",VLOOKUP(D16,'Matriz SWOT'!$J$5:$K$24,2,FALSE)) | M16: =#REF! -> #REF! | O16: 9 | P16: =VLOOKUP(LARGE('Matriz SWOT'!$I$5:$I$24,$O16),'Matriz SWOT'!$I$5:$J$24,2,FALSE)
E17: =IF(ISERROR(VLOOKUP(D17,'Matriz SWOT'!$J$5:$K$24,2,FALSE)),"",VLOOKUP(D17,'Matriz SWOT'!$J$5:$K$24,2,FALSE)) | M17: =#REF! -> #REF! | O17: 10 | P17: =VLOOKUP(LARGE('Matriz SWOT'!$I$5:$I$24,$O17),'Matriz SWOT'!$I$5:$J$24,2,FALSE)
E18: =IF(ISERROR(VLOOKUP(D18,'Matriz SWOT'!$J$5:$K$24,2,FALSE)),"",VLOOKUP(D18,'Matriz SWOT'!$J$5:$K$24,2,FALSE)) | M18: =#REF! -> #REF! | O18: 11 | P18: =VLOOKUP(LARGE('Matriz SWOT'!$I$5:$I$24,$O18),'Matriz SWOT'!$I$5:$J$24,2,FALSE)
E19: =IF(ISERROR(VLOOKUP(D19,'Matriz SWOT'!$J$5:$K$24,2,FALSE)),"",VLOOKUP(D19,'Matriz SWOT'!$J$5:$K$24,2,FALSE)) | M19: =#REF! -> #REF! | O19: 12 | P19: =VLOOKUP(LARGE('Matriz SWOT'!$I$5:$I$24,$O19),'Matriz SWOT'!$I$5:$J$24,2,FALSE)
... E27: =IF(ISERROR(VLOOKUP(D27,'Matriz SWOT'!$J$5:$K$24,2,FALSE)),"",VLOOKUP(D27,'Matriz SWOT'!$J$5:$K$24,2,FALSE)) | M27: =#REF! -> #REF! | O27: 20 | P27: =VLOOKUP(LARGE('Matriz SWOT'!$I$5:$I$24,$O27),'Matriz SWOT'!$I$5:$J$24,2,FALSE)
E28: =IF(ISERROR(VLOOKUP(D28,'Matriz SWOT'!$J$5:$K$24,2,FALSE)),"",VLOOKUP(D28,'Matriz SWOT'!$J$5:$K$24,2,FALSE)) | M28: =#REF! -> #REF!
E29: =IF(ISERROR(VLOOKUP(D29,'Matriz SWOT'!$J$5:$K$24,2,FALSE)),"",VLOOKUP(D29,'Matriz SWOT'!$J$5:$K$24,2,FALSE)) | M29: =#REF! -> #REF!
E30: =IF(ISERROR(VLOOKUP(D30,'Matriz SWOT'!$J$5:$K$24,2,FALSE)),"",VLOOKUP(D30,'Matriz SWOT'!$J$5:$K$24,2,FALSE)) | M30: =#REF! -> #REF!
E31: =IF(ISERROR(VLOOKUP(D31,'Matriz SWOT'!$J$5:$K$24,2,FALSE)),"",VLOOKUP(D31,'Matriz SWOT'!$J$5:$K$24,2,FALSE)) | M31: =#REF! -> #REF!
E32: =IF(ISERROR(VLOOKUP(D32,'Matriz SWOT'!$J$5:$K$24,2,FALSE)),"",VLOOKUP(D32,'Matriz SWOT'!$J$5:$K$24,2,FALSE)) | M32: =#REF! -> #REF!
E33: =IF(ISERROR(VLOOKUP(D33,'Matriz SWOT'!$J$5:$K$24,2,FALSE)),"",VLOOKUP(D33,'Matriz SWOT'!$J$5:$K$24,2,FALSE)) | M33: =#REF! -> #REF!
E34: =IF(ISERROR(VLOOKUP(D34,'Matriz SWOT'!$J$5:$K$24,2,FALSE)),"",VLOOKUP(D34,'Matriz SWOT'!$J$5:$K$24,2,FALSE)) | G34: =IF(F34=0,"",VLOOKUP(F34,#REF!,2,FALSE)) | M34: =#REF! -> #REF!
E35: =IF(ISERROR(VLOOKUP(D35,'Matriz SWOT'!$J$5:$K$24,2,FALSE)),"",VLOOKUP(D35,'Matriz SWOT'!$J$5:$K$24,2,FALSE)) | G35: =IF(F35=0,"",VLOOKUP(F35,#REF!,2,FALSE)) | M35: =#REF! -> #REF!
E36: =IF(ISERROR(VLOOKUP(D36,'Matriz SWOT'!$J$5:$K$24,2,FALSE)),"",VLOOKUP(D36,'Matriz SWOT'!$J$5:$K$24,2,FALSE)) | G36: =IF(F36=0,"",VLOOKUP(F36,#REF!,2,FALSE)) | M36: =#REF! -> #REF!
E37: =IF(ISERROR(VLOOKUP(D37,'Matriz SWOT'!$J$5:$K$24,2,FALSE)),"",VLOOKUP(D37,'Matriz SWOT'!$J$5:$K$24,2,FALSE)) | G37: =IF(F37=0,"",VLOOKUP(F37,#REF!,2,FALSE)) | M37: =#REF! -> #REF!
E38: =IF(ISERROR(VLOOKUP(D38,'Matriz SWOT'!$J$5:$K$24,2,FALSE)),"",VLOOKUP(D38,'Matriz SWOT'!$J$5:$K$24,2,FALSE)) | G38: =IF(F38=0,"",VLOOKUP(F38,#REF!,2,FALSE)) | M38: =#REF! -> #REF!
E39: =IF(ISERROR(VLOOKUP(D39,'Matriz SWOT'!$J$5:$K$24,2,FALSE)),"",VLOOKUP(D39,'Matriz SWOT'!$J$5:$K$24,2,FALSE)) | G39: =IF(F39=0,"",VLOOKUP(F39,#REF!,2,FALSE)) | M39: =#REF! -> #REF!
E40: =IF(ISERROR(VLOOKUP(D40,'Matriz SWOT'!$J$5:$K$24,2,FALSE)),"",VLOOKUP(D40,'Matriz SWOT'!$J$5:$K$24,2,FALSE)) | G40: =IF(F40=0,"",VLOOKUP(F40,#REF!,2,FALSE)) | M40: =#REF! -> #REF!
E41: =IF(ISERROR(VLOOKUP(D41,'Matriz SWOT'!$J$5:$K$24,2,FALSE)),"",VLOOKUP(D41,'Matriz SWOT'!$J$5:$K$24,2,FALSE)) | G41: =IF(F41=0,"",VLOOKUP(F41,#REF!,2,FALSE)) | M41: =#REF! -> #REF!
E42: =IF(ISERROR(VLOOKUP(D42,'Matriz SWOT'!$J$5:$K$24,2,FALSE)),"",VLOOKUP(D42,'Matriz SWOT'!$J$5:$K$24,2,FALSE)) | G42: =IF(F42=0,"",VLOOKUP(F42,#REF!,2,FALSE)) | M42: =#REF! -> #REF!
E43: =IF(ISERROR(VLOOKUP(D43,'Matriz SWOT'!$J$5:$K$24,2,FALSE)),"",VLOOKUP(D43,'Matriz SWOT'!$J$5:$K$24,2,FALSE)) | G43: =IF(F43=0,"",VLOOKUP(F43,#REF!,2,FALSE)) | M43: =#REF! -> #REF!
E44: =IF(ISERROR(VLOOKUP(D44,'Matriz SWOT'!$J$5:$K$24,2,FALSE)),"",VLOOKUP(D44,'Matriz SWOT'!$J$5:$K$24,2,FALSE)) | G44: =IF(F44=0,"",VLOOKUP(F44,#REF!,2,FALSE)) | M44: =#REF! -> #REF!
E45: =IF(ISERROR(VLOOKUP(D45,'Matriz SWOT'!$J$5:$K$24,2,FALSE)),"",VLOOKUP(D45,'Matriz SWOT'!$J$5:$K$24,2,FALSE)) | G45: =IF(F45=0,"",VLOOKUP(F45,#REF!,2,FALSE)) | M45: =#REF! -> #REF!
... E57: =IF(ISERROR(VLOOKUP(D57,'Matriz SWOT'!$J$5:$K$24,2,FALSE)),"",VLOOKUP(D57,'Matriz SWOT'!$J$5:$K$24,2,FALSE)) | G57: =IF(F57=0,"",VLOOKUP(F57,#REF!,2,FALSE)) | M57: =#REF! -> #REF!
E58: =IF(ISERROR(VLOOKUP(D58,'Matriz SWOT'!$J$5:$K$24,2,FALSE)),"",VLOOKUP(D58,'Matriz SWOT'!$J$5:$K$24,2,FALSE)) | G58: =IF(F58=0,"",VLOOKUP(F58,#REF!,2,FALSE))
E59: =IF(ISERROR(VLOOKUP(D59,'Matriz SWOT'!$J$5:$K$24,2,FALSE)),"",VLOOKUP(D59,'Matriz SWOT'!$J$5:$K$24,2,FALSE)) | G59: =IF(F59=0,"",VLOOKUP(F59,#REF!,2,FALSE))
E60: =IF(ISERROR(VLOOKUP(D60,'Matriz SWOT'!$J$5:$K$24,2,FALSE)),"",VLOOKUP(D60,'Matriz SWOT'!$J$5:$K$24,2,FALSE)) | G60: =IF(F60=0,"",VLOOKUP(F60,#REF!,2,FALSE))
E61: =IF(ISERROR(VLOOKUP(D61,'Matriz SWOT'!$J$5:$K$24,2,FALSE)),"",VLOOKUP(D61,'Matriz SWOT'!$J$5:$K$24,2,FALSE)) | G61: =IF(F61=0,"",VLOOKUP(F61,#REF!,2,FALSE))
E62: =IF(ISERROR(VLOOKUP(D62,'Matriz SWOT'!$J$5:$K$24,2,FALSE)),"",VLOOKUP(D62,'Matriz SWOT'!$J$5:$K$24,2,FALSE)) | G62: =IF(F62=0,"",VLOOKUP(F62,#REF!,2,FALSE))
E63: =IF(ISERROR(VLOOKUP(D63,'Matriz SWOT'!$J$5:$K$24,2,FALSE)),"",VLOOKUP(D63,'Matriz SWOT'!$J$5:$K$24,2,FALSE)) | G63: =IF(F63=0,"",VLOOKUP(F63,#REF!,2,FALSE))
E64: =IF(ISERROR(VLOOKUP(D64,'Matriz SWOT'!$J$5:$K$24,2,FALSE)),"",VLOOKUP(D64,'Matriz SWOT'!$J$5:$K$24,2,FALSE)) | G64: =IF(F64=0,"",VLOOKUP(F64,#REF!,2,FALSE))
E65: =IF(ISERROR(VLOOKUP(D65,'Matriz SWOT'!$J$5:$K$24,2,FALSE)),"",VLOOKUP(D65,'Matriz SWOT'!$J$5:$K$24,2,FALSE)) | G65: =IF(F65=0,"",VLOOKUP(F65,#REF!,2,FALSE))
E66: =IF(ISERROR(VLOOKUP(D66,'Matriz SWOT'!$J$5:$K$24,2,FALSE)),"",VLOOKUP(D66,'Matriz SWOT'!$J$5:$K$24,2,FALSE)) | G66: =IF(F66=0,"",VLOOKUP(F66,#REF!,2,FALSE))
E67: =IF(ISERROR(VLOOKUP(D67,'Matriz SWOT'!$J$5:$K$24,2,FALSE)),"",VLOOKUP(D67,'Matriz SWOT'!$J$5:$K$24,2,FALSE)) | G67: =IF(F67=0,"",VLOOKUP(F67,#REF!,2,FALSE))
E68: =IF(ISERROR(VLOOKUP(D68,'Matriz SWOT'!$J$5:$K$24,2,FALSE)),"",VLOOKUP(D68,'Matriz SWOT'!$J$5:$K$24,2,FALSE)) | G68: =IF(F68=0,"",VLOOKUP(F68,#REF!,2,FALSE))
E69: =IF(ISERROR(VLOOKUP(D69,'Matriz SWOT'!$J$5:$K$24,2,FALSE)),"",VLOOKUP(D69,'Matriz SWOT'!$J$5:$K$24,2,FALSE)) | G69: =IF(F69=0,"",VLOOKUP(F69,#REF!,2,FALSE))
... E106: =IF(ISERROR(VLOOKUP(D106,'Matriz SWOT'!$J$5:$K$24,2,FALSE)),"",VLOOKUP(D106,'Matriz SWOT'!$J$5:$K$24,2,FALSE)) | G106: =IF(F106=0,"",VLOOKUP(F106,#REF!,2,FALSE))
E107: =IF(ISERROR(VLOOKUP(D107,'Matriz SWOT'!$J$5:$K$24,2,FALSE)),"",VLOOKUP(D107,'Matriz SWOT'!$J$5:$K$24,2,FALSE)) | G107: =IF(F107=0,"",VLOOKUP(F107,#REF!,2,FALSE)) | K107: =IF(J107=0,"",IF(J107="Concluído","Concluído",IF(AND(TODAY()>I107,J107<>"Concluído"),"Atrasado",IF(AND(TODAY()<H107,J107="Não iniciado"),"Aguardando",IF(AND(TODAY()<H107,J107="Em andamento"),"Adiantado",IF(AND(TODAY()>=H107,TODAY()<=I107,J107="Em andamento"),"Em andamento","Atrasado"))))))

Sheet Gráficos
C1: 7. RESULTADOS SWOT
C4: Índice de favorabilidade
N5: Favorável - Se a sua análise está correta, vale a pena continuar a fazer o que você está fazendo apenas adicionando ações de melhorias de forças e oportunidades e medidas de contenção de possíveis fraquezas e ameaças. | U5: Setembro | V5: Outubro | W5: Novembro | X5: Dezembro | Y5: Janeiro | Z5: Fevereiro | AA5: Março | AB5: Abril | AC5: Maio | AD5: Junho | AE5: Julho | AF5: Agosto | AG5: Setembro | AH5: Outubro | AI5: Novembro | AJ5: Dezembro | AK5: Janeiro | AL5: Fevereiro | AM5: Março | AN5: Abril | AO5: Maio | AP5: Junho | AQ5: Julho | AR5: Agosto | AS5: Setembro | AT5: Outubro | AU5: Novembro | AV5: Dezembro
C6: Seu índice é | N6: Muito Desfavorável - O cenário para crescimento do seu negócio é muito desfavorável, talvez seja o momento de pensar em uma mudança estratégica drástica. | Q6: =100/160 -> 0.625 | R6: CONTA DE MÉDIA | U6: 1 | V6: 1 | W6: 1 | X6: 1 | Y6: 2 | Z6: 2 | AA6: 2 | AB6: 2 | AC6: 2 | AD6: 2 | AE6: 2 | AF6: 2 | AG6: 2 | AH6: 2 | AI6: 2 | AJ6: 2 | AK6: 3 | AL6: 3 | AM6: 3 | AN6: 3 | AO6: 3 | AP6: 3 | AQ6: 3 | AR6: 3 | AS6: 3 | AT6: 3 | AU6: 3 | AV6: 3
C7: =IF(ISERROR((('Gráficos'!D19+'Gráficos'!D21)/SUM('Gráficos'!D19:F22)-('Gráficos'!D20+'Gráficos'!D22)/SUM('Gráficos'!D19:F22))*2),0,(('Gráficos'!D19+'Gráficos'!D21)/SUM('Gráficos'!D19:F22)-('Gráficos'!D20+'Gráficos'!D22)/SUM('Gráficos'!D19:F22))*2) -> 0 | N7: Desfavorável - Uma análise SWOT desfavorável não quer dizer que você precisa desistir do seu negócio, mas é importante pensar em planos de ações direcionados à mitigar as principais ameaças e para diminuir o peso negativo de algumas fraquezas.
N8: Equilíbrio - Com um cenário equilibrado vale a pena investir mais tempo de análise para saber se o seu foco será interno ou externo.
C9: =IF(C7<=-1,N6,IF(C7<=-0.3,N7,IF(C7<=0.3,N8,IF(C7<=1,N5,IF(C7<=2,N9,""))))) -> Equilíbrio - Com um cenário equilibrado vale a pena investir mais tempo de análise para saber se o seu foco será interno ou externo. | N9: Muito Favorável - Se a sua análise está correta, vale muito a pena continuar a fazer exatamente o que você está fazendo apenas adicionando ações de melhorias de forças e oportunidades e medidas de contenção de possíveis fraquezas e ameaças.
T10: Setembro | U10: Outubro | V10: Novembro | W10: Dezembro | X10: Janeiro | Y10: Fevereiro | Z10: Março | AA10: Abril | AB10: Maio | AC10: Junho | AD10: Julho | AE10: Agosto | AF10: Setembro | AG10: Outubro | AH10: Novembro | AI10: Dezembro | AJ10: Janeiro | AK10: Fevereiro | AL10: Março | AM10: Abril | AN10: Maio | AO10: Junho | AP10: Julho | AQ10: Agosto | AR10: Setembro | AS10: Outubro | AT10: Novembro | AU10: Dezembro
C11: Análise geral dos fatores internos e externos | M11: RANK
C13: Forças | D13: =IF(ISERROR('Gráficos'!D19/SUM('Gráficos'!$D$19:$F$22)),0,'Gráficos'!D19/SUM('Gráficos'!$D$19:$F$22)) -> 0 | E13: =IF(D13<D14,"Suas forças estão mais baixas que as suas fraquezas, que tal pensar em planos de ação para ter notas melhores em relação à esse item?",IF(D13>=D14,"Suas forças estão mais altas ou iguais as suas fraquezas, mantenha esse bom resultado!","")) -> Suas forças estão mais altas ou iguais as suas fraquezas, mantenha esse bom resultado! | M13: =C13 -> Forças | N13: =IF(ISERROR(VLOOKUP(LARGE($D$13:$D$14,ROW($A1)),$D$13:$M$14,COLUMN(J$1),FALSE)),"",VLOOKUP(LARGE($D$13:$D$14,ROW($A1)),$D$13:$M$14,COLUMN(J$1),FALSE)) -> Forças | P13: 1 | Q13: Sobrevivência | R13: fraquezas | S13: ameaças | T13: =IF(AND($N$13=R13,$N$14=S13),"OK","")
C14: Fraquezas | D14: =IF(ISERROR('Gráficos'!D20/SUM('Gráficos'!$D$19:$F$22)),0,'Gráficos'!D20/SUM('Gráficos'!$D$19:$F$22)) -> 0 | E14: =IF(D14>D13,"Suas fraquezas estão maiores que as suas forças, esse é um sinal de alerta clássico que existem pontos de melhoria na sua empresa, crie planos de ação para reduzir estas fraquezas.",IF(D14<=D13,"Suas fraquezas estão mais baixas ou iguais as suas forças, esse é um bom sinal, mas não se acomode!","")) -> Suas fraquezas estão mais baixas ou iguais as suas forças, esse é um bom sinal, mas não se acomode! | M14: =C14 -> Fraquezas | N14: =IF(ISERROR(VLOOKUP(LARGE($D$15:$D$16,ROW($A1)),$D$15:$M$16,COLUMN(J$1),FALSE)),"",VLOOKUP(LARGE($D$15:$D$16,ROW($A1)),$D$15:$M$16,COLUMN(J$1),FALSE)) -> Oportunidades | P14: 2 | Q14: Manutenção | R14: forças | S14: ameaças | T14: =IF(AND($N$13=R14,$N$14=S14),"OK","")
C15: Oportunidades | D15: =IF(ISERROR('Gráficos'!D21/SUM('Gráficos'!$D$19:$F$22)),0,'Gráficos'!D21/SUM('Gráficos'!$D$19:$F$22)) -> 0 | E15: =IF(D15>=D16,"Você tem mais oportunidades do que ameaças e isso indica um futuro promissor, só falta você alinhar quais forças vão otimizar as chances delas acontecerem de fato.",IF(D15<D16,"Suas opotunidades estão mais baixas do que suas ameaças, vale a pena pensar em planos de ação para reduzir as ameaças.","")) -> Você tem mais oportunidades do que ameaças e isso indica um futuro promissor, só falta você alinhar quais forças vão otimizar as chances delas acontecerem de fato. | M15: =C15 -> Oportunidades | P15: 3 | Q15: Crescimento | R15: fraquezas | S15: oportunidades | T15: =IF(AND($N$13=R15,$N$14=S15),"OK","")
C16: Ameaças | D16: =IF(ISERROR('Gráficos'!D22/SUM('Gráficos'!$D$19:$F$22)),0,'Gráficos'!D22/SUM('Gráficos'!$D$19:$F$22)) -> 0 | E16: =IF(D16>=D15,"Suas ameaças estão maiores ou iguais as oportunidades e isso indica um futuro preocupante, você precisa pensar em planos de ação para diminuir os riscos delas acontecerem o quanto antes.",IF(D16<D15,"Suas ameaças estão mais baixas do que suas oportunidades, esse é um bom sinal, mas ainda assim vale a pena analisar as suas ameaças mais relevantes e criar planos de ações para elas.","")) -> Suas ameaças estão maiores ou iguais as oportunidades e isso indica um futuro preocupante, você precisa pensar em planos de ação para diminuir os riscos delas acontecerem o quanto antes. | M16: =C16 -> Ameaças | P16: 4 | Q16: Desenvolvimento | R16: forças | S16: oportunidades | T16: =IF(AND($N$13=R16,$N$14=S16),"OK","") -> OK
C17: Análise geral dos fatores internos e externos | H17: Gráficos radar da análise SWOT
T18: Setembro | U18: Outubro | V18: Novembro | W18: Dezembro | X18: Janeiro | Y18: Fevereiro | Z18: Março | AA18: Abril | AB18: Maio | AC18: Junho | AD18: Julho | AE18: Agosto | AF18: Setembro | AG18: Outubro | AH18: Novembro | AI18: Dezembro | AJ18: Janeiro | AK18: Fevereiro | AL18: Março | AM18: Abril | AN18: Maio | AO18: Junho | AP18: Julho | AQ18: Agosto | AR18: Setembro | AS18: Outubro | AT18: Novembro | AU18: Dezembro
C19: Forças | D19: ='Forças'!G26 -> 0 | T19: 1 | U19: 1 | V19: 1 | W19: 1 | X19: 2 | Y19: 2 | Z19: 2 | AA19: 2 | AB19: 2 | AC19: 2 | AD19: 2 | AE19: 2 | AF19: 2 | AG19: 2 | AH19: 2 | AI19: 2 | AJ19: 3 | AK19: 3 | AL19: 3 | AM19: 3 | AN19: 3 | AO19: 3 | AP19: 3 | AQ19: 3 | AR19: 3 | AS19: 3 | AT19: 3 | AU19: 3
C20: Fraquezas | D20: =Fraquezas!G26 -> 0
C21: Oportunidades | D21: =Oportunidades!G26 -> 0
C22: Ameaças | D22: ='Ameaças'!G26 -> 0
C24: Análise das forças | H24: Análise das fraquezas
C26: ='Matriz SWOT'!C6 | E26: ='Matriz SWOT'!D6 -> 0 | H26: ='Matriz SWOT'!E6 | J26: ='Matriz SWOT'!F6 -> 0
C27: ='Matriz SWOT'!C7 | E27: ='Matriz SWOT'!D7 -> 0 | H27: ='Matriz SWOT'!E7 | J27: ='Matriz SWOT'!F7 -> 0
C28: ='Matriz SWOT'!C8 | E28: ='Matriz SWOT'!D8 -> 0 | H28: ='Matriz SWOT'!E8 | J28: ='Matriz SWOT'!F8 -> 0
C29: ='Matriz SWOT'!C9 | E29: ='Matriz SWOT'!D9 -> 0 | H29: ='Matriz SWOT'!E9 | J29: ='Matriz SWOT'!F9 -> 0
C30: ='Matriz SWOT'!C10 | E30: ='Matriz SWOT'!D10 -> 0 | H30: ='Matriz SWOT'!E10 | J30: ='Matriz SWOT'!F10 -> 0
C32: Análise das oportunidades | H32: Análise das ameaças
C34: ='Matriz SWOT'!C14 | E34: ='Matriz SWOT'!D14 -> 0 | H34: ='Matriz SWOT'!E14 | J34: ='Matriz SWOT'!F14 -> 0
C35: ='Matriz SWOT'!C15 | E35: ='Matriz SWOT'!D15 -> 0 | H35: ='Matriz SWOT'!E15 | J35: ='Matriz SWOT'!F15 -> 0
C36: ='Matriz SWOT'!C16 | E36: ='Matriz SWOT'!D16 -> 0 | H36: ='Matriz SWOT'!E16 | J36: ='Matriz SWOT'!F16 -> 0
C37: ='Matriz SWOT'!C17 | E37: ='Matriz SWOT'!D17 -> 0 | H37: ='Matriz SWOT'!E17 | J37: ='Matriz SWOT'!F17 -> 0
C38: ='Matriz SWOT'!C18 | E38: ='Matriz SWOT'!D18 -> 0 | H38: ='Matriz SWOT'!E18 | J38: ='Matriz SWOT'!F18 -> 0

Sheet GPA
C1: 8. RESULTADOS PLANOS DE AÇÃO
C3: {=SUM(IFERROR(1/COUNTIF('Cruzamento - FxO'!$D$8:$D$107,'Cruzamento - FxO'!$D$8:$D$107),0))} -> 0 | D3: =20-COUNTBLANK('Matriz SWOT'!J5:J24) -> 0 | E3: =C3/D3*100 -> #DIV/0! | F3: =IF(E3<50,G3,IF(E3>=80,I3,H3)) -> #DIV/0! | G3: Se você busca melhores resultados, é preciso atuar em mais itens criando planos de ação eficientes para cada um deles! | H3: Não está ruim, mas é preciso ter atenção. Se você busca resultados melhores no seu negócio, talvez seja necessário atuar em mais itens criando ainda mais planos de ação! | I3: Legal, você criou planos de ação para todos ou quase todos os itens. Se tudo correr bem, você obterá resultados brevemente. Parabéns! | R3: No prazo | S3: =COUNTIF('Cruzamento - FxO'!$I$8:$I$107,">"&TODAY()) -> 0
C4: Desenvolvimento de planos de ação | R4: Atrasado | S4: =S11 -> 0
C5: ="Você definiu planos de ação para "&C3&" de "&D3&" dos principais itens da sua SWOT" -> Você definiu planos de ação para 0 de 0 dos principais itens da sua SWOT | E5: =IF(ISERROR(E3/100),0,E3/100) -> 0 | F5: =IF(ISERROR(F3),"",F3)
K6: 5 | L6: 6 | M6: 8
C7: Status dos seus planos de ação | F7: Conformidade do dos planos de ação | J7: 1 | K7: =VLOOKUP(LARGE($K$15:$K$34,$J7),$K$15:$R$34,K$6,FALSE) -> #REF! | L7: =VLOOKUP(LARGE($K$15:$K$34,$J7),$K$15:$R$34,L$6,FALSE) -> #REF! | M7: =VLOOKUP(LARGE($K$15:$K$34,$J7),$K$15:$R$34,M$6,FALSE) -> #REF! | R7: Aguardando | S7: =COUNTIF('Cruzamento - FxO'!$K$8:$K$107,GPA!R7) -> 0
J8: 2 | K8: =VLOOKUP(LARGE($K$15:$K$34,$J8),$K$15:$R$34,K$6,FALSE) -> #REF! | L8: =VLOOKUP(LARGE($K$15:$K$34,$J8),$K$15:$R$34,L$6,FALSE) -> #REF! | M8: =VLOOKUP(LARGE($K$15:$K$34,$J8),$K$15:$R$34,M$6,FALSE) -> #REF! | R8: Adiantado | S8: =COUNTIF('Cruzamento - FxO'!$K$8:$K$107,GPA!R8) -> 0 | U8: Setembro | V8: Outubro | W8: Novembro | X8: Dezembro | Y8: Janeiro | Z8: Fevereiro | AA8: Março | AB8: Abril | AC8: Maio | AD8: Junho | AE8: Julho | AF8: Agosto | AG8: Setembro | AH8: Outubro | AI8: Novembro | AJ8: Dezembro | AK8: Janeiro | AL8: Fevereiro | AM8: Março | AN8: Abril | AO8: Maio | AP8: Junho | AQ8: Julho | AR8: Agosto | AS8: Setembro | AT8: Outubro | AU8: Novembro | AV8: Dezembro
J9: 3 | K9: =VLOOKUP(LARGE($K$15:$K$34,$J9),$K$15:$R$34,K$6,FALSE) -> #REF! | L9: =VLOOKUP(LARGE($K$15:$K$34,$J9),$K$15:$R$34,L$6,FALSE) -> #REF! | M9: =VLOOKUP(LARGE($K$15:$K$34,$J9),$K$15:$R$34,M$6,FALSE) -> #REF! | R9: Em andamento | S9: =COUNTIF('Cruzamento - FxO'!$K$8:$K$107,GPA!R9) -> 0 | U9: 1 | V9: 1 | W9: 1 | X9: 1 | Y9: 2 | Z9: 2 | AA9: 2 | AB9: 2 | AC9: 2 | AD9: 2 | AE9: 2 | AF9: 2 | AG9: 2 | AH9: 2 | AI9: 2 | AJ9: 2 | AK9: 3 | AL9: 3 | AM9: 3 | AN9: 3 | AO9: 3 | AP9: 3 | AQ9: 3 | AR9: 3 | AS9: 3 | AT9: 3 | AU9: 3 | AV9: 3
J10: 4 | K10: =VLOOKUP(LARGE($K$15:$K$34,$J10),$K$15:$R$34,K$6,FALSE) -> #REF! | L10: =VLOOKUP(LARGE($K$15:$K$34,$J10),$K$15:$R$34,L$6,FALSE) -> #REF! | M10: =VLOOKUP(LARGE($K$15:$K$34,$J10),$K$15:$R$34,M$6,FALSE) -> #REF! | R10: Concluído | S10: =COUNTIF('Cruzamento - FxO'!$K$8:$K$107,GPA!R10) -> 0
J11: 5 | K11: =VLOOKUP(LARGE($K$15:$K$34,$J11),$K$15:$R$34,K$6,FALSE) -> #REF! | L11: =VLOOKUP(LARGE($K$15:$K$34,$J11),$K$15:$R$34,L$6,FALSE) -> #REF! | M11: =VLOOKUP(LARGE($K$15:$K$34,$J11),$K$15:$R$34,M$6,FALSE) -> #REF! | R11: Atrasado | S11: =COUNTIF('Cruzamento - FxO'!$K$8:$K$107,GPA!R11) -> 0
M12: =VLOOKUP(LARGE($L$15:$L$34,$J12),$L$15:$R$34,#REF!,FALSE) -> #REF! | N12: =VLOOKUP(LARGE($L$15:$L$34,$J12),$L$15:$R$34,#REF!,FALSE) -> #REF!
C14: Top 5: Áreas com mais planos de ação x Número de planos de ação atrasados | P14: Total de planos de ação | Q14: Total conforme | R14: Total atrasado
K15: =IF(O15="","",P15+N15) -> #REF! | L15: =IF(O15="","",Q15+N15) -> #REF! | M15: =IF(O15="","",R15+N15) -> #REF! | N15: 0.0002 | O15: =IF(#REF!=0,"",#REF!) -> #REF! | P15: =IF($O15="","",COUNTIF('Cruzamento - FxO'!$G$8:$G$107,$O15)) -> #REF! | Q15: =IF($O15="","",COUNTIFS('Cruzamento - FxO'!$G$8:$G$107,$O15,'Cruzamento - FxO'!$K$8:$K$107,"<>Atrasado")) -> #REF! | R15: =IF($O15="","",COUNTIFS('Cruzamento - FxO'!$G$8:$G$107,$O15,'Cruzamento - FxO'!$K$8:$K$107,"=Atrasado")) -> #REF!
K16: =IF(O16="","",P16+N16) -> #REF! | L16: =IF(O16="","",Q16+N16) -> #REF! | M16: =IF(O16="","",R16+N16) -> #REF! | N16: 0.00019 | O16: =IF(#REF!=0,"",#REF!) -> #REF! | P16: =IF($O16="","",COUNTIF('Cruzamento - FxO'!$G$8:$G$107,$O16)) -> #REF! | Q16: =IF($O16="","",COUNTIFS('Cruzamento - FxO'!$G$8:$G$107,$O16,'Cruzamento - FxO'!$K$8:$K$107,"<>Atrasado")) -> #REF! | R16: =IF($O16="","",COUNTIFS('Cruzamento - FxO'!$G$8:$G$107,$O16,'Cruzamento - FxO'!$K$8:$K$107,"=Atrasado")) -> #REF!
K17: =IF(O17="","",P17+N17) -> #REF! | L17: =IF(O17="","",Q17+N17) -> #REF! | M17: =IF(O17="","",R17+N17) -> #REF! | N17: 0.00018 | O17: =IF(#REF!=0,"",#REF!) -> #REF! | P17: =IF($O17="","",COUNTIF('Cruzamento - FxO'!$G$8:$G$107,$O17)) -> #REF! | Q17: =IF($O17="","",COUNTIFS('Cruzamento - FxO'!$G$8:$G$107,$O17,'Cruzamento - FxO'!$K$8:$K$107,"<>Atrasado")) -> #REF! | R17: =IF($O17="","",COUNTIFS('Cruzamento - FxO'!$G$8:$G$107,$O17,'Cruzamento - FxO'!$K$8:$K$107,"=Atrasado")) -> #REF!
K18: =IF(O18="","",P18+N18) -> #REF! | L18: =IF(O18="","",Q18+N18) -> #REF! | M18: =IF(O18="","",R18+N18) -> #REF! | N18: 0.00017 | O18: =IF(#REF!=0,"",#REF!) -> #REF! | P18: =IF($O18="","",COUNTIF('Cruzamento - FxO'!$G$8:$G$107,$O18)) -> #REF! | Q18: =IF($O18="","",COUNTIFS('Cruzamento - FxO'!$G$8:$G$107,$O18,'Cruzamento - FxO'!$K$8:$K$107,"<>Atrasado")) -> #REF! | R18: =IF($O18="","",COUNTIFS('Cruzamento - FxO'!$G$8:$G$107,$O18,'Cruzamento - FxO'!$K$8:$K$107,"=Atrasado")) -> #REF!
K19: =IF(O19="","",P19+N19) -> #REF! | L19: =IF(O19="","",Q19+N19) -> #REF! | M19: =IF(O19="","",R19+N19) -> #REF! | N19: 0.00016 | O19: =IF(#REF!=0,"",#REF!) -> #REF! | P19: =IF($O19="","",COUNTIF('Cruzamento - FxO'!$G$8:$G$107,$O19)) -> #REF! | Q19: =IF($O19="","",COUNTIFS('Cruzamento - FxO'!$G$8:$G$107,$O19,'Cruzamento - FxO'!$K$8:$K$107,"<>Atrasado")) -> #REF! | R19: =IF($O19="","",COUNTIFS('Cruzamento - FxO'!$G$8:$G$107,$O19,'Cruzamento - FxO'!$K$8:$K$107,"=Atrasado")) -> #REF!
K20: =IF(O20="","",P20+N20) -> #REF! | L20: =IF(O20="","",Q20+N20) -> #REF! | M20: =IF(O20="","",R20+N20) -> #REF! | N20: 0.00015 | O20: =IF(#REF!=0,"",#REF!) -> #REF! | P20: =IF($O20="","",COUNTIF('Cruzamento - FxO'!$G$8:$G$107,$O20)) -> #REF! | Q20: =IF($O20="","",COUNTIFS('Cruzamento - FxO'!$G$8:$G$107,$O20,'Cruzamento - FxO'!$K$8:$K$107,"<>Atrasado")) -> #REF! | R20: =IF($O20="","",COUNTIFS('Cruzamento - FxO'!$G$8:$G$107,$O20,'Cruzamento - FxO'!$K$8:$K$107,"=Atrasado")) -> #REF!
K21: =IF(O21="","",P21+N21) -> #REF! | L21: =IF(O21="","",Q21+N21) -> #REF! | M21: =IF(O21="","",R21+N21) -> #REF! | N21: 0.00014 | O21: =IF(#REF!=0,"",#REF!) -> #REF! | P21: =IF($O21="","",COUNTIF('Cruzamento - FxO'!$G$8:$G$107,$O21)) -> #REF! | Q21: =IF($O21="","",COUNTIFS('Cruzamento - FxO'!$G$8:$G$107,$O21,'Cruzamento - FxO'!$K$8:$K$107,"<>Atrasado")) -> #REF! | R21: =IF($O21="","",COUNTIFS('Cruzamento - FxO'!$G$8:$G$107,$O21,'Cruzamento - FxO'!$K$8:$K$107,"=Atrasado")) -> #REF!
K22: =IF(O22="","",P22+N22) -> #REF! | L22: =IF(O22="","",Q22+N22) -> #REF! | M22: =IF(O22="","",R22+N22) -> #REF! | N22: 0.00013 | O22: =IF(#REF!=0,"",#REF!) -> #REF! | P22: =IF($O22="","",COUNTIF('Cruzamento - FxO'!$G$8:$G$107,$O22)) -> #REF! | Q22: =IF($O22="","",COUNTIFS('Cruzamento - FxO'!$G$8:$G$107,$O22,'Cruzamento - FxO'!$K$8:$K$107,"<>Atrasado")) -> #REF! | R22: =IF($O22="","",COUNTIFS('Cruzamento - FxO'!$G$8:$G$107,$O22,'Cruzamento - FxO'!$K$8:$K$107,"=Atrasado")) -> #REF!
K23: =IF(O23="","",P23+N23) -> #REF! | L23: =IF(O23="","",Q23+N23) -> #REF! | M23: =IF(O23="","",R23+N23) -> #REF! | N23: 0.00012 | O23: =IF(#REF!=0,"",#REF!) -> #REF! | P23: =IF($O23="","",COUNTIF('Cruzamento - FxO'!$G$8:$G$107,$O23)) -> #REF! | Q23: =IF($O23="","",COUNTIFS('Cruzamento - FxO'!$G$8:$G$107,$O23,'Cruzamento - FxO'!$K$8:$K$107,"<>Atrasado")) -> #REF! | R23: =IF($O23="","",COUNTIFS('Cruzamento - FxO'!$G$8:$G$107,$O23,'Cruzamento - FxO'!$K$8:$K$107,"=Atrasado")) -> #REF!
K24: =IF(O24="","",P24+N24) -> #REF! | L24: =IF(O24="","",Q24+N24) -> #REF! | M24: =IF(O24="","",R24+N24) -> #REF! | N24: 0.00011 | O24: =IF(#REF!=0,"",#REF!) -> #REF! | P24: =IF($O24="","",COUNTIF('Cruzamento - FxO'!$G$8:$G$107,$O24)) -> #REF! | Q24: =IF($O24="","",COUNTIFS('Cruzamento - FxO'!$G$8:$G$107,$O24,'Cruzamento - FxO'!$K$8:$K$107,"<>Atrasado")) -> #REF! | R24: =IF($O24="","",COUNTIFS('Cruzamento - FxO'!$G$8:$G$107,$O24,'Cruzamento - FxO'!$K$8:$K$107,"=Atrasado")) -> #REF!
K25: =IF(O25="","",P25+N25) -> #REF! | L25: =IF(O25="","",Q25+N25) -> #REF! | M25: =IF(O25="","",R25+N25) -> #REF! | N25: 0.0001 | O25: =IF(#REF!=0,"",#REF!) -> #REF! | P25: =IF($O25="","",COUNTIF('Cruzamento - FxO'!$G$8:$G$107,$O25)) -> #REF! | Q25: =IF($O25="","",COUNTIFS('Cruzamento - FxO'!$G$8:$G$107,$O25,'Cruzamento - FxO'!$K$8:$K$107,"<>Atrasado")) -> #REF! | R25: =IF($O25="","",COUNTIFS('Cruzamento - FxO'!$G$8:$G$107,$O25,'Cruzamento - FxO'!$K$8:$K$107,"=Atrasado")) -> #REF!
K26: =IF(O26="","",P26+N26) -> #REF! | L26: =IF(O26="","",Q26+N26) -> #REF! | M26: =IF(O26="","",R26+N26) -> #REF! | N26: 9e-05 | O26: =IF(#REF!=0,"",#REF!) -> #REF! | P26: =IF($O26="","",COUNTIF('Cruzamento - FxO'!$G$8:$G$107,$O26)) -> #REF! | Q26: =IF($O26="","",COUNTIFS('Cruzamento - FxO'!$G$8:$G$107,$O26,'Cruzamento - FxO'!$K$8:$K$107,"<>Atrasado")) -> #REF! | R26: =IF($O26="","",COUNTIFS('Cruzamento - FxO'!$G$8:$G$107,$O26,'Cruzamento - FxO'!$K$8:$K$107,"=Atrasado")) -> #REF!
... K34: =IF(O34="","",P34+N34) -> #REF! | L34: =IF(O34="","",Q34+N34) -> #REF! | M34: =IF(O34="","",R34+N34) -> #REF! | N34: 1e-05 | O34: =IF(#REF!=0,"",#REF!) -> #REF! | P34: =IF($O34="","",COUNTIF('Cruzamento - FxO'!$G$8:$G$107,$O34)) -> #REF! | Q34: =IF($O34="","",COUNTIFS('Cruzamento - FxO'!$G$8:$G$107,$O34,'Cruzamento - FxO'!$K$8:$K$107,"<>Atrasado")) -> #REF! | R34: =IF($O34="","",COUNTIFS('Cruzamento - FxO'!$G$8:$G$107,$O34,'Cruzamento - FxO'!$K$8:$K$107,"=Atrasado")) -> #REF!

Sheet Imprimir
D1: 9. RELATÓRIO DE IMPRESSÃO
D4: Para toda essa sua Análise SWOT Pessoal aparecer no seu relatório final, é se suma importância que você imprima essa página em PDF, e depois faça o download no local indicado na atividade.
D5: Você deverá fazer a impressão em formato de pdf a partir da página 2, pois a página 1 é essa explicação.
D9: 1. Resultados SWOT
D10: 2. Resultados planos de ação
D13: 1. Resultados SWOT
D15: ='Gráficos'!C24 -> Análise das forças | K15: ='Gráficos'!H24 -> Análise das fraquezas
D17: ='Gráficos'!C26 | F17: ='Gráficos'!E26 -> 0 | K17: ='Gráficos'!H26 | M17: ='Gráficos'!J26 -> 0
D18: ='Gráficos'!C27 | F18: ='Gráficos'!E27 -> 0 | K18: ='Gráficos'!H27 | M18: ='Gráficos'!J27 -> 0
D19: ='Gráficos'!C28 | F19: ='Gráficos'!E28 -> 0 | K19: ='Gráficos'!H28 | M19: ='Gráficos'!J28 -> 0
D20: ='Gráficos'!C29 | F20: ='Gráficos'!E29 -> 0 | K20: ='Gráficos'!H29 | M20: ='Gráficos'!J29 -> 0
D21: ='Gráficos'!C30 | F21: ='Gráficos'!E30 -> 0 | K21: ='Gráficos'!H30 | M21: ='Gráficos'!J30 -> 0
D23: ='Gráficos'!C32 -> Análise das oportunidades | K23: ='Gráficos'!H32 -> Análise das ameaças
D25: ='Gráficos'!C34 | F25: ='Gráficos'!E34 -> 0 | K25: ='Gráficos'!H34 | M25: ='Gráficos'!J34 -> 0
D26: ='Gráficos'!C35 | F26: ='Gráficos'!E35 -> 0 | K26: ='Gráficos'!H35 | M26: ='Gráficos'!J35 -> 0
D27: ='Gráficos'!C36 | F27: ='Gráficos'!E36 -> 0 | K27: ='Gráficos'!H36 | M27: ='Gráficos'!J36 -> 0
D28: ='Gráficos'!C37 | F28: ='Gráficos'!E37 -> 0 | K28: ='Gráficos'!H37 | M28: ='Gráficos'!J37 -> 0
D29: ='Gráficos'!C38 | F29: ='Gráficos'!E38 -> 0 | K29: ='Gráficos'!H38 | M29: ='Gráficos'!J38 -> 0
D31: Índice de favorabilidade
D32: ='Gráficos'!C6 -> Seu índice é | E32: ='Gráficos'!C9 -> Equilíbrio - Com um cenário equilibrado vale a pena investir mais tempo de análise para saber se o seu foco será interno ou externo.
D33: ='Gráficos'!C7 -> 0
D34: Índice geral dos fatores internos e externos
D35: ='Gráficos'!C13 -> Forças | E35: ='Gráficos'!D13 -> 0 | F35: ='Gráficos'!E13 -> Suas forças estão mais altas ou iguais as suas fraquezas, mantenha esse bom resultado!
D36: ='Gráficos'!C14 -> Fraquezas | E36: ='Gráficos'!D14 -> 0 | F36: ='Gráficos'!E14 -> Suas fraquezas estão mais baixas ou iguais as suas forças, esse é um bom sinal, mas não se acomode!
D37: ='Gráficos'!C15 -> Oportunidades | E37: ='Gráficos'!D15 -> 0 | F37: ='Gráficos'!E15 -> Você tem mais oportunidades do que ameaças e isso indica um futuro promissor, só falta você alinhar quais forças vão otimizar as chances delas acontecerem de fato.
D38: ='Gráficos'!C16 -> Ameaças | E38: ='Gráficos'!D16 -> 0 | F38: ='Gráficos'!E16 -> Suas ameaças estão maiores ou iguais as oportunidades e isso indica um futuro preocupante, você precisa pensar em planos de ação para diminuir os riscos delas acontecerem o quanto antes.
D40: ='Gráficos'!C17 -> Análise geral dos fatores internos e externos | K40: Gráficos radar da análise SWOT
D42: ='Gráficos'!C19 -> Forças | E42: ='Gráficos'!D19 -> 0
D43: ='Gráficos'!C20 -> Fraquezas | E43: ='Gráficos'!D20 -> 0
D44: ='Gráficos'!C21 -> Oportunidades | E44: ='Gráficos'!D21 -> 0
D45: ='Gráficos'!C22 -> Ameaças | E45: ='Gráficos'!D22 -> 0
D47: 2. Resultados planos de ação
D49: =GPA!C5 -> Você definiu planos de ação para 0 de 0 dos principais itens da sua SWOT | F49: =GPA!E5 -> 0 | H49: =GPA!F5
D51: Status dos seus planos de ação | K51: Conformidade do dos planos de ação
D60: Top 5: Áreas com mais planos de ação x Número de planos de ação atrasados

Sheet Dúvidas e Respostas
C2: Receitas x Despesas | D2: Mês Anterior x Mês Atual | E2: Contas a Receber x Contas a Pagar | F2: Necessidade de Caixa x Acumulado
A3: =#REF! -> #REF! | B3: Positivo | C3: Parabéns! As suas receitas estão maiores do que as suas despesas. Meses com lucro são sempre interessantes para a sua empresa. Aproveite e dê uma olhada nas contas a pagar e a receber do próximo mês para saber se você vai continuar mandando bem. | D3: Boa! Suas finanças melhoraram do mês passado para esse. Que tal investigar os motivos e dedicar mais tempo para replicá-las? | E3: Legal, você tem mais recebimentos do que pagamentos para entrar em caixa. Só tome cuidado com o índice de inadimplência dos seus devedores para não transformar essa projeção em um resultado real ruim | F3: Sua necessidade de caixa para o mês que vem é menor do que você tem acumulado. Sua empresa está indo bem, mas fique de olho nos meses futuros para não ter surpresas!
A4: =#REF! -> #REF! | B4: Negativo | C4: Suas despesas estão maiores que as suas receitas, isso significa que esse mês foi de prejuízo. Você já sabe os motivos? Vale a pena olhar suas despesas no DRE para ter certeza que o resultado ruim não se repetirá. | D4: Tome cuidado, seu resultado mensal piorou do mês passado para esse. Esse mês é sempre ruim ou aconteceu alguma coisa que fez seu resultado piorar? | E4: Cuidado! Suas contas a pagar para esse mês estão superiores ao que você tem direito a receber, se você não procurar reverter essa situação, provavelmente terá prejuízo | F4: Sua necessidade de caixa para o mês que vem é maior do que você tem acumulado. É bom você ficar atento e correr atrás de mais receitas, afinal de contas, a previsão é que você entre no vermelho se tudo continuar assim
C6: Pergunta | D6: Resposta
C7: 1. O que significa SWOT? | D7: O termo SWOT é uma sigla oriunda do idioma inglês, e é um acrónimo de Forças (Strengths), Fraquezas (Weaknesses), Oportunidades (Opportunities) e Ameaças (Threats).
C8: 2. O que é análise SWOT? | D8: A Análise SWOT ou Análise FOFA ou FFOA (Forças, Fraquezas, Oportunidades e Ameaças) (em português) é uma ferramenta utilizada para fazer análise de cenário (ou análise de ambiente), sendo usada como base para gestão e planejamento estratégico de uma corporação ou empresa, mas podendo, devido a sua simplicidade, ser utilizada para qualquer tipo de análise de cenário, desde a criação de um blog à gestão de uma multinacional.
C9: 4. O que são fatores internos? | D9: Tratam-se das características específicas do seu negócio. Pontos fortes ou fracos da sua equipe, excelência ou improdutividade em processos internos, etc. Ou seja, forças e fraquezas relativas a outros players do mercado.
C10: 6. O que são forças? | D10: Forças - Vantagens internas da empresa em relação às empresas concorrentes.
C11: 7. O que são fraquezas? | D11: Fraquezas - Desvantagens internas da empresa em relação às empresas concorrentes.
C12: 5. O que são fatores externos? | D12: Tratam-se das características e mudanças que o mercado como um todo pode apresentar que poderão beneficiar ou atrapalhar seu negócio. Oportunidades são as positivas e Ameaças são as negativas.
C13: 6. O que são oportunidades? | D13: Oportunidades - Aspectos positivos do mercado com potencial de fazer crescer a vantagem competitiva da empresa.
C14: 7. O que são ameaças? | D14: Ameaças - Aspectos positivos do mercado com potencial de comprometer a vantagem competitiva da empresa.
C15: 8. O que são cruzamentos de dados? | D15: A combinação destes dois ambientes, interno e externo, e das suas variáveis, Forças e Fraquezas; Oportunidades e Ameaças, irá facilitar a análise e a procura para tomada de decisões na definição das estratégias de negócios da empresa. Forças e Oportunidades - Tirar o máximo partido dos pontos fortes para aproveitar ao máximo as oportunidades detectadas. Forças e Ameaças - Tirar o máximo partido dos pontos fortes para minimizar os efeitos das ameaças detectadas. Fraquezas e Oportunidades - Desenvolver estratégias que minimizem os efeitos negativos dos pontos fracos e que em simultâneo aproveitem as oportunidades detectadas. Fraquezas e Ameaças - As estratégias a adotar devem minimizar ou ultrapassar os pontos fracos e, tanto quanto possível, fazer face às ameaças.
C16: 9. O que é matriz SWOT | D16: É uma matriz em que se identificam as suas maiores forças, fraquezas, oportunidades e ameaças. Permite distinguir o ambiente interno - (factores e realidades internas - forças e fraquezas) e o ambiente externo (factores e aspectos futuros - oportunidades e ameaças) da organização.
C17: 8. Posso adicionar mais linhas e colunas na planilha? | D17: Nós recomendamos fortemente que você utilize a estrutura pronta apresentada, pois existem diversas fórmulas que podem ser afetadas pela adição de linhas e colunas. Além disso, para facilitar o preenchimento mantemos a planilha desbloqueada apenas nos locais para preenchimento.
... C21: 12. Como desbloquear a planilha? | D21: Basta entrar no menu superior "Revisão" e escolher o item desproteger planilha no grupo Alterações. As planilhas não possuem senhas, apenas estão bloqueadas para melhorar a usabilidade delas
