Workbook

Sheet Calculadora de Salário Alvo (OT
C2: CALCULADORA DE SALÁRIO ALVO (OTE) DE SDRs/BDRs
B4: Parâmetros | E4: Legenda das células
B5: Ticket Médio da Solução | C5: Acima de R$ 10.000,00 | E5: Editável ->
B6: Foco de Atuação (Canal) | C6: Outbound Sales | E6: Sugestão GM ->
B7: Região da Empresa | C7: Sudeste | E7: Não Editável ->
B8: Setor da Empresa | C8: Tecnologia, Software, Finanças, Consultoria
B9: Senioridade | C9: Junior | D9: =IF(AND(C5=Apoio!L10,C6=Apoio!F6,C9<>Apoio!O7),"Para o canal outbound marketing e tickets acima de 10 mil reais o SDR/BDR deve ser senior",IF(AND(C9=Apoio!O5,C6=Apoio!F6),"Para o canal outbound marketing, o SDR/BDR deve ser pleno ou senior",IF(AND(C5=Apoio!L10,C9=Apoio!O5),"Para tickets acima de 10 mil reais o SDR/BDR deve ser pleno ou senior",""))) -> Para o canal outbound marketing e tickets acima de 10 mil reais o SDR/BDR deve ser senior
B10: Regime de Contratação | C10: PJ
B11: % Variável do Salário Fixo | C11: 0.3
B13: Resultado
B14: Salário Fixo | C14: {=IFERROR(FLOOR(IF(Apoio!A5*INDEX(Apoio!D5:D9,MATCH(C7,Apoio!C5:C9,0))*INDEX(Apoio!G5:G9,MATCH(C6,Apoio!F5:F9,0))*INDEX(Apoio!J5:J9,MATCH(C8,Apoio!I5:I9,0))*INDEX(Apoio!M5:M12,MATCH(C5,Apoio!L5:L12,0))*INDEX(Apoio!P5:P9,MATCH(C9,Apoio!O5:O9,0))*INDEX(Apoio!U5:U9,MATCH(C10,Apoio!T5:T9,0))<1600,1600,Apoio!A5*INDEX(Apoio!D5:D9,MATCH(C7,Apoio!C5:C9,0))*INDEX(Apoio!G5:G9,MATCH(C6,Apoio!F5:F9,0))*INDEX(Apoio!J5:J9,MATCH(C8,Apoio!I5:I9,0))*INDEX(Apoio!M5:M12,MATCH(C5,Apoio!L5:L12,0))*INDEX(Apoio!P5:P9,MATCH(C9,Apoio!O5:O9,0))*INDEX(Apoio!U5:U9,MATCH(C10,Apoio!T5:T9,0))),100),"Preencha os parâmetros")} -> 1600
B15: Salário Variável | C15: =IFERROR(C14*C11,"") -> 480
B16: OTE (Salário Alvo) | C16: =SUM(C14:C15) -> 2080
B18: Definições:
B19: Existem muitos conceitos e definições diferentes para SDR e BDR. Contudo, existem dois conceitos mais fortes:
B20: 1 - SDR é quem faz inbound e BDR é quem faz outbound
B21: 2 - SDR faz inbound e oubound, desde que o ticket médio não seja tão alto e BDR faz outbound com ticket médio alto

Sheet Calculadora de Salário Variável
C2: CALCULADORA DE SALÁRIO VARIÁVEL DE SDRs/BDRs
B4: OTE Variável | C4: ='Calculadora de Salário Alvo (OT'!C15 -> 480 | F4: Legenda das células
F5: Editável ->
B6: Faixa de Atingimento da Meta x Ganho | F6: Sugestão GM ->
B7: Abaixo 75% | C7: 0.8 | F7: Não Editável ->
B8: De 75 a 100% | C8: 1
B9: De 101 a 120% | C9: 1.2
B10: Acima de 120% | C10: 1.5
B12: Critérios de Comissão (SDR Rampado) | F12: Comissão Unitária por Faixa de Atingimento
B13: Critérios | C13: % da Comissão | D13: Meta | E13: OTE Variável | F13: =B7 -> Abaixo 75% | G13: =B8 -> De 75 a 100% | H13: =B9 -> De 101 a 120% | I13: =B10 -> Acima de 120%
B14: REUNIÃO AGENDADA | C14: 0.3 | D14: 20 | E14: =C14*$C$4 -> 144 | F14: =$E14/$D14*$C$7 -> 5.76 | G14: =$E14/$D14*$C$8 -> 7.2 | H14: =$E14/$D14*$C$9 -> 8.64 | I14: =$E14/$D14*$C$10 -> 10.8
B15: REUNIÃO REALIZADA | C15: 0.7 | D15: 10 | E15: =C15*$C$4 -> 336 | F15: =$E15/$D15*$C$7 -> 26.88 | G15: =$E15/$D15*$C$8 -> 33.6 | H15: =$E15/$D15*$C$9 -> 40.32 | I15: =$E15/$D15*$C$10 -> 50.4
B17: Bonificação por Venda | F17: =E14+E15 -> 480
B18: Será Pago? | C18: Sim
B19: Meta de REUNIÃO REALIZDA | C19: 50
B20: % OTE Variável | C20: 0.3
B21: Bônus por REUNIÃO REALIZADA | C21: =IFERROR(IF(C18="Não","-",C4*C20/C19),"-") -> 2.88
B22: Bônus Total | C22: =IFERROR(IF(C18="Não","-",C21*C19),"-") -> 144
B25: Resumo do Salário OTE Final (Meta 100%)
B26: Salário Fixo | C26: ='Calculadora de Salário Alvo (OT'!C14 -> 1600
B27: Comissão | C27: =C4 -> 480
B28: Bônus | C28: =IF(C18="Não","-",C22) -> 144
B29: Salário Final | C29: =SUM(C26:C28) -> 2224
B31: Legendas
B32: OTE = On-Target Earnings = Salário Alvo; Logo, OTE Variável = Salário Variável Alvo
B33: SQL = Sales-Qualified Lead = Reunião Agendada
B34: SAL = Sales-Accepted Lead = Reunião Aceita por Vendas
B35: SDR Rampado = SDR Pós Período de Onboarding

Sheet Simulador de Comissão
C2: SIMULADOR DE COMISSÃO DE SDRs/BDRs
B4: Etapas | C4: Meta | D4: Realizado | E4: % Atingido | F4: Valor Unitário | G4: Variável
B5: SQL | C5: 25 | D5: 20 | E5: =IFERROR(D5/C5,1) -> 0.8 | F5: {=IFERROR(INDEX(Apoio!F15:F18,MATCH(TRUE(),Apoio!I15:I18,0)),"")} -> 7.2
B6: SAL | C6: 15 | D6: 12 | E6: =IFERROR(D6/C6,1) -> 0.8 | F6: {=IFERROR(INDEX(Apoio!F21:F24,MATCH(TRUE(),Apoio!I21:I24,0)),"")} -> 33.6 | G6: =F5*D5 -> 144
B7: Vendas | C7: 5 | D7: 3 | E7: =IFERROR(D7/C7,1) -> 0.6 | F7: ='Calculadora de Salário Variável'!C21 -> 2.88 | G7: =F7*D7 -> 8.64
G8: =SUM(G6:G7) -> 152.64
B10: Salário Total do Mês | E10: Legenda das células
B11: Salário Base | C11: ='Calculadora de Salário Alvo (OT'!C14 -> 1600 | E11: Editável ->
B12: Comissão | C12: =SUM(G6) -> 144 | E12: Sugestão GM ->
B13: Bonificação | C13: =G7 -> 8.64 | E13: Não Editável ->
B14: Total | C14: =SUM(C10:C12) -> 1744
B17: Comparativo - Real x OTE
B18: Salário Total | C18: =C14 -> 1744
B19: OTE | C19: ='Calculadora de Salário Alvo (OT'!C16 -> 2080
B20: % de Atingimento | C20: =C18/C19 -> 0.83846154
B22: Observação
B23: Essa aba serve para você, cliente MS, inserir o realizado e ver quanto deve pagar para o SDR/BDR no mês

Sheet Validação
B6: Mês | C6: Júnior | D6: Pleno | E6: Sênior
B7: 1 | C7: =C8-20% -> 0.4 | D7: 0.5 | E7: 0.6
B8: 2 | C8: =C9-20% -> 0.6 | D8: 0.7 | E8: 0.8
B9: 3 | C9: =C10-20% -> 0.8 | D9: 0.9 | E9: 1
B10: 4 ou mais | C10: 1 | D10: 1.1 | E10: 1.2

Sheet Apoio
A4: Salário base | C4: região | F4: Canal de Aquisição | I4: Setor da empresa | L4: Ticket Médio | O4: Senioridade | R4: % Variável do Salário Fixo | T4: Regime de contratação
A5: 1650 | C5: Sudeste | D5: 1 | F5: Inbound Sales | G5: 0.9 | I5: Tecnologia, Software, Finanças, Consultoria | J5: 1 | L5: Até R$ 600,00 | M5: 0.7 | O5: Junior | P5: 0.7 | R5: 0.2 | T5: CLT | U5: 1
C6: Centro-Oeste | D6: 0.9 | F6: Outbound Sales | G6: 1 | I6: Demais Setores (Indústria, Serviço etc) | J6: 0.8 | L6: R$ 601,00 - R$ 1.500,00 | M6: 0.8 | O6: Pleno | P6: 1 | R6: 0.3 | T6: PJ | U6: 1.2
C7: Sul | D7: 0.9 | L7: R$ 1.501,00 - R$ 2.500,00 | M7: 0.9 | O7: Senior | P7: 1.3 | R7: 0.4
C8: Norte | D8: 0.8 | L8: R$ 2.501,00 - R$ 5.000,00 | M8: 1 | R8: 0.5
C9: Nordeste | D9: 0.8 | L9: R$ 5.001,00 - R$ 10.000,00 | M9: 1 | R9: 0.7
L10: Acima de R$ 10.000,00 | M10: 1 | R10: 1
G14: SQL | H14: ='Simulador de Comissão'!E5 -> 0.8
F15: ='Calculadora de Salário Variável'!F14 -> 5.76 | G15: 0 | H15: 0.7498 | I15: =AND($H$14>=MIN(G15,H15),$H$14<=MAX(G15,H15)) -> FALSE
F16: ='Calculadora de Salário Variável'!G14 -> 7.2 | G16: 0.75 | H16: 1 | I16: =AND($H$14>=MIN(G16,H16),$H$14<=MAX(G16,H16)) -> TRUE
F17: ='Calculadora de Salário Variável'!H14 -> 8.64 | G17: 1.0001 | H17: 1.2 | I17: =AND($H$14>=MIN(G17,H17),$H$14<=MAX(G17,H17)) -> FALSE
F18: ='Calculadora de Salário Variável'!I14 -> 10.8 | G18: 1.201 | H18: 100000 | I18: =AND($H$14>=MIN(G18,H18),$H$14<=MAX(G18,H18)) -> FALSE
G20: SAL | H20: ='Simulador de Comissão'!E6 -> 0.8
F21: ='Calculadora de Salário Variável'!F15 -> 26.88 | G21: 0 | H21: 0.7499 | I21: =AND($H$20>=MIN(G21,H21),$H$20<=MAX(G21,H21)) -> FALSE
F22: ='Calculadora de Salário Variável'!G15 -> 33.6 | G22: 0.75 | H22: 1 | I22: =AND($H$20>=MIN(G22,H22),$H$20<=MAX(G22,H22)) -> TRUE
F23: ='Calculadora de Salário Variável'!H15 -> 40.32 | G23: 1.0001 | H23: 1.2 | I23: =AND($H$20>=MIN(G23,H23),$H$20<=MAX(G23,H23)) -> FALSE
C24: Bonificação | F24: ='Calculadora de Salário Variável'!I15 -> 50.4 | G24: 1.201 | H24: 100000 | I24: =AND($H$20>=MIN(G24,H24),$H$20<=MAX(G24,H24)) -> FALSE
C25: 0.2
C26: 0.3
C27: 0.4
C28: 0.5
C29: 0.7
C30: 1

Sheet Início
E2: CALCULADORA DE REMUNERAÇÃO DE SDRs/BDRs
B4: Objetivo
C6: Definir os parâmetros e calcular a remuneração total de SDRs/BDRs, dividido em salário e comissionamento. Além disso, criar o modelo variável, bem como simular o pagamento ao final do mês do colaborador
B10: Acessos Importantes de Consulta
C20: Manual do Cliente: Manual com o descritivo sobre a parte conceitual e de uso deste template
C21: Vídeo Explicativo: Vídeos explicativos sobre os conceitos e principalmente sobre o funcionamento deste template
