Workbook
Name zsupermetrics_refreshAll: SupermetricsQueries!$H$5
Name zsupermetrics_forceRefresh: SupermetricsQueries!$H$4
Name zsupermetrics_refreshAllSilent: SupermetricsQueries!$H$6

Sheet WEBINAR SEMANAL
A1: WEBINAR SEMANAL (MKT) | B1: VOLUME | J1: CUSTOS | R1: NUM FINAIS | AC1: VOLUME SEMANAL | AK1: NÚMEROS FINAIS SEMANAL
B2: Leads | C2: Leads +MQL | D2: AGENDAMENTOS | E2: CALLS | F2: PESSOAS NO PITCH | G2: VENDAS | H2: V. MKT | I2: V. COM | J2: CPL | K2: CPL MQL | L2: CP AG | M2: CP. C.R | N2: C P/ PESSOA PITCH | O2: CAC GERAL | P2: CAC MKT | Q2: CAC COM | R2: INVESTIMENTO | S2: FATURAMENTO | T2: FAT MKT | U2: FAT COM | V2: Ticket médio | W2: T.M MKT | X2: T.M COM | Y2: ROAS | Z2: ROAS MKT | AA2: ROAS COM | AC2: Leads | AD2: Leads +MQL | AE2: AGENDAMENTOS | AF2: CALLS | AG2: PESSOAS NO PITCH | AH2: VENDAS | AI2: V. MKT | AJ2: V. COM | AK2: INVESTIMENTO | AL2: FATURAMENTO | AM2: FAT MKT | AN2: FAT COM | AO2: Ticket médio | AP2: T.M MKT | AQ2: T.M COM | AR2: ROAS | AS2: ROAS MKT | AT2: ROAS COM
A3: Janeiro | B3: =R3/J3 -> 500 | C3: =B3*0.25 -> 125 | D3: =B3*0.1 -> 50 | E3: =D3*0.7 -> 35 | F3: =B3*0.25 -> 125 | G3: =H3+I3 -> 17 | H3: =F3*0.08 -> 10 | I3: =E3*0.2 -> 7 | J3: =20 -> 20 | K3: =R3/C3 -> 80 | L3: =R3/D3 -> 200 | M3: =R3/E3 -> 285.71429 | N3: =R3/F3 -> 80 | O3: =R3/G3 -> 588.23529 | P3: =R3/H3 -> 1000 | Q3: =R3/I3 -> 1428.5714 | R3: =10000 -> 10000 | S3: =T3+U3 -> 165000 | T3: =W3*H3 -> 25000 | U3: =X3*I3 -> 140000 | V3: =S3/G3 -> 9705.8824 | W3: 2500 | X3: =20000 -> 20000 | Y3: =S3/R3 -> 16.5 | Z3: =T3/R3 -> 2.5 | AA3: =U3/R3 -> 14 | AC3: =B3/4 -> 125 | AD3: =C3/4 -> 31.25 | AE3: =D3/4 -> 12.5 | AF3: =E3/4 -> 8.75 | AG3: =F3/4 -> 31.25 | AH3: =G3/4 -> 4.25 | AI3: =H3/4 -> 2.5 | AJ3: =I3/4 -> 1.75 | AK3: =R3/4 -> 2500 | AL3: =S3/4 -> 41250 | AM3: =T3/4 -> 6250 | AN3: =U3/4 -> 35000 | AO3: =AL3/AH3 -> 9705.8824 | AP3: 2500 | AQ3: =20000 -> 20000 | AR3: =AL3/AK3 -> 16.5 | AS3: =AM3/AK3 -> 2.5 | AT3: =AN3/AK3 -> 14
A4: fevereiro | B4: =R4/J4 -> 1000 | C4: =B4*0.25 -> 250 | D4: =B4*0.1 -> 100 | E4: =D4*0.7 -> 70 | F4: =B4*0.25 -> 250 | G4: =H4+I4 -> 34 | H4: =F4*0.08 -> 20 | I4: =E4*0.2 -> 14 | J4: =20 -> 20 | K4: =R4/C4 -> 80 | L4: =R4/D4 -> 200 | M4: =R4/E4 -> 285.71429 | N4: =R4/F4 -> 80 | O4: =R4/G4 -> 588.23529 | P4: =R4/H4 -> 1000 | Q4: =R4/I4 -> 1428.5714 | R4: =20000 -> 20000 | S4: =T4+U4 -> 330000 | T4: =W4*H4 -> 50000 | U4: =X4*I4 -> 280000 | V4: =S4/G4 -> 9705.8824 | W4: 2500 | X4: =20000 -> 20000 | Y4: =S4/R4 -> 16.5 | Z4: =T4/R4 -> 2.5 | AA4: =U4/R4 -> 14 | AC4: =B4/4 -> 250 | AD4: =C4/4 -> 62.5 | AE4: =D4/4 -> 25 | AF4: =E4/4 -> 17.5 | AG4: =F4/4 -> 62.5 | AH4: =G4/4 -> 8.5 | AI4: =H4/4 -> 5 | AJ4: =I4/4 -> 3.5 | AK4: =R4/4 -> 5000 | AL4: =S4/4 -> 82500 | AM4: =T4/4 -> 12500 | AN4: =U4/4 -> 70000 | AO4: =AL4/AH4 -> 9705.8824 | AP4: 2500 | AQ4: =20000 -> 20000 | AR4: =AL4/AK4 -> 16.5 | AS4: =AM4/AK4 -> 2.5 | AT4: =AN4/AK4 -> 14
A5: março | B5: =R5/J5 -> 1500 | C5: =B5*0.25 -> 375 | D5: =B5*0.1 -> 150 | E5: =D5*0.7 -> 105 | F5: =B5*0.25 -> 375 | G5: =H5+I5 -> 51 | H5: =F5*0.08 -> 30 | I5: =E5*0.2 -> 21 | J5: =20 -> 20 | K5: =R5/C5 -> 80 | L5: =R5/D5 -> 200 | M5: =R5/E5 -> 285.71429 | N5: =R5/F5 -> 80 | O5: =R5/G5 -> 588.23529 | P5: =R5/H5 -> 1000 | Q5: =R5/I5 -> 1428.5714 | R5: =30000 -> 30000 | S5: =T5+U5 -> 495000 | T5: =W5*H5 -> 75000 | U5: =X5*I5 -> 420000 | V5: =S5/G5 -> 9705.8824 | W5: 2500 | X5: =20000 -> 20000 | Y5: =S5/R5 -> 16.5 | Z5: =T5/R5 -> 2.5 | AA5: =U5/R5 -> 14 | AC5: =B5/4 -> 375 | AD5: =C5/4 -> 93.75 | AE5: =D5/4 -> 37.5 | AF5: =E5/4 -> 26.25 | AG5: =F5/4 -> 93.75 | AH5: =G5/4 -> 12.75 | AI5: =H5/4 -> 7.5 | AJ5: =I5/4 -> 5.25 | AK5: =R5/4 -> 7500 | AL5: =S5/4 -> 123750 | AM5: =T5/4 -> 18750 | AN5: =U5/4 -> 105000 | AO5: =AL5/AH5 -> 9705.8824 | AP5: 2500 | AQ5: =20000 -> 20000 | AR5: =AL5/AK5 -> 16.5 | AS5: =AM5/AK5 -> 2.5 | AT5: =AN5/AK5 -> 14
A6: abril | B6: =R6/J6 -> 2500 | C6: =B6*0.25 -> 625 | D6: =B6*0.1 -> 250 | E6: =D6*0.7 -> 175 | F6: =B6*0.25 -> 625 | G6: =H6+I6 -> 85 | H6: =F6*0.08 -> 50 | I6: =E6*0.2 -> 35 | J6: =20 -> 20 | K6: =R6/C6 -> 80 | L6: =R6/D6 -> 200 | M6: =R6/E6 -> 285.71429 | N6: =R6/F6 -> 80 | O6: =R6/G6 -> 588.23529 | P6: =R6/H6 -> 1000 | Q6: =R6/I6 -> 1428.5714 | R6: =50000 -> 50000 | S6: =T6+U6 -> 825000 | T6: =W6*H6 -> 125000 | U6: =X6*I6 -> 700000 | V6: =S6/G6 -> 9705.8824 | W6: 2500 | X6: =20000 -> 20000 | Y6: =S6/R6 -> 16.5 | Z6: =T6/R6 -> 2.5 | AA6: =U6/R6 -> 14 | AC6: =B6/4 -> 625 | AD6: =C6/4 -> 156.25 | AE6: =D6/4 -> 62.5 | AF6: =E6/4 -> 43.75 | AG6: =F6/4 -> 156.25 | AH6: =G6/4 -> 21.25 | AI6: =H6/4 -> 12.5 | AJ6: =I6/4 -> 8.75 | AK6: =R6/4 -> 12500 | AL6: =S6/4 -> 206250 | AM6: =T6/4 -> 31250 | AN6: =U6/4 -> 175000 | AO6: =AL6/AH6 -> 9705.8824 | AP6: 2500 | AQ6: =20000 -> 20000 | AR6: =AL6/AK6 -> 16.5 | AS6: =AM6/AK6 -> 2.5 | AT6: =AN6/AK6 -> 14
A7: maio | B7: =R7/J7 -> 2500 | C7: =B7*0.25 -> 625 | D7: =B7*0.1 -> 250 | E7: =D7*0.7 -> 175 | F7: =B7*0.25 -> 625 | G7: =H7+I7 -> 85 | H7: =F7*0.08 -> 50 | I7: =E7*0.2 -> 35 | J7: =20 -> 20 | K7: =R7/C7 -> 80 | L7: =R7/D7 -> 200 | M7: =R7/E7 -> 285.71429 | N7: =R7/F7 -> 80 | O7: =R7/G7 -> 588.23529 | P7: =R7/H7 -> 1000 | Q7: =R7/I7 -> 1428.5714 | R7: =50000 -> 50000 | S7: =T7+U7 -> 825000 | T7: =W7*H7 -> 125000 | U7: =X7*I7 -> 700000 | V7: =S7/G7 -> 9705.8824 | W7: 2500 | X7: =20000 -> 20000 | Y7: =S7/R7 -> 16.5 | Z7: =T7/R7 -> 2.5 | AA7: =U7/R7 -> 14 | AC7: =B7/4 -> 625 | AD7: =C7/4 -> 156.25 | AE7: =D7/4 -> 62.5 | AF7: =E7/4 -> 43.75 | AG7: =F7/4 -> 156.25 | AH7: =G7/4 -> 21.25 | AI7: =H7/4 -> 12.5 | AJ7: =I7/4 -> 8.75 | AK7: =R7/4 -> 12500 | AL7: =S7/4 -> 206250 | AM7: =T7/4 -> 31250 | AN7: =U7/4 -> 175000 | AO7: =AL7/AH7 -> 9705.8824 | AP7: 2500 | AQ7: =20000 -> 20000 | AR7: =AL7/AK7 -> 16.5 | AS7: =AM7/AK7 -> 2.5 | AT7: =AN7/AK7 -> 14
A8: junho | B8: =R8/J8 -> 500 | C8: =B8*0.25 -> 125 | D8: =B8*0.1 -> 50 | E8: =D8*0.7 -> 35 | F8: =B8*0.25 -> 125 | G8: =H8+I8 -> 17 | H8: =F8*0.08 -> 10 | I8: =E8*0.2 -> 7 | J8: =20 -> 20 | K8: =R8/C8 -> 80 | L8: =R8/D8 -> 200 | M8: =R8/E8 -> 285.71429 | N8: =R8/F8 -> 80 | O8: =R8/G8 -> 588.23529 | P8: =R8/H8 -> 1000 | Q8: =R8/I8 -> 1428.5714 | R8: =10000 -> 10000 | S8: =T8+U8 -> 165000 | T8: =W8*H8 -> 25000 | U8: =X8*I8 -> 140000 | V8: =S8/G8 -> 9705.8824 | W8: 2500 | X8: =20000 -> 20000 | Y8: =S8/R8 -> 16.5 | Z8: =T8/R8 -> 2.5 | AA8: =U8/R8 -> 14 | AC8: =B8/4 -> 125 | AD8: =C8/4 -> 31.25 | AE8: =D8/4 -> 12.5 | AF8: =E8/4 -> 8.75 | AG8: =F8/4 -> 31.25 | AH8: =G8/4 -> 4.25 | AI8: =H8/4 -> 2.5 | AJ8: =I8/4 -> 1.75 | AK8: =R8/4 -> 2500 | AL8: =S8/4 -> 41250 | AM8: =T8/4 -> 6250 | AN8: =U8/4 -> 35000 | AO8: =AL8/AH8 -> 9705.8824 | AP8: 2500 | AQ8: =20000 -> 20000 | AR8: =AL8/AK8 -> 16.5 | AS8: =AM8/AK8 -> 2.5 | AT8: =AN8/AK8 -> 14
A9: julho | B9: =R9/J9 -> 1500 | C9: =B9*0.25 -> 375 | D9: =B9*0.1 -> 150 | E9: =D9*0.7 -> 105 | F9: =B9*0.25 -> 375 | G9: =H9+I9 -> 51 | H9: =F9*0.08 -> 30 | I9: =E9*0.2 -> 21 | J9: =20 -> 20 | K9: =R9/C9 -> 80 | L9: =R9/D9 -> 200 | M9: =R9/E9 -> 285.71429 | N9: =R9/F9 -> 80 | O9: =R9/G9 -> 588.23529 | P9: =R9/H9 -> 1000 | Q9: =R9/I9 -> 1428.5714 | R9: 30000 | S9: =T9+U9 -> 495000 | T9: =W9*H9 -> 75000 | U9: =X9*I9 -> 420000 | V9: =S9/G9 -> 9705.8824 | W9: 2500 | X9: =20000 -> 20000 | Y9: =S9/R9 -> 16.5 | Z9: =T9/R9 -> 2.5 | AA9: =U9/R9 -> 14 | AC9: =B9/4 -> 375 | AD9: =C9/4 -> 93.75 | AE9: =D9/4 -> 37.5 | AF9: =E9/4 -> 26.25 | AG9: =F9/4 -> 93.75 | AH9: =G9/4 -> 12.75 | AI9: =H9/4 -> 7.5 | AJ9: =I9/4 -> 5.25 | AK9: =R9/4 -> 7500 | AL9: =S9/4 -> 123750 | AM9: =T9/4 -> 18750 | AN9: =U9/4 -> 105000 | AO9: =AL9/AH9 -> 9705.8824 | AP9: 2500 | AQ9: =20000 -> 20000 | AR9: =AL9/AK9 -> 16.5 | AS9: =AM9/AK9 -> 2.5 | AT9: =AN9/AK9 -> 14
A10: agosto | B10: =R10/J10 -> 1500 | C10: =B10*0.25 -> 375 | D10: =B10*0.1 -> 150 | E10: =D10*0.7 -> 105 | F10: =B10*0.25 -> 375 | G10: =H10+I10 -> 51 | H10: =F10*0.08 -> 30 | I10: =E10*0.2 -> 21 | J10: =20 -> 20 | K10: =R10/C10 -> 80 | L10: =R10/D10 -> 200 | M10: =R10/E10 -> 285.71429 | N10: =R10/F10 -> 80 | O10: =R10/G10 -> 588.23529 | P10: =R10/H10 -> 1000 | Q10: =R10/I10 -> 1428.5714 | R10: =30000 -> 30000 | S10: =T10+U10 -> 495000 | T10: =W10*H10 -> 75000 | U10: =X10*I10 -> 420000 | V10: =S10/G10 -> 9705.8824 | W10: 2500 | X10: =20000 -> 20000 | Y10: =S10/R10 -> 16.5 | Z10: =T10/R10 -> 2.5 | AA10: =U10/R10 -> 14 | AC10: =B10/4 -> 375 | AD10: =C10/4 -> 93.75 | AE10: =D10/4 -> 37.5 | AF10: =E10/4 -> 26.25 | AG10: =F10/4 -> 93.75 | AH10: =G10/4 -> 12.75 | AI10: =H10/4 -> 7.5 | AJ10: =I10/4 -> 5.25 | AK10: =R10/4 -> 7500 | AL10: =S10/4 -> 123750 | AM10: =T10/4 -> 18750 | AN10: =U10/4 -> 105000 | AO10: =AL10/AH10 -> 9705.8824 | AP10: 2500 | AQ10: =20000 -> 20000 | AR10: =AL10/AK10 -> 16.5 | AS10: =AM10/AK10 -> 2.5 | AT10: =AN10/AK10 -> 14
A11: setembro | B11: =R11/J11 -> 1500 | C11: =B11*0.25 -> 375 | D11: =B11*0.1 -> 150 | E11: =D11*0.7 -> 105 | F11: =B11*0.25 -> 375 | G11: =H11+I11 -> 51 | H11: =F11*0.08 -> 30 | I11: =E11*0.2 -> 21 | J11: =20 -> 20 | K11: =R11/C11 -> 80 | L11: =R11/D11 -> 200 | M11: =R11/E11 -> 285.71429 | N11: =R11/F11 -> 80 | O11: =R11/G11 -> 588.23529 | P11: =R11/H11 -> 1000 | Q11: =R11/I11 -> 1428.5714 | R11: =30000 -> 30000 | S11: =T11+U11 -> 495000 | T11: =W11*H11 -> 75000 | U11: =X11*I11 -> 420000 | V11: =S11/G11 -> 9705.8824 | W11: 2500 | X11: =20000 -> 20000 | Y11: =S11/R11 -> 16.5 | Z11: =T11/R11 -> 2.5 | AA11: =U11/R11 -> 14 | AC11: =B11/4 -> 375 | AD11: =C11/4 -> 93.75 | AE11: =D11/4 -> 37.5 | AF11: =E11/4 -> 26.25 | AG11: =F11/4 -> 93.75 | AH11: =G11/4 -> 12.75 | AI11: =H11/4 -> 7.5 | AJ11: =I11/4 -> 5.25 | AK11: =R11/4 -> 7500 | AL11: =S11/4 -> 123750 | AM11: =T11/4 -> 18750 | AN11: =U11/4 -> 105000 | AO11: =AL11/AH11 -> 9705.8824 | AP11: 2500 | AQ11: =20000 -> 20000 | AR11: =AL11/AK11 -> 16.5 | AS11: =AM11/AK11 -> 2.5 | AT11: =AN11/AK11 -> 14
A12: outubro | B12: =R12/J12 -> 2500 | C12: =B12*0.25 -> 625 | D12: =B12*0.1 -> 250 | E12: =D12*0.7 -> 175 | F12: =B12*0.25 -> 625 | G12: =H12+I12 -> 85 | H12: =F12*0.08 -> 50 | I12: =E12*0.2 -> 35 | J12: =20 -> 20 | K12: =R12/C12 -> 80 | L12: =R12/D12 -> 200 | M12: =R12/E12 -> 285.71429 | N12: =R12/F12 -> 80 | O12: =R12/G12 -> 588.23529 | P12: =R12/H12 -> 1000 | Q12: =R12/I12 -> 1428.5714 | R12: =50000 -> 50000 | S12: =T12+U12 -> 825000 | T12: =W12*H12 -> 125000 | U12: =X12*I12 -> 700000 | V12: =S12/G12 -> 9705.8824 | W12: 2500 | X12: =20000 -> 20000 | Y12: =S12/R12 -> 16.5 | Z12: =T12/R12 -> 2.5 | AA12: =U12/R12 -> 14 | AC12: =B12/4 -> 625 | AD12: =C12/4 -> 156.25 | AE12: =D12/4 -> 62.5 | AF12: =E12/4 -> 43.75 | AG12: =F12/4 -> 156.25 | AH12: =G12/4 -> 21.25 | AI12: =H12/4 -> 12.5 | AJ12: =I12/4 -> 8.75 | AK12: =R12/4 -> 12500 | AL12: =S12/4 -> 206250 | AM12: =T12/4 -> 31250 | AN12: =U12/4 -> 175000 | AO12: =AL12/AH12 -> 9705.8824 | AP12: 2500 | AQ12: =20000 -> 20000 | AR12: =AL12/AK12 -> 16.5 | AS12: =AM12/AK12 -> 2.5 | AT12: =AN12/AK12 -> 14
A13: novembro | B13: =R13/J13 -> 2500 | C13: =B13*0.25 -> 625 | D13: =B13*0.1 -> 250 | E13: =D13*0.7 -> 175 | F13: =B13*0.25 -> 625 | G13: =H13+I13 -> 85 | H13: =F13*0.08 -> 50 | I13: =E13*0.2 -> 35 | J13: =20 -> 20 | K13: =R13/C13 -> 80 | L13: =R13/D13 -> 200 | M13: =R13/E13 -> 285.71429 | N13: =R13/F13 -> 80 | O13: =R13/G13 -> 588.23529 | P13: =R13/H13 -> 1000 | Q13: =R13/I13 -> 1428.5714 | R13: =50000 -> 50000 | S13: =T13+U13 -> 825000 | T13: =W13*H13 -> 125000 | U13: =X13*I13 -> 700000 | V13: =S13/G13 -> 9705.8824 | W13: 2500 | X13: =20000 -> 20000 | Y13: =S13/R13 -> 16.5 | Z13: =T13/R13 -> 2.5 | AA13: =U13/R13 -> 14 | AC13: =B13/4 -> 625 | AD13: =C13/4 -> 156.25 | AE13: =D13/4 -> 62.5 | AF13: =E13/4 -> 43.75 | AG13: =F13/4 -> 156.25 | AH13: =G13/4 -> 21.25 | AI13: =H13/4 -> 12.5 | AJ13: =I13/4 -> 8.75 | AK13: =R13/4 -> 12500 | AL13: =S13/4 -> 206250 | AM13: =T13/4 -> 31250 | AN13: =U13/4 -> 175000 | AO13: =AL13/AH13 -> 9705.8824 | AP13: 2500 | AQ13: =20000 -> 20000 | AR13: =AL13/AK13 -> 16.5 | AS13: =AM13/AK13 -> 2.5 | AT13: =AN13/AK13 -> 14
A14: dezembro | B14: =R14/J14 -> 500 | C14: =B14*0.25 -> 125 | D14: =B14*0.1 -> 50 | E14: =D14*0.7 -> 35 | F14: =B14*0.25 -> 125 | G14: =H14+I14 -> 17 | H14: =F14*0.08 -> 10 | I14: =E14*0.2 -> 7 | J14: =20 -> 20 | K14: =R14/C14 -> 80 | L14: =R14/D14 -> 200 | M14: =R14/E14 -> 285.71429 | N14: =R14/F14 -> 80 | O14: =R14/G14 -> 588.23529 | P14: =R14/H14 -> 1000 | Q14: =R14/I14 -> 1428.5714 | R14: =10000 -> 10000 | S14: =T14+U14 -> 165000 | T14: =W14*H14 -> 25000 | U14: =X14*I14 -> 140000 | V14: =S14/G14 -> 9705.8824 | W14: 2500 | X14: =20000 -> 20000 | Y14: =S14/R14 -> 16.5 | Z14: =T14/R14 -> 2.5 | AA14: =U14/R14 -> 14 | AC14: =B14/4 -> 125 | AD14: =C14/4 -> 31.25 | AE14: =D14/4 -> 12.5 | AF14: =E14/4 -> 8.75 | AG14: =F14/4 -> 31.25 | AH14: =G14/4 -> 4.25 | AI14: =H14/4 -> 2.5 | AJ14: =I14/4 -> 1.75 | AK14: =R14/4 -> 2500 | AL14: =S14/4 -> 41250 | AM14: =T14/4 -> 6250 | AN14: =U14/4 -> 35000 | AO14: =AL14/AH14 -> 9705.8824 | AP14: 2500 | AQ14: =20000 -> 20000 | AR14: =AL14/AK14 -> 16.5 | AS14: =AM14/AK14 -> 2.5 | AT14: =AN14/AK14 -> 14
A16: TOTAL | B16: =SUM(B3:B14) -> 18500 | C16: =SUM(C3:C14) -> 4625 | D16: =SUM(D3:D14) -> 1850 | E16: =SUM(E3:E14) -> 1295 | F16: =SUM(F3:F14) -> 4625 | G16: =SUM(G3:G14) -> 629 | H16: =SUM(H3:H14) -> 370 | I16: =SUM(I3:I14) -> 259 | R16: =SUM(R3:R14) -> 370000 | S16: =SUM(S3:S14) -> 6105000 | T16: =SUM(T3:T14) -> 925000 | U16: =SUM(U3:U14) -> 5180000

Sheet TRAINING DAY (FORA DE SP)
A1: TRAINING DAY (FORA DE SP) | B1: VOLUME | J1: CUSTOS | R1: NUM FINAIS | AC1: VOLUME SEMANAL | AK1: NÚMEROS FINAIS SEMANAL
B2: Compras Pres | C2: Compras +MQL | F2: PESSOAS NO PITCH | G2: VENDAS | H2: V. MKT | I2: V. COM | J2: CAC | K2: CAC MQL | N2: C P/ PESSOA PITCH | O2: CAC GERAL | P2: CAC MKT | Q2: CAC COM | R2: INVESTIMENTO | S2: FATURAMENTO | T2: FAT MKT | U2: FAT COM | V2: Ticket médio | W2: T.M MKT | X2: T.M COM | Y2: ROAS | Z2: ROAS MKT | AA2: ROAS COM | AC2: COMPRAS | AD2: Compras +MQL | AG2: PESSOAS NO PITCH | AH2: VENDAS | AI2: V. MKT | AJ2: V. COM | AK2: INVESTIMENTO | AL2: FATURAMENTO | AM2: FAT MKT | AN2: FAT COM | AO2: Ticket médio | AP2: T.M MKT | AQ2: T.M COM | AR2: ROAS | AS2: ROAS MKT | AT2: ROAS COM
A3: Janeiro | B3: =R3/J3 -> 50 | C3: =B3*0.5 -> 25 | F3: =B3+B3*0.25 -> 62.5 | G3: =H3+I3 -> 59.375 | H3: =B3 -> 50 | I3: =F3*0.15 -> 9.375 | J3: =400 -> 400 | K3: =R3/C3 -> 800 | N3: =R3/F3 -> 320 | O3: =R3/G3 -> 336.84211 | P3: =R3/H3 -> 400 | Q3: =R3/I3 -> 2133.3333 | R3: =20000 -> 20000 | S3: =T3+U3 -> 202500 | T3: =W3*H3 -> 15000 | U3: =X3*I3 -> 187500 | V3: =S3/G3 -> 3410.5263 | W3: 300 | X3: =20000 -> 20000 | Y3: =S3/R3 -> 10.125 | Z3: =T3/R3 -> 0.75 | AA3: =U3/R3 -> 9.375 | AC3: =B3/4 -> 12.5 | AD3: =C3/4 -> 6.25 | AG3: =F3/4 -> 15.625 | AH3: =G3/4 -> 14.84375 | AI3: =H3/4 -> 12.5 | AJ3: =I3/4 -> 2.34375 | AK3: =R3/4 -> 5000 | AL3: =S3/4 -> 50625 | AM3: =T3/4 -> 3750 | AN3: =U3/4 -> 46875 | AO3: =AL3/AH3 -> 3410.5263 | AP3: 2500 | AQ3: =20000 -> 20000 | AR3: =AL3/AK3 -> 10.125 | AS3: =AM3/AK3 -> 0.75 | AT3: =AN3/AK3 -> 9.375
A4: fevereiro | B4: =R4/J4 -> 150 | C4: =B4*0.5 -> 75 | F4: =B4+B4*0.25 -> 187.5 | G4: =H4+I4 -> 178.125 | H4: =B4 -> 150 | I4: =F4*0.15 -> 28.125 | J4: =400 -> 400 | K4: =R4/C4 -> 800 | N4: =R4/F4 -> 320 | O4: =R4/G4 -> 336.84211 | P4: =R4/H4 -> 400 | Q4: =R4/I4 -> 2133.3333 | R4: =60000 -> 60000 | S4: =T4+U4 -> 607500 | T4: =W4*H4 -> 45000 | U4: =X4*I4 -> 562500 | V4: =S4/G4 -> 3410.5263 | W4: 300 | X4: =20000 -> 20000 | Y4: =S4/R4 -> 10.125 | Z4: =T4/R4 -> 0.75 | AA4: =U4/R4 -> 9.375 | AC4: =B4/4 -> 37.5 | AD4: =C4/4 -> 18.75 | AG4: =F4/4 -> 46.875 | AH4: =G4/4 -> 44.53125 | AI4: =H4/4 -> 37.5 | AJ4: =I4/4 -> 7.03125 | AK4: =R4/4 -> 15000 | AL4: =S4/4 -> 151875 | AM4: =T4/4 -> 11250 | AN4: =U4/4 -> 140625 | AO4: =AL4/AH4 -> 3410.5263 | AP4: 2500 | AQ4: =20000 -> 20000 | AR4: =AL4/AK4 -> 10.125 | AS4: =AM4/AK4 -> 0.75 | AT4: =AN4/AK4 -> 9.375
A5: março | B5: =R5/J5 -> 50 | C5: =B5*0.5 -> 25 | F5: =B5+B5*0.25 -> 62.5 | G5: =H5+I5 -> 59.375 | H5: =B5 -> 50 | I5: =F5*0.15 -> 9.375 | J5: =400 -> 400 | K5: =R5/C5 -> 800 | N5: =R5/F5 -> 320 | O5: =R5/G5 -> 336.84211 | P5: =R5/H5 -> 400 | Q5: =R5/I5 -> 2133.3333 | R5: =20000 -> 20000 | S5: =T5+U5 -> 202500 | T5: =W5*H5 -> 15000 | U5: =X5*I5 -> 187500 | V5: =S5/G5 -> 3410.5263 | W5: 300 | X5: =20000 -> 20000 | Y5: =S5/R5 -> 10.125 | Z5: =T5/R5 -> 0.75 | AA5: =U5/R5 -> 9.375 | AC5: =B5/4 -> 12.5 | AD5: =C5/4 -> 6.25 | AG5: =F5/4 -> 15.625 | AH5: =G5/4 -> 14.84375 | AI5: =H5/4 -> 12.5 | AJ5: =I5/4 -> 2.34375 | AK5: =R5/4 -> 5000 | AL5: =S5/4 -> 50625 | AM5: =T5/4 -> 3750 | AN5: =U5/4 -> 46875 | AO5: =AL5/AH5 -> 3410.5263 | AP5: 2500 | AQ5: =20000 -> 20000 | AR5: =AL5/AK5 -> 10.125 | AS5: =AM5/AK5 -> 0.75 | AT5: =AN5/AK5 -> 9.375
A6: abril | B6: =R6/J6 -> 125 | C6: =B6*0.5 -> 62.5 | F6: =B6+B6*0.25 -> 156.25 | G6: =H6+I6 -> 148.4375 | H6: =B6 -> 125 | I6: =F6*0.15 -> 23.4375 | J6: =400 -> 400 | K6: =R6/C6 -> 800 | N6: =R6/F6 -> 320 | O6: =R6/G6 -> 336.84211 | P6: =R6/H6 -> 400 | Q6: =R6/I6 -> 2133.3333 | R6: =50000 -> 50000 | S6: =T6+U6 -> 506250 | T6: =W6*H6 -> 37500 | U6: =X6*I6 -> 468750 | V6: =S6/G6 -> 3410.5263 | W6: 300 | X6: =20000 -> 20000 | Y6: =S6/R6 -> 10.125 | Z6: =T6/R6 -> 0.75 | AA6: =U6/R6 -> 9.375 | AC6: =B6/4 -> 31.25 | AD6: =C6/4 -> 15.625 | AG6: =F6/4 -> 39.0625 | AH6: =G6/4 -> 37.109375 | AI6: =H6/4 -> 31.25 | AJ6: =I6/4 -> 5.859375 | AK6: =R6/4 -> 12500 | AL6: =S6/4 -> 126562.5 | AM6: =T6/4 -> 9375 | AN6: =U6/4 -> 117187.5 | AO6: =AL6/AH6 -> 3410.5263 | AP6: 2500 | AQ6: =20000 -> 20000 | AR6: =AL6/AK6 -> 10.125 | AS6: =AM6/AK6 -> 0.75 | AT6: =AN6/AK6 -> 9.375
A7: maio | B7: =R7/J7 -> 125 | C7: =B7*0.5 -> 62.5 | F7: =B7+B7*0.25 -> 156.25 | G7: =H7+I7 -> 148.4375 | H7: =B7 -> 125 | I7: =F7*0.15 -> 23.4375 | J7: =400 -> 400 | K7: =R7/C7 -> 800 | N7: =R7/F7 -> 320 | O7: =R7/G7 -> 336.84211 | P7: =R7/H7 -> 400 | Q7: =R7/I7 -> 2133.3333 | R7: =50000 -> 50000 | S7: =T7+U7 -> 506250 | T7: =W7*H7 -> 37500 | U7: =X7*I7 -> 468750 | V7: =S7/G7 -> 3410.5263 | W7: 300 | X7: =20000 -> 20000 | Y7: =S7/R7 -> 10.125 | Z7: =T7/R7 -> 0.75 | AA7: =U7/R7 -> 9.375 | AC7: =B7/4 -> 31.25 | AD7: =C7/4 -> 15.625 | AG7: =F7/4 -> 39.0625 | AH7: =G7/4 -> 37.109375 | AI7: =H7/4 -> 31.25 | AJ7: =I7/4 -> 5.859375 | AK7: =R7/4 -> 12500 | AL7: =S7/4 -> 126562.5 | AM7: =T7/4 -> 9375 | AN7: =U7/4 -> 117187.5 | AO7: =AL7/AH7 -> 3410.5263 | AP7: 2500 | AQ7: =20000 -> 20000 | AR7: =AL7/AK7 -> 10.125 | AS7: =AM7/AK7 -> 0.75 | AT7: =AN7/AK7 -> 9.375
A8: junho | B8: =R8/J8 -> 0 | C8: =B8*0.5 -> 0 | F8: =B8+B8*0.25 -> 0 | G8: =H8+I8 -> 0 | H8: =B8 -> 0 | I8: =F8*0.15 -> 0 | J8: =400 -> 400 | K8: =R8/C8 -> #DIV/0! | N8: =R8/F8 -> #DIV/0! | O8: =R8/G8 -> #DIV/0! | P8: =R8/H8 -> #DIV/0! | Q8: =R8/I8 -> #DIV/0! | S8: =T8+U8 -> 0 | T8: =W8*H8 -> 0 | U8: =X8*I8 -> 0 | V8: =S8/G8 -> #DIV/0! | W8: 300 | X8: =20000 -> 20000 | Y8: =S8/R8 -> #DIV/0! | Z8: =T8/R8 -> #DIV/0! | AA8: =U8/R8 -> #DIV/0! | AC8: =B8/4 -> 0 | AD8: =C8/4 -> 0 | AG8: =F8/4 -> 0 | AH8: =G8/4 -> 0 | AI8: =H8/4 -> 0 | AJ8: =I8/4 -> 0 | AK8: =R8/4 -> 0 | AL8: =S8/4 -> 0 | AM8: =T8/4 -> 0 | AN8: =U8/4 -> 0 | AO8: =AL8/AH8 -> #DIV/0! | AP8: 2500 | AQ8: =20000 -> 20000 | AR8: =AL8/AK8 -> #DIV/0! | AS8: =AM8/AK8 -> #DIV/0! | AT8: =AN8/AK8 -> #DIV/0!
A9: julho | B9: =R9/J9 -> 0 | C9: =B9*0.5 -> 0 | F9: =B9+B9*0.25 -> 0 | G9: =H9+I9 -> 0 | H9: =B9 -> 0 | I9: =F9*0.15 -> 0 | J9: =400 -> 400 | K9: =R9/C9 -> #DIV/0! | N9: =R9/F9 -> #DIV/0! | O9: =R9/G9 -> #DIV/0! | P9: =R9/H9 -> #DIV/0! | Q9: =R9/I9 -> #DIV/0! | S9: =T9+U9 -> 0 | T9: =W9*H9 -> 0 | U9: =X9*I9 -> 0 | V9: =S9/G9 -> #DIV/0! | W9: 300 | X9: =20000 -> 20000 | Y9: =S9/R9 -> #DIV/0! | Z9: =T9/R9 -> #DIV/0! | AA9: =U9/R9 -> #DIV/0! | AC9: =B9/4 -> 0 | AD9: =C9/4 -> 0 | AG9: =F9/4 -> 0 | AH9: =G9/4 -> 0 | AI9: =H9/4 -> 0 | AJ9: =I9/4 -> 0 | AK9: =R9/4 -> 0 | AL9: =S9/4 -> 0 | AM9: =T9/4 -> 0 | AN9: =U9/4 -> 0 | AO9: =AL9/AH9 -> #DIV/0! | AP9: 2500 | AQ9: =20000 -> 20000 | AR9: =AL9/AK9 -> #DIV/0! | AS9: =AM9/AK9 -> #DIV/0! | AT9: =AN9/AK9 -> #DIV/0!
A10: agosto | B10: =R10/J10 -> 0 | C10: =B10*0.5 -> 0 | F10: =B10+B10*0.25 -> 0 | G10: =H10+I10 -> 0 | H10: =B10 -> 0 | I10: =F10*0.15 -> 0 | J10: =400 -> 400 | K10: =R10/C10 -> #DIV/0! | N10: =R10/F10 -> #DIV/0! | O10: =R10/G10 -> #DIV/0! | P10: =R10/H10 -> #DIV/0! | Q10: =R10/I10 -> #DIV/0! | S10: =T10+U10 -> 0 | T10: =W10*H10 -> 0 | U10: =X10*I10 -> 0 | V10: =S10/G10 -> #DIV/0! | W10: 300 | X10: =20000 -> 20000 | Y10: =S10/R10 -> #DIV/0! | Z10: =T10/R10 -> #DIV/0! | AA10: =U10/R10 -> #DIV/0! | AC10: =B10/4 -> 0 | AD10: =C10/4 -> 0 | AG10: =F10/4 -> 0 | AH10: =G10/4 -> 0 | AI10: =H10/4 -> 0 | AJ10: =I10/4 -> 0 | AK10: =R10/4 -> 0 | AL10: =S10/4 -> 0 | AM10: =T10/4 -> 0 | AN10: =U10/4 -> 0 | AO10: =AL10/AH10 -> #DIV/0! | AP10: 2500 | AQ10: =20000 -> 20000 | AR10: =AL10/AK10 -> #DIV/0! | AS10: =AM10/AK10 -> #DIV/0! | AT10: =AN10/AK10 -> #DIV/0!
A11: setembro | B11: =R11/J11 -> 0 | C11: =B11*0.5 -> 0 | F11: =B11+B11*0.25 -> 0 | G11: =H11+I11 -> 0 | H11: =B11 -> 0 | I11: =F11*0.15 -> 0 | J11: =400 -> 400 | K11: =R11/C11 -> #DIV/0! | N11: =R11/F11 -> #DIV/0! | O11: =R11/G11 -> #DIV/0! | P11: =R11/H11 -> #DIV/0! | Q11: =R11/I11 -> #DIV/0! | S11: =T11+U11 -> 0 | T11: =W11*H11 -> 0 | U11: =X11*I11 -> 0 | V11: =S11/G11 -> #DIV/0! | W11: 300 | X11: =20000 -> 20000 | Y11: =S11/R11 -> #DIV/0! | Z11: =T11/R11 -> #DIV/0! | AA11: =U11/R11 -> #DIV/0! | AC11: =B11/4 -> 0 | AD11: =C11/4 -> 0 | AG11: =F11/4 -> 0 | AH11: =G11/4 -> 0 | AI11: =H11/4 -> 0 | AJ11: =I11/4 -> 0 | AK11: =R11/4 -> 0 | AL11: =S11/4 -> 0 | AM11: =T11/4 -> 0 | AN11: =U11/4 -> 0 | AO11: =AL11/AH11 -> #DIV/0! | AP11: 2500 | AQ11: =20000 -> 20000 | AR11: =AL11/AK11 -> #DIV/0! | AS11: =AM11/AK11 -> #DIV/0! | AT11: =AN11/AK11 -> #DIV/0!
A12: outubro | B12: =R12/J12 -> 0 | C12: =B12*0.5 -> 0 | F12: =B12+B12*0.25 -> 0 | G12: =H12+I12 -> 0 | H12: =B12 -> 0 | I12: =F12*0.15 -> 0 | J12: =400 -> 400 | K12: =R12/C12 -> #DIV/0! | N12: =R12/F12 -> #DIV/0! | O12: =R12/G12 -> #DIV/0! | P12: =R12/H12 -> #DIV/0! | Q12: =R12/I12 -> #DIV/0! | S12: =T12+U12 -> 0 | T12: =W12*H12 -> 0 | U12: =X12*I12 -> 0 | V12: =S12/G12 -> #DIV/0! | W12: 300 | X12: =20000 -> 20000 | Y12: =S12/R12 -> #DIV/0! | Z12: =T12/R12 -> #DIV/0! | AA12: =U12/R12 -> #DIV/0! | AC12: =B12/4 -> 0 | AD12: =C12/4 -> 0 | AG12: =F12/4 -> 0 | AH12: =G12/4 -> 0 | AI12: =H12/4 -> 0 | AJ12: =I12/4 -> 0 | AK12: =R12/4 -> 0 | AL12: =S12/4 -> 0 | AM12: =T12/4 -> 0 | AN12: =U12/4 -> 0 | AO12: =AL12/AH12 -> #DIV/0! | AP12: 2500 | AQ12: =20000 -> 20000 | AR12: =AL12/AK12 -> #DIV/0! | AS12: =AM12/AK12 -> #DIV/0! | AT12: =AN12/AK12 -> #DIV/0!
A13: novembro | B13: =R13/J13 -> 0 | C13: =B13*0.5 -> 0 | F13: =B13+B13*0.25 -> 0 | G13: =H13+I13 -> 0 | H13: =B13 -> 0 | I13: =F13*0.15 -> 0 | J13: =400 -> 400 | K13: =R13/C13 -> #DIV/0! | N13: =R13/F13 -> #DIV/0! | O13: =R13/G13 -> #DIV/0! | P13: =R13/H13 -> #DIV/0! | Q13: =R13/I13 -> #DIV/0! | S13: =T13+U13 -> 0 | T13: =W13*H13 -> 0 | U13: =X13*I13 -> 0 | V13: =S13/G13 -> #DIV/0! | W13: 300 | X13: =20000 -> 20000 | Y13: =S13/R13 -> #DIV/0! | Z13: =T13/R13 -> #DIV/0! | AA13: =U13/R13 -> #DIV/0! | AC13: =B13/4 -> 0 | AD13: =C13/4 -> 0 | AG13: =F13/4 -> 0 | AH13: =G13/4 -> 0 | AI13: =H13/4 -> 0 | AJ13: =I13/4 -> 0 | AK13: =R13/4 -> 0 | AL13: =S13/4 -> 0 | AM13: =T13/4 -> 0 | AN13: =U13/4 -> 0 | AO13: =AL13/AH13 -> #DIV/0! | AP13: 2500 | AQ13: =20000 -> 20000 | AR13: =AL13/AK13 -> #DIV/0! | AS13: =AM13/AK13 -> #DIV/0! | AT13: =AN13/AK13 -> #DIV/0!
A14: dezembro | B14: =R14/J14 -> 0 | C14: =B14*0.5 -> 0 | F14: =B14+B14*0.25 -> 0 | G14: =H14+I14 -> 0 | H14: =B14 -> 0 | I14: =F14*0.15 -> 0 | J14: =400 -> 400 | K14: =R14/C14 -> #DIV/0! | N14: =R14/F14 -> #DIV/0! | O14: =R14/G14 -> #DIV/0! | P14: =R14/H14 -> #DIV/0! | Q14: =R14/I14 -> #DIV/0! | S14: =T14+U14 -> 0 | T14: =W14*H14 -> 0 | U14: =X14*I14 -> 0 | V14: =S14/G14 -> #DIV/0! | W14: 300 | X14: =20000 -> 20000 | Y14: =S14/R14 -> #DIV/0! | Z14: =T14/R14 -> #DIV/0! | AA14: =U14/R14 -> #DIV/0! | AC14: =B14/4 -> 0 | AD14: =C14/4 -> 0 | AG14: =F14/4 -> 0 | AH14: =G14/4 -> 0 | AI14: =H14/4 -> 0 | AJ14: =I14/4 -> 0 | AK14: =R14/4 -> 0 | AL14: =S14/4 -> 0 | AM14: =T14/4 -> 0 | AN14: =U14/4 -> 0 | AO14: =AL14/AH14 -> #DIV/0! | AP14: 2500 | AQ14: =20000 -> 20000 | AR14: =AL14/AK14 -> #DIV/0! | AS14: =AM14/AK14 -> #DIV/0! | AT14: =AN14/AK14 -> #DIV/0!
A16: TOTAL | B16: =SUM(B3:B14) -> 500 | C16: =SUM(C3:C14) -> 250 | D16: =SUM(D3:D14) -> 0 | E16: =SUM(E3:E14) -> 0 | F16: =SUM(F3:F14) -> 625 | G16: =SUM(G3:G14) -> 593.75 | H16: =SUM(H3:H14) -> 500 | I16: =SUM(I3:I14) -> 93.75 | R16: =SUM(R3:R14) -> 200000 | S16: =SUM(S3:S14) -> 2025000 | T16: =SUM(T3:T14) -> 150000 | U16: =SUM(U3:U14) -> 1875000

Sheet CAPTAÇÃO PRO COMERCIAL
A1: CAPTAÇÃO P/ COMERCIAL | B1: VOLUME | J1: CUSTOS | R1: NUM FINAIS | AC1: VOLUME SEMANAL | AK1: NÚMEROS FINAIS SEMANAL
B2: Leads | C2: Leads +MQL | D2: AGENDAMENTOS | E2: CALLS | G2: VENDAS | H2: V. MKT | I2: V. COM | J2: CPL | K2: CPL MQL | L2: CP AG | M2: CP. C.R | N2: C P/ PESSOA PITCH | O2: CAC GERAL | P2: CAC MKT | Q2: CAC COM | R2: INVESTIMENTO | S2: FATURAMENTO | T2: FAT MKT | U2: FAT COM | V2: Ticket médio | W2: T.M MKT | X2: T.M COM | Y2: ROAS | Z2: ROAS MKT | AA2: ROAS COM | AC2: Leads | AD2: Leads +MQL | AE2: AGENDAMENTOS | AF2: CALLS | AG2: PESSOAS NO PITCH | AH2: VENDAS | AI2: V. MKT | AJ2: V. COM | AK2: INVESTIMENTO | AL2: FATURAMENTO | AM2: FAT MKT | AN2: FAT COM | AO2: Ticket médio | AP2: T.M MKT | AQ2: T.M COM | AR2: ROAS | AS2: ROAS MKT | AT2: ROAS COM
A3: Janeiro | B3: =R3/J3 -> 500 | C3: =B3*0.25 -> 125 | D3: =B3*0.1 -> 50 | E3: =D3*0.7 -> 35 | G3: =H3+I3 -> 7 | H3: =F3*0.08 -> 0 | I3: =E3*0.2 -> 7 | J3: =20 -> 20 | K3: =R3/C3 -> 80 | L3: =R3/D3 -> 200 | M3: =R3/E3 -> 285.71429 | N3: =R3/F3 -> #DIV/0! | O3: =R3/G3 -> 1428.5714 | P3: =R3/H3 -> #DIV/0! | Q3: =R3/I3 -> 1428.5714 | R3: =10000 -> 10000 | S3: =T3+U3 -> 140000 | T3: =W3*H3 -> 0 | U3: =X3*I3 -> 140000 | V3: =S3/G3 -> 20000 | W3: 2500 | X3: =20000 -> 20000 | Y3: =S3/R3 -> 14 | Z3: =T3/R3 -> 0 | AA3: =U3/R3 -> 14 | AC3: =B3/4 -> 125 | AD3: =C3/4 -> 31.25 | AE3: =D3/4 -> 12.5 | AF3: =E3/4 -> 8.75 | AG3: =F3/4 -> 0 | AH3: =G3/4 -> 1.75 | AI3: =H3/4 -> 0 | AJ3: =I3/4 -> 1.75 | AK3: =R3/4 -> 2500 | AL3: =S3/4 -> 35000 | AM3: =T3/4 -> 0 | AN3: =U3/4 -> 35000 | AO3: =AL3/AH3 -> 20000 | AP3: 2500 | AQ3: =20000 -> 20000 | AR3: =AL3/AK3 -> 14 | AS3: =AM3/AK3 -> 0 | AT3: =AN3/AK3 -> 14
A4: fevereiro | B4: =R4/J4 -> 1000 | C4: =B4*0.25 -> 250 | D4: =B4*0.1 -> 100 | E4: =D4*0.7 -> 70 | G4: =H4+I4 -> 14 | H4: =F4*0.08 -> 0 | I4: =E4*0.2 -> 14 | J4: =20 -> 20 | K4: =R4/C4 -> 80 | L4: =R4/D4 -> 200 | M4: =R4/E4 -> 285.71429 | N4: =R4/F4 -> #DIV/0! | O4: =R4/G4 -> 1428.5714 | P4: =R4/H4 -> #DIV/0! | Q4: =R4/I4 -> 1428.5714 | R4: =20000 -> 20000 | S4: =T4+U4 -> 280000 | T4: =W4*H4 -> 0 | U4: =X4*I4 -> 280000 | V4: =S4/G4 -> 20000 | W4: 2500 | X4: =20000 -> 20000 | Y4: =S4/R4 -> 14 | Z4: =T4/R4 -> 0 | AA4: =U4/R4 -> 14 | AC4: =B4/4 -> 250 | AD4: =C4/4 -> 62.5 | AE4: =D4/4 -> 25 | AF4: =E4/4 -> 17.5 | AG4: =F4/4 -> 0 | AH4: =G4/4 -> 3.5 | AI4: =H4/4 -> 0 | AJ4: =I4/4 -> 3.5 | AK4: =R4/4 -> 5000 | AL4: =S4/4 -> 70000 | AM4: =T4/4 -> 0 | AN4: =U4/4 -> 70000 | AO4: =AL4/AH4 -> 20000 | AP4: 2500 | AQ4: =20000 -> 20000 | AR4: =AL4/AK4 -> 14 | AS4: =AM4/AK4 -> 0 | AT4: =AN4/AK4 -> 14
A5: março | B5: =R5/J5 -> 1500 | C5: =B5*0.25 -> 375 | D5: =B5*0.1 -> 150 | E5: =D5*0.7 -> 105 | G5: =H5+I5 -> 21 | H5: =F5*0.08 -> 0 | I5: =E5*0.2 -> 21 | J5: =20 -> 20 | K5: =R5/C5 -> 80 | L5: =R5/D5 -> 200 | M5: =R5/E5 -> 285.71429 | N5: =R5/F5 -> #DIV/0! | O5: =R5/G5 -> 1428.5714 | P5: =R5/H5 -> #DIV/0! | Q5: =R5/I5 -> 1428.5714 | R5: =30000 -> 30000 | S5: =T5+U5 -> 420000 | T5: =W5*H5 -> 0 | U5: =X5*I5 -> 420000 | V5: =S5/G5 -> 20000 | W5: 2500 | X5: =20000 -> 20000 | Y5: =S5/R5 -> 14 | Z5: =T5/R5 -> 0 | AA5: =U5/R5 -> 14 | AC5: =B5/4 -> 375 | AD5: =C5/4 -> 93.75 | AE5: =D5/4 -> 37.5 | AF5: =E5/4 -> 26.25 | AG5: =F5/4 -> 0 | AH5: =G5/4 -> 5.25 | AI5: =H5/4 -> 0 | AJ5: =I5/4 -> 5.25 | AK5: =R5/4 -> 7500 | AL5: =S5/4 -> 105000 | AM5: =T5/4 -> 0 | AN5: =U5/4 -> 105000 | AO5: =AL5/AH5 -> 20000 | AP5: 2500 | AQ5: =20000 -> 20000 | AR5: =AL5/AK5 -> 14 | AS5: =AM5/AK5 -> 0 | AT5: =AN5/AK5 -> 14
A6: abril | B6: =R6/J6 -> 2500 | C6: =B6*0.25 -> 625 | D6: =B6*0.1 -> 250 | E6: =D6*0.7 -> 175 | G6: =H6+I6 -> 35 | H6: =F6*0.08 -> 0 | I6: =E6*0.2 -> 35 | J6: =20 -> 20 | K6: =R6/C6 -> 80 | L6: =R6/D6 -> 200 | M6: =R6/E6 -> 285.71429 | N6: =R6/F6 -> #DIV/0! | O6: =R6/G6 -> 1428.5714 | P6: =R6/H6 -> #DIV/0! | Q6: =R6/I6 -> 1428.5714 | R6: =50000 -> 50000 | S6: =T6+U6 -> 700000 | T6: =W6*H6 -> 0 | U6: =X6*I6 -> 700000 | V6: =S6/G6 -> 20000 | W6: 2500 | X6: =20000 -> 20000 | Y6: =S6/R6 -> 14 | Z6: =T6/R6 -> 0 | AA6: =U6/R6 -> 14 | AC6: =B6/4 -> 625 | AD6: =C6/4 -> 156.25 | AE6: =D6/4 -> 62.5 | AF6: =E6/4 -> 43.75 | AG6: =F6/4 -> 0 | AH6: =G6/4 -> 8.75 | AI6: =H6/4 -> 0 | AJ6: =I6/4 -> 8.75 | AK6: =R6/4 -> 12500 | AL6: =S6/4 -> 175000 | AM6: =T6/4 -> 0 | AN6: =U6/4 -> 175000 | AO6: =AL6/AH6 -> 20000 | AP6: 2500 | AQ6: =20000 -> 20000 | AR6: =AL6/AK6 -> 14 | AS6: =AM6/AK6 -> 0 | AT6: =AN6/AK6 -> 14
A7: maio | B7: =R7/J7 -> 2500 | C7: =B7*0.25 -> 625 | D7: =B7*0.1 -> 250 | E7: =D7*0.7 -> 175 | G7: =H7+I7 -> 35 | H7: =F7*0.08 -> 0 | I7: =E7*0.2 -> 35 | J7: =20 -> 20 | K7: =R7/C7 -> 80 | L7: =R7/D7 -> 200 | M7: =R7/E7 -> 285.71429 | N7: =R7/F7 -> #DIV/0! | O7: =R7/G7 -> 1428.5714 | P7: =R7/H7 -> #DIV/0! | Q7: =R7/I7 -> 1428.5714 | R7: =50000 -> 50000 | S7: =T7+U7 -> 700000 | T7: =W7*H7 -> 0 | U7: =X7*I7 -> 700000 | V7: =S7/G7 -> 20000 | W7: 2500 | X7: =20000 -> 20000 | Y7: =S7/R7 -> 14 | Z7: =T7/R7 -> 0 | AA7: =U7/R7 -> 14 | AC7: =B7/4 -> 625 | AD7: =C7/4 -> 156.25 | AE7: =D7/4 -> 62.5 | AF7: =E7/4 -> 43.75 | AG7: =F7/4 -> 0 | AH7: =G7/4 -> 8.75 | AI7: =H7/4 -> 0 | AJ7: =I7/4 -> 8.75 | AK7: =R7/4 -> 12500 | AL7: =S7/4 -> 175000 | AM7: =T7/4 -> 0 | AN7: =U7/4 -> 175000 | AO7: =AL7/AH7 -> 20000 | AP7: 2500 | AQ7: =20000 -> 20000 | AR7: =AL7/AK7 -> 14 | AS7: =AM7/AK7 -> 0 | AT7: =AN7/AK7 -> 14
A8: junho | B8: =R8/J8 -> 500 | C8: =B8*0.25 -> 125 | D8: =B8*0.1 -> 50 | E8: =D8*0.7 -> 35 | G8: =H8+I8 -> 7 | H8: =F8*0.08 -> 0 | I8: =E8*0.2 -> 7 | J8: =20 -> 20 | K8: =R8/C8 -> 80 | L8: =R8/D8 -> 200 | M8: =R8/E8 -> 285.71429 | N8: =R8/F8 -> #DIV/0! | O8: =R8/G8 -> 1428.5714 | P8: =R8/H8 -> #DIV/0! | Q8: =R8/I8 -> 1428.5714 | R8: =10000 -> 10000 | S8: =T8+U8 -> 140000 | T8: =W8*H8 -> 0 | U8: =X8*I8 -> 140000 | V8: =S8/G8 -> 20000 | W8: 2500 | X8: =20000 -> 20000 | Y8: =S8/R8 -> 14 | Z8: =T8/R8 -> 0 | AA8: =U8/R8 -> 14 | AC8: =B8/4 -> 125 | AD8: =C8/4 -> 31.25 | AE8: =D8/4 -> 12.5 | AF8: =E8/4 -> 8.75 | AG8: =F8/4 -> 0 | AH8: =G8/4 -> 1.75 | AI8: =H8/4 -> 0 | AJ8: =I8/4 -> 1.75 | AK8: =R8/4 -> 2500 | AL8: =S8/4 -> 35000 | AM8: =T8/4 -> 0 | AN8: =U8/4 -> 35000 | AO8: =AL8/AH8 -> 20000 | AP8: 2500 | AQ8: =20000 -> 20000 | AR8: =AL8/AK8 -> 14 | AS8: =AM8/AK8 -> 0 | AT8: =AN8/AK8 -> 14
A9: julho | B9: =R9/J9 -> 1500 | C9: =B9*0.25 -> 375 | D9: =B9*0.1 -> 150 | E9: =D9*0.7 -> 105 | G9: =H9+I9 -> 21 | H9: =F9*0.08 -> 0 | I9: =E9*0.2 -> 21 | J9: =20 -> 20 | K9: =R9/C9 -> 80 | L9: =R9/D9 -> 200 | M9: =R9/E9 -> 285.71429 | N9: =R9/F9 -> #DIV/0! | O9: =R9/G9 -> 1428.5714 | P9: =R9/H9 -> #DIV/0! | Q9: =R9/I9 -> 1428.5714 | R9: 30000 | S9: =T9+U9 -> 420000 | T9: =W9*H9 -> 0 | U9: =X9*I9 -> 420000 | V9: =S9/G9 -> 20000 | W9: 2500 | X9: =20000 -> 20000 | Y9: =S9/R9 -> 14 | Z9: =T9/R9 -> 0 | AA9: =U9/R9 -> 14 | AC9: =B9/4 -> 375 | AD9: =C9/4 -> 93.75 | AE9: =D9/4 -> 37.5 | AF9: =E9/4 -> 26.25 | AG9: =F9/4 -> 0 | AH9: =G9/4 -> 5.25 | AI9: =H9/4 -> 0 | AJ9: =I9/4 -> 5.25 | AK9: =R9/4 -> 7500 | AL9: =S9/4 -> 105000 | AM9: =T9/4 -> 0 | AN9: =U9/4 -> 105000 | AO9: =AL9/AH9 -> 20000 | AP9: 2500 | AQ9: =20000 -> 20000 | AR9: =AL9/AK9 -> 14 | AS9: =AM9/AK9 -> 0 | AT9: =AN9/AK9 -> 14
A10: agosto | B10: =R10/J10 -> 1500 | C10: =B10*0.25 -> 375 | D10: =B10*0.1 -> 150 | E10: =D10*0.7 -> 105 | G10: =H10+I10 -> 21 | H10: =F10*0.08 -> 0 | I10: =E10*0.2 -> 21 | J10: =20 -> 20 | K10: =R10/C10 -> 80 | L10: =R10/D10 -> 200 | M10: =R10/E10 -> 285.71429 | N10: =R10/F10 -> #DIV/0! | O10: =R10/G10 -> 1428.5714 | P10: =R10/H10 -> #DIV/0! | Q10: =R10/I10 -> 1428.5714 | R10: =30000 -> 30000 | S10: =T10+U10 -> 420000 | T10: =W10*H10 -> 0 | U10: =X10*I10 -> 420000 | V10: =S10/G10 -> 20000 | W10: 2500 | X10: =20000 -> 20000 | Y10: =S10/R10 -> 14 | Z10: =T10/R10 -> 0 | AA10: =U10/R10 -> 14 | AC10: =B10/4 -> 375 | AD10: =C10/4 -> 93.75 | AE10: =D10/4 -> 37.5 | AF10: =E10/4 -> 26.25 | AG10: =F10/4 -> 0 | AH10: =G10/4 -> 5.25 | AI10: =H10/4 -> 0 | AJ10: =I10/4 -> 5.25 | AK10: =R10/4 -> 7500 | AL10: =S10/4 -> 105000 | AM10: =T10/4 -> 0 | AN10: =U10/4 -> 105000 | AO10: =AL10/AH10 -> 20000 | AP10: 2500 | AQ10: =20000 -> 20000 | AR10: =AL10/AK10 -> 14 | AS10: =AM10/AK10 -> 0 | AT10: =AN10/AK10 -> 14
A11: setembro | B11: =R11/J11 -> 1500 | C11: =B11*0.25 -> 375 | D11: =B11*0.1 -> 150 | E11: =D11*0.7 -> 105 | G11: =H11+I11 -> 21 | H11: =F11*0.08 -> 0 | I11: =E11*0.2 -> 21 | J11: =20 -> 20 | K11: =R11/C11 -> 80 | L11: =R11/D11 -> 200 | M11: =R11/E11 -> 285.71429 | N11: =R11/F11 -> #DIV/0! | O11: =R11/G11 -> 1428.5714 | P11: =R11/H11 -> #DIV/0! | Q11: =R11/I11 -> 1428.5714 | R11: =30000 -> 30000 | S11: =T11+U11 -> 420000 | T11: =W11*H11 -> 0 | U11: =X11*I11 -> 420000 | V11: =S11/G11 -> 20000 | W11: 2500 | X11: =20000 -> 20000 | Y11: =S11/R11 -> 14 | Z11: =T11/R11 -> 0 | AA11: =U11/R11 -> 14 | AC11: =B11/4 -> 375 | AD11: =C11/4 -> 93.75 | AE11: =D11/4 -> 37.5 | AF11: =E11/4 -> 26.25 | AG11: =F11/4 -> 0 | AH11: =G11/4 -> 5.25 | AI11: =H11/4 -> 0 | AJ11: =I11/4 -> 5.25 | AK11: =R11/4 -> 7500 | AL11: =S11/4 -> 105000 | AM11: =T11/4 -> 0 | AN11: =U11/4 -> 105000 | AO11: =AL11/AH11 -> 20000 | AP11: 2500 | AQ11: =20000 -> 20000 | AR11: =AL11/AK11 -> 14 | AS11: =AM11/AK11 -> 0 | AT11: =AN11/AK11 -> 14
A12: outubro | B12: =R12/J12 -> 2500 | C12: =B12*0.25 -> 625 | D12: =B12*0.1 -> 250 | E12: =D12*0.7 -> 175 | G12: =H12+I12 -> 35 | H12: =F12*0.08 -> 0 | I12: =E12*0.2 -> 35 | J12: =20 -> 20 | K12: =R12/C12 -> 80 | L12: =R12/D12 -> 200 | M12: =R12/E12 -> 285.71429 | N12: =R12/F12 -> #DIV/0! | O12: =R12/G12 -> 1428.5714 | P12: =R12/H12 -> #DIV/0! | Q12: =R12/I12 -> 1428.5714 | R12: =50000 -> 50000 | S12: =T12+U12 -> 700000 | T12: =W12*H12 -> 0 | U12: =X12*I12 -> 700000 | V12: =S12/G12 -> 20000 | W12: 2500 | X12: =20000 -> 20000 | Y12: =S12/R12 -> 14 | Z12: =T12/R12 -> 0 | AA12: =U12/R12 -> 14 | AC12: =B12/4 -> 625 | AD12: =C12/4 -> 156.25 | AE12: =D12/4 -> 62.5 | AF12: =E12/4 -> 43.75 | AG12: =F12/4 -> 0 | AH12: =G12/4 -> 8.75 | AI12: =H12/4 -> 0 | AJ12: =I12/4 -> 8.75 | AK12: =R12/4 -> 12500 | AL12: =S12/4 -> 175000 | AM12: =T12/4 -> 0 | AN12: =U12/4 -> 175000 | AO12: =AL12/AH12 -> 20000 | AP12: 2500 | AQ12: =20000 -> 20000 | AR12: =AL12/AK12 -> 14 | AS12: =AM12/AK12 -> 0 | AT12: =AN12/AK12 -> 14
A13: novembro | B13: =R13/J13 -> 2500 | C13: =B13*0.25 -> 625 | D13: =B13*0.1 -> 250 | E13: =D13*0.7 -> 175 | G13: =H13+I13 -> 35 | H13: =F13*0.08 -> 0 | I13: =E13*0.2 -> 35 | J13: =20 -> 20 | K13: =R13/C13 -> 80 | L13: =R13/D13 -> 200 | M13: =R13/E13 -> 285.71429 | N13: =R13/F13 -> #DIV/0! | O13: =R13/G13 -> 1428.5714 | P13: =R13/H13 -> #DIV/0! | Q13: =R13/I13 -> 1428.5714 | R13: =50000 -> 50000 | S13: =T13+U13 -> 700000 | T13: =W13*H13 -> 0 | U13: =X13*I13 -> 700000 | V13: =S13/G13 -> 20000 | W13: 2500 | X13: =20000 -> 20000 | Y13: =S13/R13 -> 14 | Z13: =T13/R13 -> 0 | AA13: =U13/R13 -> 14 | AC13: =B13/4 -> 625 | AD13: =C13/4 -> 156.25 | AE13: =D13/4 -> 62.5 | AF13: =E13/4 -> 43.75 | AG13: =F13/4 -> 0 | AH13: =G13/4 -> 8.75 | AI13: =H13/4 -> 0 | AJ13: =I13/4 -> 8.75 | AK13: =R13/4 -> 12500 | AL13: =S13/4 -> 175000 | AM13: =T13/4 -> 0 | AN13: =U13/4 -> 175000 | AO13: =AL13/AH13 -> 20000 | AP13: 2500 | AQ13: =20000 -> 20000 | AR13: =AL13/AK13 -> 14 | AS13: =AM13/AK13 -> 0 | AT13: =AN13/AK13 -> 14
A14: dezembro | B14: =R14/J14 -> 500 | C14: =B14*0.25 -> 125 | D14: =B14*0.1 -> 50 | E14: =D14*0.7 -> 35 | G14: =H14+I14 -> 7 | H14: =F14*0.08 -> 0 | I14: =E14*0.2 -> 7 | J14: =20 -> 20 | K14: =R14/C14 -> 80 | L14: =R14/D14 -> 200 | M14: =R14/E14 -> 285.71429 | N14: =R14/F14 -> #DIV/0! | O14: =R14/G14 -> 1428.5714 | P14: =R14/H14 -> #DIV/0! | Q14: =R14/I14 -> 1428.5714 | R14: =10000 -> 10000 | S14: =T14+U14 -> 140000 | T14: =W14*H14 -> 0 | U14: =X14*I14 -> 140000 | V14: =S14/G14 -> 20000 | W14: 2500 | X14: =20000 -> 20000 | Y14: =S14/R14 -> 14 | Z14: =T14/R14 -> 0 | AA14: =U14/R14 -> 14 | AC14: =B14/4 -> 125 | AD14: =C14/4 -> 31.25 | AE14: =D14/4 -> 12.5 | AF14: =E14/4 -> 8.75 | AG14: =F14/4 -> 0 | AH14: =G14/4 -> 1.75 | AI14: =H14/4 -> 0 | AJ14: =I14/4 -> 1.75 | AK14: =R14/4 -> 2500 | AL14: =S14/4 -> 35000 | AM14: =T14/4 -> 0 | AN14: =U14/4 -> 35000 | AO14: =AL14/AH14 -> 20000 | AP14: 2500 | AQ14: =20000 -> 20000 | AR14: =AL14/AK14 -> 14 | AS14: =AM14/AK14 -> 0 | AT14: =AN14/AK14 -> 14
A16: TOTAL | B16: =SUM(B3:B14) -> 18500 | C16: =SUM(C3:C14) -> 4625 | D16: =SUM(D3:D14) -> 1850 | E16: =SUM(E3:E14) -> 1295 | F16: =SUM(F3:F14) -> 0 | G16: =SUM(G3:G14) -> 259 | H16: =SUM(H3:H14) -> 0 | I16: =SUM(I3:I14) -> 259 | R16: =SUM(R3:R14) -> 370000 | S16: =SUM(S3:S14) -> 5180000 | T16: =SUM(T3:T14) -> 0 | U16: =SUM(U3:U14) -> 5180000

Sheet ✂️CORTE
K1: CAC DO TRAFEGO | O1: CAIXA DA VENDA MED | P1: CUSTO DA OFERTA (FORA TRÁFEGO)
B2: Lucro | D2: 0.01 | F2: =E2*30%+E2 -> 0 | G2: 0.05 | H2: =J2*I2 -> 1050 | I2: 0.75 | J2: =L2*K2 -> 1400 | K2: 0.2 | L2: 7000 | M2: 80000
B3: Lucro | D3: 0.01 | F3: =E3*30%+E3 -> 0 | G3: 0.05 | H3: =J3*I3 -> 525 | I3: 0.75 | J3: =L3*K3 -> 700 | K3: 0.2 | L3: 3500 | M3: 35000
B4: Lucro | D4: 0.02 | F4: =E4*30%+E4 -> 0 | G4: 0.05 | H4: =J4*I4 -> 375 | I4: 0.75 | J4: =L4*K4 -> 500 | K4: 0.2 | L4: 2500 | M4: 12000
B5: Lucro | D5: 0.01 | F5: =E5*30%+E5 -> 0 | G5: 0.05 | H5: =J5*I5 -> 0 | I5: 0.75 | J5: =L5*K5 -> 0 | K5: 0.2
B6: Lucro | D6: 0.01 | F6: =E6*30%+E6 -> 0 | G6: 0.05 | H6: =J6*I6 -> 150 | I6: 0.75 | J6: =L6*K6 -> 200 | K6: 0.2 | L6: 1000 | M6: 3000
B7: Cliente | D7: 0.01 | F7: =E7*30%+E7 -> 0 | G7: 0.05 | H7: =J7*I7 -> 150 | I7: 0.75 | J7: =L7*K7 -> 200 | K7: 0.2 | L7: 1000 | M7: 1500
B8: Cliente | D8: 0.01 | F8: =E8*30%+E8 -> 0 | G8: 0.05 | H8: =J8*I8 -> 60 | I8: 0.75 | J8: =L8*K8 -> 80 | K8: 0.2 | L8: 400 | M8: 300
B9: Cliente | D9: 0.01 | F9: =E9*30%+E9 -> 0 | G9: 0.05 | H9: =J9*I9 -> 30 | I9: 0.75 | J9: =L9*K9 -> 40 | K9: 0.2 | L9: 200 | M9: 100
B10: Cliente | D10: 0.01 | F10: =E10*30%+E10 -> 0 | G10: 0.05 | H10: =J10*I10 -> 0 | I10: 0.75 | J10: =L10*K10 -> 0 | K10: 0.2
B11: Cliente | D11: 0.01 | F11: =E11*30%+E11 -> 0 | G11: 0.05 | H11: =J11*I11 -> 0 | I11: 0.75 | J11: =L11*K11 -> 0 | K11: 0.2

Sheet 🗺️MICRO
A1: CONTA 2024
A2: JANEIRO | B2: LEADS | C2: VENDAS | D2: TICKET | E2: FATURAMENTO | F2: GATWAY | G2: IMPOSTOS | H2: LIQUIDO | I2: TRÁFEGO | K2: BRUTO | M2: Q1
E3: =C3*D3 -> 0 | F3: =(E3*2.9/100) -> 0 | G3: =E3*6% -> 0 | H3: =E3-F3-G3 -> 0
E4: =C4*D4 -> 0 | F4: =(E4*2.9/100) -> 0 | G4: =E4*6% -> 0 | H4: =E4-F4-G4 -> 0 | K4: =H4-I4 -> 0
E5: =C5*D5 -> 0 | F5: =(E5*2.9/100) -> 0 | G5: =E5*6% -> 0 | H5: =E5-F5-G5 -> 0 | K5: =H5-I5 -> 0 | N5: BRUTO
E6: =C6*D6 -> 0 | F6: =(E6*2.9/100) -> 0 | G6: =E6*6% -> 0 | H6: =E6-F6-G6 -> 0 | K6: =H6-I6 -> 0
E7: =C7*D7 -> 0 | F7: =(E7*2.9/100) -> 0 | G7: =E7*6% -> 0 | H7: =E7-F7-G7 -> 0 | K7: =H7-I7 -> 0 | N7: =K16+K33 -> 0
E8: =C8*D8 -> 0 | F8: =(E8*2.9/100) -> 0 | G8: =E8*6% -> 0 | H8: =E8-F8-G8 -> 0 | K8: =H8-I8 -> 0
E9: =C9*D9 -> 0 | F9: =(E9*2.9/100) -> 0 | G9: =E9*6% -> 0 | H9: =E9-F9-G9 -> 0 | K9: =H9-I9 -> 0
E10: =C10*D10 -> 0 | F10: =(E10*2.9/100) -> 0 | G10: =E10*6% -> 0 | H10: =E10-F10-G10 -> 0 | K10: =H10-I10 -> 0 | N10: OPERACIONAL
E11: =C11*D11 -> 0 | F11: =(E11*2.9/100) -> 0 | G11: =E11*6% -> 0 | H11: =E11-F11-G11 -> 0 | K11: =H11-I11 -> 0 | N11: 21500
E12: =C12*D12 -> 0 | F12: =(E12*2.9/100) -> 0 | G12: =E12*6% -> 0 | H12: =E12-F12-G12 -> 0 | K12: =H12-I12 -> 0
E13: =C13*D13 -> 0 | F13: =(E13*2.9/100) -> 0 | G13: =E13*6% -> 0 | H13: =E13-F13-G13 -> 0 | K13: =H13-I13 -> 0
E14: =C14*D14 -> 0 | F14: =(E14*2.9/100) -> 0 | G14: =E14*6% -> 0 | H14: =E14-F14-G14 -> 0 | K14: =H14-I14 -> 0
E16: =SUM(E3:E15) -> 0 | F16: =SUM(F3:F15) -> 0 | G16: =SUM(G3:G15) -> 0 | H16: =SUM(H3:H15) -> 0 | K16: =SUM(K3:K14)-I16 -> 0
N17: TRÁFEGO
A18: FEVEREIRO | B18: LEADS | C18: VENDAS | D18: TICKET | E18: FATURAMENTO | F18: GATWAY | G18: IMPOSTOS | H18: LIQUIDO | I18: TRÁFEGO | J18: EVENTO | K18: BRUTO | N18: =I14+I33 -> 0
E19: =C19*D19 -> 0 | F19: =(E19*3.24/100) -> 0 | G19: =E19*6% -> 0 | H19: =E19-F19-G19 -> 0 | K19: =I19-H19-H20-H21 -> 0
E20: =C20*D20 -> 0 | F20: =(E20*3.24/100) -> 0 | G20: =E20*6% -> 0 | H20: =E20-F20-G20 -> 0 | N20: ROAS
E21: =C21*D21 -> 0 | F21: =(E21*3.24/100) -> 0 | G21: =E21*6% -> 0 | H21: =E21-F21-G21 -> 0 | N21: =N7-N12-N18 -> 0
E22: =C22*D22 -> 0 | F22: =(E22*3.24/100) -> 0 | G22: =E22*6% -> 0 | H22: =E22-F22-G22 -> 0 | K22: =H22-I22 -> 0
E23: =C23*D23 -> 0 | F23: =(E23*3.24/100) -> 0 | G23: =E23*6% -> 0 | H23: =E23-F23-G23 -> 0 | K23: =H23-I23 -> 0
E24: =C24*D24 -> 0 | F24: =(E24*3.24/100) -> 0 | G24: =E24*6% -> 0 | H24: =E24-F24-G24 -> 0 | K24: =I24-H24-H25 -> 0
E25: =C25*D25 -> 0 | F25: =(E25*3.24/100) -> 0 | G25: =E25*6% -> 0 | H25: =E25-F25-G25 -> 0
E26: =C26*D26 -> 0 | F26: =(E26*3.24/100) -> 0 | G26: =E26*6% -> 0 | H26: =E26-F26-G26 -> 0 | K26: =H26-I26 -> 0
E27: =C27*D27 -> 0 | F27: =(E27*3.24/100) -> 0 | G27: =E27*6% -> 0 | H27: =E27-F27-G27 -> 0 | K27: =H27-I27 -> 0
E28: =C28*D28 -> 0 | F28: =(E28*3.24/100)+1 -> 1 | G28: =E28*6% -> 0 | H28: =E28-F28-G28 -> -1
E29: =C29*D29 -> 0 | F29: =(E29*3.24/100)+1 -> 1 | G29: =E29*6% -> 0 | H29: =E29-F29-G29 -> -1
E30: =C30*D30 -> 0 | F30: =(E30*3.24/100)+1 -> 1 | G30: =E30*6% -> 0 | H30: =E30-F30-G30 -> -1
E31: =C31*D31 -> 0 | F31: =(E31*3.24/100)+1 -> 1 | G31: =E31*6% -> 0 | H31: =E31-F31-G31 -> -1
E33: =SUM(E19:E31) -> 0 | F33: =SUM(F19:F31) -> 4 | G33: =SUM(G19:G31) -> 0 | I33: =SUM(I19:I31) -> 0 | K33: =SUM(K19:K31) -> 0
A36: MARÇO | C36: VENDAS | D36: TICKET | E36: FATURAMENTO | F36: GATWAY | G36: IMPOSTOS | H36: LIQUIDO | I36: TRÁFEGO | J36: EVENTO | K36: BRUTO
N38: BRUTO
N39: =K52+K64+K73 -> 0
N42: OPERACIONAL
N45: TRÁFEGO
N46: =I52+I64+I73 -> 0
N49: ROAS
N51: =N39-N43-N46 -> 0
E52: =SUM(E37:E51) -> 0 | F52: =SUM(F37:F51) -> 0 | G52: =SUM(G37:G51) -> 0 | I52: =SUM(I37:I51) -> 0 | K52: =SUM(K37:K51) -> 0
A55: ABRIL | C55: VENDAS | D55: TICKET | E55: FATURAMENTO | F55: GATWAY | G55: IMPOSTOS | H55: LIQUIDO | I55: TRÁFEGO | K55: BRUTO | M55: Q2
E64: =SUM(E56:E63) -> 0 | F64: =SUM(F56:F63) -> 0 | G64: =SUM(G56:G63) -> 0 | I64: =SUM(I56:I63) -> 0 | K64: =SUM(K56:K62) -> 0
A66: MAIO | C66: VENDAS | D66: TICKET | E66: FATURAMENTO | F66: GATWAY | G66: IMPOSTOS | H66: LIQUIDO | I66: TRÁFEGO | K66: BRUTO
I73: =SUM(I67:I71) -> 0 | K73: =SUM(K67:K71) -> 0
A75: JUNHO | C75: VENDAS | D75: TICKET | E75: FATURAMENTO | F75: GATWAY | G75: IMPOSTOS | H75: LIQUIDO | I75: TRÁFEGO | K75: BRUTO
I82: =SUM(I76:I80) -> 0 | K82: =SUM(K76:K80) -> 0

Sheet 🧮 CALCULADORA
B2: CALCULADORA DE PORCENTAGEM LIVRO | E2: CALCULADORA DE PORCENTAGEM CURSO | H2: CALCULADORA DE PORCENTAGEM CURSO | K2: CALCULADORA DE PORCENTAGEM CURSO
B3: Ticket | C3: 97 | E3: Ticket | F3: 197 | H3: Ticket | I3: 497 | K3: Ticket | L3: 5997
B4: Plataforma Gatway | C4: =(C3*9.9/100)+1 -> 10.603 | E4: Plataforma Gatway | F4: =(F3*9.9/100)+1+2.59 -> 23.093 | H4: Plataforma Gatway | I4: =(I3*9.9/100)+1+2.59 -> 52.793 | K4: Plataforma Gatway | L4: =(L3*9.9/100)+1+2.59 -> 597.293
B5: Agência % | C5: 100 | E5: Agência % | F5: 70 | H5: Agência % | I5: 70 | K5: Agência % | L5: 70
B6: Agência Investidora | C6: =(C3-C4)*C5/100 -> 86.397 | E6: Agência Investidora | F6: =(F3-F4)*F5/100 -> 121.7349 | H6: Agência Investidora | I6: =(I3-I4)*I5/100 -> 310.9449 | K6: Agência Investidora | L6: =(L3-L4)*L5/100 -> 3779.7949
B7: Produtor | C7: =C3-(C6+C4) -> 0 | E7: Produtor | F7: =F3-(F6+F4) -> 52.1721 | H7: Produtor | I7: =I3-(I6+I4) -> 133.2621 | K7: Produtor | L7: =L3-(L6+L4) -> 1619.9121
B9: CALCULADORA DE PORCENTAGEM LIVRO AFF | E9: CALCULADORA DE PORCENTAGEM CURSO AFF | H9: CALCULADORA DE PORCENTAGEM CURSO AFF | K9: CALCULADORA DE PORCENTAGEM CURSO AFF
B10: Ticket | C10: 2197 | E10: Ticket | F10: 2497 | H10: Ticket | I10: 5997 | K10: Ticket | L10: 5997
B11: Plataforma Gatway | C11: =(C10*9.9/100)+1 -> 218.503 | E11: Plataforma Gatway | F11: =(F10*9.9/100)+1+2.59 -> 250.793 | H11: Plataforma Gatway | I11: =(I10*9.9/100)+1+2.59 -> 597.293 | K11: Plataforma Gatway | L11: =(L10*9.9/100)+1+2.59 -> 597.293
B12: Agência % | C12: 50 | E12: Agência % | F12: 50 | H12: Agência % | I12: 50 | K12: Agência % | L12: 50
B13: Agência Investidora | C13: =(C10-C11)*C12/100 -> 989.2485 | E13: Agência Investidora | F13: =(F10-F11)*F12/100 -> 1123.1035 | H13: Agência Investidora | I13: =(I10-I11)*I12/100 -> 2699.8535 | K13: Agência Investidora | L13: =(L10-L11)*L12/100 -> 2699.8535
B14: Afiliado % | C14: 20 | E14: Afiliado % | F14: 20 | H14: Afiliado % | I14: 20 | K14: Afiliado % | L14: 20
B15: Afiliado Investidor | C15: =(C10-C11-C13)*C14/100 -> 197.8497 | E15: Afiliado Investidor | F15: =(F10-F11-F13)*F14/100 -> 224.6207 | H15: Afiliado Investidor | I15: =(I10-I11-I13)*I14/100 -> 539.9707 | K15: Afiliado Investidor | L15: =(L10-L11-L13)*L14/100 -> 539.9707
B16: Produtor | C16: =C10-(C13+C11+C15) -> 791.3988 | E16: Produtor | F16: =F10-(F13+F11+F15) -> 898.4828 | H16: Produtor | I16: =I10-(I13+I11+I15) -> 2159.8828 | K16: Produtor | L16: =L10-(L13+L11+L15) -> 2159.8828

Sheet 🌱 RECORRÊNCIA LIVRO FLUXO
B2: MÉTRICAS GERAIS
C4: janeiro | D4: fevereiro | E4: março | F4: abril | G4: maio | H4: junho | I4: julho | J4: agosto | K4: setembro | L4: outubro | M4: novembro | N4: dezembro
B5: INVESTIMENTO TOTAL | C5: =C6 -> 0 | D5: =D6 -> 0 | E5: =E6 -> 177.42 | F5: =F6 -> 1523.97 | G5: =G6 -> 0 | H5: =H6 -> 0 | I5: =I6 -> 0 | J5: =J6 -> 0 | ... N5: =N6 -> 0
B6: FACEBOOK | C6: 0 | D6: 0 | E6: =P26+AD26 -> 177.42 | F6: =P64 -> 1523.97 | G6: 0 | H6: 0 | I6: 0 | J6: 0 | K6: 0 | L6: 0 | M6: 0 | N6: 0
B8: CLIQUES ÚNICOS | C8: 0 | D8: 0 | E8: =W26 -> 143 | F8: =W64 -> 927 | G8: 0 | H8: 0 | I8: 0 | J8: 0 | K8: 0 | L8: 0 | M8: 0 | N8: 0
B9: CUSTO/CLIQUES ÚNICOS | C9: =C5/C8 -> #DIV/0! | D9: =D5/D8 -> #DIV/0! | E9: =E5/E8 -> 1.2406993 | F9: =F5/F8 -> 1.6439806 | G9: =G5/G8 -> #DIV/0! | H9: =H5/H8 -> #DIV/0! | I9: =I5/I8 -> #DIV/0! | J9: =J5/J8 -> #DIV/0! | ... N9: =N5/N8 -> #DIV/0!
B10: PÁGINA DE VENDAS | C10: 0 | D10: 0 | E10: =U26 -> 123 | F10: =U64 -> 690 | G10: 0 | H10: 0 | I10: 0 | J10: 0 | K10: 0 | L10: 0 | M10: 0 | N10: 0
B11: CUSTO/ PÁGINA DE VENDAS | C11: =C5/C10 -> #DIV/0! | D11: =D5/D10 -> #DIV/0! | E11: =E5/E10 -> 1.442439 | F11: =F5/F10 -> 2.2086522 | G11: =G5/G10 -> #DIV/0! | H11: =H5/H10 -> #DIV/0! | I11: =I5/I10 -> #DIV/0! | J11: =J5/J10 -> #DIV/0! | ... N11: =N5/N10 -> #DIV/0!
B12: CHECKOUT | C12: 0 | D12: 0 | E12: =S26 -> 186 | F12: =S64 -> 698 | G12: 0 | H12: 0 | I12: 0 | J12: 0 | K12: 0 | L12: 0 | M12: 0 | N12: 0
B13: CUSTO/CHECKOUT | C13: =C5/C12 -> #DIV/0! | D13: =D5/D12 -> #DIV/0! | E13: =E5/E12 -> 0.95387097 | F13: =F5/F12 -> 2.1833381 | G13: =G5/G12 -> #DIV/0! | H13: =H5/H12 -> #DIV/0! | I13: =I5/I12 -> #DIV/0! | J13: =J5/J12 -> #DIV/0! | ... N13: =N5/N12 -> #DIV/0!
B14: VENDAS | C14: 0 | D14: 0 | E14: =Q26 -> 22 | F14: =Q64 -> 104 | G14: 0 | H14: 0 | I14: 0 | J14: 0 | K14: 0 | L14: 0 | M14: 0 | N14: 0
B15: CUSTO/VENDAS | C15: =C5/C14 -> #DIV/0! | D15: =D5/D14 -> #DIV/0! | E15: =E5/E14 -> 8.0645455 | F15: =F5/F14 -> 14.653558 | G15: =G5/G14 -> #DIV/0! | H15: =H5/H14 -> #DIV/0! | I15: =I5/I14 -> #DIV/0! | J15: =J5/J14 -> #DIV/0! | ... N15: =N5/N14 -> #DIV/0!
B16: KPIS:
B17: _% Conversão Pg Vendas | C17: =C10/C8 -> #DIV/0! | D17: =D10/D8 -> #DIV/0! | E17: =E10/E8 -> 0.86013986 | F17: =F10/F8 -> 0.74433657 | G17: =G10/G8 -> #DIV/0! | H17: =H10/H8 -> #DIV/0! | I17: =I10/I8 -> #DIV/0! | J17: =J10/J8 -> #DIV/0! | ... N17: =N10/N8 -> #DIV/0!
B18: _% Conversão Checkout | C18: =C12/C10 -> #DIV/0! | D18: =D12/D10 -> #DIV/0! | E18: =E12/E10 -> 1.5121951 | F18: =F12/F10 -> 1.0115942 | G18: =G12/G10 -> #DIV/0! | H18: =H12/H10 -> #DIV/0! | I18: =I12/I10 -> #DIV/0! | J18: =J12/J10 -> #DIV/0! | ... N18: =N12/N10 -> #DIV/0!
B19: _% Conversão Vendas | C19: =C14/C12 -> #DIV/0! | D19: =D14/D12 -> #DIV/0! | E19: =E14/E12 -> 0.11827957 | F19: =F14/F12 -> 0.14899713 | G19: =G14/G12 -> #DIV/0! | H19: =H14/H12 -> #DIV/0! | I19: =I14/I12 -> #DIV/0! | J19: =J14/J12 -> #DIV/0! | ... N19: =N14/N12 -> #DIV/0!
B20: _% Order Bump | E20: =4/25 -> 0.16 | F20: =6/63 -> 0.095238095
B21: _% Upsell 1
B22: _% Upsell 2
O24: FACEBOOK ADS (OFERTA DIRETA) | AC24: FACEBOOK ADS (RMKT) | AQ24: GOOGLE ADS (OFERTA DIRETA) | BD24: GOOGLE ADS (RMKT)
B25: Março | O25: DATA | P25: Investimento | Q25: Compras | R25: Custo por Vendas | S25: Inicialização de Finalização de Compras | T25: Custo por Inicialização de Finalização de Compras | U25: Visualização Única de Página de destino | V25: Custo porVisualização Única de Página | W25: Cliques no link único | X25: Custo por Cliques no link único | Y25: % Conversão Visualização Pg Vendas | Z25: % Conversão de Compra | AA25: Diário de Bordo | AC25: DATA | AD25: Investimento | AE25: Compras | AF25: Custo por Vendas | AG25: Inicialização de Finalização de Compras | AH25: Custo por Inicialização de Finalização de Compras | AI25: Visualização Única de Página de destino | AJ25: Custo porVisualização Única de Página | AK25: Cliques no link único | AL25: Custo por Cliques no link único | AM25: % Conversão Pg Vendas | AN25: Diário de Bordo | AQ25: DATA | AR25: Investimento | AS25: Compras | AT25: Custo por Vendas | AU25: Inicialização de Finalização de Compras | AV25: Custo por Inicialização de Finalização de Compras | AW25: Visualização Única de Página de destino | AX25: Custo porVisualização Única de Página | AY25: Cliques no link único | AZ25: Custo por Cliques no link único | BA25: % Conversão Pg Vendas | BB25: Diário de Bordo | BD25: DATA | BE25: Investimento | BF25: Compras | BG25: Custo por Vendas | BH25: Inicialização de Finalização de Compras | BI25: Custo por Inicialização de Finalização de Compras | BJ25: Visualização Única de Página de destino | BK25: Custo porVisualização Única de Página | BL25: Cliques no link único | BM25: Custo por Cliques no link único | BN25: % Conversão Pg Vendas | BO25: Diário de Bordo
P26: =SUM(P27:P57) -> 177.42 | Q26: =SUM(Q27:Q57) -> 22 | R26: =P26/Q26 -> 8.0645455 | S26: =SUM(S27:S57) -> 186 | T26: =P26/S26 -> 0.95387097 | U26: =SUM(U27:U57) -> 123 | V26: =P26/U26 -> 1.442439 | W26: =SUM(W27:W57) -> 143 | X26: =P26/W26 -> 1.2406993 | Y26: =U26/W26 -> 0.86013986 | Z26: =Q26/S26 -> 0.11827957 | AD26: =SUM(AD27:AD57) -> 0 | AE26: =SUM(AE27:AE57) -> 0 | AF26: =AD26/AE26 -> #DIV/0! | AG26: =SUM(AG27:AG57) -> 0 | AH26: =AD26/AG26 -> #DIV/0! | AI26: =SUM(AI27:AI57) -> 0 | AJ26: =AD26/AI26 -> #DIV/0! | AK26: =SUM(AK27:AK57) -> 0 | AL26: =AD26/AK26 -> #DIV/0! | AM26: =AI26/AK26 -> #DIV/0! | AR26: =SUM(AR27:AR57) -> 0 | AS26: =SUM(AS27:AS57) -> 0 | AT26: =AR26/AS26 -> #DIV/0! | AU26: =SUM(AU27:AU57) -> 0 | AV26: =AR26/AU26 -> #DIV/0! | AW26: =SUM(AW27:AW57) -> 0 | AX26: =AR26/AW26 -> #DIV/0! | AY26: =SUM(AY27:AY57) -> 0 | AZ26: =AR26/AY26 -> #DIV/0! | BA26: =AW26/AY26 -> #DIV/0! | BE26: =SUM(BE27:BE57) -> 0 | BF26: =SUM(BF27:BF57) -> 0 | BG26: =BE26/BF26 -> #DIV/0! | BH26: =SUM(BH27:BH57) -> 0 | BI26: =BE26/BH26 -> #DIV/0! | BJ26: =SUM(BJ27:BJ57) -> 0 | BK26: =BE26/BJ26 -> #DIV/0! | BL26: =SUM(BL27:BL57) -> 0 | BM26: =BE26/BL26 -> #DIV/0! | BN26: =BJ26/BL26 -> #DIV/0!
N27: Sexta-feira | AB27: Sexta-feira | AC27: 44197 | AD27: 0 | AE27: 0 | AF27: =AD27/AE27 -> #DIV/0! | AG27: 0 | AH27: =AD27/AG27 -> #DIV/0! | AI27: 0 | AJ27: =AD27/AI27 -> #DIV/0! | AK27: 0 | AL27: =AD27/AK27 -> #DIV/0! | AM27: =AI27/AK27 -> #DIV/0! | AP27: Sexta-feira | AQ27: 44197 | AR27: 0 | AS27: 0 | AT27: =AR27/AS27 -> #DIV/0! | AU27: 0 | AV27: =AR27/AU27 -> #DIV/0! | AW27: 0 | AX27: =AR27/AW27 -> #DIV/0! | AY27: 0 | AZ27: =AR27/AY27 -> #DIV/0! | BA27: =AW27/AY27 -> #DIV/0! | BC27: Sexta-feira | BD27: 44197 | BE27: 0 | BF27: 0 | BG27: =BE27/BF27 -> #DIV/0! | BH27: 0 | BI27: =BE27/BH27 -> #DIV/0! | BJ27: 0 | BK27: =BE27/BJ27 -> #DIV/0! | BL27: 0 | BM27: =BE27/BL27 -> #DIV/0! | BN27: =BJ27/BL27 -> #DIV/0!
B28: Planejamento e Metas Esperadas | H28: Números Reais | N28: Sábado | AB28: Sábado | AC28: 44198 | AD28: 0 | AE28: 0 | AF28: =AD28/AE28 -> #DIV/0! | AG28: 0 | AH28: =AD28/AG28 -> #DIV/0! | AI28: 0 | AJ28: =AD28/AI28 -> #DIV/0! | AK28: 0 | AL28: =AD28/AK28 -> #DIV/0! | AM28: =AI28/AK28 -> #DIV/0! | AP28: Sábado | AQ28: 44198 | AR28: 0 | AS28: 0 | AT28: =AR28/AS28 -> #DIV/0! | AU28: 0 | AV28: =AR28/AU28 -> #DIV/0! | AW28: 0 | AX28: =AR28/AW28 -> #DIV/0! | AY28: 0 | AZ28: =AR28/AY28 -> #DIV/0! | BA28: =AW28/AY28 -> #DIV/0! | BC28: Sábado | BD28: 44198 | BE28: 0 | BF28: 0 | BG28: =BE28/BF28 -> #DIV/0! | BH28: 0 | BI28: =BE28/BH28 -> #DIV/0! | BJ28: 0 | BK28: =BE28/BJ28 -> #DIV/0! | BL28: 0 | BM28: =BE28/BL28 -> #DIV/0! | BN28: =BJ28/BL28 -> #DIV/0!
N29: Domingo | AB29: Domingo | AC29: 44199 | AD29: 0 | AE29: 0 | AF29: =AD29/AE29 -> #DIV/0! | AG29: 0 | AH29: =AD29/AG29 -> #DIV/0! | AI29: 0 | AJ29: =AD29/AI29 -> #DIV/0! | AK29: 0 | AL29: =AD29/AK29 -> #DIV/0! | AM29: =AI29/AK29 -> #DIV/0! | AP29: Domingo | AQ29: 44199 | AR29: 0 | AS29: 0 | AT29: =AR29/AS29 -> #DIV/0! | AU29: 0 | AV29: =AR29/AU29 -> #DIV/0! | AW29: 0 | AX29: =AR29/AW29 -> #DIV/0! | AY29: 0 | AZ29: =AR29/AY29 -> #DIV/0! | BA29: =AW29/AY29 -> #DIV/0! | BC29: Domingo | BD29: 44199 | BE29: 0 | BF29: 0 | BG29: =BE29/BF29 -> #DIV/0! | BH29: 0 | BI29: =BE29/BH29 -> #DIV/0! | BJ29: 0 | BK29: =BE29/BJ29 -> #DIV/0! | BL29: 0 | BM29: =BE29/BL29 -> #DIV/0! | BN29: =BJ29/BL29 -> #DIV/0!
B30: Meta de Faturamento | E30: 20160 | H30: Investimento Realizado | K30: 0 | N30: Segunda-feira | O30: 44200 | P30: 0 | Q30: 0 | R30: =P30/Q30 -> #DIV/0! | S30: 0 | T30: =P30/S30 -> #DIV/0! | U30: 0 | V30: =P30/U30 -> #DIV/0! | W30: 0 | X30: =P30/W30 -> #DIV/0! | Y30: =U30/W30 -> #DIV/0! | AB30: Segunda-feira | AC30: 44200 | AD30: 0 | AE30: 0 | AF30: =AD30/AE30 -> #DIV/0! | AG30: 0 | AH30: =AD30/AG30 -> #DIV/0! | AI30: 0 | AJ30: =AD30/AI30 -> #DIV/0! | AK30: 0 | AL30: =AD30/AK30 -> #DIV/0! | AM30: =AI30/AK30 -> #DIV/0! | AP30: Segunda-feira | AQ30: 44200 | AR30: 0 | AS30: 0 | AT30: =AR30/AS30 -> #DIV/0! | AU30: 0 | AV30: =AR30/AU30 -> #DIV/0! | AW30: 0 | AX30: =AR30/AW30 -> #DIV/0! | AY30: 0 | AZ30: =AR30/AY30 -> #DIV/0! | BA30: =AW30/AY30 -> #DIV/0! | BC30: Segunda-feira | BD30: 44200 | BE30: 0 | BF30: 0 | BG30: =BE30/BF30 -> #DIV/0! | BH30: 0 | BI30: =BE30/BH30 -> #DIV/0! | BJ30: 0 | BK30: =BE30/BJ30 -> #DIV/0! | BL30: 0 | BM30: =BE30/BL30 -> #DIV/0! | BN30: =BJ30/BL30 -> #DIV/0!
N31: Terça-feira | O31: 44201 | P31: 0 | Q31: 0 | R31: =P31/Q31 -> #DIV/0! | S31: 0 | T31: =P31/S31 -> #DIV/0! | U31: 0 | V31: =P31/U31 -> #DIV/0! | W31: 0 | X31: =P31/W31 -> #DIV/0! | Y31: =U31/W31 -> #DIV/0! | AB31: Terça-feira | AC31: 44201 | AD31: 0 | AE31: 0 | AF31: =AD31/AE31 -> #DIV/0! | AG31: 0 | AH31: =AD31/AG31 -> #DIV/0! | AI31: 0 | AJ31: =AD31/AI31 -> #DIV/0! | AK31: 0 | AL31: =AD31/AK31 -> #DIV/0! | AM31: =AI31/AK31 -> #DIV/0! | AP31: Terça-feira | AQ31: 44201 | AR31: 0 | AS31: 0 | AT31: =AR31/AS31 -> #DIV/0! | AU31: 0 | AV31: =AR31/AU31 -> #DIV/0! | AW31: 0 | AX31: =AR31/AW31 -> #DIV/0! | AY31: 0 | AZ31: =AR31/AY31 -> #DIV/0! | BA31: =AW31/AY31 -> #DIV/0! | BC31: Terça-feira | BD31: 44201 | BE31: 0 | BF31: 0 | BG31: =BE31/BF31 -> #DIV/0! | BH31: 0 | BI31: =BE31/BH31 -> #DIV/0! | BJ31: 0 | BK31: =BE31/BJ31 -> #DIV/0! | BL31: 0 | BM31: =BE31/BL31 -> #DIV/0! | BN31: =BJ31/BL31 -> #DIV/0!
B32: Ticket do Produto | E32: 97 | H32: Vendas Realizadas | K32: 0 | N32: Quarta-feira | O32: 44202 | P32: 0 | Q32: 0 | R32: =P32/Q32 -> #DIV/0! | S32: 0 | T32: =P32/S32 -> #DIV/0! | U32: 0 | V32: =P32/U32 -> #DIV/0! | W32: 0 | X32: =P32/W32 -> #DIV/0! | Y32: =U32/W32 -> #DIV/0! | AB32: Quarta-feira | AC32: 44202 | AD32: 0 | AE32: 0 | AF32: =AD32/AE32 -> #DIV/0! | AG32: 0 | AH32: =AD32/AG32 -> #DIV/0! | AI32: 0 | AJ32: =AD32/AI32 -> #DIV/0! | AK32: 0 | AL32: =AD32/AK32 -> #DIV/0! | AM32: =AI32/AK32 -> #DIV/0! | AP32: Quarta-feira | AQ32: 44202 | AR32: 0 | AS32: 0 | AT32: =AR32/AS32 -> #DIV/0! | AU32: 0 | AV32: =AR32/AU32 -> #DIV/0! | AW32: 0 | AX32: =AR32/AW32 -> #DIV/0! | AY32: 0 | AZ32: =AR32/AY32 -> #DIV/0! | BA32: =AW32/AY32 -> #DIV/0! | BC32: Quarta-feira | BD32: 44202 | BE32: 0 | BF32: 0 | BG32: =BE32/BF32 -> #DIV/0! | BH32: 0 | BI32: =BE32/BH32 -> #DIV/0! | BJ32: 0 | BK32: =BE32/BJ32 -> #DIV/0! | BL32: 0 | BM32: =BE32/BL32 -> #DIV/0! | BN32: =BJ32/BL32 -> #DIV/0!
N33: Quinta-feira | O33: 44203 | P33: 0 | Q33: 0 | R33: =P33/Q33 -> #DIV/0! | S33: 0 | T33: =P33/S33 -> #DIV/0! | U33: 0 | V33: =P33/U33 -> #DIV/0! | W33: 0 | X33: =P33/W33 -> #DIV/0! | Y33: =U33/W33 -> #DIV/0! | AB33: Quinta-feira | AC33: 44203 | AD33: 0 | AE33: 0 | AF33: =AD33/AE33 -> #DIV/0! | AG33: 0 | AH33: =AD33/AG33 -> #DIV/0! | AI33: 0 | AJ33: =AD33/AI33 -> #DIV/0! | AK33: 0 | AL33: =AD33/AK33 -> #DIV/0! | AM33: =AI33/AK33 -> #DIV/0! | AP33: Quinta-feira | AQ33: 44203 | AR33: 0 | AS33: 0 | AT33: =AR33/AS33 -> #DIV/0! | AU33: 0 | AV33: =AR33/AU33 -> #DIV/0! | AW33: 0 | AX33: =AR33/AW33 -> #DIV/0! | AY33: 0 | AZ33: =AR33/AY33 -> #DIV/0! | BA33: =AW33/AY33 -> #DIV/0! | BC33: Quinta-feira | BD33: 44203 | BE33: 0 | BF33: 0 | BG33: =BE33/BF33 -> #DIV/0! | BH33: 0 | BI33: =BE33/BH33 -> #DIV/0! | BJ33: 0 | BK33: =BE33/BJ33 -> #DIV/0! | BL33: 0 | BM33: =BE33/BL33 -> #DIV/0! | BN33: =BJ33/BL33 -> #DIV/0!
B34: Taxas da Plataforma | E34: 10.6 | H34: CPA Real | K34: =SUM(L30/L32) -> #DIV/0! | N34: Sexta-feira | O34: 44204 | P34: 0 | Q34: 0 | R34: =P34/Q34 -> #DIV/0! | S34: 0 | T34: =P34/S34 -> #DIV/0! | U34: 0 | V34: =P34/U34 -> #DIV/0! | W34: 0 | X34: =P34/W34 -> #DIV/0! | Y34: =U34/W34 -> #DIV/0! | AB34: Sexta-feira | AC34: 44204 | AD34: 0 | AE34: 0 | AF34: =AD34/AE34 -> #DIV/0! | AG34: 0 | AH34: =AD34/AG34 -> #DIV/0! | AI34: 0 | AJ34: =AD34/AI34 -> #DIV/0! | AK34: 0 | AL34: =AD34/AK34 -> #DIV/0! | AM34: =AI34/AK34 -> #DIV/0! | AP34: Sexta-feira | AQ34: 44204 | AR34: 0 | AS34: 0 | AT34: =AR34/AS34 -> #DIV/0! | AU34: 0 | AV34: =AR34/AU34 -> #DIV/0! | AW34: 0 | AX34: =AR34/AW34 -> #DIV/0! | AY34: 0 | AZ34: =AR34/AY34 -> #DIV/0! | BA34: =AW34/AY34 -> #DIV/0! | BC34: Sexta-feira | BD34: 44204 | BE34: 0 | BF34: 0 | BG34: =BE34/BF34 -> #DIV/0! | BH34: 0 | BI34: =BE34/BH34 -> #DIV/0! | BJ34: 0 | BK34: =BE34/BJ34 -> #DIV/0! | BL34: 0 | BM34: =BE34/BL34 -> #DIV/0! | BN34: =BJ34/BL34 -> #DIV/0!
N35: Sábado | O35: 44205 | P35: 0 | Q35: 0 | R35: =P35/Q35 -> #DIV/0! | S35: 0 | T35: =P35/S35 -> #DIV/0! | U35: 0 | V35: =P35/U35 -> #DIV/0! | W35: 0 | X35: =P35/W35 -> #DIV/0! | Y35: =U35/W35 -> #DIV/0! | AB35: Sábado | AC35: 44205 | AD35: 0 | AE35: 0 | AF35: =AD35/AE35 -> #DIV/0! | AG35: 0 | AH35: =AD35/AG35 -> #DIV/0! | AI35: 0 | AJ35: =AD35/AI35 -> #DIV/0! | AK35: 0 | AL35: =AD35/AK35 -> #DIV/0! | AM35: =AI35/AK35 -> #DIV/0! | AP35: Sábado | AQ35: 44205 | AR35: 0 | AS35: 0 | AT35: =AR35/AS35 -> #DIV/0! | AU35: 0 | AV35: =AR35/AU35 -> #DIV/0! | AW35: 0 | AX35: =AR35/AW35 -> #DIV/0! | AY35: 0 | AZ35: =AR35/AY35 -> #DIV/0! | BA35: =AW35/AY35 -> #DIV/0! | BC35: Sábado | BD35: 44205 | BE35: 0 | BF35: 0 | BG35: =BE35/BF35 -> #DIV/0! | BH35: 0 | BI35: =BE35/BH35 -> #DIV/0! | BJ35: 0 | BK35: =BE35/BJ35 -> #DIV/0! | BL35: 0 | BM35: =BE35/BL35 -> #DIV/0! | BN35: =BJ35/BL35 -> #DIV/0!
B36: Taxas de Coprodução | E36: 36.61 | H36: Faturamento Real | K36: =SUM(L32*F38) -> 0 | N36: Domingo | O36: 44206 | P36: 0 | Q36: 0 | R36: =P36/Q36 -> #DIV/0! | S36: 0 | T36: =P36/S36 -> #DIV/0! | U36: 0 | V36: =P36/U36 -> #DIV/0! | W36: 0 | X36: =P36/W36 -> #DIV/0! | Y36: =U36/W36 -> #DIV/0! | AB36: Domingo | AC36: 44206 | AD36: 0 | AE36: 0 | AF36: =AD36/AE36 -> #DIV/0! | AG36: 0 | AH36: =AD36/AG36 -> #DIV/0! | AI36: 0 | AJ36: =AD36/AI36 -> #DIV/0! | AK36: 0 | AL36: =AD36/AK36 -> #DIV/0! | AM36: =AI36/AK36 -> #DIV/0! | AP36: Domingo | AQ36: 44206 | AR36: 0 | AS36: 0 | AT36: =AR36/AS36 -> #DIV/0! | AU36: 0 | AV36: =AR36/AU36 -> #DIV/0! | AW36: 0 | AX36: =AR36/AW36 -> #DIV/0! | AY36: 0 | AZ36: =AR36/AY36 -> #DIV/0! | BA36: =AW36/AY36 -> #DIV/0! | BC36: Domingo | BD36: 44206 | BE36: 0 | BF36: 0 | BG36: =BE36/BF36 -> #DIV/0! | BH36: 0 | BI36: =BE36/BH36 -> #DIV/0! | BJ36: 0 | BK36: =BE36/BJ36 -> #DIV/0! | BL36: 0 | BM36: =BE36/BL36 -> #DIV/0! | BN36: =BJ36/BL36 -> #DIV/0!
N37: Segunda-feira | O37: 44207 | P37: 0 | Q37: 0 | R37: =P37/Q37 -> #DIV/0! | S37: 0 | T37: =P37/S37 -> #DIV/0! | U37: 0 | V37: =P37/U37 -> #DIV/0! | W37: 0 | X37: =P37/W37 -> #DIV/0! | Y37: =U37/W37 -> #DIV/0! | AB37: Segunda-feira | AC37: 44207 | AD37: 0 | AE37: 0 | AF37: =AD37/AE37 -> #DIV/0! | AG37: 0 | AH37: =AD37/AG37 -> #DIV/0! | AI37: 0 | AJ37: =AD37/AI37 -> #DIV/0! | AK37: 0 | AL37: =AD37/AK37 -> #DIV/0! | AM37: =AI37/AK37 -> #DIV/0! | AP37: Segunda-feira | AQ37: 44207 | AR37: 0 | AS37: 0 | AT37: =AR37/AS37 -> #DIV/0! | AU37: 0 | AV37: =AR37/AU37 -> #DIV/0! | AW37: 0 | AX37: =AR37/AW37 -> #DIV/0! | AY37: 0 | AZ37: =AR37/AY37 -> #DIV/0! | BA37: =AW37/AY37 -> #DIV/0! | BC37: Segunda-feira | BD37: 44207 | BE37: 0 | BF37: 0 | BG37: =BE37/BF37 -> #DIV/0! | BH37: 0 | BI37: =BE37/BH37 -> #DIV/0! | BJ37: 0 | BK37: =BE37/BJ37 -> #DIV/0! | BL37: 0 | BM37: =BE37/BL37 -> #DIV/0! | BN37: =BJ37/BL37 -> #DIV/0!
B38: Receita final do Produto | E38: 25.92 | H38: Lucro Bruto Real | K38: =SUM(L36-L30) -> 0 | N38: Terça-feira | O38: 44208 | P38: 0 | Q38: 0 | R38: =P38/Q38 -> #DIV/0! | S38: 0 | T38: =P38/S38 -> #DIV/0! | U38: 0 | V38: =P38/U38 -> #DIV/0! | W38: 0 | X38: =P38/W38 -> #DIV/0! | Y38: =U38/W38 -> #DIV/0! | AB38: Terça-feira | AC38: 44208 | AD38: 0 | AE38: 0 | AF38: =AD38/AE38 -> #DIV/0! | AG38: 0 | AH38: =AD38/AG38 -> #DIV/0! | AI38: 0 | AJ38: =AD38/AI38 -> #DIV/0! | AK38: 0 | AL38: =AD38/AK38 -> #DIV/0! | AM38: =AI38/AK38 -> #DIV/0! | AP38: Terça-feira | AQ38: 44208 | AR38: 0 | AS38: 0 | AT38: =AR38/AS38 -> #DIV/0! | AU38: 0 | AV38: =AR38/AU38 -> #DIV/0! | AW38: 0 | AX38: =AR38/AW38 -> #DIV/0! | AY38: 0 | AZ38: =AR38/AY38 -> #DIV/0! | BA38: =AW38/AY38 -> #DIV/0! | BC38: Terça-feira | BD38: 44208 | BE38: 0 | BF38: 0 | BG38: =BE38/BF38 -> #DIV/0! | BH38: 0 | BI38: =BE38/BH38 -> #DIV/0! | BJ38: 0 | BK38: =BE38/BJ38 -> #DIV/0! | BL38: 0 | BM38: =BE38/BL38 -> #DIV/0! | BN38: =BJ38/BL38 -> #DIV/0!
N39: Quarta-feira | O39: 44209 | P39: 0 | Q39: 0 | R39: =P39/Q39 -> #DIV/0! | S39: 0 | T39: =P39/S39 -> #DIV/0! | U39: 0 | V39: =P39/U39 -> #DIV/0! | W39: 0 | X39: =P39/W39 -> #DIV/0! | Y39: =U39/W39 -> #DIV/0! | AB39: Quarta-feira | AC39: 44209 | AD39: 0 | AE39: 0 | AF39: =AD39/AE39 -> #DIV/0! | AG39: 0 | AH39: =AD39/AG39 -> #DIV/0! | AI39: 0 | AJ39: =AD39/AI39 -> #DIV/0! | AK39: 0 | AL39: =AD39/AK39 -> #DIV/0! | AM39: =AI39/AK39 -> #DIV/0! | AP39: Quarta-feira | AQ39: 44209 | AR39: 0 | AS39: 0 | AT39: =AR39/AS39 -> #DIV/0! | AU39: 0 | AV39: =AR39/AU39 -> #DIV/0! | AW39: 0 | AX39: =AR39/AW39 -> #DIV/0! | AY39: 0 | AZ39: =AR39/AY39 -> #DIV/0! | BA39: =AW39/AY39 -> #DIV/0! | BC39: Quarta-feira | BD39: 44209 | BE39: 0 | BF39: 0 | BG39: =BE39/BF39 -> #DIV/0! | BH39: 0 | BI39: =BE39/BH39 -> #DIV/0! | BJ39: 0 | BK39: =BE39/BJ39 -> #DIV/0! | BL39: 0 | BM39: =BE39/BL39 -> #DIV/0! | BN39: =BJ39/BL39 -> #DIV/0!
B40: CPA Esperado | E40: 21.17 | N40: Quinta-feira | O40: 44210 | P40: 0 | Q40: 0 | R40: =P40/Q40 -> #DIV/0! | S40: 0 | T40: =P40/S40 -> #DIV/0! | U40: 0 | V40: =P40/U40 -> #DIV/0! | W40: 0 | X40: =P40/W40 -> #DIV/0! | Y40: =U40/W40 -> #DIV/0! | AB40: Quinta-feira | AC40: 44210 | AD40: 0 | AE40: 0 | AF40: =AD40/AE40 -> #DIV/0! | AG40: 0 | AH40: =AD40/AG40 -> #DIV/0! | AI40: 0 | AJ40: =AD40/AI40 -> #DIV/0! | AK40: 0 | AL40: =AD40/AK40 -> #DIV/0! | AM40: =AI40/AK40 -> #DIV/0! | AP40: Quinta-feira | AQ40: 44210 | AR40: 0 | AS40: 0 | AT40: =AR40/AS40 -> #DIV/0! | AU40: 0 | AV40: =AR40/AU40 -> #DIV/0! | AW40: 0 | AX40: =AR40/AW40 -> #DIV/0! | AY40: 0 | AZ40: =AR40/AY40 -> #DIV/0! | BA40: =AW40/AY40 -> #DIV/0! | BC40: Quinta-feira | BD40: 44210 | BE40: 0 | BF40: 0 | BG40: =BE40/BF40 -> #DIV/0! | BH40: 0 | BI40: =BE40/BH40 -> #DIV/0! | BJ40: 0 | BK40: =BE40/BJ40 -> #DIV/0! | BL40: 0 | BM40: =BE40/BL40 -> #DIV/0! | BN40: =BJ40/BL40 -> #DIV/0!
N41: Sexta-feira | O41: 44211 | P41: 0 | Q41: 0 | R41: =P41/Q41 -> #DIV/0! | S41: 0 | T41: =P41/S41 -> #DIV/0! | U41: 0 | V41: =P41/U41 -> #DIV/0! | W41: 0 | X41: =P41/W41 -> #DIV/0! | Y41: =U41/W41 -> #DIV/0! | AB41: Sexta-feira | AC41: 44211 | AD41: 0 | AE41: 0 | AF41: =AD41/AE41 -> #DIV/0! | AG41: 0 | AH41: =AD41/AG41 -> #DIV/0! | AI41: 0 | AJ41: =AD41/AI41 -> #DIV/0! | AK41: 0 | AL41: =AD41/AK41 -> #DIV/0! | AM41: =AI41/AK41 -> #DIV/0! | AP41: Sexta-feira | AQ41: 44211 | AR41: 0 | AS41: 0 | AT41: =AR41/AS41 -> #DIV/0! | AU41: 0 | AV41: =AR41/AU41 -> #DIV/0! | AW41: 0 | AX41: =AR41/AW41 -> #DIV/0! | AY41: 0 | AZ41: =AR41/AY41 -> #DIV/0! | BA41: =AW41/AY41 -> #DIV/0! | BC41: Sexta-feira | BD41: 44211 | BE41: 0 | BF41: 0 | BG41: =BE41/BF41 -> #DIV/0! | BH41: 0 | BI41: =BE41/BH41 -> #DIV/0! | BJ41: 0 | BK41: =BE41/BJ41 -> #DIV/0! | BL41: 0 | BM41: =BE41/BL41 -> #DIV/0! | BN41: =BJ41/BL41 -> #DIV/0!
B42: Vendas Necessárias | E42: =SUM(F30/F38) -> #DIV/0! | N42: Sábado | O42: 44212 | P42: 0 | Q42: 0 | R42: =P42/Q42 -> #DIV/0! | S42: 0 | T42: =P42/S42 -> #DIV/0! | U42: 0 | V42: =P42/U42 -> #DIV/0! | W42: 0 | X42: =P42/W42 -> #DIV/0! | Y42: =U42/W42 -> #DIV/0! | AB42: Sábado | AC42: 44212 | AD42: 0 | AE42: 0 | AF42: =AD42/AE42 -> #DIV/0! | AG42: 0 | AH42: =AD42/AG42 -> #DIV/0! | AI42: 0 | AJ42: =AD42/AI42 -> #DIV/0! | AK42: 0 | AL42: =AD42/AK42 -> #DIV/0! | AM42: =AI42/AK42 -> #DIV/0! | AP42: Sábado | AQ42: 44212 | AR42: 0 | AS42: 0 | AT42: =AR42/AS42 -> #DIV/0! | AU42: 0 | AV42: =AR42/AU42 -> #DIV/0! | AW42: 0 | AX42: =AR42/AW42 -> #DIV/0! | AY42: 0 | AZ42: =AR42/AY42 -> #DIV/0! | BA42: =AW42/AY42 -> #DIV/0! | BC42: Sábado | BD42: 44212 | BE42: 0 | BF42: 0 | BG42: =BE42/BF42 -> #DIV/0! | BH42: 0 | BI42: =BE42/BH42 -> #DIV/0! | BJ42: 0 | BK42: =BE42/BJ42 -> #DIV/0! | BL42: 0 | BM42: =BE42/BL42 -> #DIV/0! | BN42: =BJ42/BL42 -> #DIV/0!
N43: Domingo | O43: 44213 | P43: 0 | Q43: 0 | R43: =P43/Q43 -> #DIV/0! | S43: 0 | T43: =P43/S43 -> #DIV/0! | U43: 0 | V43: =P43/U43 -> #DIV/0! | W43: 0 | X43: =P43/W43 -> #DIV/0! | Y43: =U43/W43 -> #DIV/0! | AB43: Domingo | AC43: 44213 | AD43: 0 | AE43: 0 | AF43: =AD43/AE43 -> #DIV/0! | AG43: 0 | AH43: =AD43/AG43 -> #DIV/0! | AI43: 0 | AJ43: =AD43/AI43 -> #DIV/0! | AK43: 0 | AL43: =AD43/AK43 -> #DIV/0! | AM43: =AI43/AK43 -> #DIV/0! | AP43: Domingo | AQ43: 44213 | AR43: 0 | AS43: 0 | AT43: =AR43/AS43 -> #DIV/0! | AU43: 0 | AV43: =AR43/AU43 -> #DIV/0! | AW43: 0 | AX43: =AR43/AW43 -> #DIV/0! | AY43: 0 | AZ43: =AR43/AY43 -> #DIV/0! | BA43: =AW43/AY43 -> #DIV/0! | BC43: Domingo | BD43: 44213 | BE43: 0 | BF43: 0 | BG43: =BE43/BF43 -> #DIV/0! | BH43: 0 | BI43: =BE43/BH43 -> #DIV/0! | BJ43: 0 | BK43: =BE43/BJ43 -> #DIV/0! | BL43: 0 | BM43: =BE43/BL43 -> #DIV/0! | BN43: =BJ43/BL43 -> #DIV/0!
B44: Investimento Necessário | E44: =SUM(F40*F42) -> 0 | N44: Segunda-feira | O44: 44214 | P44: 0 | Q44: 0 | R44: =P44/Q44 -> #DIV/0! | S44: 0 | T44: =P44/S44 -> #DIV/0! | U44: 0 | V44: =P44/U44 -> #DIV/0! | W44: 0 | X44: =P44/W44 -> #DIV/0! | Y44: =U44/W44 -> #DIV/0! | AB44: Segunda-feira | AC44: 44214 | AD44: 0 | AE44: 0 | AF44: =AD44/AE44 -> #DIV/0! | AG44: 0 | AH44: =AD44/AG44 -> #DIV/0! | AI44: 0 | AJ44: =AD44/AI44 -> #DIV/0! | AK44: 0 | AL44: =AD44/AK44 -> #DIV/0! | AM44: =AI44/AK44 -> #DIV/0! | AP44: Segunda-feira | AQ44: 44214 | AR44: 0 | AS44: 0 | AT44: =AR44/AS44 -> #DIV/0! | AU44: 0 | AV44: =AR44/AU44 -> #DIV/0! | AW44: 0 | AX44: =AR44/AW44 -> #DIV/0! | AY44: 0 | AZ44: =AR44/AY44 -> #DIV/0! | BA44: =AW44/AY44 -> #DIV/0! | BC44: Segunda-feira | BD44: 44214 | BE44: 0 | BF44: 0 | BG44: =BE44/BF44 -> #DIV/0! | BH44: 0 | BI44: =BE44/BH44 -> #DIV/0! | BJ44: 0 | BK44: =BE44/BJ44 -> #DIV/0! | BL44: 0 | BM44: =BE44/BL44 -> #DIV/0! | BN44: =BJ44/BL44 -> #DIV/0!
N45: Terça-feira | O45: 44215 | P45: 0 | Q45: 0 | R45: =P45/Q45 -> #DIV/0! | S45: 0 | T45: =P45/S45 -> #DIV/0! | U45: 0 | V45: =P45/U45 -> #DIV/0! | W45: 0 | X45: =P45/W45 -> #DIV/0! | Y45: =U45/W45 -> #DIV/0! | AB45: Terça-feira | AC45: 44215 | AD45: 0 | AE45: 0 | AF45: =AD45/AE45 -> #DIV/0! | AG45: 0 | AH45: =AD45/AG45 -> #DIV/0! | AI45: 0 | AJ45: =AD45/AI45 -> #DIV/0! | AK45: 0 | AL45: =AD45/AK45 -> #DIV/0! | AM45: =AI45/AK45 -> #DIV/0! | AP45: Terça-feira | AQ45: 44215 | AR45: 0 | AS45: 0 | AT45: =AR45/AS45 -> #DIV/0! | AU45: 0 | AV45: =AR45/AU45 -> #DIV/0! | AW45: 0 | AX45: =AR45/AW45 -> #DIV/0! | AY45: 0 | AZ45: =AR45/AY45 -> #DIV/0! | BA45: =AW45/AY45 -> #DIV/0! | BC45: Terça-feira | BD45: 44215 | BE45: 0 | BF45: 0 | BG45: =BE45/BF45 -> #DIV/0! | BH45: 0 | BI45: =BE45/BH45 -> #DIV/0! | BJ45: 0 | BK45: =BE45/BJ45 -> #DIV/0! | BL45: 0 | BM45: =BE45/BL45 -> #DIV/0! | BN45: =BJ45/BL45 -> #DIV/0!
B46: Lucro Bruto | E46: =SUM(F30-F44) -> 0 | N46: Quarta-feira | O46: 44216 | P46: 0 | Q46: 0 | R46: =P46/Q46 -> #DIV/0! | S46: 0 | T46: =P46/S46 -> #DIV/0! | U46: 0 | V46: =P46/U46 -> #DIV/0! | W46: 0 | X46: =P46/W46 -> #DIV/0! | Y46: =U46/W46 -> #DIV/0! | AB46: Quarta-feira | AC46: 44216 | AD46: 0 | AE46: 0 | AF46: =AD46/AE46 -> #DIV/0! | AG46: 0 | AH46: =AD46/AG46 -> #DIV/0! | AI46: 0 | AJ46: =AD46/AI46 -> #DIV/0! | AK46: 0 | AL46: =AD46/AK46 -> #DIV/0! | AM46: =AI46/AK46 -> #DIV/0! | AP46: Quarta-feira | AQ46: 44216 | AR46: 0 | AS46: 0 | AT46: =AR46/AS46 -> #DIV/0! | AU46: 0 | AV46: =AR46/AU46 -> #DIV/0! | AW46: 0 | AX46: =AR46/AW46 -> #DIV/0! | AY46: 0 | AZ46: =AR46/AY46 -> #DIV/0! | BA46: =AW46/AY46 -> #DIV/0! | BC46: Quarta-feira | BD46: 44216 | BE46: 0 | BF46: 0 | BG46: =BE46/BF46 -> #DIV/0! | BH46: 0 | BI46: =BE46/BH46 -> #DIV/0! | BJ46: 0 | BK46: =BE46/BJ46 -> #DIV/0! | BL46: 0 | BM46: =BE46/BL46 -> #DIV/0! | BN46: =BJ46/BL46 -> #DIV/0!
N47: Quinta-feira | O47: 44217 | P47: 0 | Q47: 0 | R47: =P47/Q47 -> #DIV/0! | S47: 0 | T47: =P47/S47 -> #DIV/0! | U47: 0 | V47: =P47/U47 -> #DIV/0! | W47: 0 | X47: =P47/W47 -> #DIV/0! | Y47: =U47/W47 -> #DIV/0! | AB47: Quinta-feira | AC47: 44217 | AD47: 0 | AE47: 0 | AF47: =AD47/AE47 -> #DIV/0! | AG47: 0 | AH47: =AD47/AG47 -> #DIV/0! | AI47: 0 | AJ47: =AD47/AI47 -> #DIV/0! | AK47: 0 | AL47: =AD47/AK47 -> #DIV/0! | AM47: =AI47/AK47 -> #DIV/0! | AP47: Quinta-feira | AQ47: 44217 | AR47: 0 | AS47: 0 | AT47: =AR47/AS47 -> #DIV/0! | AU47: 0 | AV47: =AR47/AU47 -> #DIV/0! | AW47: 0 | AX47: =AR47/AW47 -> #DIV/0! | AY47: 0 | AZ47: =AR47/AY47 -> #DIV/0! | BA47: =AW47/AY47 -> #DIV/0! | BC47: Quinta-feira | BD47: 44217 | BE47: 0 | BF47: 0 | BG47: =BE47/BF47 -> #DIV/0! | BH47: 0 | BI47: =BE47/BH47 -> #DIV/0! | BJ47: 0 | BK47: =BE47/BJ47 -> #DIV/0! | BL47: 0 | BM47: =BE47/BL47 -> #DIV/0! | BN47: =BJ47/BL47 -> #DIV/0!
B48: Dias para alcançar a Meta | E48: 30 | N48: Sexta-feira | O48: 44218 | P48: 0 | Q48: 0 | R48: =P48/Q48 -> #DIV/0! | S48: 0 | T48: =P48/S48 -> #DIV/0! | U48: 0 | V48: =P48/U48 -> #DIV/0! | W48: 0 | X48: =P48/W48 -> #DIV/0! | Y48: =U48/W48 -> #DIV/0! | AB48: Sexta-feira | AC48: 44218 | AD48: 0 | AE48: 0 | AF48: =AD48/AE48 -> #DIV/0! | AG48: 0 | AH48: =AD48/AG48 -> #DIV/0! | AI48: 0 | AJ48: =AD48/AI48 -> #DIV/0! | AK48: 0 | AL48: =AD48/AK48 -> #DIV/0! | AM48: =AI48/AK48 -> #DIV/0! | AP48: Sexta-feira | AQ48: 44218 | AR48: 0 | AS48: 0 | AT48: =AR48/AS48 -> #DIV/0! | AU48: 0 | AV48: =AR48/AU48 -> #DIV/0! | AW48: 0 | AX48: =AR48/AW48 -> #DIV/0! | AY48: 0 | AZ48: =AR48/AY48 -> #DIV/0! | BA48: =AW48/AY48 -> #DIV/0! | BC48: Sexta-feira | BD48: 44218 | BE48: 0 | BF48: 0 | BG48: =BE48/BF48 -> #DIV/0! | BH48: 0 | BI48: =BE48/BH48 -> #DIV/0! | BJ48: 0 | BK48: =BE48/BJ48 -> #DIV/0! | BL48: 0 | BM48: =BE48/BL48 -> #DIV/0! | BN48: =BJ48/BL48 -> #DIV/0!
N49: Sábado | O49: 44219 | P49: 0 | Q49: 0 | R49: =P49/Q49 -> #DIV/0! | S49: 0 | T49: =P49/S49 -> #DIV/0! | U49: 0 | V49: =P49/U49 -> #DIV/0! | W49: 0 | X49: =P49/W49 -> #DIV/0! | Y49: =U49/W49 -> #DIV/0! | AB49: Sábado | AC49: 44219 | AD49: 0 | AE49: 0 | AF49: =AD49/AE49 -> #DIV/0! | AG49: 0 | AH49: =AD49/AG49 -> #DIV/0! | AI49: 0 | AJ49: =AD49/AI49 -> #DIV/0! | AK49: 0 | AL49: =AD49/AK49 -> #DIV/0! | AM49: =AI49/AK49 -> #DIV/0! | AP49: Sábado | AQ49: 44219 | AR49: 0 | AS49: 0 | AT49: =AR49/AS49 -> #DIV/0! | AU49: 0 | AV49: =AR49/AU49 -> #DIV/0! | AW49: 0 | AX49: =AR49/AW49 -> #DIV/0! | AY49: 0 | AZ49: =AR49/AY49 -> #DIV/0! | BA49: =AW49/AY49 -> #DIV/0! | BC49: Sábado | BD49: 44219 | BE49: 0 | BF49: 0 | BG49: =BE49/BF49 -> #DIV/0! | BH49: 0 | BI49: =BE49/BH49 -> #DIV/0! | BJ49: 0 | BK49: =BE49/BJ49 -> #DIV/0! | BL49: 0 | BM49: =BE49/BL49 -> #DIV/0! | BN49: =BJ49/BL49 -> #DIV/0!
B50: Investimento Diário | E50: =SUM(F44/F48)-F54 -> #DIV/0! | N50: Domingo | O50: 44220 | P50: 0 | Q50: 0 | R50: =P50/Q50 -> #DIV/0! | S50: 0 | T50: =P50/S50 -> #DIV/0! | U50: 0 | V50: =P50/U50 -> #DIV/0! | W50: 0 | X50: =P50/W50 -> #DIV/0! | Y50: =U50/W50 -> #DIV/0! | AB50: Domingo | AC50: 44220 | AD50: 0 | AE50: 0 | AF50: =AD50/AE50 -> #DIV/0! | AG50: 0 | AH50: =AD50/AG50 -> #DIV/0! | AI50: 0 | AJ50: =AD50/AI50 -> #DIV/0! | AK50: 0 | AL50: =AD50/AK50 -> #DIV/0! | AM50: =AI50/AK50 -> #DIV/0! | AP50: Domingo | AQ50: 44220 | AR50: 0 | AS50: 0 | AT50: =AR50/AS50 -> #DIV/0! | AU50: 0 | AV50: =AR50/AU50 -> #DIV/0! | AW50: 0 | AX50: =AR50/AW50 -> #DIV/0! | AY50: 0 | AZ50: =AR50/AY50 -> #DIV/0! | BA50: =AW50/AY50 -> #DIV/0! | BC50: Domingo | BD50: 44220 | BE50: 0 | BF50: 0 | BG50: =BE50/BF50 -> #DIV/0! | BH50: 0 | BI50: =BE50/BH50 -> #DIV/0! | BJ50: 0 | BK50: =BE50/BJ50 -> #DIV/0! | BL50: 0 | BM50: =BE50/BL50 -> #DIV/0! | BN50: =BJ50/BL50 -> #DIV/0!
N51: Segunda-feira | O51: 44221 | P51: 0 | Q51: 0 | R51: =P51/Q51 -> #DIV/0! | S51: 0 | T51: =P51/S51 -> #DIV/0! | U51: 0 | V51: =P51/U51 -> #DIV/0! | W51: 0 | X51: =P51/W51 -> #DIV/0! | Y51: =U51/W51 -> #DIV/0! | AB51: Segunda-feira | AC51: 44221 | AD51: 0 | AE51: 0 | AF51: =AD51/AE51 -> #DIV/0! | AG51: 0 | AH51: =AD51/AG51 -> #DIV/0! | AI51: 0 | AJ51: =AD51/AI51 -> #DIV/0! | AK51: 0 | AL51: =AD51/AK51 -> #DIV/0! | AM51: =AI51/AK51 -> #DIV/0! | AP51: Segunda-feira | AQ51: 44221 | AR51: 0 | AS51: 0 | AT51: =AR51/AS51 -> #DIV/0! | AU51: 0 | AV51: =AR51/AU51 -> #DIV/0! | AW51: 0 | AX51: =AR51/AW51 -> #DIV/0! | AY51: 0 | AZ51: =AR51/AY51 -> #DIV/0! | BA51: =AW51/AY51 -> #DIV/0! | BC51: Segunda-feira | BD51: 44221 | BE51: 0 | BF51: 0 | BG51: =BE51/BF51 -> #DIV/0! | BH51: 0 | BI51: =BE51/BH51 -> #DIV/0! | BJ51: 0 | BK51: =BE51/BJ51 -> #DIV/0! | BL51: 0 | BM51: =BE51/BL51 -> #DIV/0! | BN51: =BJ51/BL51 -> #DIV/0!
B52: Vendas Diárias | E52: =SUM(F42/F48) -> #DIV/0! | N52: Terça-feira | O52: 44222 | P52: 0 | Q52: 0 | R52: =P52/Q52 -> #DIV/0! | S52: 0 | T52: =P52/S52 -> #DIV/0! | U52: 0 | V52: =P52/U52 -> #DIV/0! | W52: 0 | X52: =P52/W52 -> #DIV/0! | Y52: =U52/W52 -> #DIV/0! | AB52: Terça-feira | AC52: 44222 | AD52: 0 | AE52: 0 | AF52: =AD52/AE52 -> #DIV/0! | AG52: 0 | AH52: =AD52/AG52 -> #DIV/0! | AI52: 0 | AJ52: =AD52/AI52 -> #DIV/0! | AK52: 0 | AL52: =AD52/AK52 -> #DIV/0! | AM52: =AI52/AK52 -> #DIV/0! | AP52: Terça-feira | AQ52: 44222 | AR52: 0 | AS52: 0 | AT52: =AR52/AS52 -> #DIV/0! | AU52: 0 | AV52: =AR52/AU52 -> #DIV/0! | AW52: 0 | AX52: =AR52/AW52 -> #DIV/0! | AY52: 0 | AZ52: =AR52/AY52 -> #DIV/0! | BA52: =AW52/AY52 -> #DIV/0! | BC52: Terça-feira | BD52: 44222 | BE52: 0 | BF52: 0 | BG52: =BE52/BF52 -> #DIV/0! | BH52: 0 | BI52: =BE52/BH52 -> #DIV/0! | BJ52: 0 | BK52: =BE52/BJ52 -> #DIV/0! | BL52: 0 | BM52: =BE52/BL52 -> #DIV/0! | BN52: =BJ52/BL52 -> #DIV/0!
N53: Quarta-feira | O53: 44223 | P53: 0 | Q53: 0 | R53: =P53/Q53 -> #DIV/0! | S53: 0 | T53: =P53/S53 -> #DIV/0! | U53: 0 | V53: =P53/U53 -> #DIV/0! | W53: 0 | X53: =P53/W53 -> #DIV/0! | Y53: =U53/W53 -> #DIV/0! | AB53: Quarta-feira | AC53: 44223 | AD53: 0 | AE53: 0 | AF53: =AD53/AE53 -> #DIV/0! | AG53: 0 | AH53: =AD53/AG53 -> #DIV/0! | AI53: 0 | AJ53: =AD53/AI53 -> #DIV/0! | AK53: 0 | AL53: =AD53/AK53 -> #DIV/0! | AM53: =AI53/AK53 -> #DIV/0! | AP53: Quarta-feira | AQ53: 44223 | AR53: 0 | AS53: 0 | AT53: =AR53/AS53 -> #DIV/0! | AU53: 0 | AV53: =AR53/AU53 -> #DIV/0! | AW53: 0 | AX53: =AR53/AW53 -> #DIV/0! | AY53: 0 | AZ53: =AR53/AY53 -> #DIV/0! | BA53: =AW53/AY53 -> #DIV/0! | BC53: Quarta-feira | BD53: 44223 | BE53: 0 | BF53: 0 | BG53: =BE53/BF53 -> #DIV/0! | BH53: 0 | BI53: =BE53/BH53 -> #DIV/0! | BJ53: 0 | BK53: =BE53/BJ53 -> #DIV/0! | BL53: 0 | BM53: =BE53/BL53 -> #DIV/0! | BN53: =BJ53/BL53 -> #DIV/0!
B54: % Remarketing Diário (por inicialização) | E54: =(F44*10%)/30 -> 0 | N54: Quinta-feira | O54: 44224 | P54: 0 | Q54: 0 | R54: =P54/Q54 -> #DIV/0! | S54: 0 | T54: =P54/S54 -> #DIV/0! | U54: 0 | V54: =P54/U54 -> #DIV/0! | W54: 0 | X54: =P54/W54 -> #DIV/0! | Y54: =U54/W54 -> #DIV/0! | AB54: Quinta-feira | AC54: 44224 | AD54: 0 | AE54: 0 | AF54: =AD54/AE54 -> #DIV/0! | AG54: 0 | AH54: =AD54/AG54 -> #DIV/0! | AI54: 0 | AJ54: =AD54/AI54 -> #DIV/0! | AK54: 0 | AL54: =AD54/AK54 -> #DIV/0! | AM54: =AI54/AK54 -> #DIV/0! | AP54: Quinta-feira | AQ54: 44224 | AR54: 0 | AS54: 0 | AT54: =AR54/AS54 -> #DIV/0! | AU54: 0 | AV54: =AR54/AU54 -> #DIV/0! | AW54: 0 | AX54: =AR54/AW54 -> #DIV/0! | AY54: 0 | AZ54: =AR54/AY54 -> #DIV/0! | BA54: =AW54/AY54 -> #DIV/0! | BC54: Quinta-feira | BD54: 44224 | BE54: 0 | BF54: 0 | BG54: =BE54/BF54 -> #DIV/0! | BH54: 0 | BI54: =BE54/BH54 -> #DIV/0! | BJ54: 0 | BK54: =BE54/BJ54 -> #DIV/0! | BL54: 0 | BM54: =BE54/BL54 -> #DIV/0! | BN54: =BJ54/BL54 -> #DIV/0!
N55: Sexta-feira | O55: 44225 | P55: 59.86 | Q55: 9 | R55: =P55/Q55 -> 6.6511111 | S55: 78 | T55: =P55/S55 -> 0.7674359 | U55: 44 | V55: =P55/U55 -> 1.3604545 | W55: 55 | X55: =P55/W55 -> 1.0883636 | Y55: =U55/W55 -> 0.8 | AB55: Sexta-feira | AC55: 44225 | AD55: 0 | AE55: 0 | AF55: =AD55/AE55 -> #DIV/0! | AG55: 0 | AH55: =AD55/AG55 -> #DIV/0! | AI55: 0 | AJ55: =AD55/AI55 -> #DIV/0! | AK55: 0 | AL55: =AD55/AK55 -> #DIV/0! | AM55: =AI55/AK55 -> #DIV/0! | AP55: Sexta-feira | AQ55: 44225 | AR55: 0 | AS55: 0 | AT55: =AR55/AS55 -> #DIV/0! | AU55: 0 | AV55: =AR55/AU55 -> #DIV/0! | AW55: 0 | AX55: =AR55/AW55 -> #DIV/0! | AY55: 0 | AZ55: =AR55/AY55 -> #DIV/0! | BA55: =AW55/AY55 -> #DIV/0! | BC55: Sexta-feira | BD55: 44225 | BE55: 0 | BF55: 0 | BG55: =BE55/BF55 -> #DIV/0! | BH55: 0 | BI55: =BE55/BH55 -> #DIV/0! | BJ55: 0 | BK55: =BE55/BJ55 -> #DIV/0! | BL55: 0 | BM55: =BE55/BL55 -> #DIV/0! | BN55: =BJ55/BL55 -> #DIV/0!
N56: Sábado | O56: 44226 | P56: 58.63 | Q56: 6 | R56: =P56/Q56 -> 9.7716667 | S56: 61 | T56: =P56/S56 -> 0.96114754 | U56: 45 | V56: =P56/U56 -> 1.3028889 | W56: 51 | X56: =P56/W56 -> 1.1496078 | Y56: =U56/W56 -> 0.88235294 | AB56: Sábado | AC56: 44226 | AD56: 0 | AE56: 0 | AF56: =AD56/AE56 -> #DIV/0! | AG56: 0 | AH56: =AD56/AG56 -> #DIV/0! | AI56: 0 | AJ56: =AD56/AI56 -> #DIV/0! | AK56: 0 | AL56: =AD56/AK56 -> #DIV/0! | AM56: =AI56/AK56 -> #DIV/0! | AP56: Sábado | AQ56: 44226 | AR56: 0 | AS56: 0 | AT56: =AR56/AS56 -> #DIV/0! | AU56: 0 | AV56: =AR56/AU56 -> #DIV/0! | AW56: 0 | AX56: =AR56/AW56 -> #DIV/0! | AY56: 0 | AZ56: =AR56/AY56 -> #DIV/0! | BA56: =AW56/AY56 -> #DIV/0! | BC56: Sábado | BD56: 44226 | BE56: 0 | BF56: 0 | BG56: =BE56/BF56 -> #DIV/0! | BH56: 0 | BI56: =BE56/BH56 -> #DIV/0! | BJ56: 0 | BK56: =BE56/BJ56 -> #DIV/0! | BL56: 0 | BM56: =BE56/BL56 -> #DIV/0! | BN56: =BJ56/BL56 -> #DIV/0!
N57: Domingo | O57: 44227 | P57: 58.93 | Q57: 7 | R57: =P57/Q57 -> 8.4185714 | S57: 47 | T57: =P57/S57 -> 1.2538298 | U57: 34 | V57: =P57/U57 -> 1.7332353 | W57: 37 | X57: =P57/W57 -> 1.5927027 | Y57: =U57/W57 -> 0.91891892 | AB57: Domingo | AC57: 44227 | AD57: 0 | AE57: 0 | AF57: =AD57/AE57 -> #DIV/0! | AG57: 0 | AH57: =AD57/AG57 -> #DIV/0! | AI57: 0 | AJ57: =AD57/AI57 -> #DIV/0! | AK57: 0 | AL57: =AD57/AK57 -> #DIV/0! | AM57: =AI57/AK57 -> #DIV/0! | AP57: Domingo | AQ57: 44227 | AR57: 0 | AS57: 0 | AT57: =AR57/AS57 -> #DIV/0! | AU57: 0 | AV57: =AR57/AU57 -> #DIV/0! | AW57: 0 | AX57: =AR57/AW57 -> #DIV/0! | AY57: 0 | AZ57: =AR57/AY57 -> #DIV/0! | BA57: =AW57/AY57 -> #DIV/0! | BB57: Programar novo CJA A campanha *[ABO][BM1-EA-CA001][INICIALIZAÇÃO][EA] — SKIN CARE NATURAL - FEVEREIRO foi programada para iniciar as 23:59 do dia 31/01/21, os conjuntos serão ativados gradualmente sendo analisado a cada 3 dias o seu desempenho. | BC57: Domingo | BD57: 44227 | BE57: 0 | BF57: 0 | BG57: =BE57/BF57 -> #DIV/0! | BH57: 0 | BI57: =BE57/BH57 -> #DIV/0! | BJ57: 0 | BK57: =BE57/BJ57 -> #DIV/0! | BL57: 0 | BM57: =BE57/BL57 -> #DIV/0! | BN57: =BJ57/BL57 -> #DIV/0!
O62: FACEBOOK ADS (OFERTA DIRETA) | AC62: FACEBOOK ADS (RMKT) | AQ62: GOOGLE ADS (OFERTA DIRETA) | BD62: GOOGLE ADS (RMKT)
B63: Abril | O63: DATA | P63: Investimento | Q63: Compras | R63: Custo por Vendas | S63: Inicialização de Finalização de Compras | T63: Custo por Inicialização de Finalização de Compras | U63: Visualização Única de Página de destino | V63: Custo porVisualização Única de Página | W63: Cliques no link único | X63: Custo por Cliques no link único | Y63: % Conversão Visualização Pg Vendas | Z63: % Conversão de Compra | AA63: Diário de Bordo | AC63: DATA | AD63: Investimento | AE63: Compras | AF63: Custo por Vendas | AG63: Inicialização de Finalização de Compras | AH63: Custo por Inicialização de Finalização de Compras | AI63: Visualização Única de Página de destino | AJ63: Custo porVisualização Única de Página | AK63: Cliques no link único | AL63: Custo por Cliques no link único | AM63: % Conversão Pg Vendas | AN63: Diário de Bordo | AQ63: DATA | AR63: Investimento | AS63: Compras | AT63: Custo por Vendas | AU63: Inicialização de Finalização de Compras | AV63: Custo por Inicialização de Finalização de Compras | AW63: Visualização Única de Página de destino | AX63: Custo porVisualização Única de Página | AY63: Cliques no link único | AZ63: Custo por Cliques no link único | BA63: % Conversão Pg Vendas | BB63: Diário de Bordo | BD63: DATA | BE63: Investimento | BF63: Compras | BG63: Custo por Vendas | BH63: Inicialização de Finalização de Compras | BI63: Custo por Inicialização de Finalização de Compras | BJ63: Visualização Única de Página de destino | BK63: Custo porVisualização Única de Página | BL63: Cliques no link único | BM63: Custo por Cliques no link único | BN63: % Conversão Pg Vendas | BO63: Diário de Bordo
P64: =SUM(P65:P95) -> 1523.97 | Q64: =SUM(Q65:Q95) -> 104 | R64: =P64/Q64 -> 14.653558 | S64: =SUM(S65:S95) -> 698 | T64: =P64/S64 -> 2.1833381 | U64: =SUM(U65:U95) -> 690 | V64: =P64/U64 -> 2.2086522 | W64: =SUM(W65:W95) -> 927 | X64: =P64/W64 -> 1.6439806 | Y64: =U64/W64 -> 0.74433657 | Z64: =Q64/S64 -> 0.14899713 | AD64: =SUM(AD65:AD94) -> 0 | AE64: =SUM(AE65:AE94) -> 0 | AF64: =AD64/AE64 -> #DIV/0! | AG64: =SUM(AG65:AG94) -> 0 | AH64: =AD64/AG64 -> #DIV/0! | AI64: =SUM(AI65:AI94) -> 0 | AJ64: =AD64/AI64 -> #DIV/0! | AK64: =SUM(AK65:AK94) -> 0 | AL64: =AD64/AK64 -> #DIV/0! | AM64: =AI64/AK64 -> #DIV/0! | AR64: =SUM(AR65:AR94) -> 0 | AS64: =SUM(AS65:AS94) -> 0 | AT64: =AR64/AS64 -> #DIV/0! | AU64: =SUM(AU65:AU94) -> 0 | AV64: =AR64/AU64 -> #DIV/0! | AW64: =SUM(AW65:AW94) -> 0 | AX64: =AR64/AW64 -> #DIV/0! | AY64: =SUM(AY65:AY94) -> 0 | AZ64: =AR64/AY64 -> #DIV/0! | BA64: =AW64/AY64 -> #DIV/0! | BE64: =SUM(BE65:BE94) -> 0 | BF64: =SUM(BF65:BF94) -> 0 | BG64: =BE64/BF64 -> #DIV/0! | BH64: =SUM(BH65:BH94) -> 0 | BI64: =BE64/BH64 -> #DIV/0! | BJ64: =SUM(BJ65:BJ94) -> 0 | BK64: =BE64/BJ64 -> #DIV/0! | BL64: =SUM(BL65:BL94) -> 0 | BM64: =BE64/BL64 -> #DIV/0! | BN64: =BJ64/BL64 -> #DIV/0!
N65: Quinta-feira | O65: 44287 | P65: 40.37 | Q65: 3 | R65: 13.46 | S65: 34 | T65: 1.19 | U65: 23 | V65: 1.76 | W65: 27 | X65: 1.5 | Z65: =Q65/S65 -> 0.088235294 | AB65: Quinta-feira | AC65: 44287 | AD65: 0 | AE65: 0 | AF65: =AD65/AE65 -> #DIV/0! | AG65: 0 | AH65: =AD65/AG65 -> #DIV/0! | AI65: 0 | AJ65: =AD65/AI65 -> #DIV/0! | AK65: 0 | AL65: =AD65/AK65 -> #DIV/0! | AM65: =AI65/AK65 -> #DIV/0! | AP65: Quinta-feira | AQ65: 44287 | AR65: 0 | AS65: 0 | AT65: =AR65/AS65 -> #DIV/0! | AU65: 0 | AV65: =AR65/AU65 -> #DIV/0! | AW65: 0 | AX65: =AR65/AW65 -> #DIV/0! | AY65: 0 | AZ65: =AR65/AY65 -> #DIV/0! | BA65: =AW65/AY65 -> #DIV/0! | BC65: Quinta-feira | BD65: 44287 | BE65: 0 | BF65: 0 | BG65: =BE65/BF65 -> #DIV/0! | BH65: 0 | BI65: =BE65/BH65 -> #DIV/0! | BJ65: 0 | BK65: =BE65/BJ65 -> #DIV/0! | BL65: 0 | BM65: =BE65/BL65 -> #DIV/0! | BN65: =BJ65/BL65 -> #DIV/0!
B66: Planejamento e Metas Esperadas | H66: Números Reais | N66: Sexta-feira | O66: 44288 | P66: 39.08 | Q66: 4 | R66: 9.77 | S66: 40 | T66: 0.98 | U66: 35 | V66: 1.12 | W66: 40 | X66: 0.98 | Z66: =Q66/S66 -> 0.1 | AB66: Sexta-feira | AC66: 44288 | AD66: 0 | AE66: 0 | AF66: =AD66/AE66 -> #DIV/0! | AG66: 0 | AH66: =AD66/AG66 -> #DIV/0! | AI66: 0 | AJ66: =AD66/AI66 -> #DIV/0! | AK66: 0 | AL66: =AD66/AK66 -> #DIV/0! | AM66: =AI66/AK66 -> #DIV/0! | AP66: Sexta-feira | AQ66: 44288 | AR66: 0 | AS66: 0 | AT66: =AR66/AS66 -> #DIV/0! | AU66: 0 | AV66: =AR66/AU66 -> #DIV/0! | AW66: 0 | AX66: =AR66/AW66 -> #DIV/0! | AY66: 0 | AZ66: =AR66/AY66 -> #DIV/0! | BA66: =AW66/AY66 -> #DIV/0! | BC66: Sexta-feira | BD66: 44288 | BE66: 0 | BF66: 0 | BG66: =BE66/BF66 -> #DIV/0! | BH66: 0 | BI66: =BE66/BH66 -> #DIV/0! | BJ66: 0 | BK66: =BE66/BJ66 -> #DIV/0! | BL66: 0 | BM66: =BE66/BL66 -> #DIV/0! | BN66: =BJ66/BL66 -> #DIV/0!
N67: Sábado | O67: 44289 | P67: 40.39 | Q67: 1 | R67: 40.39 | S67: 43 | T67: 0.94 | U67: 32 | V67: 1.26 | W67: 35 | X67: 1.15 | Z67: =Q67/S67 -> 0.023255814 | AB67: Sábado | AC67: 44289 | AD67: 0 | AE67: 0 | AF67: =AD67/AE67 -> #DIV/0! | AG67: 0 | AH67: =AD67/AG67 -> #DIV/0! | AI67: 0 | AJ67: =AD67/AI67 -> #DIV/0! | AK67: 0 | AL67: =AD67/AK67 -> #DIV/0! | AM67: =AI67/AK67 -> #DIV/0! | AP67: Sábado | AQ67: 44289 | AR67: 0 | AS67: 0 | AT67: =AR67/AS67 -> #DIV/0! | AU67: 0 | AV67: =AR67/AU67 -> #DIV/0! | AW67: 0 | AX67: =AR67/AW67 -> #DIV/0! | AY67: 0 | AZ67: =AR67/AY67 -> #DIV/0! | BA67: =AW67/AY67 -> #DIV/0! | BC67: Sábado | BD67: 44289 | BE67: 0 | BF67: 0 | BG67: =BE67/BF67 -> #DIV/0! | BH67: 0 | BI67: =BE67/BH67 -> #DIV/0! | BJ67: 0 | BK67: =BE67/BJ67 -> #DIV/0! | BL67: 0 | BM67: =BE67/BL67 -> #DIV/0! | BN67: =BJ67/BL67 -> #DIV/0!
B68: Meta de Faturamento | E68: =#REF! -> #REF! | H68: Investimento Realizado | K68: =P64 -> 1523.97 | N68: Domingo | O68: 44290 | P68: 38.59 | Q68: 1 | R68: 38.59 | S68: 25 | T68: 1.54 | U68: 24 | V68: 1.61 | W68: 27 | X68: 1.43 | Z68: =Q68/S68 -> 0.04 | AB68: Domingo | AC68: 44290 | AD68: 0 | AE68: 0 | AF68: =AD68/AE68 -> #DIV/0! | AG68: 0 | AH68: =AD68/AG68 -> #DIV/0! | AI68: 0 | AJ68: =AD68/AI68 -> #DIV/0! | AK68: 0 | AL68: =AD68/AK68 -> #DIV/0! | AM68: =AI68/AK68 -> #DIV/0! | AP68: Domingo | AQ68: 44290 | AR68: 0 | AS68: 0 | AT68: =AR68/AS68 -> #DIV/0! | AU68: 0 | AV68: =AR68/AU68 -> #DIV/0! | AW68: 0 | AX68: =AR68/AW68 -> #DIV/0! | AY68: 0 | AZ68: =AR68/AY68 -> #DIV/0! | BA68: =AW68/AY68 -> #DIV/0! | BC68: Domingo | BD68: 44290 | BE68: 0 | BF68: 0 | BG68: =BE68/BF68 -> #DIV/0! | BH68: 0 | BI68: =BE68/BH68 -> #DIV/0! | BJ68: 0 | BK68: =BE68/BJ68 -> #DIV/0! | BL68: 0 | BM68: =BE68/BL68 -> #DIV/0! | BN68: =BJ68/BL68 -> #DIV/0!
N69: Segunda-feira | O69: 44291 | P69: 39.34 | Q69: 1 | R69: 39.34 | S69: 27 | T69: 1.46 | U69: 20 | V69: 1.97 | W69: 24 | X69: 1.64 | Z69: =Q69/S69 -> 0.037037037 | AB69: Segunda-feira | AC69: 44291 | AD69: 0 | AE69: 0 | AF69: =AD69/AE69 -> #DIV/0! | AG69: 0 | AH69: =AD69/AG69 -> #DIV/0! | AI69: 0 | AJ69: =AD69/AI69 -> #DIV/0! | AK69: 0 | AL69: =AD69/AK69 -> #DIV/0! | AM69: =AI69/AK69 -> #DIV/0! | AP69: Segunda-feira | AQ69: 44291 | AR69: 0 | AS69: 0 | AT69: =AR69/AS69 -> #DIV/0! | AU69: 0 | AV69: =AR69/AU69 -> #DIV/0! | AW69: 0 | AX69: =AR69/AW69 -> #DIV/0! | AY69: 0 | AZ69: =AR69/AY69 -> #DIV/0! | BA69: =AW69/AY69 -> #DIV/0! | BC69: Segunda-feira | BD69: 44291 | BE69: 0 | BF69: 0 | BG69: =BE69/BF69 -> #DIV/0! | BH69: 0 | BI69: =BE69/BH69 -> #DIV/0! | BJ69: 0 | BK69: =BE69/BJ69 -> #DIV/0! | BL69: 0 | BM69: =BE69/BL69 -> #DIV/0! | BN69: =BJ69/BL69 -> #DIV/0!
B70: Ticket do Produto | E70: 97 | H70: Vendas Realizadas | K70: =Q64 -> 104 | N70: Terça-feira | O70: 44292 | P70: 40.77 | Q70: 3 | R70: 13.59 | S70: 23 | T70: 1.77 | U70: 25 | V70: 1.63 | W70: 28 | X70: 1.46 | Z70: =Q70/S70 -> 0.13043478 | AB70: Terça-feira | AC70: 44292 | AD70: 0 | AE70: 0 | AF70: =AD70/AE70 -> #DIV/0! | AG70: 0 | AH70: =AD70/AG70 -> #DIV/0! | AI70: 0 | AJ70: =AD70/AI70 -> #DIV/0! | AK70: 0 | AL70: =AD70/AK70 -> #DIV/0! | AM70: =AI70/AK70 -> #DIV/0! | AP70: Terça-feira | AQ70: 44292 | AR70: 0 | AS70: 0 | AT70: =AR70/AS70 -> #DIV/0! | AU70: 0 | AV70: =AR70/AU70 -> #DIV/0! | AW70: 0 | AX70: =AR70/AW70 -> #DIV/0! | AY70: 0 | AZ70: =AR70/AY70 -> #DIV/0! | BA70: =AW70/AY70 -> #DIV/0! | BC70: Terça-feira | BD70: 44292 | BE70: 0 | BF70: 0 | BG70: =BE70/BF70 -> #DIV/0! | BH70: 0 | BI70: =BE70/BH70 -> #DIV/0! | BJ70: 0 | BK70: =BE70/BJ70 -> #DIV/0! | BL70: 0 | BM70: =BE70/BL70 -> #DIV/0! | BN70: =BJ70/BL70 -> #DIV/0!
N71: Quarta-feira | O71: 44293 | P71: 39.66 | Q71: 2 | R71: 19.83 | S71: 33 | T71: 1.2 | U71: 24 | V71: 1.65 | W71: 27 | X71: 1.47 | Z71: =Q71/S71 -> 0.060606061 | AB71: Quarta-feira | AC71: 44293 | AD71: 0 | AE71: 0 | AF71: =AD71/AE71 -> #DIV/0! | AG71: 0 | AH71: =AD71/AG71 -> #DIV/0! | AI71: 0 | AJ71: =AD71/AI71 -> #DIV/0! | AK71: 0 | AL71: =AD71/AK71 -> #DIV/0! | AM71: =AI71/AK71 -> #DIV/0! | AP71: Quarta-feira | AQ71: 44293 | AR71: 0 | AS71: 0 | AT71: =AR71/AS71 -> #DIV/0! | AU71: 0 | AV71: =AR71/AU71 -> #DIV/0! | AW71: 0 | AX71: =AR71/AW71 -> #DIV/0! | AY71: 0 | AZ71: =AR71/AY71 -> #DIV/0! | BA71: =AW71/AY71 -> #DIV/0! | BC71: Quarta-feira | BD71: 44293 | BE71: 0 | BF71: 0 | BG71: =BE71/BF71 -> #DIV/0! | BH71: 0 | BI71: =BE71/BH71 -> #DIV/0! | BJ71: 0 | BK71: =BE71/BJ71 -> #DIV/0! | BL71: 0 | BM71: =BE71/BL71 -> #DIV/0! | BN71: =BJ71/BL71 -> #DIV/0!
B72: Taxas da Plataforma | E72: 10.6 | H72: CPA Real | K72: =SUM(K68/K70) -> 14.653558 | N72: Quinta-feira | O72: 44294 | P72: 40.63 | Q72: 3 | R72: 13.54 | S72: 36 | T72: 1.13 | U72: 29 | V72: 1.4 | W72: 31 | X72: 1.31 | Z72: =Q72/S72 -> 0.083333333 | AB72: Quinta-feira | AC72: 44294 | AD72: 0 | AE72: 0 | AF72: =AD72/AE72 -> #DIV/0! | AG72: 0 | AH72: =AD72/AG72 -> #DIV/0! | AI72: 0 | AJ72: =AD72/AI72 -> #DIV/0! | AK72: 0 | AL72: =AD72/AK72 -> #DIV/0! | AM72: =AI72/AK72 -> #DIV/0! | AP72: Quinta-feira | AQ72: 44294 | AR72: 0 | AS72: 0 | AT72: =AR72/AS72 -> #DIV/0! | AU72: 0 | AV72: =AR72/AU72 -> #DIV/0! | AW72: 0 | AX72: =AR72/AW72 -> #DIV/0! | AY72: 0 | AZ72: =AR72/AY72 -> #DIV/0! | BA72: =AW72/AY72 -> #DIV/0! | BC72: Quinta-feira | BD72: 44294 | BE72: 0 | BF72: 0 | BG72: =BE72/BF72 -> #DIV/0! | BH72: 0 | BI72: =BE72/BH72 -> #DIV/0! | BJ72: 0 | BK72: =BE72/BJ72 -> #DIV/0! | BL72: 0 | BM72: =BE72/BL72 -> #DIV/0! | BN72: =BJ72/BL72 -> #DIV/0!
N73: Sexta-feira | O73: 44295 | P73: 39.81 | Q73: 1 | R73: 39.81 | S73: 26 | T73: 1.53 | U73: 18 | V73: 2.21 | W73: 21 | X73: 1.9 | Z73: =Q73/S73 -> 0.038461538 | AB73: Sexta-feira | AC73: 44295 | AD73: 0 | AE73: 0 | AF73: =AD73/AE73 -> #DIV/0! | AG73: 0 | AH73: =AD73/AG73 -> #DIV/0! | AI73: 0 | AJ73: =AD73/AI73 -> #DIV/0! | AK73: 0 | AL73: =AD73/AK73 -> #DIV/0! | AM73: =AI73/AK73 -> #DIV/0! | AP73: Sexta-feira | AQ73: 44295 | AR73: 0 | AS73: 0 | AT73: =AR73/AS73 -> #DIV/0! | AU73: 0 | AV73: =AR73/AU73 -> #DIV/0! | AW73: 0 | AX73: =AR73/AW73 -> #DIV/0! | AY73: 0 | AZ73: =AR73/AY73 -> #DIV/0! | BA73: =AW73/AY73 -> #DIV/0! | BC73: Sexta-feira | BD73: 44295 | BE73: 0 | BF73: 0 | BG73: =BE73/BF73 -> #DIV/0! | BH73: 0 | BI73: =BE73/BH73 -> #DIV/0! | BJ73: 0 | BK73: =BE73/BJ73 -> #DIV/0! | BL73: 0 | BM73: =BE73/BL73 -> #DIV/0! | BN73: =BJ73/BL73 -> #DIV/0!
B74: Taxas de Coprodução | E74: 25.92 | H74: Faturamento Real | K74: =SUM(K70*E76) -> 6289.92 | N74: Sábado | O74: 44296 | P74: 41.19 | Q74: 5 | R74: 8.24 | S74: 29 | T74: 1.42 | U74: 22 | V74: 1.87 | W74: 23 | X74: 1.79 | Z74: =Q74/S74 -> 0.17241379 | AB74: Sábado | AC74: 44296 | AD74: 0 | AE74: 0 | AF74: =AD74/AE74 -> #DIV/0! | AG74: 0 | AH74: =AD74/AG74 -> #DIV/0! | AI74: 0 | AJ74: =AD74/AI74 -> #DIV/0! | AK74: 0 | AL74: =AD74/AK74 -> #DIV/0! | AM74: =AI74/AK74 -> #DIV/0! | AP74: Sábado | AQ74: 44296 | AR74: 0 | AS74: 0 | AT74: =AR74/AS74 -> #DIV/0! | AU74: 0 | AV74: =AR74/AU74 -> #DIV/0! | AW74: 0 | AX74: =AR74/AW74 -> #DIV/0! | AY74: 0 | AZ74: =AR74/AY74 -> #DIV/0! | BA74: =AW74/AY74 -> #DIV/0! | BC74: Sábado | BD74: 44296 | BE74: 0 | BF74: 0 | BG74: =BE74/BF74 -> #DIV/0! | BH74: 0 | BI74: =BE74/BH74 -> #DIV/0! | BJ74: 0 | BK74: =BE74/BJ74 -> #DIV/0! | BL74: 0 | BM74: =BE74/BL74 -> #DIV/0! | BN74: =BJ74/BL74 -> #DIV/0!
N75: Domingo | O75: 44297 | P75: 39.28 | Q75: 1 | R75: 39.28 | S75: 30 | T75: 1.31 | U75: 23 | V75: 1.71 | W75: 26 | X75: 1.51 | Z75: =Q75/S75 -> 0.033333333 | AB75: Domingo | AC75: 44297 | AD75: 0 | AE75: 0 | AF75: =AD75/AE75 -> #DIV/0! | AG75: 0 | AH75: =AD75/AG75 -> #DIV/0! | AI75: 0 | AJ75: =AD75/AI75 -> #DIV/0! | AK75: 0 | AL75: =AD75/AK75 -> #DIV/0! | AM75: =AI75/AK75 -> #DIV/0! | AP75: Domingo | AQ75: 44297 | AR75: 0 | AS75: 0 | AT75: =AR75/AS75 -> #DIV/0! | AU75: 0 | AV75: =AR75/AU75 -> #DIV/0! | AW75: 0 | AX75: =AR75/AW75 -> #DIV/0! | AY75: 0 | AZ75: =AR75/AY75 -> #DIV/0! | BA75: =AW75/AY75 -> #DIV/0! | BC75: Domingo | BD75: 44297 | BE75: 0 | BF75: 0 | BG75: =BE75/BF75 -> #DIV/0! | BH75: 0 | BI75: =BE75/BH75 -> #DIV/0! | BJ75: 0 | BK75: =BE75/BJ75 -> #DIV/0! | BL75: 0 | BM75: =BE75/BL75 -> #DIV/0! | BN75: =BJ75/BL75 -> #DIV/0!
B76: Receita final do Produto | E76: =SUM(E70-E72-E74) -> 60.48 | H76: Lucro Bruto Real | K76: =SUM(K74-K68) -> 4765.95 | N76: Segunda-feira | O76: 44298 | P76: 65.36 | Q76: 4 | R76: 16.34 | S76: 30 | T76: 2.18 | U76: 24 | V76: 2.72 | W76: 31 | X76: 2.11 | Z76: =Q76/S76 -> 0.13333333 | AB76: Segunda-feira | AC76: 44298 | AD76: 0 | AE76: 0 | AF76: =AD76/AE76 -> #DIV/0! | AG76: 0 | AH76: =AD76/AG76 -> #DIV/0! | AI76: 0 | AJ76: =AD76/AI76 -> #DIV/0! | AK76: 0 | AL76: =AD76/AK76 -> #DIV/0! | AM76: =AI76/AK76 -> #DIV/0! | AP76: Segunda-feira | AQ76: 44298 | AR76: 0 | AS76: 0 | AT76: =AR76/AS76 -> #DIV/0! | AU76: 0 | AV76: =AR76/AU76 -> #DIV/0! | AW76: 0 | AX76: =AR76/AW76 -> #DIV/0! | AY76: 0 | AZ76: =AR76/AY76 -> #DIV/0! | BA76: =AW76/AY76 -> #DIV/0! | BC76: Segunda-feira | BD76: 44298 | BE76: 0 | BF76: 0 | BG76: =BE76/BF76 -> #DIV/0! | BH76: 0 | BI76: =BE76/BH76 -> #DIV/0! | BJ76: 0 | BK76: =BE76/BJ76 -> #DIV/0! | BL76: 0 | BM76: =BE76/BL76 -> #DIV/0! | BN76: =BJ76/BL76 -> #DIV/0!
N77: Terça-feira | O77: 44299 | P77: 63.58 | Q77: 3 | R77: 21.19 | S77: 53 | T77: 1.2 | U77: 42 | V77: 1.51 | W77: 45 | X77: 1.41 | Z77: =Q77/S77 -> 0.056603774 | AB77: Terça-feira | AC77: 44299 | AD77: 0 | AE77: 0 | AF77: =AD77/AE77 -> #DIV/0! | AG77: 0 | AH77: =AD77/AG77 -> #DIV/0! | AI77: 0 | AJ77: =AD77/AI77 -> #DIV/0! | AK77: 0 | AL77: =AD77/AK77 -> #DIV/0! | AM77: =AI77/AK77 -> #DIV/0! | AP77: Terça-feira | AQ77: 44299 | AR77: 0 | AS77: 0 | AT77: =AR77/AS77 -> #DIV/0! | AU77: 0 | AV77: =AR77/AU77 -> #DIV/0! | AW77: 0 | AX77: =AR77/AW77 -> #DIV/0! | AY77: 0 | AZ77: =AR77/AY77 -> #DIV/0! | BA77: =AW77/AY77 -> #DIV/0! | BC77: Terça-feira | BD77: 44299 | BE77: 0 | BF77: 0 | BG77: =BE77/BF77 -> #DIV/0! | BH77: 0 | BI77: =BE77/BH77 -> #DIV/0! | BJ77: 0 | BK77: =BE77/BJ77 -> #DIV/0! | BL77: 0 | BM77: =BE77/BL77 -> #DIV/0! | BN77: =BJ77/BL77 -> #DIV/0!
B78: CPA Esperado | E78: =#REF! -> #REF! | H78: Média de Vendas por Dia | K78: =K70/30 -> 3.4666667 | N78: Quarta-feira | O78: 44300 | P78: 62.97 | Q78: 9 | R78: 7 | S78: 23 | T78: 2.74 | U78: 32 | V78: 1.97 | W78: 42 | X78: 1.5 | Z78: =Q78/S78 -> 0.39130435 | AA78: RESET (mudança de pub e posiconamento ) + pg vendas | AB78: Quarta-feira | AC78: 44300 | AD78: 0 | AE78: 0 | AF78: =AD78/AE78 -> #DIV/0! | AG78: 0 | AH78: =AD78/AG78 -> #DIV/0! | AI78: 0 | AJ78: =AD78/AI78 -> #DIV/0! | AK78: 0 | AL78: =AD78/AK78 -> #DIV/0! | AM78: =AI78/AK78 -> #DIV/0! | AP78: Quarta-feira | AQ78: 44300 | AR78: 0 | AS78: 0 | AT78: =AR78/AS78 -> #DIV/0! | AU78: 0 | AV78: =AR78/AU78 -> #DIV/0! | AW78: 0 | AX78: =AR78/AW78 -> #DIV/0! | AY78: 0 | AZ78: =AR78/AY78 -> #DIV/0! | BA78: =AW78/AY78 -> #DIV/0! | BC78: Quarta-feira | BD78: 44300 | BE78: 0 | BF78: 0 | BG78: =BE78/BF78 -> #DIV/0! | BH78: 0 | BI78: =BE78/BH78 -> #DIV/0! | BJ78: 0 | BK78: =BE78/BJ78 -> #DIV/0! | BL78: 0 | BM78: =BE78/BL78 -> #DIV/0! | BN78: =BJ78/BL78 -> #DIV/0!
N79: Quinta-feira | O79: 44301 | P79: 62.29 | Q79: 2 | R79: 31.15 | S79: 13 | T79: 4.79 | U79: 28 | V79: 2.22 | W79: 41 | X79: 1.52 | Z79: =Q79/S79 -> 0.15384615 | AB79: Quinta-feira | AP79: Quinta-feira | AQ79: 44301 | AR79: 0 | AS79: 0 | AT79: =AR79/AS79 -> #DIV/0! | AU79: 0 | AV79: =AR79/AU79 -> #DIV/0! | AW79: 0 | AX79: =AR79/AW79 -> #DIV/0! | AY79: 0 | AZ79: =AR79/AY79 -> #DIV/0! | BA79: =AW79/AY79 -> #DIV/0! | BC79: Quinta-feira | BD79: 44301 | BE79: 0 | BF79: 0 | BG79: =BE79/BF79 -> #DIV/0! | BH79: 0 | BI79: =BE79/BH79 -> #DIV/0! | BJ79: 0 | BK79: =BE79/BJ79 -> #DIV/0! | BL79: 0 | BM79: =BE79/BL79 -> #DIV/0! | BN79: =BJ79/BL79 -> #DIV/0!
B80: Vendas Necessárias | E80: =SUM(E68/E76) -> #REF! | N80: Sexta-feira | O80: 44302 | P80: 63.18 | Q80: 2 | R80: 31.59 | S80: 16 | T80: 3.95 | U80: 20 | V80: 3.16 | W80: 29 | X80: 2.18 | Z80: =Q80/S80 -> 0.125 | AB80: Sexta-feira | AP80: Sexta-feira | AQ80: 44302 | AR80: 0 | AS80: 0 | AT80: =AR80/AS80 -> #DIV/0! | AU80: 0 | AV80: =AR80/AU80 -> #DIV/0! | AW80: 0 | AX80: =AR80/AW80 -> #DIV/0! | AY80: 0 | AZ80: =AR80/AY80 -> #DIV/0! | BA80: =AW80/AY80 -> #DIV/0! | BC80: Sexta-feira | BD80: 44302 | BE80: 0 | BF80: 0 | BG80: =BE80/BF80 -> #DIV/0! | BH80: 0 | BI80: =BE80/BH80 -> #DIV/0! | BJ80: 0 | BK80: =BE80/BJ80 -> #DIV/0! | BL80: 0 | BM80: =BE80/BL80 -> #DIV/0! | BN80: =BJ80/BL80 -> #DIV/0!
N81: Sábado | O81: 44303 | P81: 63.21 | Q81: 4 | R81: 15.8 | S81: 12 | T81: 5.27 | U81: 26 | V81: 2.43 | W81: 33 | X81: 1.92 | Z81: =Q81/S81 -> 0.33333333 | AB81: Sábado | AP81: Sábado | AQ81: 44303 | AR81: 0 | AS81: 0 | AT81: =AR81/AS81 -> #DIV/0! | AU81: 0 | AV81: =AR81/AU81 -> #DIV/0! | AW81: 0 | AX81: =AR81/AW81 -> #DIV/0! | AY81: 0 | AZ81: =AR81/AY81 -> #DIV/0! | BA81: =AW81/AY81 -> #DIV/0! | BC81: Sábado | BD81: 44303 | BE81: 0 | BF81: 0 | BG81: =BE81/BF81 -> #DIV/0! | BH81: 0 | BI81: =BE81/BH81 -> #DIV/0! | BJ81: 0 | BK81: =BE81/BJ81 -> #DIV/0! | BL81: 0 | BM81: =BE81/BL81 -> #DIV/0! | BN81: =BJ81/BL81 -> #DIV/0!
B82: Investimento Necessário | E82: =SUM(E78*E80) -> #REF! | N82: Domingo | O82: 44304 | P82: 59.75 | Q82: 7 | R82: 8.54 | S82: 19 | T82: 3.14 | U82: 23 | V82: 2.6 | W82: 27 | X82: 2.21 | Z82: =Q82/S82 -> 0.36842105 | AB82: Domingo | AP82: Domingo | AQ82: 44304 | AR82: 0 | AS82: 0 | AT82: =AR82/AS82 -> #DIV/0! | AU82: 0 | AV82: =AR82/AU82 -> #DIV/0! | AW82: 0 | AX82: =AR82/AW82 -> #DIV/0! | AY82: 0 | AZ82: =AR82/AY82 -> #DIV/0! | BA82: =AW82/AY82 -> #DIV/0! | BC82: Domingo | BD82: 44304 | BE82: 0 | BF82: 0 | BG82: =BE82/BF82 -> #DIV/0! | BH82: 0 | BI82: =BE82/BH82 -> #DIV/0! | BJ82: 0 | BK82: =BE82/BJ82 -> #DIV/0! | BL82: 0 | BM82: =BE82/BL82 -> #DIV/0! | BN82: =BJ82/BL82 -> #DIV/0!
N83: Segunda-feira | O83: 44305 | P83: 60.56 | Q83: 7 | R83: 8.65 | S83: 22 | T83: 2.75 | U83: 25 | V83: 2.42 | W83: 28 | X83: 2.16 | Z83: =Q83/S83 -> 0.31818182 | AB83: Segunda-feira | AP83: Segunda-feira | AQ83: 44305 | AR83: 0 | AS83: 0 | AT83: =AR83/AS83 -> #DIV/0! | AU83: 0 | AV83: =AR83/AU83 -> #DIV/0! | AW83: 0 | AX83: =AR83/AW83 -> #DIV/0! | AY83: 0 | AZ83: =AR83/AY83 -> #DIV/0! | BA83: =AW83/AY83 -> #DIV/0! | BC83: Segunda-feira | BD83: 44305 | BE83: 0 | BF83: 0 | BG83: =BE83/BF83 -> #DIV/0! | BH83: 0 | BI83: =BE83/BH83 -> #DIV/0! | BJ83: 0 | BK83: =BE83/BJ83 -> #DIV/0! | BL83: 0 | BM83: =BE83/BL83 -> #DIV/0! | BN83: =BJ83/BL83 -> #DIV/0!
B84: Lucro Bruto | E84: =SUM(E68-E82) -> #REF! | N84: Terça-feira | O84: 44306 | P84: 59.87 | Q84: 5 | R84: 11.97 | S84: 32 | T84: 1.87 | U84: 34 | V84: 1.76 | W84: 38 | X84: 1.58 | Z84: =Q84/S84 -> 0.15625 | AB84: Terça-feira | AP84: Terça-feira | AQ84: 44306 | AR84: 0 | AS84: 0 | AT84: =AR84/AS84 -> #DIV/0! | AU84: 0 | AV84: =AR84/AU84 -> #DIV/0! | AW84: 0 | AX84: =AR84/AW84 -> #DIV/0! | AY84: 0 | AZ84: =AR84/AY84 -> #DIV/0! | BA84: =AW84/AY84 -> #DIV/0! | BC84: Terça-feira | BD84: 44306 | BE84: 0 | BF84: 0 | BG84: =BE84/BF84 -> #DIV/0! | BH84: 0 | BI84: =BE84/BH84 -> #DIV/0! | BJ84: 0 | BK84: =BE84/BJ84 -> #DIV/0! | BL84: 0 | BM84: =BE84/BL84 -> #DIV/0! | BN84: =BJ84/BL84 -> #DIV/0!
N85: Quarta-feira | O85: 44307 | P85: 59.37 | Q85: 7 | R85: 8.48 | S85: 16 | T85: 3.71 | U85: 25 | V85: 2.37 | W85: 35 | X85: 1.7 | Z85: =Q85/S85 -> 0.4375 | AB85: Quarta-feira | AN85: PAUSADO | AP85: Quarta-feira | AQ85: 44307 | AR85: 0 | AS85: 0 | AT85: =AR85/AS85 -> #DIV/0! | AU85: 0 | AV85: =AR85/AU85 -> #DIV/0! | AW85: 0 | AX85: =AR85/AW85 -> #DIV/0! | AY85: 0 | AZ85: =AR85/AY85 -> #DIV/0! | BA85: =AW85/AY85 -> #DIV/0! | BC85: Quarta-feira | BD85: 44307 | BE85: 0 | BF85: 0 | BG85: =BE85/BF85 -> #DIV/0! | BH85: 0 | BI85: =BE85/BH85 -> #DIV/0! | BJ85: 0 | BK85: =BE85/BJ85 -> #DIV/0! | BL85: 0 | BM85: =BE85/BL85 -> #DIV/0! | BN85: =BJ85/BL85 -> #DIV/0!
B86: Dias para alcançar a Meta | E86: 30 | N86: Quinta-feira | O86: 44308 | P86: 61.65 | Q86: 4 | R86: 15.41 | S86: 15 | T86: 4.11 | U86: 20 | V86: 3.08 | W86: 22 | X86: 2.8 | Z86: =Q86/S86 -> 0.26666667 | AB86: Quinta-feira | AC86: 44308 | AD86: 0 | AE86: 0 | AF86: =AD86/AE86 -> #DIV/0! | AG86: 0 | AH86: =AD86/AG86 -> #DIV/0! | AI86: 0 | AJ86: =AD86/AI86 -> #DIV/0! | AK86: 0 | AL86: =AD86/AK86 -> #DIV/0! | AM86: =AI86/AK86 -> #DIV/0! | AP86: Quinta-feira | AQ86: 44308 | AR86: 0 | AS86: 0 | AT86: =AR86/AS86 -> #DIV/0! | AU86: 0 | AV86: =AR86/AU86 -> #DIV/0! | AW86: 0 | AX86: =AR86/AW86 -> #DIV/0! | AY86: 0 | AZ86: =AR86/AY86 -> #DIV/0! | BA86: =AW86/AY86 -> #DIV/0! | BC86: Quinta-feira | BD86: 44308 | BE86: 0 | BF86: 0 | BG86: =BE86/BF86 -> #DIV/0! | BH86: 0 | BI86: =BE86/BH86 -> #DIV/0! | BJ86: 0 | BK86: =BE86/BJ86 -> #DIV/0! | BL86: 0 | BM86: =BE86/BL86 -> #DIV/0! | BN86: =BJ86/BL86 -> #DIV/0!
N87: Sexta-feira | O87: 44309 | P87: 59.13 | Q87: 1 | R87: 59.13 | S87: 6 | T87: 9.86 | U87: 25 | V87: 2.37 | W87: 32 | X87: 1.85 | Z87: =Q87/S87 -> 0.16666667 | AB87: Sexta-feira | AC87: 44309 | AD87: 0 | AE87: 0 | AF87: =AD87/AE87 -> #DIV/0! | AG87: 0 | AH87: =AD87/AG87 -> #DIV/0! | AI87: 0 | AJ87: =AD87/AI87 -> #DIV/0! | AK87: 0 | AL87: =AD87/AK87 -> #DIV/0! | AM87: =AI87/AK87 -> #DIV/0! | AP87: Sexta-feira | AQ87: 44309 | AR87: 0 | AS87: 0 | AT87: =AR87/AS87 -> #DIV/0! | AU87: 0 | AV87: =AR87/AU87 -> #DIV/0! | AW87: 0 | AX87: =AR87/AW87 -> #DIV/0! | AY87: 0 | AZ87: =AR87/AY87 -> #DIV/0! | BA87: =AW87/AY87 -> #DIV/0! | BC87: Sexta-feira | BD87: 44309 | BE87: 0 | BF87: 0 | BG87: =BE87/BF87 -> #DIV/0! | BH87: 0 | BI87: =BE87/BH87 -> #DIV/0! | BJ87: 0 | BK87: =BE87/BJ87 -> #DIV/0! | BL87: 0 | BM87: =BE87/BL87 -> #DIV/0! | BN87: =BJ87/BL87 -> #DIV/0!
B88: Investimento Diário | E88: =SUM(E82/E86)-E92 -> #REF! | N88: Sábado | O88: 44310 | P88: 57.1 | Q88: 1 | R88: 57.1 | S88: 9 | T88: 6.34 | U88: 21 | V88: 2.72 | W88: 28 | X88: 2.04 | Z88: =Q88/S88 -> 0.11111111 | AB88: Sábado | AC88: 44310 | AD88: 0 | AE88: 0 | AF88: =AD88/AE88 -> #DIV/0! | AG88: 0 | AH88: =AD88/AG88 -> #DIV/0! | AI88: 0 | AJ88: =AD88/AI88 -> #DIV/0! | AK88: 0 | AL88: =AD88/AK88 -> #DIV/0! | AM88: =AI88/AK88 -> #DIV/0! | AP88: Sábado | AQ88: 44310 | AR88: 0 | AS88: 0 | AT88: =AR88/AS88 -> #DIV/0! | AU88: 0 | AV88: =AR88/AU88 -> #DIV/0! | AW88: 0 | AX88: =AR88/AW88 -> #DIV/0! | AY88: 0 | AZ88: =AR88/AY88 -> #DIV/0! | BA88: =AW88/AY88 -> #DIV/0! | BC88: Sábado | BD88: 44310 | BE88: 0 | BF88: 0 | BG88: =BE88/BF88 -> #DIV/0! | BH88: 0 | BI88: =BE88/BH88 -> #DIV/0! | BJ88: 0 | BK88: =BE88/BJ88 -> #DIV/0! | BL88: 0 | BM88: =BE88/BL88 -> #DIV/0! | BN88: =BJ88/BL88 -> #DIV/0!
N89: Domingo | O89: 44311 | P89: 39.33 | Q89: 8 | R89: 4.92 | S89: 17 | T89: 2.31 | U89: 32 | V89: 1.23 | W89: 36 | X89: 1.09 | Z89: =Q89/S89 -> 0.47058824 | AB89: Domingo | AC89: 44311 | AD89: 0 | AE89: 0 | AF89: =AD89/AE89 -> #DIV/0! | AG89: 0 | AH89: =AD89/AG89 -> #DIV/0! | AI89: 0 | AJ89: =AD89/AI89 -> #DIV/0! | AK89: 0 | AL89: =AD89/AK89 -> #DIV/0! | AM89: =AI89/AK89 -> #DIV/0! | AP89: Domingo | AQ89: 44311 | AR89: 0 | AS89: 0 | AT89: =AR89/AS89 -> #DIV/0! | AU89: 0 | AV89: =AR89/AU89 -> #DIV/0! | AW89: 0 | AX89: =AR89/AW89 -> #DIV/0! | AY89: 0 | AZ89: =AR89/AY89 -> #DIV/0! | BA89: =AW89/AY89 -> #DIV/0! | BC89: Domingo | BD89: 44311 | BE89: 0 | BF89: 0 | BG89: =BE89/BF89 -> #DIV/0! | BH89: 0 | BI89: =BE89/BH89 -> #DIV/0! | BJ89: 0 | BK89: =BE89/BJ89 -> #DIV/0! | BL89: 0 | BM89: =BE89/BL89 -> #DIV/0! | BN89: =BJ89/BL89 -> #DIV/0!
B90: Vendas Diárias | E90: =SUM(E80/E86) -> #REF! | N90: Segunda-feira | O90: 44312 | P90: 39.74 | Q90: 4 | R90: 9.94 | S90: 16 | T90: 2.48 | U90: 28 | V90: 1.42 | W90: 33 | X90: 1.2 | Z90: =Q90/S90 -> 0.25 | AB90: Segunda-feira | AC90: 44312 | AD90: 0 | AE90: 0 | AF90: =AD90/AE90 -> #DIV/0! | AG90: 0 | AH90: =AD90/AG90 -> #DIV/0! | AI90: 0 | AJ90: =AD90/AI90 -> #DIV/0! | AK90: 0 | AL90: =AD90/AK90 -> #DIV/0! | AM90: =AI90/AK90 -> #DIV/0! | AP90: Segunda-feira | AQ90: 44312 | AR90: 0 | AS90: 0 | AT90: =AR90/AS90 -> #DIV/0! | AU90: 0 | AV90: =AR90/AU90 -> #DIV/0! | AW90: 0 | AX90: =AR90/AW90 -> #DIV/0! | AY90: 0 | AZ90: =AR90/AY90 -> #DIV/0! | BA90: =AW90/AY90 -> #DIV/0! | BC90: Segunda-feira | BD90: 44312 | BE90: 0 | BF90: 0 | BG90: =BE90/BF90 -> #DIV/0! | BH90: 0 | BI90: =BE90/BH90 -> #DIV/0! | BJ90: 0 | BK90: =BE90/BJ90 -> #DIV/0! | BL90: 0 | BM90: =BE90/BL90 -> #DIV/0! | BN90: =BJ90/BL90 -> #DIV/0!
N91: Terça-feira | O91: 44313 | P91: 40.35 | Q91: 3 | R91: 13.45 | S91: 13 | T91: 3.1 | U91: 10 | V91: 4.04 | W91: 32 | X91: 1.26 | Z91: =Q91/S91 -> 0.23076923 | AB91: Terça-feira | AC91: 44313 | AD91: 0 | AE91: 0 | AF91: =AD91/AE91 -> #DIV/0! | AG91: 0 | AH91: =AD91/AG91 -> #DIV/0! | AI91: 0 | AJ91: =AD91/AI91 -> #DIV/0! | AK91: 0 | AL91: =AD91/AK91 -> #DIV/0! | AM91: =AI91/AK91 -> #DIV/0! | AP91: Terça-feira | AQ91: 44313 | AR91: 0 | AS91: 0 | AT91: =AR91/AS91 -> #DIV/0! | AU91: 0 | AV91: =AR91/AU91 -> #DIV/0! | AW91: 0 | AX91: =AR91/AW91 -> #DIV/0! | AY91: 0 | AZ91: =AR91/AY91 -> #DIV/0! | BA91: =AW91/AY91 -> #DIV/0! | BC91: Terça-feira | BD91: 44313 | BE91: 0 | BF91: 0 | BG91: =BE91/BF91 -> #DIV/0! | BH91: 0 | BI91: =BE91/BH91 -> #DIV/0! | BJ91: 0 | BK91: =BE91/BJ91 -> #DIV/0! | BL91: 0 | BM91: =BE91/BL91 -> #DIV/0! | BN91: =BJ91/BL91 -> #DIV/0!
B92: % Remarketing Diário (por inicialização) | E92: =(E82*10%)/E86 -> #REF! | N92: Quarta-feira | O92: 44314 | P92: 39.68 | Q92: 3 | R92: 13.23 | S92: 7 | T92: 5.67 | W92: 15 | X92: 2.65 | Z92: =Q92/S92 -> 0.42857143 | AB92: Quarta-feira | AC92: 44314 | AD92: 0 | AE92: 0 | AF92: =AD92/AE92 -> #DIV/0! | AG92: 0 | AH92: =AD92/AG92 -> #DIV/0! | AI92: 0 | AJ92: =AD92/AI92 -> #DIV/0! | AK92: 0 | AL92: =AD92/AK92 -> #DIV/0! | AM92: =AI92/AK92 -> #DIV/0! | AP92: Quarta-feira | AQ92: 44314 | AR92: 0 | AS92: 0 | AT92: =AR92/AS92 -> #DIV/0! | AU92: 0 | AV92: =AR92/AU92 -> #DIV/0! | AW92: 0 | AX92: =AR92/AW92 -> #DIV/0! | AY92: 0 | AZ92: =AR92/AY92 -> #DIV/0! | BA92: =AW92/AY92 -> #DIV/0! | BC92: Quarta-feira | BD92: 44314 | BE92: 0 | BF92: 0 | BG92: =BE92/BF92 -> #DIV/0! | BH92: 0 | BI92: =BE92/BH92 -> #DIV/0! | BJ92: 0 | BK92: =BE92/BJ92 -> #DIV/0! | BL92: 0 | BM92: =BE92/BL92 -> #DIV/0! | BN92: =BJ92/BL92 -> #DIV/0!
N93: Quinta-feira | O93: 44315 | P93: 63.67 | S93: 15 | T93: 4.24 | W93: 37 | X93: 1.72 | Z93: =Q93/S93 -> 0 | AA93: MORNO ATIVADO | AB93: Quinta-feira | AC93: 44315 | AD93: 0 | AE93: 0 | AF93: =AD93/AE93 -> #DIV/0! | AG93: 0 | AH93: =AD93/AG93 -> #DIV/0! | AI93: 0 | AJ93: =AD93/AI93 -> #DIV/0! | AK93: 0 | AL93: =AD93/AK93 -> #DIV/0! | AM93: =AI93/AK93 -> #DIV/0! | AP93: Quinta-feira | AQ93: 44315 | AR93: 0 | AS93: 0 | AT93: =AR93/AS93 -> #DIV/0! | AU93: 0 | AV93: =AR93/AU93 -> #DIV/0! | AW93: 0 | AX93: =AR93/AW93 -> #DIV/0! | AY93: 0 | AZ93: =AR93/AY93 -> #DIV/0! | BA93: =AW93/AY93 -> #DIV/0! | BC93: Quinta-feira | BD93: 44315 | BE93: 0 | BF93: 0 | BG93: =BE93/BF93 -> #DIV/0! | BH93: 0 | BI93: =BE93/BH93 -> #DIV/0! | BJ93: 0 | BK93: =BE93/BJ93 -> #DIV/0! | BL93: 0 | BM93: =BE93/BL93 -> #DIV/0! | BN93: =BJ93/BL93 -> #DIV/0!
N94: Sexta-feira | O94: 44316 | P94: 64.07 | Q94: 5 | R94: 12.81 | S94: 18 | T94: 3.56 | W94: 34 | X94: 1.88 | Z94: =Q94/S94 -> 0.27777778 | AB94: Sexta-feira | AC94: 44316 | AD94: 0 | AE94: 0 | AF94: =AD94/AE94 -> #DIV/0! | AG94: 0 | AH94: =AD94/AG94 -> #DIV/0! | AI94: 0 | AJ94: =AD94/AI94 -> #DIV/0! | AK94: 0 | AL94: =AD94/AK94 -> #DIV/0! | AM94: =AI94/AK94 -> #DIV/0! | AP94: Sexta-feira | AQ94: 44316 | AR94: 0 | AS94: 0 | AT94: =AR94/AS94 -> #DIV/0! | AU94: 0 | AV94: =AR94/AU94 -> #DIV/0! | AW94: 0 | AX94: =AR94/AW94 -> #DIV/0! | AY94: 0 | AZ94: =AR94/AY94 -> #DIV/0! | BA94: =AW94/AY94 -> #DIV/0! | BC94: Sexta-feira | BD94: 44316 | BE94: 0 | BF94: 0 | BG94: =BE94/BF94 -> #DIV/0! | BH94: 0 | BI94: =BE94/BH94 -> #DIV/0! | BJ94: 0 | BK94: =BE94/BJ94 -> #DIV/0! | BL94: 0 | BM94: =BE94/BL94 -> #DIV/0! | BN94: =BJ94/BL94 -> #DIV/0!
O100: FACEBOOK ADS (OFERTA DIRETA) | AC100: FACEBOOK ADS (RMKT) | AQ100: GOOGLE ADS (OFERTA DIRETA) | BD100: GOOGLE ADS (RMKT)
B101: Maio | O101: DATA | P101: Investimento | Q101: Compras | R101: Custo por Vendas | S101: Inicialização de Finalização de Compras | T101: Custo por Inicialização de Finalização de Compras | U101: Visualização Única de Página de destino | V101: Custo porVisualização Única de Página | W101: Cliques no link único | X101: Custo por Cliques no link único | Y101: % Conversão Visualização Pg Vendas | Z101: % Conversão de Compra | AA101: Diário de Bordo | AC101: DATA | AD101: Investimento | AE101: Compras | AF101: Custo por Vendas | AG101: Inicialização de Finalização de Compras | AH101: Custo por Inicialização de Finalização de Compras | AI101: Visualização Única de Página de destino | AJ101: Custo porVisualização Única de Página | AK101: Cliques no link único | AL101: Custo por Cliques no link único | AM101: % Conversão Pg Vendas | AN101: Diário de Bordo | AQ101: DATA | AR101: Investimento | AS101: Compras | AT101: Custo por Vendas | AU101: Inicialização de Finalização de Compras | AV101: Custo por Inicialização de Finalização de Compras | AW101: Visualização Única de Página de destino | AX101: Custo porVisualização Única de Página | AY101: Cliques no link único | AZ101: Custo por Cliques no link único | BA101: % Conversão Pg Vendas | BB101: Diário de Bordo | BD101: DATA | BE101: Investimento | BF101: Compras | BG101: Custo por Vendas | BH101: Inicialização de Finalização de Compras | BI101: Custo por Inicialização de Finalização de Compras | BJ101: Visualização Única de Página de destino | BK101: Custo porVisualização Única de Página | BL101: Cliques no link único | BM101: Custo por Cliques no link único | BN101: % Conversão Pg Vendas | BO101: Diário de Bordo
P102: =SUM(P103:P133) -> 752.12 | Q102: =SUM(Q103:Q133) -> 39 | R102: =P102/Q102 -> 19.285128 | S102: =SUM(S103:S133) -> 169 | T102: =P102/S102 -> 4.4504142 | U102: =SUM(U103:U133) -> 0 | V102: =P102/U102 -> #DIV/0! | W102: =SUM(W103:W133) -> 391 | X102: =P102/W102 -> 1.9235806 | Y102: =U102/W102 -> 0 | Z102: =Q102/S102 -> 0.23076923 | AD102: =SUM(AD103:AD132) -> 0 | AE102: =SUM(AE103:AE132) -> 0 | AF102: =AD102/AE102 -> #DIV/0! | AG102: =SUM(AG103:AG132) -> 0 | AH102: =AD102/AG102 -> #DIV/0! | AI102: =SUM(AI103:AI132) -> 0 | AJ102: =AD102/AI102 -> #DIV/0! | AK102: =SUM(AK103:AK132) -> 0 | AL102: =AD102/AK102 -> #DIV/0! | AM102: =AI102/AK102 -> #DIV/0! | AR102: =SUM(AR103:AR132) -> 0 | AS102: =SUM(AS103:AS132) -> 0 | AT102: =AR102/AS102 -> #DIV/0! | AU102: =SUM(AU103:AU132) -> 0 | AV102: =AR102/AU102 -> #DIV/0! | AW102: =SUM(AW103:AW132) -> 0 | AX102: =AR102/AW102 -> #DIV/0! | AY102: =SUM(AY103:AY132) -> 0 | AZ102: =AR102/AY102 -> #DIV/0! | BA102: =AW102/AY102 -> #DIV/0! | BE102: =SUM(BE103:BE132) -> 0 | BF102: =SUM(BF103:BF132) -> 0 | BG102: =BE102/BF102 -> #DIV/0! | BH102: =SUM(BH103:BH132) -> 0 | BI102: =BE102/BH102 -> #DIV/0! | BJ102: =SUM(BJ103:BJ132) -> 0 | BK102: =BE102/BJ102 -> #DIV/0! | BL102: =SUM(BL103:BL132) -> 0 | BM102: =BE102/BL102 -> #DIV/0! | BN102: =BJ102/BL102 -> #DIV/0!
N103: Sábado | O103: 44317 | P103: 63.01 | Q103: 3 | R103: 21 | S103: 14 | T103: 4.5 | W103: 47 | X103: 1.34 | Z103: =Q103/S103 -> 0.21428571 | AB103: Sábado | AC103: 44317 | AD103: 0 | AE103: 0 | AF103: =AD103/AE103 -> #DIV/0! | AG103: 0 | AH103: =AD103/AG103 -> #DIV/0! | AI103: 0 | AJ103: =AD103/AI103 -> #DIV/0! | AK103: 0 | AL103: =AD103/AK103 -> #DIV/0! | AM103: =AI103/AK103 -> #DIV/0! | AP103: Sábado | AQ103: 44317 | AR103: 0 | AS103: 0 | AT103: =AR103/AS103 -> #DIV/0! | AU103: 0 | AV103: =AR103/AU103 -> #DIV/0! | AW103: 0 | AX103: =AR103/AW103 -> #DIV/0! | AY103: 0 | AZ103: =AR103/AY103 -> #DIV/0! | BA103: =AW103/AY103 -> #DIV/0! | BC103: Sábado | BD103: 44317 | BE103: 0 | BF103: 0 | BG103: =BE103/BF103 -> #DIV/0! | BH103: 0 | BI103: =BE103/BH103 -> #DIV/0! | BJ103: 0 | BK103: =BE103/BJ103 -> #DIV/0! | BL103: 0 | BM103: =BE103/BL103 -> #DIV/0! | BN103: =BJ103/BL103 -> #DIV/0!
B104: Planejamento e Metas Esperadas | H104: Números Reais | N104: Domingo | O104: 44318 | P104: 59.59 | Q104: 5 | R104: 11.92 | S104: 15 | T104: 3.97 | W104: 61 | X104: 0.98 | Z104: =Q104/S104 -> 0.33333333 | AB104: Domingo | AC104: 44318 | AD104: 0 | AE104: 0 | AF104: =AD104/AE104 -> #DIV/0! | AG104: 0 | AH104: =AD104/AG104 -> #DIV/0! | AI104: 0 | AJ104: =AD104/AI104 -> #DIV/0! | AK104: 0 | AL104: =AD104/AK104 -> #DIV/0! | AM104: =AI104/AK104 -> #DIV/0! | AP104: Domingo | AQ104: 44318 | AR104: 0 | AS104: 0 | AT104: =AR104/AS104 -> #DIV/0! | AU104: 0 | AV104: =AR104/AU104 -> #DIV/0! | AW104: 0 | AX104: =AR104/AW104 -> #DIV/0! | AY104: 0 | AZ104: =AR104/AY104 -> #DIV/0! | BA104: =AW104/AY104 -> #DIV/0! | BC104: Domingo | BD104: 44318 | BE104: 0 | BF104: 0 | BG104: =BE104/BF104 -> #DIV/0! | BH104: 0 | BI104: =BE104/BH104 -> #DIV/0! | BJ104: 0 | BK104: =BE104/BJ104 -> #DIV/0! | BL104: 0 | BM104: =BE104/BL104 -> #DIV/0! | BN104: =BJ104/BL104 -> #DIV/0!
N105: Segunda-feira | O105: 44319 | P105: 58.51 | Q105: 6 | R105: 9.75 | S105: 12 | T105: 4.88 | W105: 40 | X105: 1.46 | Z105: =Q105/S105 -> 0.5 | AB105: Segunda-feira | AC105: 44319 | AD105: 0 | AE105: 0 | AF105: =AD105/AE105 -> #DIV/0! | AG105: 0 | AH105: =AD105/AG105 -> #DIV/0! | AI105: 0 | AJ105: =AD105/AI105 -> #DIV/0! | AK105: 0 | AL105: =AD105/AK105 -> #DIV/0! | AM105: =AI105/AK105 -> #DIV/0! | AP105: Segunda-feira | AQ105: 44319 | AR105: 0 | AS105: 0 | AT105: =AR105/AS105 -> #DIV/0! | AU105: 0 | AV105: =AR105/AU105 -> #DIV/0! | AW105: 0 | AX105: =AR105/AW105 -> #DIV/0! | AY105: 0 | AZ105: =AR105/AY105 -> #DIV/0! | BA105: =AW105/AY105 -> #DIV/0! | BC105: Segunda-feira | BD105: 44319 | BE105: 0 | BF105: 0 | BG105: =BE105/BF105 -> #DIV/0! | BH105: 0 | BI105: =BE105/BH105 -> #DIV/0! | BJ105: 0 | BK105: =BE105/BJ105 -> #DIV/0! | BL105: 0 | BM105: =BE105/BL105 -> #DIV/0! | BN105: =BJ105/BL105 -> #DIV/0!
B106: Meta de Faturamento | E106: =#REF! -> #REF! | H106: Investimento Realizado | K106: =P102 -> 752.12 | N106: Terça-feira | O106: 44320 | P106: 59.34 | Q106: 5 | R106: 11.87 | S106: 19 | T106: 3.12 | W106: 36 | X106: 1.65 | Z106: =Q106/S106 -> 0.26315789 | AB106: Terça-feira | AC106: 44320 | AD106: 0 | AE106: 0 | AF106: =AD106/AE106 -> #DIV/0! | AG106: 0 | AH106: =AD106/AG106 -> #DIV/0! | AI106: 0 | AJ106: =AD106/AI106 -> #DIV/0! | AK106: 0 | AL106: =AD106/AK106 -> #DIV/0! | AM106: =AI106/AK106 -> #DIV/0! | AP106: Terça-feira | AQ106: 44320 | AR106: 0 | AS106: 0 | AT106: =AR106/AS106 -> #DIV/0! | AU106: 0 | AV106: =AR106/AU106 -> #DIV/0! | AW106: 0 | AX106: =AR106/AW106 -> #DIV/0! | AY106: 0 | AZ106: =AR106/AY106 -> #DIV/0! | BA106: =AW106/AY106 -> #DIV/0! | BC106: Terça-feira | BD106: 44320 | BE106: 0 | BF106: 0 | BG106: =BE106/BF106 -> #DIV/0! | BH106: 0 | BI106: =BE106/BH106 -> #DIV/0! | BJ106: 0 | BK106: =BE106/BJ106 -> #DIV/0! | BL106: 0 | BM106: =BE106/BL106 -> #DIV/0! | BN106: =BJ106/BL106 -> #DIV/0!
N107: Quarta-feira | O107: 44321 | P107: 60.16 | Q107: 3 | R107: 20.05 | S107: 13 | T107: 4.63 | W107: 18 | X107: 3.34 | Z107: =Q107/S107 -> 0.23076923 | AB107: Quarta-feira | AC107: 44321 | AD107: 0 | AE107: 0 | AF107: =AD107/AE107 -> #DIV/0! | AG107: 0 | AH107: =AD107/AG107 -> #DIV/0! | AI107: 0 | AJ107: =AD107/AI107 -> #DIV/0! | AK107: 0 | AL107: =AD107/AK107 -> #DIV/0! | AM107: =AI107/AK107 -> #DIV/0! | AP107: Quarta-feira | AQ107: 44321 | AR107: 0 | AS107: 0 | AT107: =AR107/AS107 -> #DIV/0! | AU107: 0 | AV107: =AR107/AU107 -> #DIV/0! | AW107: 0 | AX107: =AR107/AW107 -> #DIV/0! | AY107: 0 | AZ107: =AR107/AY107 -> #DIV/0! | BA107: =AW107/AY107 -> #DIV/0! | BC107: Quarta-feira | BD107: 44321 | BE107: 0 | BF107: 0 | BG107: =BE107/BF107 -> #DIV/0! | BH107: 0 | BI107: =BE107/BH107 -> #DIV/0! | BJ107: 0 | BK107: =BE107/BJ107 -> #DIV/0! | BL107: 0 | BM107: =BE107/BL107 -> #DIV/0! | BN107: =BJ107/BL107 -> #DIV/0!
B108: Ticket do Produto | E108: 97 | H108: Vendas Realizadas | K108: =Q102 -> 39 | N108: Quinta-feira | O108: 44322 | P108: 59.4 | Q108: 2 | R108: 29.7 | S108: 13 | T108: 4.57 | W108: 32 | X108: 1.86 | Z108: =Q108/S108 -> 0.15384615 | AB108: Quinta-feira | AC108: 44322 | AD108: 0 | AE108: 0 | AF108: =AD108/AE108 -> #DIV/0! | AG108: 0 | AH108: =AD108/AG108 -> #DIV/0! | AI108: 0 | AJ108: =AD108/AI108 -> #DIV/0! | AK108: 0 | AL108: =AD108/AK108 -> #DIV/0! | AM108: =AI108/AK108 -> #DIV/0! | AP108: Quinta-feira | AQ108: 44322 | AR108: 0 | AS108: 0 | AT108: =AR108/AS108 -> #DIV/0! | AU108: 0 | AV108: =AR108/AU108 -> #DIV/0! | AW108: 0 | AX108: =AR108/AW108 -> #DIV/0! | AY108: 0 | AZ108: =AR108/AY108 -> #DIV/0! | BA108: =AW108/AY108 -> #DIV/0! | BC108: Quinta-feira | BD108: 44322 | BE108: 0 | BF108: 0 | BG108: =BE108/BF108 -> #DIV/0! | BH108: 0 | BI108: =BE108/BH108 -> #DIV/0! | BJ108: 0 | BK108: =BE108/BJ108 -> #DIV/0! | BL108: 0 | BM108: =BE108/BL108 -> #DIV/0! | BN108: =BJ108/BL108 -> #DIV/0!
N109: Sexta-feira | O109: 44323 | P109: 61.07 | Q109: 4 | R109: 15.27 | S109: 19 | T109: 3.21 | W109: 24 | X109: 2.54 | Z109: =Q109/S109 -> 0.21052632 | AB109: Sexta-feira | AC109: 44323 | AD109: 0 | AE109: 0 | AF109: =AD109/AE109 -> #DIV/0! | AG109: 0 | AH109: =AD109/AG109 -> #DIV/0! | AI109: 0 | AJ109: =AD109/AI109 -> #DIV/0! | AK109: 0 | AL109: =AD109/AK109 -> #DIV/0! | AM109: =AI109/AK109 -> #DIV/0! | AP109: Sexta-feira | AQ109: 44323 | AR109: 0 | AS109: 0 | AT109: =AR109/AS109 -> #DIV/0! | AU109: 0 | AV109: =AR109/AU109 -> #DIV/0! | AW109: 0 | AX109: =AR109/AW109 -> #DIV/0! | AY109: 0 | AZ109: =AR109/AY109 -> #DIV/0! | BA109: =AW109/AY109 -> #DIV/0! | BC109: Sexta-feira | BD109: 44323 | BE109: 0 | BF109: 0 | BG109: =BE109/BF109 -> #DIV/0! | BH109: 0 | BI109: =BE109/BH109 -> #DIV/0! | BJ109: 0 | BK109: =BE109/BJ109 -> #DIV/0! | BL109: 0 | BM109: =BE109/BL109 -> #DIV/0! | BN109: =BJ109/BL109 -> #DIV/0!
B110: Taxas da Plataforma | E110: 10.6 | H110: CPA Real | K110: =SUM(K106/K108) -> 19.285128 | N110: Sábado | O110: 44324 | P110: 61.93 | Q110: 7 | R110: 8.85 | S110: 18 | T110: 3.44 | W110: 38 | X110: 1.63 | Z110: =Q110/S110 -> 0.38888889 | AB110: Sábado | AC110: 44324 | AD110: 0 | AE110: 0 | AF110: =AD110/AE110 -> #DIV/0! | AG110: 0 | AH110: =AD110/AG110 -> #DIV/0! | AI110: 0 | AJ110: =AD110/AI110 -> #DIV/0! | AK110: 0 | AL110: =AD110/AK110 -> #DIV/0! | AM110: =AI110/AK110 -> #DIV/0! | AP110: Sábado | AQ110: 44324 | AR110: 0 | AS110: 0 | AT110: =AR110/AS110 -> #DIV/0! | AU110: 0 | AV110: =AR110/AU110 -> #DIV/0! | AW110: 0 | AX110: =AR110/AW110 -> #DIV/0! | AY110: 0 | AZ110: =AR110/AY110 -> #DIV/0! | BA110: =AW110/AY110 -> #DIV/0! | BC110: Sábado | BD110: 44324 | BE110: 0 | BF110: 0 | BG110: =BE110/BF110 -> #DIV/0! | BH110: 0 | BI110: =BE110/BH110 -> #DIV/0! | BJ110: 0 | BK110: =BE110/BJ110 -> #DIV/0! | BL110: 0 | BM110: =BE110/BL110 -> #DIV/0! | BN110: =BJ110/BL110 -> #DIV/0!
N111: Domingo | O111: 44325 | P111: 58.49 | Q111: 3 | R111: 19.5 | S111: 9 | T111: 6.5 | W111: 25 | X111: 2.34 | Z111: =Q111/S111 -> 0.33333333 | AB111: Domingo | AC111: 44325 | AD111: 0 | AE111: 0 | AF111: =AD111/AE111 -> #DIV/0! | AG111: 0 | AH111: =AD111/AG111 -> #DIV/0! | AI111: 0 | AJ111: =AD111/AI111 -> #DIV/0! | AK111: 0 | AL111: =AD111/AK111 -> #DIV/0! | AM111: =AI111/AK111 -> #DIV/0! | AP111: Domingo | AQ111: 44325 | AR111: 0 | AS111: 0 | AT111: =AR111/AS111 -> #DIV/0! | AU111: 0 | AV111: =AR111/AU111 -> #DIV/0! | AW111: 0 | AX111: =AR111/AW111 -> #DIV/0! | AY111: 0 | AZ111: =AR111/AY111 -> #DIV/0! | BA111: =AW111/AY111 -> #DIV/0! | BC111: Domingo | BD111: 44325 | BE111: 0 | BF111: 0 | BG111: =BE111/BF111 -> #DIV/0! | BH111: 0 | BI111: =BE111/BH111 -> #DIV/0! | BJ111: 0 | BK111: =BE111/BJ111 -> #DIV/0! | BL111: 0 | BM111: =BE111/BL111 -> #DIV/0! | BN111: =BJ111/BL111 -> #DIV/0!
B112: Taxas de Coprodução | E112: 25.92 | H112: Faturamento Real | K112: =SUM(K108*E114) -> 2358.72 | N112: Segunda-feira | O112: 44326 | P112: 59.06 | S112: 8 | T112: 7.38 | W112: 22 | X112: 2.68 | Z112: =Q112/S112 -> 0 | AB112: Segunda-feira | AC112: 44326 | AD112: 0 | AE112: 0 | AF112: =AD112/AE112 -> #DIV/0! | AG112: 0 | AH112: =AD112/AG112 -> #DIV/0! | AI112: 0 | AJ112: =AD112/AI112 -> #DIV/0! | AK112: 0 | AL112: =AD112/AK112 -> #DIV/0! | AM112: =AI112/AK112 -> #DIV/0! | AP112: Segunda-feira | AQ112: 44326 | AR112: 0 | AS112: 0 | AT112: =AR112/AS112 -> #DIV/0! | AU112: 0 | AV112: =AR112/AU112 -> #DIV/0! | AW112: 0 | AX112: =AR112/AW112 -> #DIV/0! | AY112: 0 | AZ112: =AR112/AY112 -> #DIV/0! | BA112: =AW112/AY112 -> #DIV/0! | BC112: Segunda-feira | BD112: 44326 | BE112: 0 | BF112: 0 | BG112: =BE112/BF112 -> #DIV/0! | BH112: 0 | BI112: =BE112/BH112 -> #DIV/0! | BJ112: 0 | BK112: =BE112/BJ112 -> #DIV/0! | BL112: 0 | BM112: =BE112/BL112 -> #DIV/0! | BN112: =BJ112/BL112 -> #DIV/0!
N113: Terça-feira | O113: 44327 | P113: 60.99 | Q113: 1 | R113: 60.99 | S113: 12 | T113: 5.08 | W113: 22 | X113: 2.77 | Z113: =Q113/S113 -> 0.083333333 | AB113: Terça-feira | AC113: 44327 | AD113: 0 | AE113: 0 | AF113: =AD113/AE113 -> #DIV/0! | AG113: 0 | AH113: =AD113/AG113 -> #DIV/0! | AI113: 0 | AJ113: =AD113/AI113 -> #DIV/0! | AK113: 0 | AL113: =AD113/AK113 -> #DIV/0! | AM113: =AI113/AK113 -> #DIV/0! | AP113: Terça-feira | AQ113: 44327 | AR113: 0 | AS113: 0 | AT113: =AR113/AS113 -> #DIV/0! | AU113: 0 | AV113: =AR113/AU113 -> #DIV/0! | AW113: 0 | AX113: =AR113/AW113 -> #DIV/0! | AY113: 0 | AZ113: =AR113/AY113 -> #DIV/0! | BA113: =AW113/AY113 -> #DIV/0! | BC113: Terça-feira | BD113: 44327 | BE113: 0 | BF113: 0 | BG113: =BE113/BF113 -> #DIV/0! | BH113: 0 | BI113: =BE113/BH113 -> #DIV/0! | BJ113: 0 | BK113: =BE113/BJ113 -> #DIV/0! | BL113: 0 | BM113: =BE113/BL113 -> #DIV/0! | BN113: =BJ113/BL113 -> #DIV/0!
...

Sheet SupermetricsQueries
A1: Supermetrics Queries
A3: All the queries created by Supermetrics are stored here, each in its own row.
A5: On this sheet you can:
A6: 1. Modify the parameters of a query. Any changes will be visible when you run a refresh.
A8: 2. Remove a query by deleting its row | H8: America/Los_Angeles
A10: 3. Add new queries: type a range address and query parameters, leave the query ID empty. The query will be added when you run a refresh. (Of course, it's much easier to use the sidebar to add new queries.)
A13: Queries are stored with the authentication of the original user that created the query. If you want to transfer a query to the currently active Google Sheets user, delete its query ID from column A and run a refresh. For complete instructions on transferring queries, see https://support.supermetrics.com/support/solutions/articles/19000050074-how-can-i-transfer-queries-from-one-user-to-another-
A16: Don't delete or rename this sheet. If you delete or rename it, your existing queries can no longer be refreshed. Hiding the sheet is OK. Also, don't delete any rows above row 21.
A19: Query ID | D19: Sheet name | E19: Range address | G19: Created | H19: Updated | I19: Last status | J19: Last refresh ID | K19: Results contain sampled data | L19: Execution time (sec) | M19: Object type | N19: Linked chart ID | O19: Data source | Q19: Date range type | R19: Start date | S19: End date | T19: Compare to | U19: Comparison value type | W19: Accounts/views | X19: Metrics | Y19: Dimensions | Z19: Pivot dimensions | AA19: Filters | AB19: Segment ID | AC19: Sort | AD19: Max rows | AE19: Max pivot categories | AF19: Special settings | AG19: Other parameters | AJ19: Result type | AK19: Language/country | AL19: Translate to | AN19: SQL | AO19: Database name | AP19: Range address (static) | AQ19: Report type | AT19: Highlight with colour | AU19: Refresh with user account | AV19: Returned data
A20: paramsID | C20: ssID | D20: sheetName | E20: rangeAddress | G20: created | H20: updated | I20: lastStatus | J20: lastqueryID | K20: sampled | L20: runtime_sec | M20: objType | N20: linkedChartID | O20: dataSource | Q20: dateRangeType | R20: startDateString | S20: endDateString | T20: comp | U20: cvt | W20: profiles | X20: metrics | Y20: dimensions | Z20: sd | AA20: filterArr | AB20: segment | AC20: sort | AD20: maxResults | AE20: maxCategories | AF20: specialSettings | AG20: otherParams | AJ20: sds_result_type | AK20: sds_lang | AL20: sds_tolang | AN20: sql | AO20: db_name | AP20: rangeAddressStatic | AQ20: rt | AR20: scopeMZ | AS20: sortMZ | AT20: condform | AU20: authUser | AV20: metaDataToUser

Sheet Página20
A1: 2H | D1: 1H | G1: 1H
A2: 115.33 | B2: =A2*10% -> 11.533 | D2: 115.33 | E2: =D2*10% -> 11.533 | G2: 115.33 | H2: =G2*10% -> 11.533
A3: =A2+B2 -> 126.863 | B3: =A3*10% -> 12.6863 | D3: =D2+E2 -> 126.863 | E3: =D3*10% -> 12.6863 | G3: =G2+H2 -> 126.863 | H3: =G3*10% -> 12.6863
A4: =A3+B3 -> 139.5493 | B4: =A4*10% -> 13.95493 | D4: =D3+E3 -> 139.5493 | E4: =D4*10% -> 13.95493 | G4: =G3+H3 -> 139.5493 | H4: =G4*10% -> 13.95493
A5: =A4+B4 -> 153.50423 | B5: =A5*10% -> 15.350423 | D5: =D4+E4 -> 153.50423 | E5: =D5*10% -> 15.350423 | G5: =G4+H4 -> 153.50423 | H5: =G5*10% -> 15.350423
A6: =A5+B5 -> 168.85465 | B6: =A6*10% -> 16.885465 | D6: =D5+E5 -> 168.85465 | E6: =D6*10% -> 16.885465 | G6: =G5+H5 -> 168.85465 | H6: =G6*10% -> 16.885465
A7: =A6+B6 -> 185.74012 | B7: =A7*10% -> 18.574012 | D7: =D6+E6 -> 185.74012 | E7: =D7*10% -> 18.574012 | G7: =G6+H6 -> 185.74012 | H7: =G7*10% -> 18.574012
A8: =A7+B7 -> 204.31413 | B8: =A8*10% -> 20.431413 | D8: =D7+E7 -> 204.31413 | E8: =D8*10% -> 20.431413 | G8: =G7+H7 -> 204.31413 | H8: =G8*10% -> 20.431413
A9: =A8+B8 -> 224.74554 | B9: =A9*10% -> 22.474554 | D9: =D8+E8 -> 224.74554 | E9: =D9*10% -> 22.474554 | G9: =G8+H8 -> 224.74554 | H9: =G9*10% -> 22.474554
A10: =A9+B9 -> 247.2201 | B10: =A10*10% -> 24.72201 | D10: =D9+E9 -> 247.2201 | E10: =D10*10% -> 24.72201 | G10: =G9+H9 -> 247.2201 | H10: =G10*10% -> 24.72201
A11: =A10+B10 -> 271.94211 | B11: =A11*10% -> 27.194211 | D11: =D10+E10 -> 271.94211 | E11: =D11*10% -> 27.194211 | G11: =G10+H10 -> 271.94211 | H11: =G11*10% -> 27.194211
A12: =A11+B11 -> 299.13632 | B12: =A12*10% -> 29.913632 | D12: =D11+E11 -> 299.13632 | E12: =D12*10% -> 29.913632 | G12: =G11+H11 -> 299.13632 | H12: =G12*10% -> 29.913632
A13: =A12+B12 -> 329.04995 | B13: =A13*10% -> 32.904995 | D13: =D12+E12 -> 329.04995 | E13: =D13*10% -> 32.904995 | G13: =G12+H12 -> 329.04995 | H13: =G13*10% -> 32.904995
D14: =D13+E13 -> 361.95494 | E14: =D14*10% -> 36.195494 | G14: =G13+H13 -> 361.95494 | H14: =G14*10% -> 36.195494
D15: =D14+E14 -> 398.15044 | E15: =D15*10% -> 39.815044 | G15: =G14+H14 -> 398.15044 | H15: =G15*10% -> 39.815044
D16: =D15+E15 -> 437.96548 | E16: =D16*10% -> 43.796548 | G16: =G15+H15 -> 437.96548 | H16: =G16*10% -> 43.796548
D17: =D16+E16 -> 481.76203 | E17: =D17*10% -> 48.176203 | G17: =G16+H16 -> 481.76203 | H17: =G17*10% -> 48.176203
D18: =D17+E17 -> 529.93823 | E18: =D18*10% -> 52.993823 | G18: =G17+H17 -> 529.93823 | H18: =G18*10% -> 52.993823
D19: =D18+E18 -> 582.93206 | E19: =D19*10% -> 58.293206 | G19: =G18+H18 -> 582.93206 | H19: =G19*10% -> 58.293206
D20: =D19+E19 -> 641.22526 | E20: =D20*10% -> 64.122526 | G20: =G19+H19 -> 641.22526 | H20: =G20*10% -> 64.122526
D21: =D20+E20 -> 705.34779 | E21: =D21*10% -> 70.534779 | G21: =G20+H20 -> 705.34779 | H21: =G21*10% -> 70.534779
D22: =D21+E21 -> 775.88257 | E22: =D22*10% -> 77.588257 | G22: =G21+H21 -> 775.88257 | H22: =G22*10% -> 77.588257
D23: =D22+E22 -> 853.47083 | E23: =D23*10% -> 85.347083 | G23: =G22+H22 -> 853.47083 | H23: =G23*10% -> 85.347083
D24: =D23+E23 -> 938.81791 | E24: =D24*10% -> 93.881791 | G24: =G23+H23 -> 938.81791 | H24: =G24*10% -> 93.881791
G25: =G24+H24 -> 1032.6997 | H25: =G25*10% -> 103.26997
G26: =G25+H25 -> 1135.9697 | H26: =G26*10% -> 113.59697
G27: =G26+H26 -> 1249.5666 | H27: =G27*10% -> 124.95666
G28: =G27+H27 -> 1374.5233 | H28: =G28*10% -> 137.45233
G29: =G28+H28 -> 1511.9756 | H29: =G29*10% -> 151.19756
G30: =G29+H29 -> 1663.1732 | H30: =G30*10% -> 166.31732
G31: =G30+H30 -> 1829.4905 | H31: =G31*10% -> 182.94905
G32: =G31+H31 -> 2012.4396 | H32: =G32*10% -> 201.24396
G33: =G32+H32 -> 2213.6835 | H33: =G33*10% -> 221.36835
G34: =G33+H33 -> 2435.0519 | H34: =G34*10% -> 243.50519
G35: =G34+H34 -> 2678.5571 | H35: =G35*10% -> 267.85571
G36: =G35+H35 -> 2946.4128 | H36: =G36*10% -> 294.64128
... G48: =G47+H47 -> 9247.1054 | H48: =G48*10% -> 924.71054

Sheet TRACK
A1: GOOGLE
A2: {lpurl}?utm_source=adwords&utm_medium={_adcampaign}&utm_campaign=perpetuo-sa&utm_content={_adgroupname}&utm_term={_adname}
A5: adcampaign
A6: s_ekanta
A8: adgroupname
A9: GP01
A11: adname
A12: AD01
A16: FACEBOOK ADS
A17: PRODUTO | B17: LANÇAMENTO | C17: Parâmetros de URL - Facebook Ads | J17: UTM_CAMPAIGN
A18: Formação Aroma | B18: Classico | C18: utm_source=facebook&utm_medium={{campaign.name}}&utm_campaign=perpetuo-sa&utm_content={{adset.name}}&utm_term={{ad.name}} | J18: lancamento-fa
A19: Apostila Sexualidade Tantra | B19: Perpetuo | J19: perpetuo-st
A20: Apostila Cold Process | B20: Perpetuo | J20: perpetuo-cp
A21: Apostila Make Natural | B21: Perpetuo | J21: perpetuo-mn
A22: Apostila Fitoterapia | B22: Perpetuo | J22: perpetuo-fi
A23: Beleza Aroma | B23: Perpetuo | J23: perpetuo-ba
A24: Lavanda Experience | B24: Perpetuo | J24: perpetuo-le
A25: Empreende Aroma | B25: Perpetuo | J25: perpetuo-ea
A26: Saboaria Aroma | B26: Perpetuo | J26: perpetuo-sa
A27: Saúde Aroma | B27: Perpetuo | J27: perpetuo-su
A28: Relacionamento Consciente | B28: Perpetuo | J28: perpetuo-rc
A29: Saboaria Aroma | B29: Meteorico | J29: meteorico-sa
A30: Empreende Aroma | B30: Meteorico | J30: meteorico-ea
... A32: Relacionamento Consciente | B32: Meteorico | J32: meteorico-rc

Sheet x
B2: META ANUAL 2020 PROJETADA | D2: =B7+N7+Z7+AL7 -> #REF!
B6: Q1 | N6: Q2 | Z6: Q3 | AL6: Q4
B7: =B12+F12+J12 -> #REF! | N7: =N12+R12+V12 -> #REF! | Z7: =Z12+AD12+AH12 -> #REF! | AL7: =AL12+AP12+AT12 -> #REF!
B12: =sum(E18:E34) -> #REF! | F12: =sum(I18:I34) -> #REF! | J12: =sum(M18:M34) -> #REF! | N12: =SUM(Q18:Q34) -> #REF! | R12: =SUM(U18:U34) -> #REF! | V12: =SUM(Y18:Y34) -> #REF! | Z12: =sum(AC18:AC34) -> #REF! | AD12: =sum(AG18:AG34) -> #REF! | AH12: =sum(AK18:AK34) -> #REF! | AL12: =SUM(AO18:AO34) -> #REF! | AP12: =SUM(AS18:AS34) -> #REF! | AT12: =SUM(AW18:AW34) -> #REF!
B16: JANEIRO | F16: FEVEREIRO | J16: MARÇO | N16: ABRIL | R16: MAIO | V16: JUNHO | Z16: JULHO | AD16: AGOSTO | AH16: SETEMBRO | AL16: OUTUBRO | AP16: NOVEMBRO | AT16: DEZEMBRO
B17: PRODUTO | C17: VENDAS | D17: TICKET | E17: FATURAMENTO | F17: PRODUTO | G17: VENDAS | H17: TICKET | I17: FATURAMENTO | J17: PRODUTO | K17: VENDAS | L17: TICKET | M17: FATURAMENTO | N17: PRODUTO | O17: VENDAS | P17: TICKET | Q17: FATURAMENTO | R17: PRODUTO | S17: VENDAS | T17: TICKET | U17: FATURAMENTO | V17: PRODUTO | W17: VENDAS | X17: TICKET | Y17: FATURAMENTO | Z17: PRODUTO | AA17: VENDAS | AB17: TICKET | AC17: FATURAMENTO | AD17: PRODUTO | AE17: VENDAS | AF17: TICKET | AG17: FATURAMENTO | AH17: PRODUTO | AI17: VENDAS | AJ17: TICKET | AK17: FATURAMENTO | AL17: PRODUTO | AM17: VENDAS | AN17: TICKET | AO17: FATURAMENTO | AP17: PRODUTO | AQ17: VENDAS | AR17: TICKET | AS17: FATURAMENTO | AT17: PRODUTO | AU17: VENDAS | AV17: TICKET | AW17: FATURAMENTO
B18: Acesso Vitalício Saúde Aroma | C18: =#REF!/3 -> #REF! | D18: =#REF! -> #REF! | E18: =C18*D18 -> #REF! | F18: Acesso Vitalício Saúde Aroma | G18: =#REF!/3 -> #REF! | H18: =#REF! -> #REF! | I18: =G18*H18 -> #REF! | J18: Acesso Vitalício Saúde Aroma | K18: =#REF!/3 -> #REF! | L18: =#REF! -> #REF! | M18: =K18*L18 -> #REF! | N18: Acesso Vitalício Saúde Aroma | O18: =#REF!/3 -> #REF! | P18: =#REF! -> #REF! | Q18: =O18*P18 -> #REF! | R18: Acesso Vitalício Saúde Aroma | S18: =#REF!/3 -> #REF! | T18: =#REF! -> #REF! | U18: =S18*T18 -> #REF! | V18: Acesso Vitalício Saúde Aroma | W18: =#REF!/3 -> #REF! | X18: =#REF! -> #REF! | Y18: =W18*X18 -> #REF! | Z18: Acesso Vitalício Saúde Aroma | AA18: =#REF!/3 -> #REF! | AB18: =#REF! -> #REF! | AC18: =AA18*AB18 -> #REF! | AD18: Acesso Vitalício Saúde Aroma | AE18: =#REF!/3 -> #REF! | AF18: =#REF! -> #REF! | AG18: =AE18*AF18 -> #REF! | AH18: Acesso Vitalício Saúde Aroma | AI18: =#REF!/3 -> #REF! | AJ18: =#REF! -> #REF! | AK18: =AI18*AJ18 -> #REF! | AL18: Acesso Vitalício Saúde Aroma | AM18: =#REF!/3 -> #REF! | AN18: =#REF! -> #REF! | AO18: =AM18*AN18 -> #REF! | AP18: Acesso Vitalício Saúde Aroma | AQ18: =#REF!/3 -> #REF! | AR18: =#REF! -> #REF! | AS18: =AQ18*AR18 -> #REF! | AT18: Acesso Vitalício Saúde Aroma | AU18: =#REF!/3 -> #REF! | AV18: =#REF! -> #REF! | AW18: =AU18*AV18 -> #REF!
B19: Acesso Vitalício Empreende Aroma | C19: =#REF!/3 -> #REF! | D19: =#REF! -> #REF! | E19: =C19*D19 -> #REF! | F19: Acesso Vitalício Empreende Aroma | G19: =#REF!/3 -> #REF! | H19: =#REF! -> #REF! | I19: =G19*H19 -> #REF! | J19: Acesso Vitalício Empreende Aroma | K19: =#REF!/3 -> #REF! | L19: =#REF! -> #REF! | M19: =K19*L19 -> #REF! | N19: Acesso Vitalício Empreende Aroma | O19: =#REF!/3 -> #REF! | P19: =#REF! -> #REF! | Q19: =O19*P19 -> #REF! | R19: Acesso Vitalício Empreende Aroma | S19: =#REF!/3 -> #REF! | T19: =#REF! -> #REF! | U19: =S19*T19 -> #REF! | V19: Acesso Vitalício Empreende Aroma | W19: =#REF!/3 -> #REF! | X19: =#REF! -> #REF! | Y19: =W19*X19 -> #REF! | Z19: Acesso Vitalício Empreende Aroma | AA19: =#REF!/3 -> #REF! | AB19: =#REF! -> #REF! | AC19: =AA19*AB19 -> #REF! | AD19: Acesso Vitalício Empreende Aroma | AE19: =#REF!/3 -> #REF! | AF19: =#REF! -> #REF! | AG19: =AE19*AF19 -> #REF! | AH19: Acesso Vitalício Empreende Aroma | AI19: =#REF!/3 -> #REF! | AJ19: =#REF! -> #REF! | AK19: =AI19*AJ19 -> #REF! | AL19: Acesso Vitalício Empreende Aroma | AM19: =#REF!/3 -> #REF! | AN19: =#REF! -> #REF! | AO19: =AM19*AN19 -> #REF! | AP19: Acesso Vitalício Empreende Aroma | AQ19: =#REF!/3 -> #REF! | AR19: =#REF! -> #REF! | AS19: =AQ19*AR19 -> #REF! | AT19: Acesso Vitalício Empreende Aroma | AU19: =#REF!/3 -> #REF! | AV19: =#REF! -> #REF! | AW19: =AU19*AV19 -> #REF!
B20: Acesso Vitalício Saboaria Aroma | C20: =#REF!/3 -> #REF! | D20: =#REF! -> #REF! | E20: =C20*D20 -> #REF! | F20: Acesso Vitalício Saboaria Aroma | G20: =#REF!/3 -> #REF! | H20: =#REF! -> #REF! | I20: =G20*H20 -> #REF! | J20: Acesso Vitalício Saboaria Aroma | K20: =#REF!/3 -> #REF! | L20: =#REF! -> #REF! | M20: =K20*L20 -> #REF! | N20: Acesso Vitalício Saboaria Aroma | O20: =#REF!/3 -> #REF! | P20: =#REF! -> #REF! | Q20: =O20*P20 -> #REF! | R20: Acesso Vitalício Saboaria Aroma | S20: =#REF!/3 -> #REF! | T20: =#REF! -> #REF! | U20: =S20*T20 -> #REF! | V20: Acesso Vitalício Saboaria Aroma | W20: =#REF!/3 -> #REF! | X20: =#REF! -> #REF! | Y20: =W20*X20 -> #REF! | Z20: Acesso Vitalício Saboaria Aroma | AA20: =#REF!/3 -> #REF! | AB20: =#REF! -> #REF! | AC20: =AA20*AB20 -> #REF! | AD20: Acesso Vitalício Saboaria Aroma | AE20: =#REF!/3 -> #REF! | AF20: =#REF! -> #REF! | AG20: =AE20*AF20 -> #REF! | AH20: Acesso Vitalício Saboaria Aroma | AI20: =#REF!/3 -> #REF! | AJ20: =#REF! -> #REF! | AK20: =AI20*AJ20 -> #REF! | AL20: Acesso Vitalício Saboaria Aroma | AM20: =#REF!/3 -> #REF! | AN20: =#REF! -> #REF! | AO20: =AM20*AN20 -> #REF! | AP20: Acesso Vitalício Saboaria Aroma | AQ20: =#REF!/3 -> #REF! | AR20: =#REF! -> #REF! | AS20: =AQ20*AR20 -> #REF! | AT20: Acesso Vitalício Saboaria Aroma | AU20: =#REF!/3 -> #REF! | AV20: =#REF! -> #REF! | AW20: =AU20*AV20 -> #REF!
B21: Apostila Digital Cold Process | C21: =#REF!/3 -> #REF! | D21: ='WEBINAR SEMANAL'!L8 -> 200 | E21: =C21*D21 -> #REF! | F21: Apostila Digital Cold Process | G21: =#REF!/3 -> #REF! | H21: ='WEBINAR SEMANAL'!L8 -> 200 | I21: =G21*H21 -> #REF! | J21: Apostila Digital Cold Process | K21: =#REF!/3 -> #REF! | L21: ='WEBINAR SEMANAL'!L8 -> 200 | M21: =K21*L21 -> #REF! | N21: Apostila Digital Cold Process | O21: =#REF!/3 -> #REF! | P21: ='WEBINAR SEMANAL'!L8 -> 200 | Q21: =O21*P21 -> #REF! | R21: Apostila Digital Cold Process | S21: =#REF!/3 -> #REF! | T21: ='WEBINAR SEMANAL'!L8 -> 200 | U21: =S21*T21 -> #REF! | V21: Apostila Digital Cold Process | W21: =#REF!/3 -> #REF! | X21: ='WEBINAR SEMANAL'!L8 -> 200 | Y21: =W21*X21 -> #REF! | Z21: Apostila Digital Cold Process | AA21: =#REF!/3 -> #REF! | AB21: ='WEBINAR SEMANAL'!L8 -> 200 | AC21: =AA21*AB21 -> #REF! | AD21: Apostila Digital Cold Process | AE21: =#REF!/3 -> #REF! | AF21: ='WEBINAR SEMANAL'!L8 -> 200 | AG21: =AE21*AF21 -> #REF! | AH21: Apostila Digital Cold Process | AI21: =#REF!/3 -> #REF! | AJ21: ='WEBINAR SEMANAL'!L8 -> 200 | AK21: =AI21*AJ21 -> #REF! | AL21: Apostila Digital Cold Process | AM21: =#REF!/3 -> #REF! | AN21: ='WEBINAR SEMANAL'!L8 -> 200 | AO21: =AM21*AN21 -> #REF! | AP21: Apostila Digital Cold Process | AQ21: =#REF!/3 -> #REF! | AR21: ='WEBINAR SEMANAL'!L8 -> 200 | AS21: =AQ21*AR21 -> #REF! | AT21: Apostila Digital Cold Process | AU21: =#REF!/3 -> #REF! | AV21: ='WEBINAR SEMANAL'!L8 -> 200 | AW21: =AU21*AV21 -> #REF!
B22: Fitoterapia Integrativa | C22: =#REF!/3 -> #REF! | D22: ='WEBINAR SEMANAL'!L11 -> 200 | E22: =C22*D22 -> #REF! | F22: Fitoterapia Integrativa | G22: =#REF!/3 -> #REF! | H22: ='WEBINAR SEMANAL'!L11 -> 200 | I22: =G22*H22 -> #REF! | J22: Fitoterapia Integrativa | K22: =#REF!/3 -> #REF! | L22: ='WEBINAR SEMANAL'!L11 -> 200 | M22: =K22*L22 -> #REF! | N22: Fitoterapia Integrativa | O22: =#REF!/3 -> #REF! | P22: ='WEBINAR SEMANAL'!L11 -> 200 | Q22: =O22*P22 -> #REF! | R22: Fitoterapia Integrativa | S22: =#REF!/3 -> #REF! | T22: ='WEBINAR SEMANAL'!L11 -> 200 | U22: =S22*T22 -> #REF! | V22: Fitoterapia Integrativa | W22: =#REF!/3 -> #REF! | X22: ='WEBINAR SEMANAL'!L11 -> 200 | Y22: =W22*X22 -> #REF! | Z22: Fitoterapia Integrativa | AA22: =#REF!/3 -> #REF! | AB22: ='WEBINAR SEMANAL'!L11 -> 200 | AC22: =AA22*AB22 -> #REF! | AD22: Fitoterapia Integrativa | AE22: =#REF!/3 -> #REF! | AF22: ='WEBINAR SEMANAL'!L11 -> 200 | AG22: =AE22*AF22 -> #REF! | AH22: Fitoterapia Integrativa | AI22: =#REF!/3 -> #REF! | AJ22: ='WEBINAR SEMANAL'!L11 -> 200 | AK22: =AI22*AJ22 -> #REF! | AL22: Fitoterapia Integrativa | AM22: =#REF!/3 -> #REF! | AN22: ='WEBINAR SEMANAL'!L11 -> 200 | AO22: =AM22*AN22 -> #REF! | AP22: Fitoterapia Integrativa | AQ22: =#REF!/3 -> #REF! | AR22: ='WEBINAR SEMANAL'!L11 -> 200 | AS22: =AQ22*AR22 -> #REF! | AT22: Fitoterapia Integrativa | AU22: =#REF!/3 -> #REF! | AV22: ='WEBINAR SEMANAL'!L11 -> 200 | AW22: =AU22*AV22 -> #REF!
B23: Empreende Aroma | C23: =#REF!/3 -> #REF! | D23: =#REF! -> #REF! | E23: =C23*D23 -> #REF! | F23: Empreende Aroma | G23: =#REF!/3 -> #REF! | H23: =#REF! -> #REF! | I23: =G23*H23 -> #REF! | J23: Empreende Aroma | K23: =#REF!/3 -> #REF! | L23: =#REF! -> #REF! | M23: =K23*L23 -> #REF! | N23: Empreende Aroma | O23: =#REF!/3 -> #REF! | P23: =#REF! -> #REF! | Q23: =O23*P23 -> #REF! | R23: Empreende Aroma | S23: =#REF!/3 -> #REF! | T23: =#REF! -> #REF! | U23: =S23*T23 -> #REF! | V23: Empreende Aroma | W23: =#REF!/3 -> #REF! | X23: =#REF! -> #REF! | Y23: =W23*X23 -> #REF! | Z23: Empreende Aroma | AA23: =#REF!/3 -> #REF! | AB23: =#REF! -> #REF! | AC23: =AA23*AB23 -> #REF! | AD23: Empreende Aroma | AE23: =#REF!/3 -> #REF! | AF23: =#REF! -> #REF! | AG23: =AE23*AF23 -> #REF! | AH23: Empreende Aroma | AI23: =#REF!/3 -> #REF! | AJ23: =#REF! -> #REF! | AK23: =AI23*AJ23 -> #REF! | AL23: Empreende Aroma | AM23: =#REF!/3 -> #REF! | AN23: =#REF! -> #REF! | AO23: =AM23*AN23 -> #REF! | AP23: Empreende Aroma | AQ23: =#REF!/3 -> #REF! | AR23: =#REF! -> #REF! | AS23: =AQ23*AR23 -> #REF! | AT23: Empreende Aroma | AU23: =#REF!/3 -> #REF! | AV23: =#REF! -> #REF! | AW23: =AU23*AV23 -> #REF!
B24: Formação Aroma | C24: =#REF!/3 -> #REF! | D24: =#REF! -> #REF! | E24: =C24*D24 -> #REF! | F24: Formação Aroma | G24: =#REF!/3 -> #REF! | H24: =#REF! -> #REF! | I24: =G24*H24 -> #REF! | J24: Formação Aroma | K24: =#REF!/3 -> #REF! | L24: =#REF! -> #REF! | M24: =K24*L24 -> #REF! | N24: Formação Aroma | O24: =#REF!/3 -> #REF! | P24: =#REF! -> #REF! | Q24: =O24*P24 -> #REF! | R24: Formação Aroma | S24: =#REF!/3 -> #REF! | T24: =#REF! -> #REF! | U24: =S24*T24 -> #REF! | V24: Formação Aroma | W24: =#REF!/3 -> #REF! | X24: =#REF! -> #REF! | Y24: =W24*X24 -> #REF! | Z24: Formação Aroma | AA24: =#REF!/3 -> #REF! | AB24: =#REF! -> #REF! | AC24: =AA24*AB24 -> #REF! | AD24: Formação Aroma | AE24: =#REF!/3 -> #REF! | AF24: =#REF! -> #REF! | AG24: =AE24*AF24 -> #REF! | AH24: Formação Aroma | AI24: =#REF!/3 -> #REF! | AJ24: =#REF! -> #REF! | AK24: =AI24*AJ24 -> #REF! | AL24: Formação Aroma | AM24: =#REF!/3 -> #REF! | AN24: =#REF! -> #REF! | AO24: =AM24*AN24 -> #REF! | AP24: Formação Aroma | AQ24: =#REF!/3 -> #REF! | AR24: =#REF! -> #REF! | AS24: =AQ24*AR24 -> #REF! | AT24: Formação Aroma | AU24: =#REF!/3 -> #REF! | AV24: =#REF! -> #REF! | AW24: =AU24*AV24 -> #REF!
B25: Lavanda Experience | C25: =#REF!/3 -> #REF! | D25: =#REF! -> #REF! | E25: =C25*D25 -> #REF! | F25: Lavanda Experience | G25: =#REF!/3 -> #REF! | H25: =#REF! -> #REF! | I25: =G25*H25 -> #REF! | J25: Lavanda Experience | K25: =#REF!/3 -> #REF! | L25: =#REF! -> #REF! | M25: =K25*L25 -> #REF! | N25: Lavanda Experience | O25: =#REF!/3 -> #REF! | P25: =#REF! -> #REF! | Q25: =O25*P25 -> #REF! | R25: Lavanda Experience | S25: =#REF!/3 -> #REF! | T25: =#REF! -> #REF! | U25: =S25*T25 -> #REF! | V25: Lavanda Experience | W25: =#REF!/3 -> #REF! | X25: =#REF! -> #REF! | Y25: =W25*X25 -> #REF! | Z25: Lavanda Experience | AA25: =#REF!/3 -> #REF! | AB25: =#REF! -> #REF! | AC25: =AA25*AB25 -> #REF! | AD25: Lavanda Experience | AE25: =#REF!/3 -> #REF! | AF25: =#REF! -> #REF! | AG25: =AE25*AF25 -> #REF! | AH25: Lavanda Experience | AI25: =#REF!/3 -> #REF! | AJ25: =#REF! -> #REF! | AK25: =AI25*AJ25 -> #REF! | AL25: Lavanda Experience | AM25: =#REF!/3 -> #REF! | AN25: =#REF! -> #REF! | AO25: =AM25*AN25 -> #REF! | AP25: Lavanda Experience | AQ25: =#REF!/3 -> #REF! | AR25: =#REF! -> #REF! | AS25: =AQ25*AR25 -> #REF! | AT25: Lavanda Experience | AU25: =#REF!/3 -> #REF! | AV25: =#REF! -> #REF! | AW25: =AU25*AV25 -> #REF!
B26: Make Natural | C26: =#REF!/3 -> #REF! | D26: ='WEBINAR SEMANAL'!L10 -> 200 | E26: =C26*D26 -> #REF! | F26: Make Natural | G26: =#REF!/3 -> #REF! | H26: ='WEBINAR SEMANAL'!L10 -> 200 | I26: =G26*H26 -> #REF! | J26: Make Natural | K26: =#REF!/3 -> #REF! | L26: ='WEBINAR SEMANAL'!L10 -> 200 | M26: =K26*L26 -> #REF! | N26: Make Natural | O26: =#REF!/3 -> #REF! | P26: ='WEBINAR SEMANAL'!L10 -> 200 | Q26: =O26*P26 -> #REF! | R26: Make Natural | S26: =#REF!/3 -> #REF! | T26: ='WEBINAR SEMANAL'!L10 -> 200 | U26: =S26*T26 -> #REF! | V26: Make Natural | W26: =#REF!/3 -> #REF! | X26: ='WEBINAR SEMANAL'!L10 -> 200 | Y26: =W26*X26 -> #REF! | Z26: Make Natural | AA26: =#REF!/3 -> #REF! | AB26: ='WEBINAR SEMANAL'!L10 -> 200 | AC26: =AA26*AB26 -> #REF! | AD26: Make Natural | AE26: =#REF!/3 -> #REF! | AF26: ='WEBINAR SEMANAL'!L10 -> 200 | AG26: =AE26*AF26 -> #REF! | AH26: Make Natural | AI26: =#REF!/3 -> #REF! | AJ26: ='WEBINAR SEMANAL'!L10 -> 200 | AK26: =AI26*AJ26 -> #REF! | AL26: Make Natural | AM26: =#REF!/3 -> #REF! | AN26: ='WEBINAR SEMANAL'!L10 -> 200 | AO26: =AM26*AN26 -> #REF! | AP26: Make Natural | AQ26: =#REF!/3 -> #REF! | AR26: ='WEBINAR SEMANAL'!L10 -> 200 | AS26: =AQ26*AR26 -> #REF! | AT26: Make Natural | AU26: =#REF!/3 -> #REF! | AV26: ='WEBINAR SEMANAL'!L10 -> 200 | AW26: =AU26*AV26 -> #REF!
B27: Mini-Curso Beleza Aroma | C27: =#REF!/3 -> #REF! | D27: =#REF! -> #REF! | E27: =C27*D27 -> #REF! | F27: Mini-Curso Beleza Aroma | G27: =#REF!/3 -> #REF! | H27: =#REF! -> #REF! | I27: =G27*H27 -> #REF! | J27: Mini-Curso Beleza Aroma | K27: =#REF!/3 -> #REF! | L27: =#REF! -> #REF! | M27: =K27*L27 -> #REF! | N27: Mini-Curso Beleza Aroma | O27: =#REF!/3 -> #REF! | P27: =#REF! -> #REF! | Q27: =O27*P27 -> #REF! | R27: Mini-Curso Beleza Aroma | S27: =#REF!/3 -> #REF! | T27: =#REF! -> #REF! | U27: =S27*T27 -> #REF! | V27: Mini-Curso Beleza Aroma | W27: =#REF!/3 -> #REF! | X27: =#REF! -> #REF! | Y27: =W27*X27 -> #REF! | Z27: Mini-Curso Beleza Aroma | AA27: =#REF!/3 -> #REF! | AB27: =#REF! -> #REF! | AC27: =AA27*AB27 -> #REF! | AD27: Mini-Curso Beleza Aroma | AE27: =#REF!/3 -> #REF! | AF27: =#REF! -> #REF! | AG27: =AE27*AF27 -> #REF! | AH27: Mini-Curso Beleza Aroma | AI27: =#REF!/3 -> #REF! | AJ27: =#REF! -> #REF! | AK27: =AI27*AJ27 -> #REF! | AL27: Mini-Curso Beleza Aroma | AM27: =#REF!/3 -> #REF! | AN27: =#REF! -> #REF! | AO27: =AM27*AN27 -> #REF! | AP27: Mini-Curso Beleza Aroma | AQ27: =#REF!/3 -> #REF! | AR27: =#REF! -> #REF! | AS27: =AQ27*AR27 -> #REF! | AT27: Mini-Curso Beleza Aroma | AU27: =#REF!/3 -> #REF! | AV27: =#REF! -> #REF! | AW27: =AU27*AV27 -> #REF!
B28: Saboaria Aroma | C28: =#REF!/3 -> #REF! | D28: ='WEBINAR SEMANAL'!L3 -> 200 | E28: =C28*D28 -> #REF! | F28: Saboaria Aroma | G28: =#REF!/3 -> #REF! | H28: ='WEBINAR SEMANAL'!L3 -> 200 | I28: =G28*H28 -> #REF! | J28: Saboaria Aroma | K28: =#REF!/3 -> #REF! | L28: ='WEBINAR SEMANAL'!L3 -> 200 | M28: =K28*L28 -> #REF! | N28: Saboaria Aroma | O28: =#REF!/3 -> #REF! | P28: ='WEBINAR SEMANAL'!L3 -> 200 | Q28: =O28*P28 -> #REF! | R28: Saboaria Aroma | S28: =#REF!/3 -> #REF! | T28: ='WEBINAR SEMANAL'!L3 -> 200 | U28: =S28*T28 -> #REF! | V28: Saboaria Aroma | W28: =#REF!/3 -> #REF! | X28: ='WEBINAR SEMANAL'!L3 -> 200 | Y28: =W28*X28 -> #REF! | Z28: Saboaria Aroma | AA28: =#REF!/3 -> #REF! | AB28: ='WEBINAR SEMANAL'!L3 -> 200 | AC28: =AA28*AB28 -> #REF! | AD28: Saboaria Aroma | AE28: =#REF!/3 -> #REF! | AF28: ='WEBINAR SEMANAL'!L3 -> 200 | AG28: =AE28*AF28 -> #REF! | AH28: Saboaria Aroma | AI28: =#REF!/3 -> #REF! | AJ28: ='WEBINAR SEMANAL'!L3 -> 200 | AK28: =AI28*AJ28 -> #REF! | AL28: Saboaria Aroma | AM28: =#REF!/3 -> #REF! | AN28: ='WEBINAR SEMANAL'!L3 -> 200 | AO28: =AM28*AN28 -> #REF! | AP28: Saboaria Aroma | AQ28: =#REF!/3 -> #REF! | AR28: ='WEBINAR SEMANAL'!L3 -> 200 | AS28: =AQ28*AR28 -> #REF! | AT28: Saboaria Aroma | AU28: =#REF!/3 -> #REF! | AV28: ='WEBINAR SEMANAL'!L3 -> 200 | AW28: =AU28*AV28 -> #REF!
B29: Saúde Aroma | C29: =#REF!/3 -> #REF! | D29: ='WEBINAR SEMANAL'!L5 -> 200 | E29: =C29*D29 -> #REF! | F29: Saúde Aroma | G29: =#REF!/3 -> #REF! | H29: ='WEBINAR SEMANAL'!L5 -> 200 | I29: =G29*H29 -> #REF! | J29: Saúde Aroma | K29: =#REF!/3 -> #REF! | L29: ='WEBINAR SEMANAL'!L5 -> 200 | M29: =K29*L29 -> #REF! | N29: Saúde Aroma | O29: =#REF!/3 -> #REF! | P29: ='WEBINAR SEMANAL'!L5 -> 200 | Q29: =O29*P29 -> #REF! | R29: Saúde Aroma | S29: =#REF!/3 -> #REF! | T29: ='WEBINAR SEMANAL'!L5 -> 200 | U29: =S29*T29 -> #REF! | V29: Saúde Aroma | W29: =#REF!/3 -> #REF! | X29: ='WEBINAR SEMANAL'!L5 -> 200 | Y29: =W29*X29 -> #REF! | Z29: Saúde Aroma | AA29: =#REF!/3 -> #REF! | AB29: ='WEBINAR SEMANAL'!L5 -> 200 | AC29: =AA29*AB29 -> #REF! | AD29: Saúde Aroma | AE29: =#REF!/3 -> #REF! | AF29: ='WEBINAR SEMANAL'!L5 -> 200 | AG29: =AE29*AF29 -> #REF! | AH29: Saúde Aroma | AI29: =#REF!/3 -> #REF! | AJ29: ='WEBINAR SEMANAL'!L5 -> 200 | AK29: =AI29*AJ29 -> #REF! | AL29: Saúde Aroma | AM29: =#REF!/3 -> #REF! | AN29: ='WEBINAR SEMANAL'!L5 -> 200 | AO29: =AM29*AN29 -> #REF! | AP29: Saúde Aroma | AQ29: =#REF!/3 -> #REF! | AR29: ='WEBINAR SEMANAL'!L5 -> 200 | AS29: =AQ29*AR29 -> #REF! | AT29: Saúde Aroma | AU29: =#REF!/3 -> #REF! | AV29: ='WEBINAR SEMANAL'!L5 -> 200 | AW29: =AU29*AV29 -> #REF!
B30: Formação Fitoterapia NOVO | C30: =#REF!/3 -> #REF! | D30: ='WEBINAR SEMANAL'!L2 -> CP AG | E30: =C30*D30 -> #REF! | F30: Formação Fitoterapia NOVO | G30: =#REF!/3 -> #REF! | H30: ='WEBINAR SEMANAL'!L2 -> CP AG | I30: =G30*H30 -> #REF! | J30: Formação Fitoterapia NOVO | K30: =#REF!/3 -> #REF! | L30: ='WEBINAR SEMANAL'!L2 -> CP AG | M30: =K30*L30 -> #REF! | N30: Formação Fitoterapia NOVO | O30: =#REF!/3 -> #REF! | P30: ='WEBINAR SEMANAL'!L2 -> CP AG | Q30: =O30*P30 -> #REF! | R30: Formação Fitoterapia NOVO | S30: =#REF!/3 -> #REF! | T30: ='WEBINAR SEMANAL'!L2 -> CP AG | U30: =S30*T30 -> #REF! | V30: Formação Fitoterapia NOVO | W30: =#REF!/3 -> #REF! | X30: ='WEBINAR SEMANAL'!L2 -> CP AG | Y30: =W30*X30 -> #REF! | Z30: Formação Fitoterapia NOVO | AA30: =#REF!/3 -> #REF! | AB30: ='WEBINAR SEMANAL'!L2 -> CP AG | AC30: =AA30*AB30 -> #REF! | AD30: Formação Fitoterapia NOVO | AE30: =#REF!/3 -> #REF! | AF30: ='WEBINAR SEMANAL'!L2 -> CP AG | AG30: =AE30*AF30 -> #REF! | AH30: Formação Fitoterapia NOVO | AI30: =#REF!/3 -> #REF! | AJ30: ='WEBINAR SEMANAL'!L2 -> CP AG | AK30: =AI30*AJ30 -> #REF! | AL30: Formação Fitoterapia NOVO | AM30: =#REF!/3 -> #REF! | AN30: ='WEBINAR SEMANAL'!L2 -> CP AG | AO30: =AM30*AN30 -> #REF! | AP30: Formação Fitoterapia NOVO | AQ30: =#REF!/3 -> #REF! | AR30: ='WEBINAR SEMANAL'!L2 -> CP AG | AS30: =AQ30*AR30 -> #REF! | AT30: Formação Fitoterapia NOVO | AU30: =#REF!/3 -> #REF! | AV30: ='WEBINAR SEMANAL'!L2 -> CP AG | AW30: =AU30*AV30 -> #REF!
B31: Apostila Aromaterapia e Sexualidade NOVO | C31: =#REF!/3 -> #REF! | D31: ='WEBINAR SEMANAL'!L9 -> 200 | E31: =C31*D31 -> #REF! | F31: Apostila Aromaterapia e Sexualidade NOVO | G31: =#REF!/3 -> #REF! | H31: ='WEBINAR SEMANAL'!L9 -> 200 | I31: =G31*H31 -> #REF! | J31: Apostila Aromaterapia e Sexualidade NOVO | K31: =#REF!/3 -> #REF! | L31: ='WEBINAR SEMANAL'!L9 -> 200 | M31: =K31*L31 -> #REF! | N31: Apostila Aromaterapia e Sexualidade NOVO | O31: =#REF!/3 -> #REF! | P31: ='WEBINAR SEMANAL'!L9 -> 200 | Q31: =O31*P31 -> #REF! | R31: Apostila Aromaterapia e Sexualidade NOVO | S31: =#REF!/3 -> #REF! | T31: ='WEBINAR SEMANAL'!L9 -> 200 | U31: =S31*T31 -> #REF! | V31: Apostila Aromaterapia e Sexualidade NOVO | W31: =#REF!/3 -> #REF! | X31: ='WEBINAR SEMANAL'!L9 -> 200 | Y31: =W31*X31 -> #REF! | Z31: Apostila Aromaterapia e Sexualidade NOVO | AA31: =#REF!/3 -> #REF! | AB31: ='WEBINAR SEMANAL'!L9 -> 200 | AC31: =AA31*AB31 -> #REF! | AD31: Apostila Aromaterapia e Sexualidade NOVO | AE31: =#REF!/3 -> #REF! | AF31: ='WEBINAR SEMANAL'!L9 -> 200 | AG31: =AE31*AF31 -> #REF! | AH31: Apostila Aromaterapia e Sexualidade NOVO | AI31: =#REF!/3 -> #REF! | AJ31: ='WEBINAR SEMANAL'!L9 -> 200 | AK31: =AI31*AJ31 -> #REF! | AL31: Apostila Aromaterapia e Sexualidade NOVO | AM31: =#REF!/3 -> #REF! | AN31: ='WEBINAR SEMANAL'!L9 -> 200 | AO31: =AM31*AN31 -> #REF! | AP31: Apostila Aromaterapia e Sexualidade NOVO | AQ31: =#REF!/3 -> #REF! | AR31: ='WEBINAR SEMANAL'!L9 -> 200 | AS31: =AQ31*AR31 -> #REF! | AT31: Apostila Aromaterapia e Sexualidade NOVO | AU31: =#REF!/3 -> #REF! | AV31: ='WEBINAR SEMANAL'!L9 -> 200 | AW31: =AU31*AV31 -> #REF!
B32: Academia da Saúde Integrativa (recorrência) NOVO | C32: =#REF!/3 -> #REF! | D32: =#REF! -> #REF! | E32: =C32*D32 -> #REF! | F32: Academia da Saúde Integrativa (recorrência) NOVO | G32: =#REF!/3 -> #REF! | H32: =#REF! -> #REF! | I32: =G32*H32 -> #REF! | J32: Academia da Saúde Integrativa (recorrência) NOVO | K32: =#REF!/3 -> #REF! | L32: =#REF! -> #REF! | M32: =K32*L32 -> #REF! | N32: Academia da Saúde Integrativa (recorrência) NOVO | O32: =#REF!/3 -> #REF! | P32: =#REF! -> #REF! | Q32: =O32*P32 -> #REF! | R32: Academia da Saúde Integrativa (recorrência) NOVO | S32: =#REF!/3 -> #REF! | T32: =#REF! -> #REF! | U32: =S32*T32 -> #REF! | V32: Academia da Saúde Integrativa (recorrência) NOVO | W32: =#REF!/3 -> #REF! | X32: =#REF! -> #REF! | Y32: =W32*X32 -> #REF! | Z32: Academia da Saúde Integrativa (recorrência) NOVO | AA32: =#REF!/3 -> #REF! | AB32: =#REF! -> #REF! | AC32: =AA32*AB32 -> #REF! | AD32: Academia da Saúde Integrativa (recorrência) NOVO | AE32: =#REF!/3 -> #REF! | AF32: =#REF! -> #REF! | AG32: =AE32*AF32 -> #REF! | AH32: Academia da Saúde Integrativa (recorrência) NOVO | AI32: =#REF!/3 -> #REF! | AJ32: =#REF! -> #REF! | AK32: =AI32*AJ32 -> #REF! | AL32: Academia da Saúde Integrativa (recorrência) NOVO | AM32: =#REF!/3 -> #REF! | AN32: =#REF! -> #REF! | AO32: =AM32*AN32 -> #REF! | AP32: Academia da Saúde Integrativa (recorrência) NOVO | AQ32: =#REF!/3 -> #REF! | AR32: =#REF! -> #REF! | AS32: =AQ32*AR32 -> #REF! | AT32: Academia da Saúde Integrativa (recorrência) NOVO | AU32: =#REF!/3 -> #REF! | AV32: =#REF! -> #REF! | AW32: =AU32*AV32 -> #REF!
B33: Formação Tantra NOVO | C33: =#REF!/3 -> #REF! | D33: =#REF! -> #REF! | E33: =C33*D33 -> #REF! | F33: Formação Tantra NOVO | G33: =#REF!/3 -> #REF! | H33: =#REF! -> #REF! | I33: =G33*H33 -> #REF! | J33: Formação Tantra NOVO | K33: =#REF!/3 -> #REF! | L33: =#REF! -> #REF! | M33: =K33*L33 -> #REF! | N33: Formação Tantra NOVO | O33: =#REF!/3 -> #REF! | P33: =#REF! -> #REF! | Q33: =O33*P33 -> #REF! | R33: Formação Tantra NOVO | S33: =#REF!/3 -> #REF! | T33: =#REF! -> #REF! | U33: =S33*T33 -> #REF! | V33: Formação Tantra NOVO | W33: =#REF!/3 -> #REF! | X33: =#REF! -> #REF! | Y33: =W33*X33 -> #REF! | Z33: Formação Tantra NOVO | AA33: =#REF!/3 -> #REF! | AB33: =#REF! -> #REF! | AC33: =AA33*AB33 -> #REF! | AD33: Formação Tantra NOVO | AE33: =#REF!/3 -> #REF! | AF33: =#REF! -> #REF! | AG33: =AE33*AF33 -> #REF! | AH33: Formação Tantra NOVO | AI33: =#REF!/3 -> #REF! | AJ33: =#REF! -> #REF! | AK33: =AI33*AJ33 -> #REF! | AL33: Formação Tantra NOVO | AM33: =#REF!/3 -> #REF! | AN33: =#REF! -> #REF! | AO33: =AM33*AN33 -> #REF! | AP33: Formação Tantra NOVO | AQ33: =#REF!/3 -> #REF! | AR33: =#REF! -> #REF! | AS33: =AQ33*AR33 -> #REF! | AT33: Formação Tantra NOVO | AU33: =#REF!/3 -> #REF! | AV33: =#REF! -> #REF! | AW33: =AU33*AV33 -> #REF!
B34: Certificação Fitoretapia NOVO | C34: =#REF!/3 -> #REF! | D34: =#REF! -> #REF! | E34: =C34*D34 -> #REF! | F34: Certificação Fitoretapia NOVO | G34: =#REF!/3 -> #REF! | H34: =#REF! -> #REF! | I34: =G34*H34 -> #REF! | J34: Certificação Fitoretapia NOVO | K34: =#REF!/3 -> #REF! | L34: =#REF! -> #REF! | M34: =K34*L34 -> #REF! | N34: Certificação Fitoretapia NOVO | O34: =#REF!/3 -> #REF! | P34: =#REF! -> #REF! | Q34: =O34*P34 -> #REF! | R34: Certificação Fitoretapia NOVO | S34: =#REF!/3 -> #REF! | T34: =#REF! -> #REF! | U34: =S34*T34 -> #REF! | V34: Certificação Fitoretapia NOVO | W34: =#REF!/3 -> #REF! | X34: =#REF! -> #REF! | Y34: =W34*X34 -> #REF! | Z34: Certificação Fitoretapia NOVO | AA34: =#REF!/3 -> #REF! | AB34: =#REF! -> #REF! | AC34: =AA34*AB34 -> #REF! | AD34: Certificação Fitoretapia NOVO | AE34: =#REF!/3 -> #REF! | AF34: =#REF! -> #REF! | AG34: =AE34*AF34 -> #REF! | AH34: Certificação Fitoretapia NOVO | AI34: =#REF!/3 -> #REF! | AJ34: =#REF! -> #REF! | AK34: =AI34*AJ34 -> #REF! | AL34: Certificação Fitoretapia NOVO | AM34: =#REF!/3 -> #REF! | AN34: =#REF! -> #REF! | AO34: =AM34*AN34 -> #REF! | AP34: Certificação Fitoretapia NOVO | AQ34: =#REF!/3 -> #REF! | AR34: =#REF! -> #REF! | AS34: =AQ34*AR34 -> #REF! | AT34: Certificação Fitoretapia NOVO | AU34: =#REF!/3 -> #REF! | AV34: =#REF! -> #REF! | AW34: =AU34*AV34 -> #REF!
B35: META ALCANÇADA 2020 | D35: =B40+N40+Z40+AL40 -> #REF!
B39: Q1 | N39: Q2 | Z39: Q3 | AL39: Q4
B40: =B45+F45+J45 -> #REF! | N40: =N45+R45+V45 -> #REF! | Z40: =Z45+AD45+AH45 -> #REF! | AL40: =AL45+AP45+AT45 -> #REF!
B45: =sum(E51:E71) -> #REF! | F45: =sum(I51:I71) -> #REF! | J45: =sum(M51:M71) -> #REF! | N45: =SUM(Q51:Q64) -> #REF! | R45: =SUM(U51:U72) -> #REF! | V45: =SUM(Y51:Y75) -> 278704 | Z45: =sum(AC51:AC63) -> #REF! | AD45: =sum(AG51:AG63) -> #REF! | AH45: =sum(AK51:AK63) -> #REF! | AL45: =SUM(AO51:AO63) -> #REF! | AP45: =SUM(AS51:AS63) -> #REF! | AT45: =SUM(AW51:AW63) -> #REF!
B49: JANEIRO | F49: FEVEREIRO | J49: MARÇO | N49: ABRIL | R49: MAIO | V49: JUNHO | Z49: JULHO | AD49: AGOSTO | AH49: SETEMBRO | AL49: OUTUBRO | AP49: NOVEMBRO | AT49: DEZEMBRO
B50: PRODUTO | C50: VENDAS | D50: TICKET | E50: FATURAMENTO | F50: PRODUTO | G50: VENDAS | H50: TICKET | I50: FATURAMENTO | J50: PRODUTO | K50: VENDAS | L50: TICKET | M50: FATURAMENTO | N50: PRODUTO | O50: VENDAS | P50: TICKET | Q50: FATURAMENTO | R50: PRODUTO | S50: VENDAS | T50: TICKET | U50: FATURAMENTO | V50: PRODUTO | W50: VENDAS | X50: TICKET | Y50: FATURAMENTO | Z50: PRODUTO | AA50: VENDAS | AB50: TICKET | AC50: FATURAMENTO | AD50: PRODUTO | AE50: VENDAS | AF50: TICKET | AG50: FATURAMENTO | AH50: PRODUTO | AI50: VENDAS | AJ50: TICKET | AK50: FATURAMENTO | AL50: PRODUTO | AM50: VENDAS | AN50: TICKET | AO50: FATURAMENTO | AP50: PRODUTO | AQ50: VENDAS | AR50: TICKET | AS50: FATURAMENTO | AT50: PRODUTO | AU50: VENDAS | AV50: TICKET | AW50: FATURAMENTO
B51: Acesso Vitalício Saúde Aroma | C51: 5 | D51: =#REF! -> #REF! | E51: =C51*D51 -> #REF! | F51: Acesso Vitalício Saúde Aroma | G51: 5 | H51: =#REF! -> #REF! | I51: =G51*H51 -> #REF! | J51: Acesso Vitalício Saúde Aroma | K51: 6 | L51: =#REF! -> #REF! | M51: =K51*L51 -> #REF! | N51: Acesso Vitalício Saúde Aroma | O51: 106 | P51: =#REF! -> #REF! | Q51: =O51*P51 -> #REF! | R51: Acesso Vitalício Saúde Aroma | S51: 88 | T51: =#REF! -> #REF! | U51: =S51*T51 -> #REF! | V51: Acesso Vitalício Saúde Aroma | W51: 88 | X51: 47 | Y51: =W51*X51 -> 4136 | Z51: Acesso Vitalício Saúde Aroma | AA51: 0 | AB51: =#REF! -> #REF! | AC51: =AA51*AB51 -> #REF! | AD51: Acesso Vitalício Saúde Aroma | AE51: 0 | AF51: =#REF! -> #REF! | AG51: =AE51*AF51 -> #REF! | AH51: Acesso Vitalício Saúde Aroma | AI51: 0 | AJ51: =#REF! -> #REF! | AK51: =AI51*AJ51 -> #REF! | AL51: Acesso Vitalício Saúde Aroma | AM51: 0 | AN51: =#REF! -> #REF! | AO51: =AM51*AN51 -> #REF! | AP51: Acesso Vitalício Saúde Aroma | AQ51: 0 | AR51: =#REF! -> #REF! | AS51: =AQ51*AR51 -> #REF! | AT51: Acesso Vitalício Saúde Aroma | AU51: 0 | AV51: =#REF! -> #REF! | AW51: =AU51*AV51 -> #REF!
B52: Acesso Vitalício Empreende Aroma | C52: 60 | D52: =#REF! -> #REF! | E52: =C52*D52 -> #REF! | F52: Acesso Vitalício Empreende Aroma | G52: 39 | H52: =#REF! -> #REF! | I52: =G52*H52 -> #REF! | J52: Acesso Vitalício Empreende Aroma | K52: 51 | L52: =#REF! -> #REF! | M52: =K52*L52 -> #REF! | N52: Acesso Vitalício Empreende Aroma | O52: 45 | P52: =#REF! -> #REF! | Q52: =O52*P52 -> #REF! | R52: Acesso Vitalício Empreende Aroma | S52: 62 | T52: =#REF! -> #REF! | U52: =S52*T52 -> #REF! | V52: Acesso Vitalício Empreende Aroma | W52: 9 | X52: 47 | Y52: =W52*X52 -> 423 | Z52: Acesso Vitalício Empreende Aroma | AA52: 0 | AB52: =#REF! -> #REF! | AC52: =AA52*AB52 -> #REF! | AD52: Acesso Vitalício Empreende Aroma | AE52: 0 | AF52: =#REF! -> #REF! | AG52: =AE52*AF52 -> #REF! | AH52: Acesso Vitalício Empreende Aroma | AI52: 0 | AJ52: =#REF! -> #REF! | AK52: =AI52*AJ52 -> #REF! | AL52: Acesso Vitalício Empreende Aroma | AM52: 0 | AN52: =#REF! -> #REF! | AO52: =AM52*AN52 -> #REF! | AP52: Acesso Vitalício Empreende Aroma | AQ52: 0 | AR52: =#REF! -> #REF! | AS52: =AQ52*AR52 -> #REF! | AT52: Acesso Vitalício Empreende Aroma | AU52: 0 | AV52: =#REF! -> #REF! | AW52: =AU52*AV52 -> #REF!
B53: Acesso Vitalício Saboaria Aroma | C53: 33 | D53: =#REF! -> #REF! | E53: =C53*D53 -> #REF! | F53: Acesso Vitalício Saboaria Aroma | G53: 218 | H53: =#REF! -> #REF! | I53: =G53*H53 -> #REF! | J53: Acesso Vitalício Saboaria Aroma | K53: 13 | L53: =#REF! -> #REF! | M53: =K53*L53 -> #REF! | N53: Acesso Vitalício Saboaria Aroma | O53: 41 | P53: =#REF! -> #REF! | Q53: =O53*P53 -> #REF! | R53: Acesso Vitalício Saboaria Aroma | S53: 44 | T53: =#REF! -> #REF! | U53: =S53*T53 -> #REF! | V53: Acesso Vitalício Saboaria Aroma | W53: 74 | X53: 47 | Y53: =W53*X53 -> 3478 | Z53: Acesso Vitalício Saboaria Aroma | AA53: 0 | AB53: =#REF! -> #REF! | AC53: =AA53*AB53 -> #REF! | AD53: Acesso Vitalício Saboaria Aroma | AE53: 0 | AF53: =#REF! -> #REF! | AG53: =AE53*AF53 -> #REF! | AH53: Acesso Vitalício Saboaria Aroma | AI53: 0 | AJ53: =#REF! -> #REF! | AK53: =AI53*AJ53 -> #REF! | AL53: Acesso Vitalício Saboaria Aroma | AM53: 0 | AN53: =#REF! -> #REF! | AO53: =AM53*AN53 -> #REF! | AP53: Acesso Vitalício Saboaria Aroma | AQ53: 0 | AR53: =#REF! -> #REF! | AS53: =AQ53*AR53 -> #REF! | AT53: Acesso Vitalício Saboaria Aroma | AU53: 0 | AV53: =#REF! -> #REF! | AW53: =AU53*AV53 -> #REF!
B54: Apostila Digital Cold Process | C54: 229 | D54: ='WEBINAR SEMANAL'!L8 -> 200 | E54: =C54*D54 -> 45800 | F54: Apostila Digital Cold Process | G54: 250 | H54: ='WEBINAR SEMANAL'!L8 -> 200 | I54: =G54*H54 -> 50000 | J54: Apostila Digital Cold Process | K54: 257 | L54: ='WEBINAR SEMANAL'!L8 -> 200 | M54: =K54*L54 -> 51400 | N54: Apostila Digital Cold Process | O54: 399 | P54: ='WEBINAR SEMANAL'!L8 -> 200 | Q54: =O54*P54 -> 79800 | R54: Apostila Digital Cold Process | S54: 377 | T54: ='WEBINAR SEMANAL'!L8 -> 200 | U54: =S54*T54 -> 75400 | V54: Apostila Digital Cold Process | W54: 283 | X54: 37 | Y54: =W54*X54 -> 10471 | Z54: Apostila Digital Cold Process | AA54: 0 | AB54: ='WEBINAR SEMANAL'!L8 -> 200 | AC54: =AA54*AB54 -> 0 | AD54: Apostila Digital Cold Process | AE54: 0 | AF54: ='WEBINAR SEMANAL'!L8 -> 200 | AG54: =AE54*AF54 -> 0 | AH54: Apostila Digital Cold Process | AI54: 0 | AJ54: ='WEBINAR SEMANAL'!L8 -> 200 | AK54: =AI54*AJ54 -> 0 | AL54: Apostila Digital Cold Process | AM54: 0 | AN54: ='WEBINAR SEMANAL'!L8 -> 200 | AO54: =AM54*AN54 -> 0 | AP54: Apostila Digital Cold Process | AQ54: 0 | AR54: ='WEBINAR SEMANAL'!L8 -> 200 | AS54: =AQ54*AR54 -> 0 | AT54: Apostila Digital Cold Process | AU54: 0 | AV54: ='WEBINAR SEMANAL'!L8 -> 200 | AW54: =AU54*AV54 -> 0
B55: Fitoterapia Integrativa | C55: 0 | D55: ='WEBINAR SEMANAL'!L11 -> 200 | E55: =C55*D55 -> 0 | F55: Fitoterapia Integrativa | G55: 0 | H55: ='WEBINAR SEMANAL'!L11 -> 200 | I55: =G55*H55 -> 0 | J55: Fitoterapia Integrativa | K55: 0 | L55: ='WEBINAR SEMANAL'!L11 -> 200 | M55: =K55*L55 -> 0 | N55: Fitoterapia Integrativa | O55: 285 | P55: ='WEBINAR SEMANAL'!L11 -> 200 | Q55: =O55*P55 -> 57000 | R55: Fitoterapia Integrativa | S55: 410 | T55: ='WEBINAR SEMANAL'!L11 -> 200 | U55: =S55*T55 -> 82000 | V55: Fitoterapia Integrativa | W55: 312 | X55: ='WEBINAR SEMANAL'!L11 -> 200 | Y55: =W55*X55 -> 62400 | Z55: Fitoterapia Integrativa | AA55: 0 | AB55: ='WEBINAR SEMANAL'!L11 -> 200 | AC55: =AA55*AB55 -> 0 | AD55: Fitoterapia Integrativa | AE55: 0 | AF55: ='WEBINAR SEMANAL'!L11 -> 200 | AG55: =AE55*AF55 -> 0 | AH55: Fitoterapia Integrativa | AI55: 0 | AJ55: ='WEBINAR SEMANAL'!L11 -> 200 | AK55: =AI55*AJ55 -> 0 | AL55: Fitoterapia Integrativa | AM55: 0 | AN55: ='WEBINAR SEMANAL'!L11 -> 200 | AO55: =AM55*AN55 -> 0 | AP55: Fitoterapia Integrativa | AQ55: 0 | AR55: ='WEBINAR SEMANAL'!L11 -> 200 | AS55: =AQ55*AR55 -> 0 | AT55: Fitoterapia Integrativa | AU55: 0 | AV55: ='WEBINAR SEMANAL'!L11 -> 200 | AW55: =AU55*AV55 -> 0
B56: Empreende Aroma | C56: 126 | D56: =#REF! -> #REF! | E56: =C56*D56 -> #REF! | F56: Empreende Aroma | G56: 93 | H56: =#REF! -> #REF! | I56: =G56*H56 -> #REF! | J56: Empreende Aroma | K56: 115 | L56: =#REF! -> #REF! | M56: =K56*L56 -> #REF! | N56: Empreende Aroma | O56: 103 | P56: =#REF! -> #REF! | Q56: =O56*P56 -> #REF! | R56: Empreende Aroma | S56: 115 | T56: =#REF! -> #REF! | U56: =S56*T56 -> #REF! | V56: Empreende Aroma | W56: 120 | X56: 397 | Y56: =W56*X56 -> 47640 | Z56: Empreende Aroma | AA56: 0 | AB56: =#REF! -> #REF! | AC56: =AA56*AB56 -> #REF! | AD56: Empreende Aroma | AE56: 0 | AF56: =#REF! -> #REF! | AG56: =AE56*AF56 -> #REF! | AH56: Empreende Aroma | AI56: 0 | AJ56: =#REF! -> #REF! | AK56: =AI56*AJ56 -> #REF! | AL56: Empreende Aroma | AM56: 0 | AN56: =#REF! -> #REF! | AO56: =AM56*AN56 -> #REF! | AP56: Empreende Aroma | AQ56: 0 | AR56: =#REF! -> #REF! | AS56: =AQ56*AR56 -> #REF! | AT56: Empreende Aroma | AU56: 0 | AV56: =#REF! -> #REF! | AW56: =AU56*AV56 -> #REF!
R57: Empreende Aroma DESC | S57: 249 | T57: 197 | U57: =S57*T57 -> 49053 | V57: Empreende Aroma DESC | W57: 0 | X57: 197 | Y57: =W57*X57 -> 0 | Z57: Empreende Aroma DESC | AA57: 0 | AB57: 197 | AC57: =AA57*AB57 -> 0
R58: Empreende Aroma DESC | S58: 15 | T58: 297 | U58: =S58*T58 -> 4455 | V58: Empreende Aroma DESC | W58: 78 | X58: 297 | Y58: =W58*X58 -> 23166 | Z58: Empreende Aroma DESC | AA58: 0 | AB58: 297 | AC58: =AA58*AB58 -> 0
B59: Formação Aroma | C59: 3 | D59: =#REF! -> #REF! | E59: =C59*D59 -> #REF! | F59: Formação Aroma | G59: 2 | H59: =#REF! -> #REF! | I59: =G59*H59 -> #REF! | J59: Formação Aroma | K59: 0 | L59: =#REF! -> #REF! | M59: =K59*L59 -> #REF! | N59: Formação Aroma | O59: 228 | P59: =#REF! -> #REF! | Q59: =O59*P59 -> #REF! | R59: Formação Aroma | S59: 0 | T59: =#REF! -> #REF! | U59: =S59*T59 -> #REF! | V59: Formação Aroma | W59: 1 | X59: 997 | Y59: =W59*X59 -> 997 | Z59: Formação Aroma | AA59: 0 | AB59: =#REF! -> #REF! | AC59: =AA59*AB59 -> #REF! | AD59: Formação Aroma | AE59: 0 | AF59: =#REF! -> #REF! | AG59: =AE59*AF59 -> #REF! | AH59: Formação Aroma | AI59: 0 | AJ59: =#REF! -> #REF! | AK59: =AI59*AJ59 -> #REF! | AL59: Formação Aroma | AM59: 0 | AN59: =#REF! -> #REF! | AO59: =AM59*AN59 -> #REF! | AP59: Formação Aroma | AQ59: 0 | AR59: =#REF! -> #REF! | AS59: =AQ59*AR59 -> #REF! | AT59: Formação Aroma | AU59: 0 | AV59: =#REF! -> #REF! | AW59: =AU59*AV59 -> #REF!
B60: Lavanda Experience | C60: 3 | D60: =#REF! -> #REF! | E60: =C60*D60 -> #REF! | F60: Lavanda Experience | G60: 0 | H60: =#REF! -> #REF! | I60: =G60*H60 -> #REF! | J60: Lavanda Experience | K60: 4 | L60: =#REF! -> #REF! | M60: =K60*L60 -> #REF! | N60: Lavanda Experience | O60: 1 | P60: =#REF! -> #REF! | Q60: =O60*P60 -> #REF! | R60: Lavanda Experience | S60: 0 | T60: =#REF! -> #REF! | U60: =S60*T60 -> #REF! | V60: Lavanda Experience | W60: 4 | X60: 197 | Y60: =W60*X60 -> 788 | Z60: Lavanda Experience | AA60: 0 | AB60: =#REF! -> #REF! | AC60: =AA60*AB60 -> #REF! | AD60: Lavanda Experience | AE60: 0 | AF60: =#REF! -> #REF! | AG60: =AE60*AF60 -> #REF! | AH60: Lavanda Experience | AI60: 0 | AJ60: =#REF! -> #REF! | AK60: =AI60*AJ60 -> #REF! | AL60: Lavanda Experience | AM60: 0 | AN60: =#REF! -> #REF! | AO60: =AM60*AN60 -> #REF! | AP60: Lavanda Experience | AQ60: 0 | AR60: =#REF! -> #REF! | AS60: =AQ60*AR60 -> #REF! | AT60: Lavanda Experience | AU60: 0 | AV60: =#REF! -> #REF! | AW60: =AU60*AV60 -> #REF!
B61: Make Natural | C61: 88 | D61: ='WEBINAR SEMANAL'!L10 -> 200 | E61: =C61*D61 -> 17600 | F61: Make Natural | G61: 73 | H61: ='WEBINAR SEMANAL'!L10 -> 200 | I61: =G61*H61 -> 14600 | J61: Make Natural | K61: 87 | L61: ='WEBINAR SEMANAL'!L10 -> 200 | M61: =K61*L61 -> 17400 | N61: Make Natural | O61: 142 | P61: ='WEBINAR SEMANAL'!L10 -> 200 | Q61: =O61*P61 -> 28400 | R61: Make Natural | S61: 151 | T61: ='WEBINAR SEMANAL'!L10 -> 200 | U61: =S61*T61 -> 30200 | V61: Make Natural | W61: 161 | X61: 97 | Y61: =W61*X61 -> 15617 | Z61: Make Natural | AA61: 0 | AB61: ='WEBINAR SEMANAL'!L10 -> 200 | AC61: =AA61*AB61 -> 0 | AD61: Make Natural | AE61: 0 | AF61: ='WEBINAR SEMANAL'!L10 -> 200 | AG61: =AE61*AF61 -> 0 | AH61: Make Natural | AI61: 0 | AJ61: ='WEBINAR SEMANAL'!L10 -> 200 | AK61: =AI61*AJ61 -> 0 | AL61: Make Natural | AM61: 0 | AN61: ='WEBINAR SEMANAL'!L10 -> 200 | AO61: =AM61*AN61 -> 0 | AP61: Make Natural | AQ61: 0 | AR61: ='WEBINAR SEMANAL'!L10 -> 200 | AS61: =AQ61*AR61 -> 0 | AT61: Make Natural | AU61: 0 | AV61: ='WEBINAR SEMANAL'!L10 -> 200 | AW61: =AU61*AV61 -> 0
B62: Mini-Curso Beleza Aroma | C62: 14 | D62: =#REF! -> #REF! | E62: =C62*D62 -> #REF! | F62: Mini-Curso Beleza Aroma | G62: 8 | H62: =#REF! -> #REF! | I62: =G62*H62 -> #REF! | J62: Mini-Curso Beleza Aroma | K62: 7 | L62: =#REF! -> #REF! | M62: =K62*L62 -> #REF! | N62: Mini-Curso Beleza Aroma | O62: 18 | P62: =#REF! -> #REF! | Q62: =O62*P62 -> #REF! | R62: Mini-Curso Beleza Aroma | S62: 21 | T62: =#REF! -> #REF! | U62: =S62*T62 -> #REF! | V62: Mini-Curso Beleza Aroma | W62: 18 | X62: 97 | Y62: =W62*X62 -> 1746 | Z62: Mini-Curso Beleza Aroma | AA62: 0 | AB62: =#REF! -> #REF! | AC62: =AA62*AB62 -> #REF! | AD62: Mini-Curso Beleza Aroma | AE62: 0 | AF62: =#REF! -> #REF! | AG62: =AE62*AF62 -> #REF! | AH62: Mini-Curso Beleza Aroma | AI62: 0 | AJ62: =#REF! -> #REF! | AK62: =AI62*AJ62 -> #REF! | AL62: Mini-Curso Beleza Aroma | AM62: 0 | AN62: =#REF! -> #REF! | AO62: =AM62*AN62 -> #REF! | AP62: Mini-Curso Beleza Aroma | AQ62: 0 | AR62: =#REF! -> #REF! | AS62: =AQ62*AR62 -> #REF! | AT62: Mini-Curso Beleza Aroma | AU62: 0 | AV62: =#REF! -> #REF! | AW62: =AU62*AV62 -> #REF!
B63: Saboaria Aroma | C63: 95 | D63: ='WEBINAR SEMANAL'!L3 -> 200 | E63: =C63*D63 -> 19000 | F63: Saboaria Aroma | G63: 218 | H63: ='WEBINAR SEMANAL'!L3 -> 200 | I63: =G63*H63 -> 43600 | J63: Saboaria Aroma | K63: 46 | L63: ='WEBINAR SEMANAL'!L3 -> 200 | M63: =K63*L63 -> 9200 | N63: Saboaria Aroma | O63: 69 | P63: ='WEBINAR SEMANAL'!L3 -> 200 | Q63: =O63*P63 -> 13800 | R63: Saboaria Aroma | S63: 101 | T63: ='WEBINAR SEMANAL'!L3 -> 200 | U63: =S63*T63 -> 20200 | V63: Saboaria Aroma | W63: 77 | X63: 397 | Y63: =W63*X63 -> 30569 | Z63: Saboaria Aroma | AA63: 0 | AB63: ='WEBINAR SEMANAL'!L3 -> 200 | AC63: =AA63*AB63 -> 0 | AD63: Saboaria Aroma | AE63: 0 | AF63: ='WEBINAR SEMANAL'!L3 -> 200 | AG63: =AE63*AF63 -> 0 | AH63: Saboaria Aroma | AI63: 0 | AJ63: ='WEBINAR SEMANAL'!L3 -> 200 | AK63: =AI63*AJ63 -> 0 | AL63: Saboaria Aroma | AM63: 0 | AN63: ='WEBINAR SEMANAL'!L3 -> 200 | AO63: =AM63*AN63 -> 0 | AP63: Saboaria Aroma | AQ63: 0 | AR63: ='WEBINAR SEMANAL'!L3 -> 200 | AS63: =AQ63*AR63 -> 0 | AT63: Saboaria Aroma | AU63: 0 | AV63: ='WEBINAR SEMANAL'!L3 -> 200 | AW63: =AU63*AV63 -> 0
B64: Saúde Aroma | C64: 5 | D64: ='WEBINAR SEMANAL'!L5 -> 200 | E64: =C64*D64 -> 1000 | F64: Saúde Aroma | G64: 9 | H64: ='WEBINAR SEMANAL'!L5 -> 200 | I64: =G64*H64 -> 1800 | J64: Saúde Aroma | K64: 13 | L64: ='WEBINAR SEMANAL'!L5 -> 200 | M64: =K64*L64 -> 2600 | N64: Saúde Aroma | O64: 10 | P64: ='WEBINAR SEMANAL'!L5 -> 200 | Q64: =O64*P64 -> 2000 | R64: Saúde Aroma | S64: 21 | T64: ='WEBINAR SEMANAL'!L5 -> 200 | U64: =S64*T64 -> 4200 | V64: Saboaria Aroma DESC | W64: 6 | X64: 297 | Y64: =W64*X64 -> 1782 | Z64: Saúde Aroma | AA64: 0 | AB64: ='WEBINAR SEMANAL'!L5 -> 200 | AC64: =AA64*AB64 -> 0 | AD64: Saúde Aroma | AE64: 0 | AF64: ='WEBINAR SEMANAL'!L5 -> 200 | AG64: =AE64*AF64 -> 0 | AH64: Saúde Aroma | AI64: 0 | AJ64: ='WEBINAR SEMANAL'!L5 -> 200 | AK64: =AI64*AJ64 -> 0 | AL64: Saúde Aroma | AM64: 0 | AN64: ='WEBINAR SEMANAL'!L5 -> 200 | AO64: =AM64*AN64 -> 0 | AP64: Saúde Aroma | AQ64: 0 | AR64: ='WEBINAR SEMANAL'!L5 -> 200 | AS64: =AQ64*AR64 -> 0 | AT64: Saúde Aroma | AU64: 0 | AV64: ='WEBINAR SEMANAL'!L5 -> 200 | AW64: =AU64*AV64 -> 0
R65: Saúde Aroma DESC | S65: 40 | T65: 297 | U65: =S65*T65 -> 11880 | V65: Saboaria Aroma DESC | W65: 105 | X65: 197 | Y65: =W65*X65 -> 20685
B66: Formação Fitoterapia NOVO | C66: 0 | D66: ='WEBINAR SEMANAL'!L2 -> CP AG | E66: =C66*D66 -> #VALUE! | F66: Formação Fitoterapia NOVO | G66: 0 | H66: ='WEBINAR SEMANAL'!L2 -> CP AG | I66: =G66*H66 -> #VALUE! | J66: Formação Fitoterapia NOVO | K66: 0 | L66: ='WEBINAR SEMANAL'!L2 -> CP AG | M66: =K66*L66 -> #VALUE! | N66: Formação Fitoterapia NOVO | O66: 0 | P66: ='WEBINAR SEMANAL'!L2 -> CP AG | Q66: =O66*P66 -> #VALUE! | R66: Saúde Aroma DESC | S66: 49 | T66: 197 | U66: =S66*T66 -> 9653 | V66: Jabon Aroma | W66: 18 | X66: 197 | Y66: =W66*X66 -> 3546 | Z66: Formação Fitoterapia NOVO | AA66: 0 | AB66: ='WEBINAR SEMANAL'!L2 -> CP AG | AC66: =AA66*AB66 -> #VALUE! | AD66: Formação Fitoterapia NOVO | AE66: 0 | AF66: ='WEBINAR SEMANAL'!L2 -> CP AG | AG66: =AE66*AF66 -> #VALUE! | AH66: Formação Fitoterapia NOVO | AI66: 0 | AJ66: ='WEBINAR SEMANAL'!L2 -> CP AG | AK66: =AI66*AJ66 -> #VALUE! | AL66: Formação Fitoterapia NOVO | AM66: 0 | AN66: ='WEBINAR SEMANAL'!L2 -> CP AG | AO66: =AM66*AN66 -> #VALUE! | AP66: Formação Fitoterapia NOVO | AQ66: 0 | AR66: ='WEBINAR SEMANAL'!L2 -> CP AG | AS66: =AQ66*AR66 -> #VALUE! | AT66: Formação Fitoterapia NOVO | AU66: 0 | AV66: ='WEBINAR SEMANAL'!L2 -> CP AG | AW66: =AU66*AV66 -> #VALUE!
B67: Apostila Aromaterapia e Sexualidade NOVO | C67: 0 | D67: ='WEBINAR SEMANAL'!L9 -> 200 | E67: =C67*D67 -> 0 | F67: Apostila Aromaterapia e Sexualidade NOVO | G67: 0 | H67: ='WEBINAR SEMANAL'!L9 -> 200 | I67: =G67*H67 -> 0 | J67: Apostila Aromaterapia e Sexualidade NOVO | K67: 0 | L67: ='WEBINAR SEMANAL'!L9 -> 200 | M67: =K67*L67 -> 0 | N67: Apostila Aromaterapia e Sexualidade NOVO | O67: 0 | P67: ='WEBINAR SEMANAL'!L9 -> 200 | Q67: =O67*P67 -> 0 | R67: Formação Fitoterapia NOVO | S67: 0 | T67: ='WEBINAR SEMANAL'!L2 -> CP AG | U67: =S67*T67 -> #VALUE! | V67: Saúde Aroma | W67: 27 | X67: 397 | Y67: =W67*X67 -> 10719 | Z67: Apostila Aromaterapia e Sexualidade NOVO | AA67: 0 | AB67: ='WEBINAR SEMANAL'!L9 -> 200 | AC67: =AA67*AB67 -> 0 | AD67: Apostila Aromaterapia e Sexualidade NOVO | AE67: 0 | AF67: ='WEBINAR SEMANAL'!L9 -> 200 | AG67: =AE67*AF67 -> 0 | AH67: Apostila Aromaterapia e Sexualidade NOVO | AI67: 0 | AJ67: ='WEBINAR SEMANAL'!L9 -> 200 | AK67: =AI67*AJ67 -> 0 | AL67: Apostila Aromaterapia e Sexualidade NOVO | AM67: 0 | AN67: ='WEBINAR SEMANAL'!L9 -> 200 | AO67: =AM67*AN67 -> 0 | AP67: Apostila Aromaterapia e Sexualidade NOVO | AQ67: 0 | AR67: ='WEBINAR SEMANAL'!L9 -> 200 | AS67: =AQ67*AR67 -> 0 | AT67: Apostila Aromaterapia e Sexualidade NOVO | AU67: 0 | AV67: ='WEBINAR SEMANAL'!L9 -> 200 | AW67: =AU67*AV67 -> 0
B68: Academia da Saúde Integrativa (recorrência) NOVO | C68: 0 | D68: =#REF! -> #REF! | E68: =C68*D68 -> #REF! | F68: Academia da Saúde Integrativa (recorrência) NOVO | G68: 0 | H68: =#REF! -> #REF! | I68: =G68*H68 -> #REF! | J68: Academia da Saúde Integrativa (recorrência) NOVO | K68: 0 | L68: =#REF! -> #REF! | M68: =K68*L68 -> #REF! | N68: Academia da Saúde Integrativa (recorrência) NOVO | O68: 0 | P68: =#REF! -> #REF! | Q68: =O68*P68 -> #REF! | R68: Apostila Aromaterapia e Sexualidade NOVO | S68: 0 | T68: ='WEBINAR SEMANAL'!L9 -> 200 | U68: =S68*T68 -> 0 | V68: Saúde Aroma DESC | W68: 10 | X68: 297 | Y68: =W68*X68 -> 2970 | Z68: Academia da Saúde Integrativa (recorrência) NOVO | AA68: 0 | AB68: =#REF! -> #REF! | AC68: =AA68*AB68 -> #REF! | AD68: Academia da Saúde Integrativa (recorrência) NOVO | AE68: 0 | AF68: =#REF! -> #REF! | AG68: =AE68*AF68 -> #REF! | AH68: Academia da Saúde Integrativa (recorrência) NOVO | AI68: 0 | AJ68: =#REF! -> #REF! | AK68: =AI68*AJ68 -> #REF! | AL68: Academia da Saúde Integrativa (recorrência) NOVO | AM68: 0 | AN68: =#REF! -> #REF! | AO68: =AM68*AN68 -> #REF! | AP68: Academia da Saúde Integrativa (recorrência) NOVO | AQ68: 0 | AR68: =#REF! -> #REF! | AS68: =AQ68*AR68 -> #REF! | AT68: Academia da Saúde Integrativa (recorrência) NOVO | AU68: 0 | AV68: =#REF! -> #REF! | AW68: =AU68*AV68 -> #REF!
B69: Formação Tantra NOVO | C69: 0 | D69: =#REF! -> #REF! | E69: =C69*D69 -> #REF! | F69: Formação Tantra NOVO | G69: 0 | H69: =#REF! -> #REF! | I69: =G69*H69 -> #REF! | J69: Formação Tantra NOVO | K69: 0 | L69: =#REF! -> #REF! | M69: =K69*L69 -> #REF! | N69: Formação Tantra NOVO | O69: 0 | P69: =#REF! -> #REF! | Q69: =O69*P69 -> #REF! | R69: Academia da Saúde Integrativa (recorrência) NOVO | S69: 0 | T69: =#REF! -> #REF! | U69: =S69*T69 -> #REF! | V69: Saúde Aroma DESC | W69: 18 | X69: 197 | Y69: =W69*X69 -> 3546 | Z69: Formação Tantra NOVO | AA69: 0 | AB69: =#REF! -> #REF! | AC69: =AA69*AB69 -> #REF! | AD69: Formação Tantra NOVO | AE69: 0 | AF69: =#REF! -> #REF! | AG69: =AE69*AF69 -> #REF! | AH69: Formação Tantra NOVO | AI69: 0 | AJ69: =#REF! -> #REF! | AK69: =AI69*AJ69 -> #REF! | AL69: Formação Tantra NOVO | AM69: 0 | AN69: =#REF! -> #REF! | AO69: =AM69*AN69 -> #REF! | AP69: Formação Tantra NOVO | AQ69: 0 | AR69: =#REF! -> #REF! | AS69: =AQ69*AR69 -> #REF! | AT69: Formação Tantra NOVO | AU69: 0 | AV69: =#REF! -> #REF! | AW69: =AU69*AV69 -> #REF!
B70: Certificação Fitoretapia NOVO | C70: 0 | D70: =#REF! -> #REF! | E70: =C70*D70 -> #REF! | F70: Certificação Fitoretapia NOVO | G70: 0 | H70: =#REF! -> #REF! | I70: =G70*H70 -> #REF! | J70: Certificação Fitoretapia NOVO | K70: 0 | L70: =#REF! -> #REF! | M70: =K70*L70 -> #REF! | N70: Certificação Fitoretapia NOVO | O70: 0 | P70: =#REF! -> #REF! | Q70: =O70*P70 -> #REF! | R70: Formação Tantra NOVO | S70: 0 | T70: =#REF! -> #REF! | U70: =S70*T70 -> #REF! | V70: Formação Fitoterapia NOVO | W70: 0 | X70: 997 | Y70: =W70*X70 -> 0 | Z70: Certificação Fitoretapia NOVO | AA70: 0 | AB70: =#REF! -> #REF! | AC70: =AA70*AB70 -> #REF! | AD70: Certificação Fitoretapia NOVO | AE70: 0 | AF70: =#REF! -> #REF! | AG70: =AE70*AF70 -> #REF! | AH70: Certificação Fitoretapia NOVO | AI70: 0 | AJ70: =#REF! -> #REF! | AK70: =AI70*AJ70 -> #REF! | AL70: Certificação Fitoretapia NOVO | AM70: 0 | AN70: =#REF! -> #REF! | AO70: =AM70*AN70 -> #REF! | AP70: Certificação Fitoretapia NOVO | AQ70: 0 | AR70: =#REF! -> #REF! | AS70: =AQ70*AR70 -> #REF! | AT70: Certificação Fitoretapia NOVO | AU70: 0 | AV70: =#REF! -> #REF! | AW70: =AU70*AV70 -> #REF!
R71: Certificação Fitoretapia NOVO | S71: 0 | T71: =#REF! -> #REF! | U71: =S71*T71 -> #REF! | V71: Apostila Aromaterapia e Sexualidade NOVO | W71: 249 | X71: 47 | Y71: =W71*X71 -> 11703
V72: Academia da Saúde Integrativa (recorrência) NOVO | W72: 0 | X72: 97 | Y72: =W72*X72 -> 0
V73: Formação Tantra NOVO Sem KIT | W73: 14 | X73: 997 | Y73: =W73*X73 -> 13958
B74: ANO 2019 | D74: =B79+N79+Z79+AL79 -> 2311013 | V74: Formação Tantra NOVO Com KIT | W74: 6 | X74: 1394 | Y74: =W74*X74 -> 8364
V75: Certificação Fitoretapia NOVO | W75: 0 | X75: 997 | Y75: =W75*X75 -> 0
B78: Q1 | N78: Q2 | Z78: Q3 | AL78: Q4
B79: =B84+F84+J84 -> 536855 | N79: =N84+R84+V84 -> 656052 | Z79: =Z84+AD84+AH84 -> 618631 | AL79: =AL84+AP84+AT84 -> 499475
B84: =sum(E91:E101) -> 162500 | F84: =sum(I91:I101) -> 163706 | J84: =sum(M91:M101) -> 210649 | N84: =SUM(Q90:Q101) -> 233972 | R84: =SUM(U90:U101) -> 225140 | V84: =SUM(Y90:Y101) -> 196940 | Z84: =sum(AC90:AC101) -> 222106 | AD84: =sum(AG90:AG101) -> 220382 | AH84: =sum(AK90:AK101) -> 176143 | AL84: =SUM(AO90:AO101) -> 170939 | AP84: =SUM(AS90:AS101) -> 120411 | AT84: =SUM(AW90:AW101) -> 208125
B88: JANEIRO | F88: FEVEREIRO | J88: MARÇO | N88: ABRIL | R88: MAIO | V88: JUNHO | Z88: JULHO | AD88: AGOSTO | AH88: SETEMBRO | AL88: OUTUBRO | AP88: NOVEMBRO | AT88: DEZEMBRO
B89: PRODUTO | C89: VENDAS | D89: TICKET | E89: FATURAMENTO | F89: PRODUTO | G89: VENDAS | H89: TICKET | I89: FATURAMENTO | J89: PRODUTO | K89: VENDAS | L89: TICKET | M89: FATURAMENTO | N89: PRODUTO | O89: VENDAS | P89: TICKET | Q89: FATURAMENTO | R89: PRODUTO | S89: VENDAS | T89: TICKET | U89: FATURAMENTO | V89: PRODUTO | W89: VENDAS | X89: TICKET | Y89: FATURAMENTO | Z89: PRODUTO | AA89: VENDAS | AB89: TICKET | AC89: FATURAMENTO | AD89: PRODUTO | AE89: VENDAS | AF89: TICKET | AG89: FATURAMENTO | AH89: PRODUTO | AI89: VENDAS | AJ89: TICKET | AK89: FATURAMENTO | AL89: PRODUTO | AM89: VENDAS | AN89: TICKET | AO89: FATURAMENTO | AP89: PRODUTO | AQ89: VENDAS | AR89: TICKET | AS89: FATURAMENTO | AT89: PRODUTO | AU89: VENDAS | AV89: TICKET | AW89: FATURAMENTO
B90: Acesso Vitalício Saúde Aroma | C90: 0 | D90: 47 | E90: =C90*D90 -> 0 | F90: Acesso Vitalício Saúde Aroma | G90: 0 | H90: 47 | I90: =G90*H90 -> 0 | J90: Acesso Vitalício Saúde Aroma | K90: 0 | L90: 47 | M90: =K90*L90 -> 0 | N90: Acesso Vitalício Saúde Aroma | O90: 0 | P90: 47 | Q90: =O90*P90 -> 0 | R90: Acesso Vitalício Saúde Aroma | S90: 0 | T90: 47 | U90: =S90*T90 -> 0 | V90: Acesso Vitalício Saúde Aroma | W90: 0 | X90: 47 | Y90: =W90*X90 -> 0 | Z90: Acesso Vitalício Saúde Aroma | AA90: 0 | AB90: 47 | AC90: =AA90*AB90 -> 0 | AD90: Acesso Vitalício Saúde Aroma | AE90: 0 | AF90: 47 | AG90: =AE90*AF90 -> 0 | AH90: Acesso Vitalício Saúde Aroma | AI90: 0 | AJ90: 47 | AK90: =AI90*AJ90 -> 0 | AL90: Acesso Vitalício Saúde Aroma | AM90: 46 | AN90: 47 | AO90: =AM90*AN90 -> 2162 | AP90: Acesso Vitalício Saúde Aroma | AQ90: 6 | AR90: 47 | AS90: =AQ90*AR90 -> 282 | AT90: Acesso Vitalício Saúde Aroma | AU90: 55 | AV90: 47 | AW90: =AU90*AV90 -> 2585
B91: Acesso Vitalício Empreende Aroma | C91: 0 | D91: 47 | E91: =C91*D91 -> 0 | F91: Acesso Vitalício Empreende Aroma | G91: 0 | H91: 47 | I91: =G91*H91 -> 0 | J91: Acesso Vitalício Empreende Aroma | K91: 0 | L91: 47 | M91: =K91*L91 -> 0 | N91: Acesso Vitalício Empreende Aroma | O91: 70 | P91: 47 | Q91: =O91*P91 -> 3290 | R91: Acesso Vitalício Empreende Aroma | S91: 106 | T91: 47 | U91: =S91*T91 -> 4982 | V91: Acesso Vitalício Empreende Aroma | W91: 95 | X91: 47 | Y91: =W91*X91 -> 4465 | Z91: Acesso Vitalício Empreende Aroma | AA91: 0 | AB91: 47 | AC91: =AA91*AB91 -> 0 | AD91: Acesso Vitalício Empreende Aroma | AE91: 135 | AF91: 47 | AG91: =AE91*AF91 -> 6345 | AH91: Acesso Vitalício Empreende Aroma | AI91: 88 | AJ91: 47 | AK91: =AI91*AJ91 -> 4136 | AL91: Acesso Vitalício Empreende Aroma | AM91: 69 | AN91: 47 | AO91: =AM91*AN91 -> 3243 | AP91: Acesso Vitalício Empreende Aroma | AQ91: 78 | AR91: 47 | AS91: =AQ91*AR91 -> 3666 | AT91: Acesso Vitalício Empreende Aroma | AU91: 57 | AV91: 47 | AW91: =AU91*AV91 -> 2679
B92: Acesso Vitalício Saboaria Aroma | C92: 0 | D92: 47 | E92: =C92*D92 -> 0 | F92: Acesso Vitalício Saboaria Aroma | G92: 0 | H92: 47 | I92: =G92*H92 -> 0 | J92: Acesso Vitalício Saboaria Aroma | K92: 0 | L92: 47 | M92: =K92*L92 -> 0 | N92: Acesso Vitalício Saboaria Aroma | O92: 95 | P92: 47 | Q92: =O92*P92 -> 4465 | R92: Acesso Vitalício Saboaria Aroma | S92: 75 | T92: 47 | U92: =S92*T92 -> 3525 | V92: Acesso Vitalício Saboaria Aroma | W92: 90 | X92: 47 | Y92: =W92*X92 -> 4230 | Z92: Acesso Vitalício Saboaria Aroma | AA92: 194 | AB92: 47 | AC92: =AA92*AB92 -> 9118 | AD92: Acesso Vitalício Saboaria Aroma | AE92: 54 | AF92: 47 | AG92: =AE92*AF92 -> 2538 | AH92: Acesso Vitalício Saboaria Aroma | AI92: 64 | AJ92: 47 | AK92: =AI92*AJ92 -> 3008 | AL92: Acesso Vitalício Saboaria Aroma | AM92: 50 | AN92: 47 | AO92: =AM92*AN92 -> 2350 | AP92: Acesso Vitalício Saboaria Aroma | AQ92: 32 | AR92: 47 | AS92: =AQ92*AR92 -> 1504 | AT92: Acesso Vitalício Saboaria Aroma | AU92: 35 | AV92: 47 | AW92: =AU92*AV92 -> 1645
B93: Apostila Digital Cold Process | C93: 0 | D93: 37 | E93: =C93*D93 -> 0 | F93: Apostila Digital Cold Process | G93: 0 | H93: 37 | I93: =G93*H93 -> 0 | J93: Apostila Digital Cold Process | K93: 0 | L93: 37 | M93: =K93*L93 -> 0 | N93: Apostila Digital Cold Process | O93: 0 | P93: 37 | Q93: =O93*P93 -> 0 | R93: Apostila Digital Cold Process | S93: 60 | T93: 37 | U93: =S93*T93 -> 2220 | V93: Apostila Digital Cold Process | W93: 125 | X93: 37 | Y93: =W93*X93 -> 4625 | Z93: Apostila Digital Cold Process | AA93: 144 | AB93: 37 | AC93: =AA93*AB93 -> 5328 | AD93: Apostila Digital Cold Process | AE93: 229 | AF93: 37 | AG93: =AE93*AF93 -> 8473 | AH93: Apostila Digital Cold Process | AI93: 130 | AJ93: 37 | AK93: =AI93*AJ93 -> 4810 | AL93: Apostila Digital Cold Process | AM93: 85 | AN93: 37 | AO93: =AM93*AN93 -> 3145 | AP93: Apostila Digital Cold Process | AQ93: 103 | AR93: 37 | AS93: =AQ93*AR93 -> 3811 | AT93: Apostila Digital Cold Process | AU93: 167 | AV93: 37 | AW93: =AU93*AV93 -> 6179
B94: Fitoterapia Integrativa | C94: 0 | D94: 97 | E94: =C94*D94 -> 0 | F94: Fitoterapia Integrativa | G94: 0 | H94: 97 | I94: =G94*H94 -> 0 | J94: Fitoterapia Integrativa | K94: 0 | L94: 97 | M94: =K94*L94 -> 0 | N94: Fitoterapia Integrativa | O94: 0 | P94: 97 | Q94: =O94*P94 -> 0 | R94: Fitoterapia Integrativa | S94: 0 | T94: 97 | U94: =S94*T94 -> 0 | V94: Fitoterapia Integrativa | W94: 0 | X94: 97 | Y94: =W94*X94 -> 0 | Z94: Fitoterapia Integrativa | AA94: 0 | AB94: 97 | AC94: =AA94*AB94 -> 0 | AD94: Fitoterapia Integrativa | AE94: 0 | AF94: 97 | AG94: =AE94*AF94 -> 0 | AH94: Fitoterapia Integrativa | AI94: 0 | AJ94: 97 | AK94: =AI94*AJ94 -> 0 | AL94: Fitoterapia Integrativa | AM94: 0 | AN94: 97 | AO94: =AM94*AN94 -> 0 | AP94: Fitoterapia Integrativa | AQ94: 0 | AR94: 97 | AS94: =AQ94*AR94 -> 0 | AT94: Fitoterapia Integrativa | AU94: 0 | AV94: 97 | AW94: =AU94*AV94 -> 0
B95: Empreende Aroma | C95: 363 | D95: 397 | E95: =C95*D95 -> 144111 | F95: Empreende Aroma | G95: 341 | H95: 397 | I95: =G95*H95 -> 135377 | J95: Empreende Aroma | K95: 463 | L95: 397 | M95: =K95*L95 -> 183811 | N95: Empreende Aroma | O95: 287 | P95: 397 | Q95: =O95*P95 -> 113939 | R95: Empreende Aroma | S95: 297 | T95: 397 | U95: =S95*T95 -> 117909 | V95: Empreende Aroma | W95: 262 | X95: 397 | Y95: =W95*X95 -> 104014 | Z95: Empreende Aroma | AA95: 309 | AB95: 397 | AC95: =AA95*AB95 -> 122673 | AD95: Empreende Aroma | AE95: 330 | AF95: 397 | AG95: =AE95*AF95 -> 131010 | AH95: Empreende Aroma | AI95: 194 | AJ95: 397 | AK95: =AI95*AJ95 -> 77018 | AL95: Empreende Aroma | AM95: 130 | AN95: 397 | AO95: =AM95*AN95 -> 51610 | AP95: Empreende Aroma | AQ95: 179 | AR95: 397 | AS95: =AQ95*AR95 -> 71063 | AT95: Empreende Aroma | AU95: 103 | AV95: 397 | AW95: =AU95*AV95 -> 40891
B96: Formação Aroma | C96: 0 | D96: 997 | E96: =C96*D96 -> 0 | F96: Formação Aroma | G96: 0 | H96: 997 | I96: =G96*H96 -> 0 | J96: Formação Aroma | K96: 0 | L96: 997 | M96: =K96*L96 -> 0 | N96: Formação Aroma | O96: 0 | P96: 997 | Q96: =O96*P96 -> 0 | R96: Formação Aroma | S96: 0 | T96: 997 | U96: =S96*T96 -> 0 | V96: Formação Aroma | W96: 0 | X96: 997 | Y96: =W96*X96 -> 0 | Z96: Formação Aroma | AA96: 0 | AB96: 997 | AC96: =AA96*AB96 -> 0 | AD96: Formação Aroma | AE96: 0 | AF96: 997 | AG96: =AE96*AF96 -> 0 | AH96: Formação Aroma | AI96: 0 | AJ96: 997 | AK96: =AI96*AJ96 -> 0 | AL96: Formação Aroma | AM96: 0 | AN96: 997 | AO96: =AM96*AN96 -> 0 | AP96: Formação Aroma | AQ96: 0 | AR96: 997 | AS96: =AQ96*AR96 -> 0 | AT96: Formação Aroma | AU96: 108 | AV96: 997 | AW96: =AU96*AV96 -> 107676
B97: Lavanda Experience | C97: 0 | D97: 197 | E97: =C97*D97 -> 0 | F97: Lavanda Experience | G97: 0 | H97: 197 | I97: =G97*H97 -> 0 | J97: Lavanda Experience | K97: 0 | L97: 197 | M97: =K97*L97 -> 0 | N97: Lavanda Experience | O97: 0 | P97: 197 | Q97: =O97*P97 -> 0 | R97: Lavanda Experience | S97: 0 | T97: 197 | U97: =S97*T97 -> 0 | V97: Lavanda Experience | W97: 0 | X97: 197 | Y97: =W97*X97 -> 0 | Z97: Lavanda Experience | AA97: 0 | AB97: 197 | AC97: =AA97*AB97 -> 0 | AD97: Lavanda Experience | AE97: 0 | AF97: 197 | AG97: =AE97*AF97 -> 0 | AH97: Lavanda Experience | AI97: 23 | AJ97: 197 | AK97: =AI97*AJ97 -> 4531 | AL97: Lavanda Experience | AM97: 12 | AN97: 197 | AO97: =AM97*AN97 -> 2364 | AP97: Lavanda Experience | AQ97: 0 | AR97: 197 | AS97: =AQ97*AR97 -> 0 | AT97: Lavanda Experience | AU97: 0 | AV97: 197 | AW97: =AU97*AV97 -> 0
B98: Make Natural | C98: 0 | D98: 97 | E98: =C98*D98 -> 0 | F98: Make Natural | G98: 0 | H98: 97 | I98: =G98*H98 -> 0 | J98: Make Natural | K98: 0 | L98: 97 | M98: =K98*L98 -> 0 | N98: Make Natural | O98: 0 | P98: 97 | Q98: =O98*P98 -> 0 | R98: Make Natural | S98: 0 | T98: 97 | U98: =S98*T98 -> 0 | V98: Make Natural | W98: 0 | X98: 97 | Y98: =W98*X98 -> 0 | Z98: Make Natural | AA98: 0 | AB98: 97 | AC98: =AA98*AB98 -> 0 | AD98: Make Natural | AE98: 0 | AF98: 97 | AG98: =AE98*AF98 -> 0 | AH98: Make Natural | AI98: 0 | AJ98: 97 | AK98: =AI98*AJ98 -> 0 | AL98: Make Natural | AM98: 0 | AN98: 97 | AO98: =AM98*AN98 -> 0 | AP98: Make Natural | AQ98: 0 | AR98: 97 | AS98: =AQ98*AR98 -> 0 | AT98: Make Natural | AU98: 109 | AV98: 97 | AW98: =AU98*AV98 -> 10573
B99: Mini-Curso Beleza Aroma | C99: 0 | D99: 97 | E99: =C99*D99 -> 0 | F99: Mini-Curso Beleza Aroma | G99: 0 | H99: 97 | I99: =G99*H99 -> 0 | J99: Mini-Curso Beleza Aroma | K99: 0 | L99: 97 | M99: =K99*L99 -> 0 | N99: Mini-Curso Beleza Aroma | O99: 0 | P99: 97 | Q99: =O99*P99 -> 0 | R99: Mini-Curso Beleza Aroma | S99: 0 | T99: 97 | U99: =S99*T99 -> 0 | V99: Mini-Curso Beleza Aroma | W99: 5 | X99: 97 | Y99: =W99*X99 -> 485 | Z99: Mini-Curso Beleza Aroma | AA99: 86 | AB99: 97 | AC99: =AA99*AB99 -> 8342 | AD99: Mini-Curso Beleza Aroma | AE99: 71 | AF99: 97 | AG99: =AE99*AF99 -> 6887 | AH99: Mini-Curso Beleza Aroma | AI99: 23 | AJ99: 97 | AK99: =AI99*AJ99 -> 2231 | AL99: Mini-Curso Beleza Aroma | AM99: 7 | AN99: 97 | AO99: =AM99*AN99 -> 679 | AP99: Mini-Curso Beleza Aroma | AQ99: 9 | AR99: 97 | AS99: =AQ99*AR99 -> 873 | AT99: Mini-Curso Beleza Aroma | AU99: 18 | AV99: 97 | AW99: =AU99*AV99 -> 1746
B100: Saboaria Aroma | C100: 0 | D100: 397 | E100: =C100*D100 -> 0 | F100: Saboaria Aroma | G100: 0 | H100: 397 | I100: =G100*H100 -> 0 | J100: Saboaria Aroma | K100: 0 | L100: 397 | M100: =K100*L100 -> 0 | N100: Saboaria Aroma | O100: 239 | P100: 397 | Q100: =O100*P100 -> 94883 | R100: Saboaria Aroma | S100: 188 | T100: 397 | U100: =S100*T100 -> 74636 | V100: Saboaria Aroma | W100: 168 | X100: 397 | Y100: =W100*X100 -> 66696 | Z100: Saboaria Aroma | AA100: 153 | AB100: 397 | AC100: =AA100*AB100 -> 60741 | AD100: Saboaria Aroma | AE100: 129 | AF100: 397 | AG100: =AE100*AF100 -> 51213 | AH100: Saboaria Aroma | AI100: 175 | AJ100: 397 | AK100: =AI100*AJ100 -> 69475 | AL100: Saboaria Aroma | AM100: 129 | AN100: 397 | AO100: =AM100*AN100 -> 51213 | AP100: Saboaria Aroma | AQ100: 85 | AR100: 397 | AS100: =AQ100*AR100 -> 33745 | AT100: Saboaria Aroma | AU100: 71 | AV100: 397 | AW100: =AU100*AV100 -> 28187
B101: Saúde Aroma | C101: 37 | D101: 497 | E101: =C101*D101 -> 18389 | F101: Saúde Aroma | G101: 57 | H101: 497 | I101: =G101*H101 -> 28329 | J101: Saúde Aroma | K101: 54 | L101: 497 | M101: =K101*L101 -> 26838 | N101: Saúde Aroma | O101: 35 | P101: 497 | Q101: =O101*P101 -> 17395 | R101: Saúde Aroma | S101: 44 | T101: 497 | U101: =S101*T101 -> 21868 | V101: Saúde Aroma | W101: 25 | X101: 497 | Y101: =W101*X101 -> 12425 | Z101: Saúde Aroma | AA101: 32 | AB101: 497 | AC101: =AA101*AB101 -> 15904 | AD101: Saúde Aroma | AE101: 28 | AF101: 497 | AG101: =AE101*AF101 -> 13916 | AH101: Saúde Aroma | AI101: 22 | AJ101: 497 | AK101: =AI101*AJ101 -> 10934 | AL101: Saúde Aroma | AM101: 109 | AN101: 497 | AO101: =AM101*AN101 -> 54173 | AP101: Saúde Aroma | AQ101: 11 | AR101: 497 | AS101: =AQ101*AR101 -> 5467 | AT101: Saúde Aroma | AU101: 12 | AV101: 497 | AW101: =AU101*AV101 -> 5964
... B106: Certificação Fitoretapia NOVO | C106: 0 | D106: 997 | E106: =C106*D106 -> 0 | F106: Certificação Fitoretapia NOVO | G106: 0 | H106: 997 | I106: =G106*H106 -> 0 | J106: Certificação Fitoretapia NOVO | K106: 0 | L106: 997 | M106: =K106*L106 -> 0 | N106: Certificação Fitoretapia NOVO | O106: 0 | P106: 997 | Q106: =O106*P106 -> 0 | R106: Certificação Fitoretapia NOVO | S106: 0 | T106: 997 | U106: =S106*T106 -> 0 | V106: Certificação Fitoretapia NOVO | W106: 0 | X106: 997 | Y106: =W106*X106 -> 0 | Z106: Certificação Fitoretapia NOVO | AA106: 0 | AB106: 997 | AC106: =AA106*AB106 -> 0 | AD106: Certificação Fitoretapia NOVO | AE106: 0 | AF106: 997 | AG106: =AE106*AF106 -> 0 | AH106: Certificação Fitoretapia NOVO | AI106: 0 | AJ106: 997 | AK106: =AI106*AJ106 -> 0 | AL106: Certificação Fitoretapia NOVO | AM106: 0 | AN106: 997 | AO106: =AM106*AN106 -> 0 | AP106: Certificação Fitoretapia NOVO | AQ106: 0 | AR106: 997 | AS106: =AQ106*AR106 -> 0 | AT106: Certificação Fitoretapia NOVO | AU106: 0 | AV106: 997 | AW106: =AU106*AV106 -> 0

Sheet ESTEIRA
A1: IMÃS DIGITAIS | C1: 1ª OFERTA | F1: 2ª OFERTA (order bump / plataforma) | G1: 3ª OFERTA (order bump / plataforma) | H1: 4ª OFERTA (order bump / plataforma) | I1: 5ª OFERTA (plataforma / página de obrigada) | M1: 1ª OFERTA | P1: 2ª OFERTA (order bump / plataforma) | Q1: 3ª OFERTA (order bump / plataforma) | R1: 4ª OFERTA (order bump / plataforma) | S1: 4ª OFERTA (plataforma / página de obrigada) | U1: 1ª OFERTA | X1: 2ª OFERTA (order bump / plataforma) | Y1: 3ª OFERTA (order bump / plataforma) | Z1: 4ª OFERTA (order bump / plataforma) | AA1: 4ª OFERTA (plataforma / página de obrigada)
C2: Front End (Entrada) PARA VOCÊ (R$ 97 > R$ 397) | M2: Back End (Estrela) CERTIFICAÇÃO / NA PRÁTICA AVANÇADO (R$ 497 > R$ 997) | U2: High End (Alto Valor) PROFISSÃO (R$ 1997 - INFINITO)
A4: 1 | B4: Amostra Plataforma Apostila Digital Cold Process | C4: Apostila Digital Cold Process R$ 47 | F4: Saboaria Aroma | I4: Empreende Aroma | K4: 1 | L4: Aprenda Como Viver de Forma PLENA utilizando a Aromaterapia no seu dia-a-dia | M4: Saúde Aroma | P4: Acesso Vitalício Saúde Aroma | Q4: KIT LAVANDA EXPERIENCE | S4: Saboaria Aroma | U4: Formação Aroma | X4: Acesso Vitalício Formação Aroma
A6: 2 | K6: 2 | L6: Como descobrir as causas da ansiedade e depressão
A8: 3 | K8: 3 | L8: Amostra Plataforma Saúde Aroma
A11: 1 | B11: Amostra Plataforma Apostila Fitoterapia Integrativa | C11: Apostila Fitoterapia Integrativa R$97 | F11: Saúde Aroma por R$ 197 | G11: Beleza Aroma | I11: Empreende Aroma | K11: 1 | L11: Aprenda a fazer 5 Produtos para Cuidar da Beleza e Ganhar Dinheiro com a Aromaterapia | M11: Empreende Aroma | P11: Acesso Vitalício Empreende Aroma | S11: Saboaria Aroma | U11: Formação Fitoterapia NOVO | X11: Acesso Vitalício Formação Fitoterapia
A13: 2 | K13: 2 | L13: Amostra Plataforma Empreende Aroma
A15: 3 | K15: 3 | L15: Webinar Prosperando com Aromaterapia
A18: 1 | B18: Amostra Plataforma Make Natural | C18: Make Natural | F18: Empreende Aroma | I18: Saboaria Aroma | K18: 1 | L18: Saboaria Chatboot | M18: Saboaria Aroma | P18: Acesso Vitalício Saboaria Aroma | S18: Empreende Aroma | U18: Mentoria Negócio de Cosmeticos Naturais
A20: 2 | K20: 2 | L20: Como fazer sabonetes naturais com os beneficios da Aromaterapia
A22: 3 | K22: 3 | L22: Amostra Plataforma Saboaria Aroma
A25: 1 | B25: Amostra Plataforma Mini-Curso Beleza Aroma | C25: Mini-Curso Beleza Aroma | F25: Empreende Aroma | I25: Saboaria Aroma | K25: 1 | L25: Webinar Sexualidade Sagrada | M25: Tantra NOVO | P25: Acesso Vitalício Tantra | Q25: KIT FÍSICO | S25: Saúde Aroma
A27: 2 | K27: 2
A29: 3 | K29: 3
A32: 1 | B32: Amostra Plataforma Apostila Aromaterapia e Sexualidade NOVO | C32: Apostila Aromaterapia e Sexualidade NOVO | F32: Make Natural | G32: Mini-Curso Beleza Aroma | I32: Tantra NOVO | K32: 1
A34: 2 | K34: 2
A36: 3 | K36: 3
A39: 1 | B39: Amostra Plataforma Lavanda Experience | C39: Lavanda Experience | F39: Make Natural | G39: Mini-Curso Beleza Aroma | I39: Empreende Aroma | K39: 1
A41: 2 | K41: 2
A43: 3 | K43: 3
A46: 1 | B46: Amostra Plataforma Academia da Saúde Integrativa (recorrência) NOVO | C46: Academia da Saúde Integrativa (recorrência) NOVO | F46: Apostila Aromaterapia e Sexualidade NOVO | G46: Empreende Aroma | I46: - | K46: 1
A48: 2 | K48: 2
A50: 3 | K50: 3
A53: 1 | B53: Amostra Plataforma Academia Revendedores Ekanta | C53: Academia Revendedores Ekanta | F53: - | I53: - | K53: 1
A55: 2 | K55: 2
A57: 3 | K57: 3
K60: 1
K62: 2
K64: 3
K67: 1 | P67: -
K69: 2
K71: 3
K74: 1 | P74: -
K76: 2
K78: 3

Sheet LINHA DE CRÉDITO FB
A1: Aquisição com Oferta Imediata
A3: Produtos | B3: Custo Méd Lead | C3: Leads | D3: Investimento
A4: Cosmética Natural | B4: 0.88 | C4: 2500 | D4: 4400
A5: Saboaria Natural | B5: 0.44 | C5: 2500 | D5: 2200
A6: Aromaterapia | B6: 0.72 | C6: 2500 | D6: =C6*B6 -> 1800
A7: Sexualidade | B7: 1 | C7: 2500 | D7: =C7*B7 -> 2500
A10: Aquisição com Modulo Grátis
A12: Produtos | B12: Custo Méd Lead | C12: Leads | D12: Investimento
A13: Cosmética Natural - Make Natural | B13: 1.96 | C13: 2500 | D13: =C13*B13 -> 4900
A14: Saboaria Natural | B14: 2 | C14: 2500 | D14: =C14*B14 -> 5000
A15: Aromaterapia | B15: 2 | C15: 2500 | D15: =C15*B15 -> 5000
A16: Sexualidade | B16: 2 | C16: 2500 | D16: =C16*B16 -> 5000
A18: Aquisição com Aula Gravada
A20: Produtos | B20: Custo Méd Lead | C20: Leads | D20: Investimento
A21: Cosmética Natural | B21: 2 | C21: 2500 | D21: =C21*B21 -> 5000
A22: Saboaria Natural | B22: 2 | C22: 2500 | D22: =C22*B22 -> 5000
A23: Aromaterapia | B23: 2 | C23: 2500 | D23: =C23*B23 -> 5000
A24: Sexualidade | B24: 2 | C24: 2500 | D24: =C24*B24 -> 5000
A26: Monetizações com Lançamento Meteórico
A28: Produtos | B28: Custo Méd Lead | C28: Leads | D28: Investimento
A29: Empreende Aroma Back End R$ 297 | B29: 1.87 | C29: 1500 | D29: =B29*C29 -> 2805
A30: Saboaria Aroma Back End R$ 297 | B30: 3.24 | C30: 1500 | D30: =B30*C30 -> 4860
A31: Saúde Aroma Back End R$ 297 | B31: 1.7 | C31: 1500 | D31: =B31*C31 -> 2550
A32: Sexualidade ? Back End R$ 297 | B32: 0 | C32: 0 | D32: 5000
A34: Tráfego Direto
A36: Produtos | B36: Custo Méd Venda | C36: Vendas | D36: Investimento
A37: Apostila Fitoterapia Front End R$ 97 | B37: =D37/C37 -> 20.129253 | C37: =176+132 -> 308 | D37: 6199.81 | E37: =D37/30 -> 206.66033
A38: Apostila Make Natural Front End R$ 97 | B38: =D38/C38 -> 18.70185 | C38: =91+70+93 -> 254 | D38: 4750.27 | E38: =D38/30 -> 158.34233
A39: Empreende Aroma Back End R$ 397 | B39: =D39/C39 -> 129.77596 | C39: =45+41+23 -> 109 | D39: =12765.3+1380.28 -> 14145.58
A40: Apostila Cold Process Front End R$ 47 | B40: =D40/C40 -> 14.711488 | C40: 168 | D40: 2471.53
A41: Saboaria Aroma Back End R$ 397 | B41: =D41/C41 -> 84.754096 | C41: =21+3+59 -> 83 | D41: 7034.59
A42: Saúde Aroma Front End R$ 97
A43: Saúde Aroma Back End R$ 397 | B43: =D43/C43 -> 29.59875 | C43: 16 | D43: 473.58
A44: Apostila Sexualidade Front End R$ 37 | B44: =D44/C44 -> 41.116216 | C44: 111 | D44: 4563.9 | E44: =D44/30 -> 152.13
A45: Sexualidade ? Back End R$ 397 | B45: =D45/C45 -> 50 | C45: 100 | D45: 5000
A48: Lançamentos
A50: Produtos | B50: Custo Méd Lead | C50: Leads | D50: Investimento | E50: RMKT | F50: Vendas | G50: Custo Méd Venda
A51: Formação Aroma High End com KIT R$ 1394 sem KIT R$ 997 | B51: R$ 1,40 | C51: 15000 | D51: 20000 | E51: 20000 | F51: 200 | G51: =(D51+E51)/F51 -> 200
A52: Tantra Healing High End com KIT R$ 1394 sem KIT R$ 997 | B52: 0.65 | C52: 12000 | D52: 7500 | E52: 7500 | F52: 30 | G52: =(D52+E52)/F52 -> 500
B55: INVESTIMENTO MENSAL | D55: =D6+D4+D5+D7+D15+D13+D14+D16+D29+D30+D31+D31+D39+D41+D43+D45+D37+D44+D40+D38 -> 88204.26
B57: INVESTIMENTO TRIMESTRAL | D57: =(D55*3)+D51+E51+D52+E52 -> 319612.78
B59: INVESTIMENTO ANUAL | D59: =(D55*12)+(D51+E51+D52+E52)*3 -> 1223451.1

Sheet MONETIZAÇÕES
A1: Status | B1: Lista | C1: Segmentação | D1: Campanha | E1: Produto | F1: Data Envio | G1: Hora | H1: Assunto | I1: Tamanho Lista | J1: % | K1: Abertura | L1: % | M1: Cliques | N1: Vendas | O1: Link no e-mail
A2: ✅ ENVIADO | B2: LISTA DE CONTATO PRINCIPAL | C2: INTERESSE SABOARIA ENGAJADO | D2: [MO-OUT][SAB][E1A-ENG] | E2: EMPREENDE AROMA | J2: =K2/I2 -> #DIV/0! | L2: =M2/K2 -> #DIV/0! | N2: 1
A3: ✅ ENVIADO | B3: LISTA DE CONTATO PRINCIPAL | C3: INTERESSE COSMÉTICA DESENGAJADO | D3: [MO1-OUT][EA][E1D-DESENG] | E3: EMPREENDE AROMA | J3: =K3/I3 -> #DIV/0! | L3: =M3/K3 -> #DIV/0! | N3: 1
A4: ✅ ENVIADO | B4: LISTA DE CONTATO PRINCIPAL | C4: INTERESSE SABOARIA ENGAJADO | D4: [MO-OUT][SAB][E2A-ENG] | E4: APOSTILA | J4: =K4/I4 -> #DIV/0! | L4: =M4/K4 -> #DIV/0! | N4: 2
A5: ✅ ENVIADO | B5: LISTA DE CONTATO PRINCIPAL | C5: INTERESSE SABOARIA ENGAJADO | D5: [MO-OUT][SAB][E1C-ENG] | E5: APOSTILA | J5: =K5/I5 -> #DIV/0! | L5: =M5/K5 -> #DIV/0! | N5: 2
A6: ✅ ENVIADO | B6: LISTA DE CONTATO PRINCIPAL | C6: INTERESSE SABOARIA ENGAJADO | D6: [MO1-OUT][APOSTILA][E3A-ENG] | E6: APOSTILA | J6: =K6/I6 -> #DIV/0! | L6: =M6/K6 -> #DIV/0! | N6: 1
A7: ✅ ENVIADO | B7: LISTA DE CONTATO PRINCIPAL | C7: INTERESSE SABOARIA ENGAJADO | D7: [MO1-OUT][APOSTILA][E5 A-ENG] | E7: APOSTILA | J7: =K7/I7 -> #DIV/0! | L7: =M7/K7 -> #DIV/0! | N7: 1

Sheet SU - VENDAS
B3: Novembro | N3: NOVEMBRO | V3: DIÁRIO DE BORDO
N4: DIA | O4: DATA | P4: Investimento | Q4: Produto Principal | R4: CPA Principal | S4: Receita | T4: ROAS | U4: %
N5: 1 | O5: domingo | P5: 0 | Q5: 0 | R5: =P5/Q5 -> #DIV/0! | S5: =Q5*E16 -> 0 | T5: =S5-P5 -> 0 | U5: =T5/S5 -> #DIV/0!
B6: Planejamento e Metas Esperadas | H6: Números Reais | N6: 2 | O6: segunda-feira | P6: 182.02 | Q6: 0 | R6: =P6/Q6 -> #DIV/0! | S6: =Q6*E16 -> 0 | T6: =S6-P6 -> -182.02 | U6: =T6/S6 -> #DIV/0!
N7: 3 | O7: terça-feira | P7: 288.27 | Q7: 0 | R7: =P7/Q7 -> #DIV/0! | S7: =Q7*E16 -> 0 | T7: =S7-P7 -> -288.27 | U7: =T7/S7 -> #DIV/0!
B8: Meta de Faturamento | E8: 32951 | H8: Investimento Realizado | K8: 0 | N8: 4 | O8: quarta-feira | P8: 321.65 | Q8: 0 | R8: =P8/Q8 -> #DIV/0! | S8: =Q8*E16 -> 0 | T8: =S8-P8 -> -321.65 | U8: =T8/S8 -> #DIV/0!
N9: 5 | O9: quinta-feira | P9: 316.53 | Q9: 0 | R9: =P9/Q9 -> #DIV/0! | S9: =Q9*E16 -> 0 | T9: =S9-P9 -> -316.53 | U9: =T9/S9 -> #DIV/0!
B10: Ticket do Produto | E10: 397 | H10: Vendas Realizadas | K10: 0 | N10: 6 | O10: sexta-feira | P10: 307.26 | Q10: 0 | R10: =P10/Q10 -> #DIV/0! | S10: =Q10*E16 -> 0 | T10: =S10-P10 -> -307.26 | U10: =T10/S10 -> #DIV/0!
N11: 7 | O11: sábado | P11: 293.63 | Q11: 0 | R11: =P11/Q11 -> #DIV/0! | S11: =Q11*E16 -> 0 | T11: =S11-P11 -> -293.63 | U11: =T11/S11 -> #DIV/0!
B12: Taxas da Plataforma | E12: =27.39+1+2.49 -> 30.88 | H12: CPA Real | K12: =SUM(K8/K10) -> #DIV/0! | N12: 8 | O12: domingo | P12: 290.12 | Q12: 0 | R12: =P12/Q12 -> #DIV/0! | S12: =Q12*E16 -> 0 | T12: =S12-P12 -> -290.12 | U12: =T12/S12 -> #DIV/0!
N13: 9 | O13: segunda-feira | P13: 296.68 | Q13: 0 | R13: =P13/Q13 -> #DIV/0! | S13: =Q13*E16 -> 0 | T13: =S13-P13 -> -296.68 | U13: =T13/S13 -> #DIV/0!
